Workbook

Sheet PRICING
A1: Updated - 30/03/2026 | F1: Updated - 26/02/2026 | I1: Updated - 25/03/2026 | L1: Updated - 27/02/2026 | O1: Updated - 25/03/2026 | R1: Updated -31/3/2026 | U1: Updated -31/03/2025 | X1: Updated - 31/03/2026 | AA1: Updated -05/03/2026 | AD1: Updated -29/07/2025 | AG1: Updated - 25/02/2026 | AJ1: Updated - 31/05/2023 | AM1: Updated - 31/03/2026 | AP1: Updated - 29/04/2024 | AS1: Updated - 31/03/2026 | AV1: Updated - 25/03/2026 | AY1: Updated - 27/02/2026 | BB1: Updated 27/03/2026 | BE1: Updated -31/10/2024 | BH1: Updated -24/03/2026 | BK1: Updated 31/3/2026 | BN1: Updated - 31/03/2026 | BQ1: Updated - 31/03/2026 | BT1: Updated - 25/02/2026 | BW1: Updated - 23/03/2026 | BZ1: Updated - 31/03/2026 | CC1: Updated - 18/07/2025 | CF1: Updated - 31/03/2026 | CI1: Updated - 31/03/2026 | CL1: Updated - 30/03/2026 | CO1: Updated - 20/03/2026
A2: YEALINK | F2: DNAKE | I2: CALL4TEL | L2: LG | O2: SHELLY | R2: MIKROTIK | U2: ZYXEL | X2: NETOGY | AA2: TP-LINK | AD2: APACHE OPTICS | AG2: VILO | AJ2: CAMBIUM | AM2: BLUETTI | AP2: MIKROCLOUD | AS2: MOTOROLA | AV2: NEAT | AY2: INOGENI | BB2: LOGITECH | BE2: TELRAD | BH2: HUAWEI | BK2: TELTONIKA | BN2: MECOOL | BQ2: MINIX | BT2: ZTE | BW2: H3C | BZ2: Samsung | CC2: H3C Enterprise | CF2: BARK | CI2: WHALE OS | CL2: GoBright | CO2: Videri
A3: Stock Code | B3: Price (excl. VAT) | C3: SAP | D3: MSRP | F3: Stock Code | G3: Price (excl. VAT) | I3: Stock Code | J3: Price (excl. VAT) | L3: Stock Code | M3: Price (excl. VAT) | O3: Stock Code | P3: Price (excl. VAT) | R3: Stock Code | S3: Price (excl. VAT) | U3: Stock Code | V3: Price (excl. VAT) | X3: Stock Code | Y3: Price (excl. VAT) | AA3: Stock Code | AB3: Price (excl. VAT) | AD3: Stock Code | AE3: Price (excl. VAT) | AG3: Stock Code | AH3: Price (excl. VAT) | AJ3: Stock Code | AK3: Price (excl. VAT) | AM3: Stock Code | AN3: Price (excl. VAT) | AP3: Stock Code | AQ3: Price (excl. VAT) | AS3: Stock Code | AT3: Price (excl. VAT) | AV3: Stock Code | AW3: Price (excl. VAT) | AY3: Stock Code | AZ3: Price (excl. VAT) | BB3: Stock Code | BC3: Pice(excl.VAT) | BE3: Stock Code | BF3: Price (excl. VAT) | BH3: Stock Code | BI3: Price (excl. VAT) | BK3: Stock Code | BL3: Price (excl. VAT) | BN3: Stock Code | BO3: Price (excl. VAT) | BQ3: Stock Code | BR3: Price (excl. VAT) | BT3: Stock Code | BU3: Price (excl. VAT) | BW3: Stock Code | BX3: Price (excl. VAT) | BZ3: Stock Code | CA3: Price (excl. VAT) | CC3: Stock Code | CD3: Price (excl. VAT) | CF3: Stock Code | CG3: Price (excl. VAT) | CI3: Stock Code | CJ3: Price (excl. VAT) | CL3: Stock Code | CM3: Price (excl. VAT) | CO3: Stock Code | CP3: Price (excl. VAT)
A4: AMS | B4: P.O.R | F4: 280M-S8 | G4: 515 | I4: NX32 LITE | J4: 5299 | L4: 22SM3G | M4: 6334 | O4: SHELLY DUO CW/WW (E27) | P4: 229 | R4: ACT-NVD | S4: 409 | U4: NWA110AX | V4: 3388.416 | X4: NOVA10 | Y4: 849 | AA4: ARCHER C80 | AB4: 613 | AD4: 1P-SFP1GESX | AE4: 431 | AG4: Vilo-5-3 | AH4: 1299 | AJ4: 1CMXEX1010XXAE | AK4: 5727 | AM4: PV120 | AN4: 2899 | AP4: MC-SDWAN | AQ4: 8 | AS4: MA1 | AT4: 799 | AV4: NEATPAD-SE | AW4: 14181 | AY4: 4KX-PLUS | AZ4: 11385 | BB4: 12X2S00012 | BC4: 27299 | BE4: BreezeAIR AXE-L 5-200-17-PTMP-CPE | BF4: 6469 | BH4: AP362 | BI4: 1843 | BK4: OTD140 | BL4: 2240 | BN4: KD3 | BO4: 799 | BQ4: C1-NS | BR4: 969 | BT4: ZXHN-H3601P | BU4: 525 | BW4: LS-1600V2-6P-HPWR-GL | BX4: 997 | BZ4: 58-QB65C | CA4: 14565 | CC4: TEST | CD4: 999 | CF4: BARK HOME 5100-S | CG4: 1599 | CI4: WHALE OS PROJECTOR | CJ4: 2599 | CL4: GB-ROOM 1-9 | CM4: 3360 | CO4: Spark2 | CP4: 33630
A5: YDMP | B5: P.O.R | F5: 902M-S8 | G5: 675 | I5: NX96(B) | J5: 17499 | L5: 32SM5JB | M5: 7205 | O5: SHELLY VINTAGE A60 (E27) | P5: 229 | R5: 18POW | S5: 105 | U5: NWA210AX | V5: 4271.22 | X5: NOVA10 BLUETOOTH RCU | Y5: 129 | AA5: ARCHER MR200 | AB5: 955 | AD5: 1P-SFP1GELX | AE5: 482 | AJ5: 1CMXEX1010PXAE | AK5: 8040 | AP5: MC-ADV_MON | AQ5: 30 | AS5: SJMC302 | AT5: 199 | AV5: NEATPADPRO10-SE | AW5: 20580 | AY5: 4KXUSB3 | AZ5: 10893 | BB5: 910-003357 | BC5: 89 | BE5: BreezeAIR AXE-L 5-200-23-PTMP-CPE | BF5: 7255 | BH5: AC650-128AP | BI5: 6037 | BK5: RUT140 | BL5: 997 | BN5: KM7 PLUS | BO5: 899 | BQ5: H1-NS | BR5: 969 | BT5: ZXHN-H3601P-INT | BU5: 525 | BW5: LS-1600V2-10P-HPWR-GL | BX5: 1507 | BZ5: 58-QB75C | CA5: 24999 | CL5: GB-ROOM 10-24 | CM5: 3150 | CO5: SparkQ+ | CP5: 43985
A6: SIP-T30 | B6: 642 | C6: N/A | D6: N/A | F6: 904M-S3 | G6: 833 | I6: NX256 | J6: 44999 | L6: 43UH5QE | M6: 10168 | O6: SHELLY VINTAGE G125 (E27) | P6: 359 | R6: 24HPOW | S6: 256 | U6: WX3100-T0 | V6: 629 | X6: NOVA PRO BLUETOOTH RCU | Y6: 129 | AA6: ARCHER MR600 V5 | AB6: 1538 | AD6: 1P-SFP1GET | AE6: 1147 | AJ6: 1CMXEX1028XXAE | AK6: 10342 | AP6: MC-SEC_ESS | AQ6: 59 | AS6: SJMC502 | AT6: 349 | AV6: NEATPAD-GLASSMOUNT | AW6: 1020 | AY6: 4K2USB3 | AZ6: 7780 | BB6: 910-006221 | BC6: 789 | BE6: BreezeAIR AXE-L 5-500-17-PTMP-CPE | BF6: 7299 | BH6: S310-24P4S | BI6: 5737 | BK6: RUT142 | BL6: 1109 | BN6: V02 | BO6: 129 | BQ6: CP86-CP-NS | BR6: 769 | BT6: G5TS | BU6: 1650 | BW6: LS-1600V2-18P-HPWR-GL | BX6: 3194 | BZ6: 58-QB85C | CA6: 33152 | CL6: GB-ROOM 25-49 | CM6: 2940 | CO6: Spark3 | CP6: 31040
A7: PSU-12V/1A | B7: 148 | C7: N/A | D7: N/A | F7: 905D-Y4 | G7: 2795 | L7: 49UH5NM | M7: 12317 | O7: SHELLY TEMP SENSOR (DS18B20) | P7: 74.510909 | R7: 48POW | S7: 249 | U7: GS1008-HP | V7: 1371.72 | X7: YCABLE | Y7: 59 | AA7: CPE210 | AB7: 429 | AD7: 1P-SFP10GSR | AE7: 1017 | AJ7: 1CMXEX1028PXAE | AK7: 15200 | AP7: MC-WEB_CON | AQ7: 74 | AS7: SJMC682 | AT7: 399 | AV7: NEATBOARDPRO-SE | AW7: 140636 | AY7: HD2USB3 | AZ7: 6306 | BB7: 910-006274 | BC7: 509 | BE7: BreezeAIR AXE-L 5-500-23-PTMP-CPE | BF7: 7998 | BH7: S380-L4P1T | BI7: 2788 | BK7: RUT361 | BL7: 3694 | BN7: KS3 | BO7: 5999 | BQ7: CP89-HD-NS | BR7: 3799 | BW7: LS-1600V2-26P-HPWR-GL | BX7: 4494 | BZ7: 58-QM50C | CA7: 10653 | CL7: GB-ROOM 50+ | CM7: 2730 | CO7: Spark4 | CP7: 36219
A8: COM-W73P/H-CHRG | B8: 49 | C8: N/A | D8: N/A | L8: 55UH5Q-E | M8: 13250 | O8: SHELLY BYPASS | P8: 53.865974 | R8: ACRPSMA | S8: 128 | U8: GS1200-5HPv2 | V8: 1269.768 | X8: UPS100-PLUS | Y8: 599 | AA8: CPE220 | AB8: 600 | AD8: 1P-SFP10GLR | AE8: 1448 | AJ8: 1CMXEX2010xxA0 | AK8: 10270 | AP8: MC-WAN-F/O | AQ8: 74 | AV8: NEATBOARDPRO-ADAPTIVE-STAND | AW8: 61559 | AY8: HD2USB3UP | AZ8: 1440 | BB8: 910-006275 | BC8: 489 | BE8: BreezeAirAXE-5-1G-17-PTMP-CPE | BF8: 8125 | BH8: S380-S8P2T | BI8: 4468 | BK8: RUT200 | BL8: 1575 | BN8: GM1 | BO8: 599 | BQ8: CP86-AA-NS | BR8: 769 | BW8: LS-1600V2-26S-HPWR-GL | BX8: 4672 | BZ8: 58-QM55C | CA8: 13586 | CL8: GB-ROOMSIG 1-9 | CM8: 2520 | CO8: Spark5 | CP8: 38809
A9: COM-W59R-CHRG | B9: 122 | C9: N/A | D9: N/A | L9: 65UL3Q-E | M9: 16676 | O9: SHELLY 50A CLAMP | P9: 252.44364 | R9: C52IG-5HAXD2HAXD-TC | S9: 1431 | U9: GS1200-8HPv2 | V9: 1458.768 | X9: NOVA PRO | Y9: 1099 | AA9: CPE510 | AB9: 695 | AD9: 1P-SFP10GUTP | AE9: 2954 | AJ9: 1CMXEX2010PxA0 | AK9: 14420 | AP9: MC-STATIC | AQ9: 129 | AV9: NEATBOARDPRO-ADAPTIVE-MOUNT | AW9: 26765 | AY9: SDI2USB3 | AZ9: 8927 | BB9: 910-006348 | BC9: 489 | BE9: BreezeAirAXE-5-1G-23-PTMP-CPE | BF9: 8738.9957 | BH9: S380-H8T3ST | BI9: 6406 | BK9: RUT260 | BL9: 3067 | BN9: G20 | BO9: 199 | BW9: LS-1850V2-10P-HPWR-EI-GL | BX9: 2540 | BZ9: 58-QM65C | CA9: 16847 | CL9: GB-ROOMSIG 10-24 | CM9: 2363
A10: COM-W56P/H-CHRG | B10: 65 | C10: N/A | D10: N/A | L10: 65UH5Q-E | M10: 16676 | O10: SHELLY 120A CLAMP | P10: 340.78815 | R10: CAPGI-5HAXD2HAXD | S10: 1922 | U10: GS1900-8HP | V10: 1951.728 | X10: AIRNOVA | Y10: 799 | AA10: CPE610 | AB10: 929 | AD10: 1P-SFP25GSR | AE10: 1630 | AJ10: 1CMXEX2028xxA0 | AK10: 18569 | AP10: MC-VPN-ACC | AQ10: 130 | AV10: NEATBOARDPRO-WALLMOUNT | AW10: 7206 | AY10: TOGGLE | AZ10: 8108 | BB10: 910-006438 | BC10: 739 | BE10: BreezeAirAXE-5-2G-PTMP | BF10: 29475 | BH10: AR730 | BI10: 15398 | BK10: RUT901 | BL10: 2393 | BW10: LS-1850V2-28P-HPWR-EI-GL | BX10: 5398 | BZ10: 58-QM75C | CA10: 33695 | CL10: GB-ROOM 25-49 | CM10: 2205
A11: COM-W56P/H-BACK-COVER | B11: 20 | C11: N/A | D11: N/A | L11: 75UH5N-M | M11: 32608 | O11: SHELLY PLUS ADD-ON | P11: 271.32435 | R11: CCR2004-16G-2S+ | S11: 6942 | U11: GS1900-10HP | V11: 2592.7625 | X11: AIRNOVAMAX | Y11: 1199 | AA11: CPE710 | AB11: 1074 | AD11: 1P-SFP25GLR | AE11: 2547 | AJ11: 1CMXEX2028PxA0 | AK11: 26869 | AP11: MC-VPN-USER | AQ11: 26 | AV11: NEATBOARD32-SE | AW11: 71163 | AY11: TOGGLE ROOMS | AZ11: 18755 | BB11: 910-006494 | BC11: 1039 | BE11: BreezeAirAXE-5-1G-PTMP | BF11: 25025 | BH11: AR720 | BI11: 7350 | BK11: RUT906 | BL11: 2530 | BW11: LS-1850V2-52X-PWR-GL | BX11: 13689 | BZ11: 58-QM85C | CA11: 41303 | CL11: GB-ROOMSIG 50+ | CM11: 2048
A12: COM-W56H-BC | B12: 25 | C12: N/A | D12: N/A | L12: 86UL5Q-E | M12: 40790 | O12: SHELLY PLUS SMOKE ALARM | P12: 841.26098 | R12: CCR2004-16G-2S+PC | S12: 6788 | U12: GS1900-24HPv2 | V12: 6349.6224 | AA12: DECO E4-1 | AB12: 408 | AD12: 1P-SFP25GER | AE12: 10700 | AJ12: 1CMXEX2052GxxA00 | AK12: 31019 | AP12: MC-MIK-RENTAL | AQ12: 135 | AV12: NB32-TBLST | AW12: 7206 | AY12: U-BRIDGE | AZ12: 6306 | BB12: 910-006496 | BC12: 999 | BE12: FLAT-PANEL-ANT-5G-90 | BF12: 8145 | BH12: S110-8P2ST | BI12: 733 | BK12: RUT951 | BL12: 3648 | BW12: LS-5120V3-28P-PWR-LI-GL | BX12: 5530 | CL12: GB-CATSERVL | CM12: 1106
A13: COM-T7-WMB | B13: 60 | C13: N/A | D13: N/A | L13: 98UM5K | M13: 89483 | O13: SHELLY PRO 2PM | P13: 1566.7834 | R13: CCR2004-1G-12S+2XS | S13: 8864 | U13: GS1920-8HPv2 | V13: 4233.0816 | AA13: DECO E4-2 | AB13: 784 | AD13: 1P-SFP25GZR | AE13: 101909 | AJ13: 1CMXEX2052GxPA00 | AK13: 43468 | AP13: VG10 | AQ13: 432 | AV13: NB32-WALL-MNT | AW13: 5147 | AY13: U-BRIDGE3 | AZ13: 13227 | BB13: 910-006582 | BC13: 1899 | BE13: DISH-ANT-5G-5 | BF13: 7325 | BH13: S110-16LP2SR | BI13: 2951 | BK13: RUT956 | BL13: 4156 | BW13: LS-5120V3-28P-HPWR-LI-GL | BX13: 6199 | CL13: GB-DESK 1-249 | CM13: 448
A14: COM-T56/T58-HS | B14: 75 | C14: N/A | D14: N/A | L14: 98UH5J-H | M14: 114130 | O14: SHELLY PRO 3EM-120A | P14: 2254.0553 | R14: CCR2116-12G-4S+ | S14: 15209 | U14: GS1920-24HPv2 | V14: 8115.06 | AA14: DECO E4-3 | AB14: 1160 | AD14: 1P-QSFP40GSR | AE14: 2038 | AJ14: 1CMXEX2052GxPA10 | AK14: 37243 | AP14: VG25 | AQ14: 972 | AV14: NB32-AD-TBLST | AW14: 16265 | AY14: U-CAM | AZ14: 9746 | BB14: 910-006958 | BC14: 1359 | BE14: DISH-ANT-5G-3-5 | BF14: 8775 | BH14: S110-24LP2SR | BI14: 4250 | BK14: RUTX10 | BL14: 3233 | BW14: LS-5120V3-52P-PWR-LI-GL | BX14: 11502 | CL14: GB-DESK 250-999 | CM14: 420
A15: COM-T48 WMB | B15: 60 | C15: N/A | D15: N/A | L15: 110UM5K | M15: 209783 | O15: SHELLY PRO 3EM-400A | P15: 4447.517 | R15: CCR2216-1G-12XS-2XQ | S15: 37307 | U15: GS1920-48HPv2 | V15: 11218.008 | AA15: DECO M4-1 | AB15: 545 | AD15: 1P-QSFP40GLR | AE15: 8152 | AJ15: 1CPLE410X00BRW | AK15: 4835 | AP15: VG50 | AQ15: 1620 | AV15: NB32-AD-TBLST-B | AW15: 5015 | AY15: CAM230 | AZ15: 15970 | BB15: 910-006959 | BC15: 1319 | BE15: DISH-ANT-5G-3 | BF15: 20525 | BH15: S220-24T4X | BI15: 4474 | BK15: RUTX11 | BL15: 5726 | BW15: LS-5120V3-28S-PWR-LI-GL | BX15: 7722 | CL15: GB-DESK 1000-1999 | CM15: 392
A16: COM-T46G/T46U/T48G/T48U HS | B16: 98 | C16: N/A | D16: N/A | L16: 55TR3DQ | M16: 24999 | O16: SHELLY PRO 4PM | P16: 1856.7965 | R16: CRS112-8P-4S-IN | S16: 3182 | U16: USGFLEX100-D | V16: 8756.923 | AA16: DECO M4-2 | AB16: 1023 | AD16: 1P-QSFP40GER | AE16: 32101 | AJ16: 1CPLE510X00ARW | AK16: 9706 | AP16: VG100 | AQ16: 2160 | AV16: NB32-AD-TBLCL | AW16: 16265 | AY16: SHARE2U | AZ16: 34316 | BB16: 910-007182 | BC16: 269 | BE16: BREEZEAIR-AXE | BF16: 10999 | BH16: S220-24P4X | BI16: 5333 | BK16: RUTX12 | BL16: 8265 | BW16: LS-5120V3-28S-HPWR-LI-GL | BX16: 9865 | CL16: GB-DESK 2000+ | CM16: 364
A17: COM-T46 WMB | B17: 60 | C17: N/A | D17: N/A | L17: 65TR3DQ | M17: 28260 | O17: SHELLY PRO 1PM | P17: 1177.0088 | R17: CRS305-1G-4S+IN | S17: 2287 | U17: USGFLEX200-D | V17: 12434.677 | AA17: DECO M4-3 | AB17: 1501 | AD17: 1P-QSFP40GZR | AE17: 91718 | AJ17: 1CPLE600X00ARW | AK17: 7987 | AP17: VG150 | AQ17: 3240 | AV17: NB32-AD-TBLCL-B | AW17: 5015 | AY17: SHARE2 | AZ17: 26126 | BB17: 910-007511 | BC17: 449 | BE17: BREEZEAIR-AXE-CON | BF17: 9499 | BH17: S220-48T4X | BI17: 7891 | BK17: RUTX14 | BL17: 6649 | BW17: LS-5120V3-28F-LI-GL | BX17: 6175 | CL17: GB-PARKING 1-249 | CM17: 448
A18: COM-T40/T41/T42 WMB | B18: 59 | C18: N/A | D18: N/A | L18: 75TR3DQ | M18: 32608 | O18: SHELLY BLU BUTTON1 (BLUE) | P18: 299 | R18: CRS309-1G-8S+IN | S18: 4058 | U18: NWA50AX | V18: 1656.996 | AA18: DECO M5-3 | AB18: 2252 | AD18: 1P-QSFP100GSR | AE18: 2751 | AJ18: 1CPLE700X00ARW | AK18: 16631 | AP18: VG250 | AQ18: 4320 | AV18: NB32-AD-TBL-BLT | AW18: 5015 | AY18: CAM300 | AZ18: 29402 | BB18: 920-002479 | BC18: 229 | BH18: S220-48T4S | BI18: 5688 | BK18: RUTX50 | BL18: 8270 | BW18: LS-6520X-16ST-SI-GL | BX18: 15855 | CL18: GB-PARKING 250-999 | CM18: 420
A19: COM-T3X HST | B19: 88 | C19: N/A | D19: N/A | L19: 86TR3DQ | M19: 38042 | O19: SHELLY BLU BUTTON1 (RED) | P19: 299 | R19: CRS310-1G-5S-4S+IN | S19: 2966 | U19: IES5206M-ZZ01V1F | V19: P.O.R | AA19: DECO X10-2P | AB19: 1364 | AD19: 1P-QSFP100GLR | AE19: 12025 | AJ19: 1CXV22X00A00RW | AK19: 8892 | AP19: VG500 | AQ19: 8640 | AV19: NB32-PRIV | AW19: 2594 | BB19: 920-004509 | BC19: 379 | BH19: S220-48P4X | BI19: 9471 | BK19: RUTM10 | BL19: 2217 | BW19: PSR75-12A-GL | BX19: 1102 | CL19: GB-PARKING 1000-1999 | CM19: 392
A20: COM-T33G-WMB | B20: 60 | C20: N/A | D20: N/A | L20: 75UR640S | M20: 18477.174 | O20: SHELLY BLU BUTTON1 (BLACK) | P20: 299 | R20: CRS310-1G-5S-4S+OUT | S20: 3655 | U20: IES5206M-ZZ01V2F | V20: P.O.R | AA20: DECO X20-2 | AB20: 1706 | AD20: 1P-QSFP100GER | AE20: 47387 | AJ20: 1CXV221X0A00RW | AK20: 5965 | AP20: VG1000 | AQ20: 12960 | AV20: NB32-CBL-LOCK | AW20: 2594 | BB20: 920-009204 | BC20: 879 | BH20: S220-48P4S | BI20: 8462 | BK20: TAP200 | BL20: 1011 | BW20: EWP-WA6020 | BX20: 1098 | CL20: GB-PARKING 2000+ | CM20: 364
A21: COM-T29G-WMB | B21: 58 | C21: N/A | D21: N/A | O21: SHELLY 1 MINI GEN3 | P21: 253.12684 | R21: CRS312-4C+8XG-RM | S21: 10552 | U21: IES5212M-ZZ01V1F | V21: P.O.R | AA21: DECO X20-3 | AB21: 2525 | AD21: 1P-QSFP100GZR | AE21: 81527 | AJ21: 1CXV222H0A00RW | AK21: 6976 | AV21: NEATBOARD50-SE | AW21: 112471 | BB21: 920-010251 | BC21: 2059 | BH21: S310-24T4X | BI21: 4663 | BK21: TRB140 | BL21: 2122 | BW21: EWP-WA6022H | BX21: 966 | CL21: GB-MAP 1-9 | CM21: 6286
A22: COM-SC | B22: 25 | C22: N/A | D22: N/A | O22: SHELLY 1PM MINI GEN3 | P22: 287.05733 | R22: CRS317-1G-16S+RM | S22: 7917 | U22: OLT1404A-ZZ01V1F | V22: P.O.R | AA22: DECO X55-1 | AB22: 955 | AD22: 1P-BU1310155010KM | AE22: 560 | AJ22: 1CXV22T0XA00RW | AK22: 13106 | AV22: NEATBOARD50-WALLMOUNT | AW22: 6382 | BB22: 920-010352 | BC22: 2239 | BH22: S310-24P4X | BI22: 6628 | BK22: TRB142 | BL22: 1894 | BW22: EWP-WA6120 | BX22: 1375 | CL22: GP-MAP 10-24 | CM22: 5893
A23: COM-EAR-CUSHION-BH72-5PR | B23: 1004 | C23: N/A | D23: N/A | O23: SHELLY BLU GATEWAY | P23: 272.69355 | R23: CRS318-16P-2S+OUT | S23: 4165 | U23: OLT1408A-ZZ01V1F | V23: P.O.R | AA23: DECO X55-2 | AB23: 1842 | AD23: 1P-BD1550131010KM | AE23: 662 | AJ23: 1CXV22T1XA00RW | AK23: 15076 | AV23: NEATBOARD50-ADAPTIVESTAND | AW23: 40970 | BB23: 920-010608 | BC23: 1859 | BH23: S310-48T4X | BI23: 10814 | BK23: TRB143 | BL23: 3065 | BW23: EWP-WA6126 | BX23: 3162 | CL23: GB-MAP 25-49 | CM23: 5500
A24: COM-EAR-CUSHION-BH72-1PR | B24: 200 | C24: N/A | D24: N/A | O24: SHELLY BLU MOTION | P24: 370.88636 | R24: CRS318-1FI-15FR-2S-OUT | S24: 2435 | U24: OLT2406-ZZ01V1F | V24: P.O.R | AA24: DECO XE75(3-PACK) | AB24: 4437 | AJ24: 1CXV38X00A00RW | AK24: 24281 | AV24: NEATBOARD50-ADAPTIVEMOUNT | AW24: 24706 | BB24: 920-010933 | BC24: 3539 | BH24: S310-48P4X | BI24: 10072 | BK24: TRB145 | BL24: 1894 | BW24: EWP-WA6120H | BX24: 1881 | CL24: GB-MAP 50+ | CM24: 5107
A25: CAM50 | B25: 1149 | C25: 1775.1 | D25: 2013 | O25: SHELLY BLU BUTTON TOUGH 1 BLAC | P25: 331.24826 | R25: CRS326-24G-2S+RM | S25: 3239 | U25: ALM2406 | V25: P.O.R | AA25: EAP110 | AB25: 442 | AJ25: 1CXE34X00A06RW | AK25: 15081 | AV25: NEATBAR-BYOD | AW25: 11805 | BB25: 920-011004 | BC25: 1319 | BH25: S310-48P4S | BI25: 10505 | BK25: TRB246 | BL25: 2425 | BW25: EWP-WA6120X | BX25: 3506 | CL25: GB-VISITL | CM25: 17500
A26: COM-W52P/H-BC | B26: 15 | C26: N/A | D26: N/A | O26: SHELLY BLU H&T (BLACK) | P26: 340.93091 | R26: CRS326-24S+2Q+RM | S26: 8901 | U26: OFC2406 | V26: P.O.R | AA26: EAP115 | AB26: 378 | AJ26: 1CXE58X00A00RW | AK26: 36987 | AV26: NEATBAR2-SE | AW26: 59521 | BB26: 920-011032 | BC26: 1279 | BH26: AP361 | BI26: 791 | BK26: TSW010 | BL26: 501 | BW26: EWP-WSG1812X-PWR | BX26: 6087 | CL26: GB-VIEW-CORE 1-9 | CM26: 3486
A27: UH36-MONO-USBC | B27: 669 | C27: N/A | D27: N/A | O27: SHELLY PLUS UNI | P27: 281.79394 | R27: CRS328-24P-4S+RM | S27: 7419 | U27: OPA2406 | V27: P.O.R | AA27: EAP115-WALL | AB27: 347 | AV27: NEATBAR2-BE | AW27: 59521 | BB27: 920-012077 | BC27: 699 | BH27: AP160 | BI27: 975 | BK27: TSW100 | BL27: 1434 | BW27: EWP-WSG1840X | BX27: 6135 | CL27: GB-VIEW-CORE 10-24 | CM27: 3268
A28: CP965-TEAMS | B28: 9112 | C28: 13017 | D28: 15642 | O28: SHELLY PM MINI GEN3 | P28: 273.47074 | R28: CRS328-4C-20S-4S+RM | S28: 6354 | U28: MSC1240XA-ZZ01V1F | V28: P.O.R | AA28: EAP225 | AB28: 821 | AV28: NEATBARPRO-SE | AW28: 94445 | BB28: 920-012334 | BC28: 1029 | BH28: AP761 | BI28: 3099 | BK28: TSW101 | BL28: 1230 | BW28: NS-SecPath F100-C-A1-I | BX28: 4741 | CL28: GB-VIEW-CORE 25-49 | CM28: 3050
A29: MP52 E2 | B29: 2199 | C29: 4110 | D29: 3984 | O29: SHELLY BLU DOOR WINDOW BLACK | P29: 310.11188 | R29: CRS354-48G-4S+2Q+RM | S29: 9163 | U29: MSC1280XA-ZZ01V1F | V29: P.O.R | AA29: EAP225-OUTDOOR | AB29: 821 | AV29: NEATFRAME-SE | AW29: 10359 | BB29: 920-012508 | BC29: 1629 | BH29: AP371 | BI29: 1390 | BK29: TSW200 | BL29: 1669 | BW29: RT-MSR610 | BX29: 2246 | CL29: GB-VIEW-CORE 50+ | CM29: 2832
A30: MP54 E2 | B30: 3596 | C30: 5138 | D30: 5028 | O30: SHELLY BLU DOOR WINDOW WHITE | P30: 323.41527 | R30: CRS354-48P-4S+2Q+RM | S30: 14784 | U30: OLC3416-42A-ZZ01V1F | V30: P.O.R | AA30: EAP245 | AB30: 1074 | AV30: NEATCENTER-SE | AW30: 39604 | BB30: 920-013333 | BC30: 879 | BH30: S220-8T4S | BI30: 1756 | BK30: TSW202 | BL30: 2194 | BW30: SFP-GE-SX-MM850-A | BX30: 1681 | CL30: GB-VIEW-PREMIUM 1-9 | CM30: 658
A31: MP55 E2 | B31: 3788 | C31: 5412 | D31: 5550 | O31: SHELLY BLU RC BUTTON 4 | P31: 292.01711 | R31: CRS504-4XQ-IN | S31: 12916 | U31: GLC1440X-55-ZZ01V1F | V31: P.O.R | AA31: EAP610 | AB31: 1137 | AV31: POE-INJ-NEATCENTER | AW31: 1556 | BB31: 920-013349 | BC31: 1239 | BH31: S220-8P4S | BI31: 2644 | BK31: TSW212 | BL31: 1894 | BW31: SFP-GE-LX-SM1310-A | BX31: 3738 | CL31: GB-VIEW-PREMIUM 10-24 | CM31: 617
A32: MP56 E2 | B32: 4556 | C32: 6508 | D32: 6246 | O32: SHELLY WALL DISPLAY + BLU H&T | P32: 2472.906 | R32: CRS510-8XS-2XQ-IN | S32: 14931 | U32: GLC1440X-55A-ZZ01V1F | V32: P.O.R | AA32: EAP610-OUTDOOR | AB32: 1770 | AV32: NEATPAD-HEX8-4 | AW32: 156 | BB32: 939-001487 | BC32: 2779 | BH32: AR303 | BI32: 1486 | BK32: PR1ICC60 | BL32: 2540 | BW32: SFP-XG-SX-MM850-E | BX32: 814 | CL32: GB-VIEW-PREMIUM 25-49 | CM32: 575
A33: MP58-WH E2 | B33: 5515 | C33: 7878 | D33: 8334 | O33: SHELLY WALL DISPLAY+BLU H&T(W) | P33: 2571.3964 | R33: CRS518-16XS-2XQ-RM | S33: 25857 | U33: OMU2442-ZZ01V1F | V33: P.O.R | AA33: EAP615-WALL | AB33: 884 | AV33: NEATPAD-WALLADAPT | AW33: 502 | BB33: 939-001490 | BC33: 3719 | BH33: S530-48S4XE | BI33: 11809 | BK33: RUTM11 | BL33: 4895 | BW33: SFP-XG-LX-SM1310 | BX33: 1481 | CL33: GB-VIEW-PREMIUM 50+ | CM33: 535
A34: AX83H | B34: 1693 | C34: 2419 | D34: 2766 | O34: SHELLY TEMP SENSOR DS18B20 3M | P34: 137.34611 | R34: CSS326-24G-2S+RM | S34: 2413 | U34: OLC2404-22-ZZ01V2F | V34: P.O.R | AA34: EAP620 HD | AB34: 1580 | AV34: NEATPAD-SIDEMOUNT | AW34: 597 | BB34: 939-001498 | BC34: 1719 | BH34: S530-24ST4XE | BI34: 8124 | BK34: RUT241-eSIM | BL34: 2702 | BW34: EWPAM1HPOE-GL | BX34: 343 | CL34: GB-WEEKPLANNER | CM34: 9086
A35: AX86R | B35: 2469 | C35: 3528 | D35: 3810 | O35: SHELLY H&T GEN3 (BLACK) | P35: 622.21972 | R35: CSS610-1GI-7R-2S+OUT | S35: 2114 | U35: EX3301-T0 | V35: 799 | AA35: EAP650 | AB35: 1264 | AV35: NEATPAD-WALLBRACK | AW35: 674 | BB35: 939-001644 | BC35: 4579 | BH35: S530-24T4XE | BI35: 6773 | BK35: PR313EU3 | BL35: 1142 | BW35: SOHO-SWITCH-FL-02 | BX35: 26 | CL35: GB-WAYFINDERL | CM35: 5586
A36: COM-BTH58 | B36: 564 | C36: 806 | D36: 870 | O36: SHELLY PRO EM - 50 | P36: 1442.0024 | R36: CSS610-8P-2S+IN | S36: 3396 | U36: EX5301-B3 | V36: 1749 | AA36: EAP660 HD | AB36: 2971 | AV36: BARPRO-MOUNT-ADAPTER | AW36: 1626 | BB36: 939-001647 | BC36: 5169 | BH36: USG6000E-S03 | BI36: 0 | BK36: PR1KCL25 | BL36: 194 | BW36: RTU-FL-F | BX36: 56 | CL36: GB-LOCKERBANK | CM36: 6286
A37: CP925 | B37: 5174 | C37: 7392 | D37: 10422 | O37: SHELLY DIMMER 0/1-10V GEN3 | P37: 320.52106 | R37: D53G-5HACD2HND-TC&RG520F-EU | S37: 7278 | U37: GS1915-24E | V37: 2699 | AA37: EAP670 | AB37: 1833 | AV37: BARPRO-SCREENMOUNT-HORIZONTALBAR | AW37: 1193 | BB37: 939-001656 | BC37: 2849 | BH37: USG6000E-S13 | BI37: 18678 | BK37: SWM282 | BL37: 5667 | BW37: LS-1850V2-10P-EI-GL | BX37: 1683 | CL37: GB-API-ACCESS | CM37: 16786
A38: CP935W | B38: 7762 | C38: 11089 | D38: 13902 | O38: SHELLY DIMMER GEN3 | P38: 691.26849 | R38: E50UG | S38: 831 | U38: GS1915-24EP | V38: 5363.9578 | AA38: EC220-G5 | AB38: 358 | AV38: BARPRO-SCREENMOUNT-VERTICALBAR | AW38: 1193 | BB38: 939-001799 | BC38: 5629 | BH38: S380-L4T1T | BI38: 1936 | BK38: SWM281 | BL38: 3442 | BW38: LS-6520X-24ST-SI-GL | BX38: 19021 | CL38: GB-ANALYTICS-ADV | CM38: 9086
A39: CP965 | B39: 7399 | C39: 12769 | D39: 15642 | O39: SHELLY EM GEN3 | P39: 1129.5856 | R39: L009UIGS-2HAXD-IN | S39: 1922 | U39: GS1915-8 | V39: 1428.665 | AA39: ER605 | AB39: 631 | AV39: BARPRO-TABLESTAND | AW39: 1420 | BB39: 939-001799-S | BC39: 5539 | BH39: HWA-01 | BI39: 2101 | BK39: DAP140 | BL39: 1018 | BW39: LS-1850V2-28P-EI-GL | BX39: 2345
A40: CPE90 | B40: 1176 | C40: 1680 | D40: 1740 | O40: SHELLY 120A CT PRO 3EM | P40: 346.38751 | R40: L009UIGS-RM | S40: 1610 | U40: GS1915-8EP | V40: 2645.676 | AA40: EX141 | AB40: 437 | AV40: BARPRO-WALLMOUNT | AW40: 1029 | BB40: 939-001802 | BC40: 12979 | BH40: ICD OPS I5 D | BI40: 15523 | BK40: RUTM30 | BL40: 7619 | BW40: LS-1850V2-52P-EI-GL | BX40: 4459
A41: CPN10 | B41: 423 | C41: N/A | D41: 348 | O41: SHELLY 400A CT PRO 3EM | P41: 1133.9825 | R41: L41G-2AXD | S41: 854 | U41: LTE7490 | V41: 4999 | AA41: EX511 | AB41: 626 | AV41: NEATBOARD-STYLUS-2PK | AW41: 2352 | BB41: 939-001805 | BC41: 20499 | BH41: ICD OPS I7 Z | BI41: 25237 | BK41: RUT951-POE | BL41: 4450 | BW41: LS-1850V2-28X-HPWR-GL | BX41: 7085
A42: CPW65 | B42: 3057 | C42: 4368 | D42: 5220 | O42: SHELLY 1 GEN3 | P42: 306.66128 | R42: L41G-2AXD&FG621-EA | S42: 1415 | AA42: HX141 | AB42: 497 | AV42: NEAT-ACTIVE-MARKER | AW42: 1712 | BB42: 939-001805-S | BC42: 20499 | BH42: IDH-TP | BI42: 448 | BK42: RUTX09 | BL42: 5080
A43: DD10K | B43: 258 | C43: N/A | D43: 348 | O43: OGEMRAY SMART RELAY 25A | P43: 672.53985 | R43: LHGGR&FG621-EA | S43: 2670 | AA43: HX510 | AB43: 795 | AV43: PULSE-PLUS-PAD1 | AW43: 951 | BB43: 939-001811 | BC43: 4089 | BH43: IHB2-65PU | BI43: 43763 | BK43: TSW210 | BL43: 1419
A44: EXP43 | B44: 1246 | C44: N/A | D44: 1722 | O44: SHELLY WAVE 1 | P44: 472.27458 | R44: MTAD-5G-30D3-PA | S44: 3232 | AA44: HX710 | AB44: 994 | AV44: PULSE-PLUS-PAD3 | AW44: 1888 | BB44: 939-001817 | BC44: 4359 | BH44: IHB2-75PU | BI44: 64152 | BK44: PR5MEC00 | BL44: 72
A45: EXP50 | B45: 1646 | C45: N/A | D45: 1827 | O45: SHELLY 1PM GEN4 | P45: 431.67358 | R45: MTP250-53V47-OD | S45: 1495 | AA45: M7450 | AB45: 1867 | AV45: PULSE-PRO-PAD1 | AW45: 1427 | BB45: 939-001950 | BC45: 16469 | BH45: IHB2-86PU | BI45: 87694 | BK45: PR3PREU6 | BL45: 114
A46: EXP55 | B46: 1364 | C46: 1949 | D46: 1914 | O46: SHELLY 1PM GEN3 | P46: 365.60807 | R46: QMP | S46: 96 | AA46: MC220L | AB46: 163 | AV46: PULSE-PRO-PAD3 | AW46: 3545 | BB46: 950-000005 | BC46: 2409 | BH46: IHB3-65SA | BI46: 49455 | BK46: EBD021 | BL46: 693
A47: PSU-MONO | B47: 105 | C47: N/A | D47: 174 | O47: SHELLY 2PM GEN4 | P47: 674.40727 | R47: QMP-LHG | S47: 96 | AA47: MR150 | AB47: 933 | AV47: PULSE-PLUS-PADPRO1 | AW47: 1484 | BB47: 950-000085 | BC47: 14329 | BH47: IHB3-75SA | BI47: 70038 | BK47: RUT976 | BL47: 6150
A48: PSU-COLOUR | B48: 129 | C48: N/A | D48: 261 | O48: SHELLY 80A CLAMP | P48: 266.87564 | R48: RB1100AHX4 | S48: 4837 | AA48: NX510V | AB48: 3570 | AV48: PULSE-PLUS-PADPRO3 | AW48: 3343 | BB48: 950-000085-S | BC48: 14329 | BH48: IHB3-86SA | BI48: 94070 | BK48: RUTC41 | BL48: 5426
A49: RT30 | B49: 1740 | C49: 2175 | D49: 2175 | O49: SHELLY 2PM GEN3 | P49: 533.44057 | R49: RB1100DX4 | S49: 5874 | AA49: OC200 | AB49: 1011 | AV49: PULSE-PRO-PADPRO1 | AW49: 2234 | BB49: 950-000086 | BC49: 14329 | BH49: IHC | BI49: 369
A50: SIP-T31G | B50: 893 | C50: 1276 | D50: 1374 | O50: SHELLY I4 GEN3 | P50: 258.1425 | R50: RB4011IGS+RM | S50: 3010 | AA50: OC300 | AB50: 2529 | AV50: PULSE-PRO-PADPRO3 | AW50: 5577 | BB50: 952-000002 | BC50: 1669 | BH50: IHS2-65SA | BI50: 61363
A51: SIP-T31P | B51: 752 | C51: 1075 | D51: 1131 | O51: SHELLY PRO DIMMER 2PM | P51: 1421.2997 | R51: RB5009UG+S+IN | S51: 2996 | AA51: PA4010 KIT | AB51: 511 | AV51: PULSE-PLUS-BARB-PLUS1 | AW51: 1153 | BB51: 952-000010 | BC51: 14339 | BH51: IHS2-75SA | BI51: 83881
A52: SIP-T31W | B52: 940 | C52: 1344 | D52: 1548 | O52: SHELLY PRO 3 | P52: 1426.7418 | R52: RB5009UPR+S+IN | S52: 4140 | AA52: POE150S | AB52: 189 | AV52: PULSE-PLUS-BARB-PLUS3 | AW52: 2565 | BB52: 952-000010-S | BC52: 15239 | BH52: IHS2-86SA | BI52: 112030
A53: SIP-T33G | B53: 964 | C53: 1377 | D53: 1896 | O53: SHELLY PRO 3EM SWITCH ADD-ON | P53: 385.45818 | R53: RB750GR3 | S53: 896 | AA53: RE450 | AB53: 678 | AV53: PULSE-PRO-BARB-PRO1 | AW53: 1700 | BB53: 952-000019 | BC53: 7589 | BH53: IHS3-65SA | BI53: 56268
A54: SIP-T34W | B54: 1129 | C54: 1612 | D54: 2523 | O54: SHELLY BYPASS FOR DIMMER GEN3 | P54: 77.218723 | R54: RB750R2 | S54: 639 | AA54: SM311LS | AB54: 176 | AV54: PULSE-PRO-BARB-PRO3 | AW54: 4280 | BB54: 952-000020 | BC54: 1479 | BH54: IHS3-75SA | BI54: 76917
A55: SIP-T43U | B55: 1398 | C55: 2251 | D55: 2940 | O55: SHELLY 50A CLAMP EM GEN3 | P55: 237.77358 | R55: RB750UPR2 | S55: 896 | AA55: TL-MR100 | AB55: 645 | AV55: PULSE-PLUS-BAR2-1 | AW55: 4597 | BB55: 952-000038 | BC55: 6189 | BH55: ISK | BI55: 2243
A56: SIP-T44U | B56: 1576 | C56: 2251 | D56: 2940 | O56: SHELLY BLU BUTTON TOUGH 1 MOCH | P56: 309.13547 | R56: RB760IGS | S56: 1090 | AA56: TL-R480T+ | AB56: 663 | AV56: PULSE-PLUS-BAR2-3 | AW56: 10348 | BB56: 952-000041 | BC56: 3669 | BH56: WB1M0BRACKET01 | BI56: 892
A57: SIP-T44W | B57: 1648 | C57: 2688 | D57: 3288 | O57: SHELLY FLOOD GEN4 | P57: 490.41455 | R57: RB912R-2ND-LTM&EC200A-EU | S57: 1495 | AA57: TL-SG1005P | AB57: 505 | AV57: PULSE-PRO-BAR2-1 | AW57: 6903 | BB57: 952-000044 | BC57: 2039 | BH57: WB1M0IDEAHUB07 | BI57: 5164
A58: SIP-T46U | B58: 2375 | C58: 3393 | D58: 4158 | O58: SHELLY LEAK SENSOR CABLE | P58: 116.17143 | R58: RB924I-2ND-BT5&BG77 | S58: 1503 | AA58: TL-SG1008P | AB58: 631 | AV58: PULSE-PRO-BAR2-3 | AW58: 17251 | BB58: 952-000047 | BC58: 3849 | BH58: WB1M0IDEAHUB07-001 | BI58: 5164
A59: SIP-T48U | B59: 2849 | C59: 4603 | D59: 5550 | O59: FRANKEVER SMART VALVE DN20 | P59: 2360.4727 | R59: RB941-2ND-TC | S59: 368 | AA59: TL-SG1210MPE | AB59: 1390 | AV59: PULSE-PLUS-BARPRO1 | AW59: 6745 | BB59: 952-000057 | BC59: 1179
A60: SIP-T57W | B60: 3299 | C60: 5645 | D60: 6246 | O60: SHELLY WALL DISPLAY XL BLACK | P60: 5388.3653 | R60: RB951UI-2HND | S60: 896 | AA60: TL-SG1210P | AB60: 1011 | AV60: PULSE-PLUS-BARPRO3 | AW60: 15176 | BB60: 952-000057-S | BC60: 1179
A61: SIP-T73U | B61: 1576 | C61: 2251 | D61: 2940 | O61: FRANKEVER SPRINKLER FK-06X | P61: 1988.1901 | R61: RB951UI-2ND | S61: 662 | AA61: TL-SG1218MPE | AB61: 2592 | AV61: PULSE-PRO-BARPRO1 | AW61: 10117 | BB61: 952-000074 | BC61: 1639
A62: SIP-T73W | B62: 1787 | C62: 2553 | D62: 3288 | O62: ECOWITT WEATHER STATION WS90 | P62: 3493.0327 | R62: RB952UI-5AC2ND | S62: 854 | AA62: TL-SG2210MP | AB62: 2023 | AV62: PULSE-PRO-BARPRO3 | AW62: 25293 | BB62: 952-000080 | BC62: 4429
A63: SIP-T74U | B63: 2375 | C63: 3393 | D63: 4158 | O63: SHELLY 2L GEN3 | P63: 708.37108 | R63: RB952UI-5AC2ND-TC | S63: 854 | AA63: TL-SG2428P | AB63: 3351 | AV63: PULSE-PLUS-BOARD32-1 | AW63: 4367 | BB63: 952-000085 | BC63: 11639
A64: SIP-T74W | B64: 2611 | C64: 3730 | D64: 4506 | O64: SHELLY WALL DISPLAY X2i BLACK | P64: 3283.5927 | R64: RB960PGS | S64: 1345 | AA64: TL-SG3210 | AB64: 1201 | AV64: PULSE-PLUS-BOARD32-3 | AW64: 9829 | BB64: 952-000088 | BC64: 11719
A65: SIP-T77U | B65: 3222 | C65: 4603 | D65: 5550 | O65: SHELLY WALL DISPLAY X2i SILVER | P65: 3283.5927 | R65: RB962UIGS-5HACT2HNT | S65: 2023 | AA65: TL-SG3428 | AB65: 2213 | AV65: PULSE-PLUS-BOARD32-5 | AW65: 16386 | BB65: 952-000091 | BC65: 12959
A66: SIP-T85W | B66: 2728 | C66: 3898 | D66: 5376 | R66: RBCAP2ND | S66: 747 | AA66: TL-SG3428MP | AB66: 4110 | AV66: PULSE-PRO-BOARD32-1 | AW66: 6557 | BB66: 952-000094 | BC66: 15819
A67: SIP-T87W | B67: 3951 | C67: 5645 | D67: 6246 | R67: RBCAPGI-5ACD2ND | S67: 1312 | AA67: TL-SG3428X | AB67: 2845 | AV67: PULSE-PRO-BOARD32-3 | AW67: 16386 | BB67: 952-000097 | BC67: 2479
A68: SIP-T88V | B68: 6068 | C68: 8669 | D68: 9900 | R68: RBCAPL-2ND | S68: 427 | AA68: TL-SG3428XMP | AB68: 5059 | AV68: PULSE-PRO-BOARD32-5 | AW68: 27310 | BB68: 952-000105 | BC68: 979
A69: SIP-T88V PRO | B69: 6586 | C69: 9409 | D69: 10770 | R69: RBD25G-5HPACQD2HPND | S69: 2520 | AA69: TL-SG3428XPP-M2 | AB69: 8221 | AV69: PULSE-PLUS-BOARD50-1 | AW69: 6903 | BB69: 952-000105-S | BC69: 859
A70: SIP-T88W | B70: 4892 | C70: 6989 | D70: 7986 | R70: RBD52G-5HACD2HND-TC | S70: 1061 | AA70: TL-SG3452P | AB70: 6956 | AV70: PULSE-PLUS-BOARD50-3 | AW70: 15536 | BB70: 952-000123 | BC70: 2309
A71: SIP-T88W PRO | B71: 5386 | C71: 7695 | D71: 8856 | R71: RBD53IG-5HACD2HND | S71: 1644 | AA71: TL-SG3452XP | AB71: 8853 | AV71: PULSE-PRO-BOARD50-1 | AW71: 10376 | BB71: 952-000126 | BC71: 2409
A72: VP59 | B72: 7598 | C72: 12198 | D72: 13902 | R72: RBFTC11 | S72: 576 | AA72: TL-WN725N | AB72: 99 | AV72: PULSE-PRO-BOARD50-3 | AW72: 25898 | BB72: 952-000127 | BC72: 2239
A73: W56H | B73: 1176 | C73: 1548 | D73: 1548 | R73: RBGPOE | S73: 85 | AA73: UB500 | AB73: 92 | AV73: PULSE-PLUS-BOARDPRO-1 | AW73: 8647 | BB73: 952-000181 | BC73: 2279
A74: W57R | B74: 1764 | C74: 2520 | D74: 3114 | R74: RBGPOE-CON-HP | S74: 469 | AA74: VIGI C220I(2.8MM) | AB74: 471 | AV74: PULSE-PLUS-BOARDPRO-3 | AW74: 19456 | BB74: 952-000195 | BC74: 3629
A75: W59R | B75: 1798 | C75: 2940 | D75: 2940 | R75: RBLHG-5HPND-XL4PACK | S75: 5895 | AA75: VIGI C230I MINI(2.8MM) | AB75: 648 | AV75: PULSE-PRO-BOARDPRO-1 | AW75: 12971 | BB75: 952-000199 | BC75: 15839
A76: W59R PRO | B76: 2069 | C76: 2940 | D76: 2940 | R76: RBPOE | S76: 46 | AA76: VIGI C240(2.8MM) | AB76: 707 | AV76: PULSE-PRO-BOARDPRO-3 | AW76: 32426 | BB76: 952-000251 | BC76: 48709
A77: W70B | B77: 940 | C77: 1344 | D77: 1374 | R77: RBSXTSQG-5ACD | S77: 961 | AA77: VIGI C250(4MM) | AB77: 766 | AV77: PULSE-PLUS-FRAME1 | AW77: 692 | BB77: 960-000867 | BC77: 3899
... A84: W78H | B84: 1552 | C84: 2217 | D84: 2592 | R84: S-3553LC20D | S84: 1046 | AA84: VIGI C340I(4MM) | AB84: 530 | AV84: PULSE-PRO-CENTER3 | AW84: 9900 | BB84: 960-001227 | BC84: 17729
A85: W78P | B85: 2234 | C85: 3192 | D85: 3810 | R85: S53UG+5HAXD2HAXD-TC&FG621-EA | S85: 2814 | AA85: VIGI C340-W(4MM) | AB85: 884 | BB85: 960-001230 | BC85: 5329
A86: W80B | B86: 3293 | C86: 4704 | D86: 6942 | R86: S-85DLC05D | S86: 256 | AA86: VIGI C430I(2.8MM) | AB86: 453 | BB86: 960-001237 | BC86: 37809
A87: W80B-DM | B87: 3293 | C87: 4704 | D87: 6942 | R87: SAW30-240-1200GR2A | S87: 149 | AA87: VIGI C540(4MM) | AB87: 1002 | BB87: 960-001240 | BC87: 40089
A88: W90B | B88: 3498 | C88: 5544 | D88: 8160 | R88: S-RJ01 | S88: 427 | AA88: VIGI NVR1008H | AB88: 855 | BB88: 960-001242 | BC88: 45639
A89: W90DM | B89: 3881 | C89: 5544 | D89: 8160 | R89: TG-BT5-IN | S89: 149 | AA89: VIGI NVR1008H-8P | AB89: 1415 | BB89: 960-001313 | BC89: 64289
A90: WF40 | B90: 352 | C90: N/A | D90: 504 | R90: XQ+31LC10D | S90: 5212 | AA90: VIGI NVR1016H | AB90: 943 | BB90: 960-001332 | BC90: 20909
A91: WF50 | B91: 423 | C91: N/A | D91: 609 | R91: XS+31LC10D | S91: 2136 | AA91: VIGI NVR2016H | AB91: 1828 | BB91: 960-001341 | BC91: 47639
A92: YLPOE30 | B92: 470 | C92: N/A | D92: 1026 | R92: RB3011UiAS-RM | S92: -- | AA92: VIGI NVR2016H-16P | AB92: 3067 | BB92: 960-001360 | BC92: 1659
A93: BH70-MONO-USB-C/A | B93: 1289 | C93: 1842 | D93: 2940 | R93: D53G-5HacD2HnD-TC&EG120K-EA | S93: 2776 | AA93: VIGI NVR4032H | AB93: 4011 | BB93: 960-001459 | BC93: 2019
A94: BH70-DUAL-USB-C/A | B94: 1528 | C94: 2183 | D94: 3288 | R94: ATLGM&EG18-EA | S94: 4522 | AA94: W8961N | AB94: 272 | BB94: 960-001469 | BC94: 899
A95: BH71 LITE | B95: 1074 | C95: 1305 | D95: 1305 | R95: CRS106-1C-5S | S95: 870 | AA95: WA850RE | AB95: 272 | BB95: 960-001510 | BC95: 31269
A96: BH71 PRO USB-C/A | B96: 1671 | C96: 2388 | D96: 4315 | R96: E60iUGS | S96: 950 | AA96: WA855RE | AB96: 251 | BB96: 960-001530 | BC96: 3079
A97: BH71 WORKSTATION | B97: 3152 | C97: 4503 | D97: 5462 | AA97: WN722N | AB97: 142 | BB97: 960-001572 | BC97: 27219
A98: BH71 WORKSTATION PRO USB-C/A | B98: 4060 | C98: 5800 | D98: 6558 | AA98: WN881ND | AB98: 178 | BB98: 960-001592 | BC98: 449
A99: BH74 TEAMS USB-C/A | B99: 1719 | C99: 2456 | D99: 3393 | AA99: WPA4220 KIT | AB99: 750 | BB99: 960-001681 | BC99: 16359
A100: BH76-PLUS-USB C/A | B100: 2388 | C100: 3411 | D100: 5550 | AA100: WR840N | AB100: 204 | BB100: 960-001724 | BC100: 2609
A101: BHC76 | B101: 859 | C101: N/A | D101: 1370 | AA101: WR850N | AB101: 210 | BB101: 960-001751 | BC101: 131119
A102: BLT60 | B102: 238 | C102: N/A | D102: 365 | AA102: TL-SG1008D | AB102: 271 | BB102: 981-000406 | BC102: 419
A103: BT41 | B103: 358 | C103: N/A | D103: 504 | AA103: VIGI C340(2.8mm) | AB103: 678 | BB103: 981-000475 | BC103: 379
A104: BT51-A | B104: 358 | C104: N/A | D104: 504 | AA104: InSight S345ZI | AB104: 2123 | BB104: 981-000519 | BC104: 1079
A105: BT51-A-S | B105: 358 | C105: N/A | D105: 504 | AA105: EAP215-Bridge KIT | AB105: 1584 | BB105: 981-000571 | BC105: 809
A106: BT51-C | B106: 358 | C106: N/A | D106: 504 | AA106: SG2005P-PD | AB106: 1137 | BB106: 981-000575 | BC106: 999
...

Sheet Categories
B2: Gauteng Tel: 010 824 0040 E-mail: sales@nology.co.za Cape Town Tel: 010 824 0044 E-mail: cptsales@nology.co.za
B9: CONSUMER | D9: NETWORKING | F9: UNIFIED COMMUNICATIONS
B26: E & OE Terms & Conditions: Pricing valid from 1 April 2026 until 30 April 2026. All pricing is Exclusive of VAT and subject to stock availability and lead times. Pricing is subject to change without notice and is linked to the exchange rate. CLICK HERE to view our full Terms and Conditions.

Sheet EOL Products
F1: Return
B6: END OF LIFE PRODUCTS
B12: SKU | C12: DESCRIPTION | D12: REPLACEMENT SKU | E12: REPLACEMENT DESCRIPTION | F12: COMMENTS
B13: D53G-5HacD2HnD-TC&RG502Q-EA | C13: Chateau 5G kit with 716MHz four core CPU, 256MB RAM, 5 x Gigabit LAN, two wireless interfaces (built-in 2.4Ghz 802.11b/g/n two chain wireless with integrated antennas, built-in 5Ghz 802.11ac two chain wireless with integrated antennas), RG502Q-EA LTE/5G modem for bands 1/3/5/7/8/18/19/20/26/28/32/34/38/39/40/41/42/43/77/78/79, two external and six internal LTE/5G antennas, tower case, USB, 1m RJ45 cable, PSU, RouterOS L4 | D13: S53UG+5HaxD2HaxD-TC&FG621-EA | E13: Chateau LTE6 ax with 1.8GHz four core CPU, 1GB RAM, 1 x 2.5 Gigabit LAN, 4 x Gigabit LAN, two wireless interfaces (built-in 2.4Ghz 802.11b/g/n/ax two chain wireless, built-in 5Ghz 802.11a/n/ac/ax two chain wireless) with external antennas, LTE CAT6 modem for International bands 1/3/5/7/8/20/28/38/40/41 with integrated antennas, SMA connectors for external antennas, tower case, USB, PSU, RouterOS L4, International version | F13: EOL
B14: MTAS-5G-15D120 | C14: MikroTik Dual-polarization 5Ghz 15dBi 120 degree beamwidth antenna with two RP-SMA connectors | D14: L22UGS-5HaxD2HaxD-15S (mANTBox ax 15s) | E14: mANTBox ax 15s with with dual-core ARM IPQ-5010 800MHz CPU, 256MB RAM, 1x2.5Gigabit SFP port, 1xGigabit LAN, built-in dual-band 2.4GHz 802.11b/g/n/ax dual-chain, 5GHz 802.11a/n/ac/ax dual-chain wireless, USB, RouterOS L4, outdoor enclosure, PSU, Gigabit PoE injector, pole mounting set (metal ring, quickMOUNT pro), integrated 2.4GHz 12 dBi and 5GHz 15 dBi sector antenna | F14: EOL
B15: RBLHGR | C15: MikroTik LHG 2G/3G/4G/LTE High Gain 17dBi CPE for Very Remote Areas (International Bands) | D15: LHGGR&FG621-EA | E15: LHGG LTE6 kit with 17dBi 25 degrees LTE directional antenna, 800MHz dual-core CPU, 256MB RAM, 1 x Gigabit Ethernet port (802.3af/at PoE-in), LTE CAT6 modem (R11eL-FG621-EA) for International bands 1/3/5/7/8/20/28/38/40/41, RouterOS L3, outdoor enclosure, PSU, PoE injector, pole mounting bracket | F15: EOL
B16: MTAD-5G-30D3-4STD | C16: MikroTik MTAD-5G-30D3-4STD Parabolic dish antenna for 5GHz, 30dBi gain (4-pack) | D16: MTAD-5G-30D3-4PA | E16: mANT 30dBi 5Ghz Parabolic Dish antenna with precision aligmnent mount, 4-pack (all four antennas in single box) | F16: EOL
B17: RBwAPR-2nD&R11e-LR8 | C17: MikroTik wAP LR8 Kit 2.4Ghz 2dBi LoraWAN Gateway | D17: RBwAPR-2nD&R11e-LR8G | E17: wAP LR8G kit for 863-870MHz frequency (European Union, India etc.) - 650MHz CPU, 64MB RAM, 1xLAN, built-in 2.4Ghz 802.11b/g/n Dual Chain wireless with integrated antenna, R11e-LR8G card, LoRa internal antenna with connector, RouterOS L4, outdoor enclosure, PSU, PoE injector | F17: EOL
B18: LtAP-2HnD&FG621-EA&LR8 | C18: MikroTik LtAP LR8 LTE kit with dual core 880MHz CPU, 128MB RAM, 1 x Gigabit LAN, built-in High Power 2.4Ghz 802.11b/g/n Dual Chain wireless with integrated antenna, LTE CAT6 modem for International bands 1/3/5/7/8/20/28/38/40/41 with with internal LTE antenna, GPS, LoRa miniPCI-e card for 863-870MHz frequency (European Union, India etc) with connector for external antenna, three miniSIM slots, RouterOS L4, outdoor enclosure, PSU | D18: LtAP-2HnD&FG621-EA&LR8G | E18: LtAP LR8G LTE kit with dual core 880MHz CPU, 128MB RAM, 1 x Gigabit LAN, built-in High Power 2.4Ghz 802.11b/g/n Dual Chain wireless with integrated antenna, LTE CAT6 modem for International bands 1/3/5/7/8/20/28/38/40/41 with with internal LTE antenna, GPS, LoRa R11e-LR8G miniPCI-e card for 863-870MHz frequency (European Union, India etc) with connector for external antenna, three miniSIM slots, RouterOS L4, outdoor enclosure, PSU | F18: EOL
B19: RB3011UiAS-RM | C19: MikroTik RouterBOARD RB3011UiAS, 10x GB LAN, 1x SFP port, RouterOS L5, 1U rACkmount case, LCD panel | D19: L009UiGS-RM, | E19: L009UiGS with dual core 800MHz CPU, 512MB RAM, 8 x Gbit LAN, 1 x 2.5 Gbit SFP port, USB, desktop/1U rackmount case, PSU, K-79 rackmount kit, RouterOS L5 | F19: EOL
B20: RB3011UiAS-RM | C20: MikroTik RouterBOARD RB3011UiAS, 10x GB LAN, 1x SFP port, RouterOS L5, 1U rACkmount case, LCD panel | D20: RB4011iGS+RM | E20: RouterBOARD 4011iGS+ with Annapurna Alpine AL21400 Cortex A15 CPU (4-cores, 1.4GHz per core), 1GB RAM, 10xGbit LAN, 1xSFP+ port, RouterOS L5, desktop case, rackmount ears, PSU | F20: EOL
B21: RB3011UiAS-RM | C21: MikroTik RouterBOARD RB3011UiAS, 10x GB LAN, 1x SFP port, RouterOS L5, 1U rACkmount case, LCD panel | D21: RB5009UG+S+IN | E21: RouterBORD 5009UG+S+ with Marvell Armada ARMv8 CPU (4-cores, 1.4GHz per core), 1GB of DDR4 RAM, 1GB NAND storage, 1x 2.5Gbit LAN, 7x 1Gbit LAN, 1x SFP+ port, RouterOS L5, metal desktop case, PSU | F21: EOL
B23: SIP PHONES
B24: SIP-T43U | C24: Yealink T43U Advanced Gb IP Phone With Dual USB Ports, Excludes PSU | D24: SIP-T73U | E24: Yealink T73U Gb IP Phone With USB Port, Excludes PSU | F24: EOL / Last Stock Replacement Available
B25: SIP-T44W | C25: Yealink T44W Gigabit Desktop IP Phone With Built-in Wi-Fi, Bluetooth And Dual USB Ports, Excludes PSU | D25: SIP-T73W | E25: Yealink T73W Multifunctional SIP Phone, Wi-Fi, Built-in Bluetooth, PoE support, Excludes PSU | F25: EOL / Last Stock Replacement Available
B26: SIP-T48U | C26: Yealink T48U Gb IP Phone With 7" Touch LCD And Dual USB Ports, Excludes PSU | D26: SIP-T77U | E26: Yealink T77U SIP Phone With 7" Touch Screen, Dual-port Gigabit Ethernet, PoE Support, Dual USB Ports | F26: EOL / Last Stock Replacement Available
B27: SIP-T57W | C27: Yealink T57W Dual Band IP Desktop Phone, Excludes PSU | D27: SIP-T87W | E27: Yealink T87W Prime Business Phone, 7" Touch Screen, Built-In Bluetooth, Wi-Fi, PoE Support, Excludes PSU | F27: EOL / Last Stock Replacement Available
B28: IP CONFERENCE PHONES
B29: CPW65 | C29: Yealink CPW65 Wireless DECT Microphones For CP965 | F29: EOL / LAST STOCK
B30: USB HEADSETS
B31: UH34-SE-MONO-USBC | C31: Yealink UH34 Mono Headset Special Edition With USB-C Connection, Teams Edition | D31: UH42 MONO TEAMS USB-C/A | E31: Yealink UH42 Mono USB Headset, USB-C With USB-C/A Adapter, Teams Certified | F31: EOL / Last Stock Replacement Available
B32: UH34-SE-DUAL-USBC | C32: Yealink UH34 Dual Headset Special Edition With USB-C Connection, Teams Edition | D32: UH42 DUAL TEAMS USB-C/A | E32: Yealink UH42 Dual USB Headset, USB-C With USB-C/A Adapter, Teams Certified | F32: EOL / Last Stock Replacement Available
B33: UH36-MONO-USBC | C33: Yealink UH36 Mono Headset With USB-C Connection (EOL) | D33: UH37 MONO TEAMS USB-C/A | E33: Yealink UH37 Mono USB Headset, USB-C With USB-C/A Adapter, Teams Certified | F33: EOL / Last Stock Replacement Available
B34: UH37 MONO TEAMS USB-C/A | C34: Yealink UH37 Mono USB Headset, USB-C With USB-C/A Adapter, Teams Certified | D34: UH46 MONO TEAMS USB-C/A | E34: Yealink UH46 Mono USB Headset, USB-C With USB-C/A Adapter, Teams Certified | F34: EOL / Last Stock Replacement Available
B35: UH37 DUAL TEAMS USB-C/A | C35: Yealink UH37 Dual USB Headset, USB-C With USB-C/A Adapter, Teams Certified | D35: UH46 DUAL TEAMS USB-C/A | E35: Yealink UH46 Dual USB Headset, USB-C With USB-C/A Adapter, Teams Certified | F35: EOL / Last Stock Replacement Available
B36: DECT WIRELESS HEADSETS
B37: WH62-DUAL | C37: Yealink WH62-Dual DECT Wireless On Ear Dual Headset (EOL) | F37: EOL / LAST STOCK
B38: WH64-HYBRID-MONO | C38: Yealink WH64 Hybrid Mono DECT And Bluetooth Hybrid Wireless Headset, Teams Certified, Includes Dongle, Does Not Include Stand | F38: EOL / LAST STOCK
B39: WH68 HYBRID TEAMS | C39: Yealink WH68 Hybrid DECT Wireless Headset, Teams Certified | F39: EOL / LAST STOCK
B40: RJ-9 HEADSETS
B41: YHS34-LITE-MONO | C41: Yealink YHS34 Lite Mono Headset With RJ-9 And Foam Ear Cushions | D41: YHS34-MONO | E41: =VLOOKUP(D41,[1]Yealink!B:G,2,0) -> Yealink YHS34 Mono Headset With RJ-9 And Leatherette Ear Cushions | F41: EOL / Last Stock Replacement Available
B42: YHS34-LITE-DUAL | C42: Yealink YHS34 Lite Dual Headset With RJ-9 And Foam Ear Cushions | D42: YHS34-DUAL | E42: =VLOOKUP(D42,[1]Yealink!B:G,2,0) -> Yealink YHS34 Dual Headset With RJ-9 And Leatherette Ear Cushions | F42: EOL / Last Stock Replacement Available
B43: YHS36-MONO | C43: Yealink YHS36 Mono Headset With RJ-9 And Leatherette Ear Cushions | D43: YHS36 E2 MONO | E43: Yealink YHS36 E2 Mono Headset With RJ-9 And noise Cancelling Microphone And Leatherette Ear Cushions | F43: EOL / Last Stock Replacement Coming Soon
B44: YHS36-DUAL | C44: Yealink YHS36 Dual Headset With RJ-9 And Leatherette Ear Cushions | D44: YHS36 E2 DUAL | E44: Yealink YHS36 E2 Dual Headset With RJ-9 And Noise Cancelling Microphone And Leatherette Ear Cushions | F44: EOL / Last Stock Replacement Coming Soon
B47: SHELLY BLU BUTTON1 (BLACK) | C47: Shelly BLU Button1 (Black) Bluetooth Button For Operated Actions And Scene Activation | F47: EOL, last stock PROMOTION
B48: SHELLY BLU BUTTON1 (BLUE) | C48: Shelly BLU Button1 (Blue) Bluetooth Button For Operated Actions And Scene Activation | F48: EOL, last stock PROMOTION
B49: SHELLY BLU BUTTON1 (RED) | C49: Shelly BLU Button1 (Red) Bluetooth Button For Operated Actions And Scene Activation | F49: EOL, last stock PROMOTION
B50: SHELLY DUO CW/WW (E27) | C50: Shelly Duo CW/WW (E27) Smart Cool Or Warm White Dimmable Bulb | F50: EOL, last stock PROMOTION
B51: SHELLY VINTAGE A60 (E27) | C51: Shelly Vintage A60 (E27) Dimmable Smart Bulb | F51: EOL, last stock PROMOTION
B52: SHELLY VINTAGE G125 (E27) | C52: Shelly Vintage G125 (E27) Dimmable Smart Bulb | F52: EOL, last stock PROMOTION
B53: SHELLY WALL DISPLAY+BLU H&T(W) | C53: Shelly Wall Display + Blu H&T (White) Smart Control Panel With Temperature, Humidity & LUX Sensors | F53: EOL / Last Stock Replacement Coming Soon
B56: USB Headset
B57: 994-000082 | C57: Logitech JumpStart | F57: EOL
B60: PORTABLE POWER STATIONS
B61: PV120 | C61: Bluetti PV120 Solar Panel 120W | F61: EOL, last stock
B63: PORTABLE POWER STATIONS
B64: VILO-5-3 | C64: Vilo Mesh Wi-Fi 5 System, 1 Pack | F64: EOL, last stock
B65: E & OE Terms & Conditions: Pricing valid from 1 April 2026 until 30 April 2026. All pricing is Exclusive of VAT and subject to stock availability and lead times. Pricing is subject to change without notice and is linked to the exchange rate. CLICK HERE to view our full Terms and Conditions.

Sheet Promotions
H1: Return
B6: PROMOTIONS
C9: YEALINK VOICE PROMOTION
C10: SKU | D10: DESCRIPTION | E10: PRICE | F10: Suggested advertising price | G10: MSRP | H10: COMMENTS
C11: IP DESKTOP PHONES
C12: SIP-T48U | D12: Yealink T48U Gb IP Phone With 7" Touch LCD And Dual USB Ports, Excludes PSU | E12: =_xlfn.XLOOKUP(C12,PRICING!A:A,PRICING!B:B,"No Record",0,1) -> 2849 | F12: =INDEX(PRICING!C:C,MATCH(C12,PRICING!A:A,0),1) -> 4603 | G12: =INDEX(PRICING!D:D,MATCH(C12,PRICING!A:A,0),1) -> 5550 | H12: PROMOTION + Extra 5% discount when ordering 5 or more units
C13: SIP-T44W | D13: Yealink T44W Gigabit Desktop IP Phone With Built-in Wi-Fi, Bluetooth And Dual USB Ports, Excludes PSU | E13: =_xlfn.XLOOKUP(C13,PRICING!A:A,PRICING!B:B,"No Record",0,1) -> 1648 | F13: =INDEX(PRICING!C:C,MATCH(C13,PRICING!A:A,0),1) -> 2688 | G13: =INDEX(PRICING!D:D,MATCH(C13,PRICING!A:A,0),1) -> 3288 | H13: PROMOTION + Extra 5% discount when ordering 5 or more units
C14: SIP-T43U | D14: Yealink T43U Advanced Gb IP Phone With Dual USB Ports, Excludes PSU | E14: =_xlfn.XLOOKUP(C14,PRICING!A:A,PRICING!B:B,"No Record",0,1) -> 1398 | F14: =INDEX(PRICING!C:C,MATCH(C14,PRICING!A:A,0),1) -> 2251 | G14: =INDEX(PRICING!D:D,MATCH(C14,PRICING!A:A,0),1) -> 2940 | H14: PROMOTION + Extra 5% discount when ordering 5 or more units
C15: SIP-T57W | D15: Yealink T57W Dual Band IP Desktop Phone, Excludes PSU | E15: =_xlfn.XLOOKUP(C15,PRICING!A:A,PRICING!B:B,"No Record",0,1) -> 3299 | F15: =INDEX(PRICING!C:C,MATCH(C15,PRICING!A:A,0),1) -> 5645 | G15: =INDEX(PRICING!D:D,MATCH(C15,PRICING!A:A,0),1) -> 6246 | H15: PROMOTION + Extra 5% discount when ordering 5 or more units
C16: IP VIDEO PHONE
C17: VP59 | D17: Yealink VP59 Video Phone For Video Conference Calls, Excludes PSU | E17: =_xlfn.XLOOKUP(C17,PRICING!A:A,PRICING!B:B,"No Record",0,1) -> 7598 | F17: =INDEX(PRICING!C:C,MATCH(C17,PRICING!A:A,0),1) -> 12198 | G17: =INDEX(PRICING!D:D,MATCH(C17,PRICING!A:A,0),1) -> 13902 | H17: PROMOTION
C18: IP CONFERENCE PHONE
C19: CP965 | D19: Yealink CP965 Android IP Conference Phone (SIP ONLY) | E19: =_xlfn.XLOOKUP(C19,PRICING!A:A,PRICING!B:B,"No Record",0,1) -> 7399 | F19: =INDEX(PRICING!C:C,MATCH(C19,PRICING!A:A,0),1) -> 12769 | G19: =INDEX(PRICING!D:D,MATCH(C19,PRICING!A:A,0),1) -> 15642 | H19: PROMOTION
C20: IP DECT PHONE
C21: W59R | D21: Yealink W59R Rugged DECT Handset IP67 | E21: =_xlfn.XLOOKUP(C21,PRICING!A:A,PRICING!B:B,"No Record",0,1) -> 1798 | F21: =INDEX(PRICING!C:C,MATCH(C21,PRICING!A:A,0),1) -> 2940 | G21: =INDEX(PRICING!D:D,MATCH(C21,PRICING!A:A,0),1) -> 2940 | H21: PROMOTION
C22: W90B | D22: Yealink W90B Multi-Cell DECT Base Station | E22: =_xlfn.XLOOKUP(C22,PRICING!A:A,PRICING!B:B,"No Record",0,1) -> 3498 | F22: =INDEX(PRICING!C:C,MATCH(C22,PRICING!A:A,0),1) -> 5544 | G22: =INDEX(PRICING!D:D,MATCH(C22,PRICING!A:A,0),1) -> 8160 | H22: PROMOTION
C23: MP PHONE
C24: MP52 E2 | D24: Yealink MP52 E2 Basic Phone For Microsoft Teams Excludes PSU | E24: =_xlfn.XLOOKUP(C24,PRICING!A:A,PRICING!B:B,"No Record",0,1) -> 2199 | F24: =INDEX(PRICING!C:C,MATCH(C24,PRICING!A:A,0),1) -> 4110 | G24: =INDEX(PRICING!D:D,MATCH(C24,PRICING!A:A,0),1) -> 3984 | H24: PROMOTION
C25: USB HEADSETS
C26: UH34-MONO | D26: Yealink UH34 Mono Single Earpiece USB Headset With Leatherette Ear Cushions Teams Edition | E26: =_xlfn.XLOOKUP(C26,PRICING!A:A,PRICING!B:B,"No Record",0,1) -> 369 | F26: =INDEX(PRICING!C:C,MATCH(C26,PRICING!A:A,0),1) -> 614 | G26: =INDEX(PRICING!D:D,MATCH(C26,PRICING!A:A,0),1) -> 895 | H26: PROMOTION
C27: UH34-DUAL | D27: Yealink UH34 Dual Earpiece USB Headset With Leatherette Ear Cushions Teams Edition | E27: =_xlfn.XLOOKUP(C27,PRICING!A:A,PRICING!B:B,"No Record",0,1) -> 499 | F27: =INDEX(PRICING!C:C,MATCH(C27,PRICING!A:A,0),1) -> 835 | G27: =INDEX(PRICING!D:D,MATCH(C27,PRICING!A:A,0),1) -> 1200 | H27: PROMOTION
C28: UH34-SE-DUAL-USBC | D28: Yealink UH34 Dual Headset Special Edition With USB-C Connection, Teams Edition | E28: =_xlfn.XLOOKUP(C28,PRICING!A:A,PRICING!B:B,"No Record",0,1) -> 599 | F28: =INDEX(PRICING!C:C,MATCH(C28,PRICING!A:A,0),1) -> 989 | G28: =INDEX(PRICING!D:D,MATCH(C28,PRICING!A:A,0),1) -> 1653 | H28: PROMOTION
C29: UH34 SE DUAL USB A | D29: Yealink UH34 Dual Headset Special Edition With USB-A, 3.5mm jack Connection, Teams edition | E29: =_xlfn.XLOOKUP(C29,PRICING!A:A,PRICING!B:B,"No Record",0,1) -> 579 | F29: =INDEX(PRICING!C:C,MATCH(C29,PRICING!A:A,0),1) -> 955 | G29: =INDEX(PRICING!D:D,MATCH(C29,PRICING!A:A,0),1) -> 1600 | H29: PROMOTION
C30: UH36-MONO-USBC | D30: Yealink UH36 Mono Headset With USB-C Connection | E30: =_xlfn.XLOOKUP(C30,PRICING!A:A,PRICING!B:B,"No Record",0,1) -> 669 | F30: =INDEX(PRICING!C:C,MATCH(C30,PRICING!A:A,0),1) -> N/A | G30: =INDEX(PRICING!D:D,MATCH(C30,PRICING!A:A,0),1) -> N/A | H30: PROMOTION
C31: DECT WIRELESS HEADSETS
C32: WH66-MONO | D32: Yealink WH66 Mono DECT Wireless On Ear Mono Headset With Touch Screen Base Station | E32: =_xlfn.XLOOKUP(C32,PRICING!A:A,PRICING!B:B,"No Record",0,1) -> 3198 | F32: =INDEX(PRICING!C:C,MATCH(C32,PRICING!A:A,0),1) -> 5049 | G32: =INDEX(PRICING!D:D,MATCH(C32,PRICING!A:A,0),1) -> 6010 | H32: PROMOTION
C33: WH66-DUAL | D33: Yealink WH66 Dual DECT Wireless On Ear Stereo Headset With Touch Screen Base Station | E33: =_xlfn.XLOOKUP(C33,PRICING!A:A,PRICING!B:B,"No Record",0,1) -> 3398 | F33: =INDEX(PRICING!C:C,MATCH(C33,PRICING!A:A,0),1) -> 5458 | G33: =INDEX(PRICING!D:D,MATCH(C33,PRICING!A:A,0),1) -> 6558 | H33: PROMOTION
C34: WH67 | D34: Yealink WH67 DECT Wireless Convertible Headset With Touch Screen Base Station | E34: =_xlfn.XLOOKUP(C34,PRICING!A:A,PRICING!B:B,"No Record",0,1) -> 2999 | F34: =INDEX(PRICING!C:C,MATCH(C34,PRICING!A:A,0),1) -> 4844 | G34: =INDEX(PRICING!D:D,MATCH(C34,PRICING!A:A,0),1) -> 5828 | H34: PROMOTION
C35: WH68 HYBRID TEAMS | D35: Yealink WH68 Hybrid DECT Wireless Headset, Teams Certified | E35: =_xlfn.XLOOKUP(C35,PRICING!A:A,PRICING!B:B,"No Record",0,1) -> 1999 | F35: =INDEX(PRICING!C:C,MATCH(C35,PRICING!A:A,0),1) -> 3275 | G35: =INDEX(PRICING!D:D,MATCH(C35,PRICING!A:A,0),1) -> 4158 | H35: PROMOTION
C36: WH68 DUAL | D36: Yealink WH68 Dual DECT Wireless Headset | E36: =_xlfn.XLOOKUP(C36,PRICING!A:A,PRICING!B:B,"No Record",0,1) -> 2498 | F36: =INDEX(PRICING!C:C,MATCH(C36,PRICING!A:A,0),1) -> 4094 | G36: =INDEX(PRICING!D:D,MATCH(C36,PRICING!A:A,0),1) -> 5202 | H36: PROMOTION
C37: RJ & QD HEADSETS
C38: YHS36-MONO | D38: Yealink YHS36 Mono Headset With RJ-9 And Leatherette Ear Cushions | E38: =_xlfn.XLOOKUP(C38,PRICING!A:A,PRICING!B:B,"No Record",0,1) -> 459 | F38: =INDEX(PRICING!C:C,MATCH(C38,PRICING!A:A,0),1) -> 750 | G38: =INDEX(PRICING!D:D,MATCH(C38,PRICING!A:A,0),1) -> 895 | H38: PROMOTION
C39: ACCESSORIES
C40: CAM50 | D40: Yealink CAM50 USB Camera For Use With T58W (PRO) | E40: =_xlfn.XLOOKUP(C40,PRICING!A:A,PRICING!B:B,"No Record",0,1) -> 1149 | F40: =INDEX(PRICING!C:C,MATCH(C40,PRICING!A:A,0),1) -> 1775.1 | G40: =INDEX(PRICING!D:D,MATCH(C40,PRICING!A:A,0),1) -> 2013 | H40: PROMOTION
C42: YEALINK VC PROMOTION
C43: SKU | D43: DESCRIPTION | E43: PRICE | F43: Suggested advertising price | G43: MSRP | H43: COMMENTS
C44: ROOM CAMERAS & AUDIO DEVICE & BYOD KIT
C45: MTOWER | D45: Yealink MTower Center-view Intelligent Camera | E45: =_xlfn.XLOOKUP(C45,PRICING!A:A,PRICING!B:B) -> 18798 | F45: =_xlfn.XLOOKUP(C45,PRICING!A:A,PRICING!C:C) -> 29562 | G45: =_xlfn.XLOOKUP(C45,PRICING!A:A,PRICING!D:D) -> 29562 | H45: PROMOTION 2 YEAR WARRANTY
C46: BYOD-BOX | D46: Yealink BYOD Connection Box | E46: =_xlfn.XLOOKUP(C46,PRICING!A:A,PRICING!B:B) -> 1199 | F46: =_xlfn.XLOOKUP(C46,PRICING!A:A,PRICING!C:C) -> 2088 | G46: =_xlfn.XLOOKUP(C46,PRICING!A:A,PRICING!D:D) -> 2940 | H46: PROMOTION 2 YEAR WARRANTY
C47: ROOM AUDIO DEVICE
C48: AVHUB | D48: Yealink AVHub Meeting AV Processor, Incl: 7.5M Cat5E Cable, 2.5M USB Cable, Power Adapter | E48: =_xlfn.XLOOKUP(C48,PRICING!A:A,PRICING!B:B) -> 18498 | F48: =_xlfn.XLOOKUP(C48,PRICING!A:A,PRICING!C:C) -> 32886 | G48: =_xlfn.XLOOKUP(C48,PRICING!A:A,PRICING!D:D) -> 34782 | H48: PROMOTION 2 YEAR WARRANTY
C49: CONTENT SHARING DEVICE
C50: MSHARE E2 | D50: Yealink MShare E2 Wired Content Sharing Adapter | E50: =_xlfn.XLOOKUP(C50,PRICING!A:A,PRICING!B:B) -> 2999 | F50: =_xlfn.XLOOKUP(C50,PRICING!A:A,PRICING!C:C) -> 5481 | G50: =_xlfn.XLOOKUP(C50,PRICING!A:A,PRICING!D:D) -> 5202 | H50: PROMOTION 2 YEAR WARRANTY
C51: COLLABORATION BOARD
C52: MB75C-EDLA | D52: Yealink MeetingBoard 75C for Small and Medium Rooms, Manager Office - 75-inch all-in-one Collaboration Display, Google EDLA certified, Google Play, Supports casting, Whiteboard, USB-BYOD | E52: =_xlfn.XLOOKUP(C52,PRICING!A:A,PRICING!B:B) -> 44000 | F52: =_xlfn.XLOOKUP(C52,PRICING!A:A,PRICING!C:C) -> 69582 | G52: =_xlfn.XLOOKUP(C52,PRICING!A:A,PRICING!D:D) -> 69582 | H52: PROMOTION 2 YEAR WARRANTY
C53: CONTROLLER
C54: CTP18-STD | D54: Yealink CTP18 Touch Panel for A20 and A30 | E54: =_xlfn.XLOOKUP(C54,PRICING!A:A,PRICING!B:B) -> 4999 | F54: =_xlfn.XLOOKUP(C54,PRICING!A:A,PRICING!C:C) -> 9135 | G54: =_xlfn.XLOOKUP(C54,PRICING!A:A,PRICING!D:D) -> 10422 | H54: PROMOTION 2 YEAR WARRANTY
C55: MEETINGBOARD ACCESSORIES
C56: MB-CAMERA-6X | D56: Yealink 6x Optical PTZ Camera for MeetingBoard | E56: =_xlfn.XLOOKUP(C56,PRICING!A:A,PRICING!B:B) -> 7799 | F56: =_xlfn.XLOOKUP(C56,PRICING!A:A,PRICING!C:C) -> 11466 | G56: =_xlfn.XLOOKUP(C56,PRICING!A:A,PRICING!D:D) -> 11466 | H56: PROMOTION 2 YEAR WARRANTY
C57: MEETING DISPLAY
C58: MD65 | D58: Yealink MeetingDisplay 65 inch | E58: =_xlfn.XLOOKUP(C58,PRICING!A:A,PRICING!B:B) -> 14700 | F58: =_xlfn.XLOOKUP(C58,PRICING!A:A,PRICING!C:C) -> 25734 | G58: =_xlfn.XLOOKUP(C58,PRICING!A:A,PRICING!D:D) -> 29562 | H58: PROMOTION 2 YEAR WARRANTY
C59: MD75 | D59: Yealink MeetingDisplay 75 inch | E59: =_xlfn.XLOOKUP(C59,PRICING!A:A,PRICING!B:B) -> 19799 | F59: =_xlfn.XLOOKUP(C59,PRICING!A:A,PRICING!C:C) -> 34678 | G59: =_xlfn.XLOOKUP(C59,PRICING!A:A,PRICING!D:D) -> 46962 | H59: PROMOTION 2 YEAR WARRANTY
C60: MD86 | D60: Yealink MeetingDisplay 86 inch | E60: =_xlfn.XLOOKUP(C60,PRICING!A:A,PRICING!B:B) -> 27599 | F60: =_xlfn.XLOOKUP(C60,PRICING!A:A,PRICING!C:C) -> 48476 | G60: =_xlfn.XLOOKUP(C60,PRICING!A:A,PRICING!D:D) -> 69582 | H60: PROMOTION 2 YEAR WARRANTY
C62: Power Your Voice with H3C! Powering your Yealink IP Phones has never been easier than with H3C's Power over Ethernet Switches. When you order Yealink Phones* and H3C switches* together, you get an additional 7.5% discount off the H3C switches. *Applicable models: - H3C Switches: LS-1850V2-10-HPWR-EI-GL; LS-5120V3-28P-PWR-LI-GL; LS-5120V3-28P-HPWR-LI-GL - Yealink IP Phones: SIP-T43U; SIP-T44W; SIP-T48U; SIP-T57W - Make it 5 phones of the same model and get an additional 5% discount off the phones - Limited stock available
C63: SKU | D63: DESCRIPTION | E63: PRICE | F63: BUNDLE PRICE | H63: COMMENTS
C64: PoE SWITCHES
C65: LS-1850V2-10P-HPWR-EI-GL | D65: H3C S1850V2-10P-HPWR-EI L2 Ethernet Switch with 8x 10/100/1000 BASE-T PoE+ Ports and 2x 1000 BASE-X SFP Ports, 125W PoE Capacity, AC PSU | E65: 2540 | F65: 2350 | H65: H3C + YEALINK BUNDLE PROMOTION 5 YEAR WARRANTY
C66: LS-5120V3-28P-PWR-LI-GL | D66: H3C S5120V3-28P-PWR-LI L3 Ethernet Switch with 24x 10/100/1000 BASE-T PoE+ Ports and 4x1000 BASE-X SFP Ports, 240W PoE+ Capacity, AC PSU | E66: 5530 | F66: 5115 | H66: H3C + YEALINK BUNDLE PROMOTION 5 YEAR WARRANTY
C67: LS-5120V3-28P-HPWR-LI-GL | D67: H3C S5120V3-28P-HPWR-LI L3 Ethernet Switch with 24x 10/100/1000 BASE-T PoE+ Ports, 4x 100/1000 BASE-X SFP Ports, and 4x GE Combo Ports, 370W PoE+ Capacity, AC PSU | E67: 6199 | F67: 5735 | H67: H3C + YEALINK BUNDLE PROMOTION 5 YEAR WARRANTY
C69: Real Discounts, No Jokes! Don't be an April Fool, get up to 10% discount on these H3C SMB Products.
C70: SKU | D70: DESCRIPTION | E70: WAS | F70: NOW | H70: COMMENTS
C71: WIRELESS ACCESS POINTS
C72: EWP-WA6020 | D72: H3C WA6020 Access Point, Dual Radio 802.11ax (1500Mbps), Internal Antennas, 4 Streams | E72: 1220 | F72: 1098 | H72: PROMOTION 5 YEAR WARRANTY
C73: EWP-WA6022H | D73: H3C WA6022H Wall-plate Access Point, Dual Radio 802.11ax (1500Mbps), Internal Antennas, 4 Streams, 2x Gb Ethernet Ports | E73: 1074 | F73: 966 | H73: PROMOTION 5 YEAR WARRANTY
C74: EWP-WA6120 | D74: H3C WA6120 Access Point, Dual Radio 802.11ax (3000Mbps), Internal Antennas, 4 Streams | E74: 1507 | F74: 1375 | H74: PROMOTION 5 YEAR WARRANTY
C75: SWITCHES
C76: LS-1850V2-28P-EI-GL | D76: H3C S1850V2-28P-EI Layer 2 Ethernet Switch 24x 10/100/1000Mbps Ports and 4x 1Gbps SFP Ports, AC PSU | E76: 2571 | F76: 2345 | H76: PROMOTION 5 YEAR WARRANTY
C77: LS-5120V3-28F-LI-GL | D77: H3C S5120V3-28F-LI L3 Ethernet Switch with 24x 100/1000 Base-X Ports, 2x 10/100/1000 Base-T Combo Ports, 2x 1000 Base-X SFP Ports and 2*1G/10G Basse-X SFP+ Ports, AC PSU | E77: 6689 | F77: 6175 | H77: PROMOTION 5 YEAR WARRANTY
C78: LS-6520X-16ST-SI-GL | D78: H3C S6520X-16ST-SI L3 Ethernet Switch with 16x 1G/10G Base-X SFP+ Ports (2x Combo Ports), Excludes Power Supplies | E78: 17335 | F78: 15855 | H78: PROMOTION 3 YEAR WARRANTY
C79: SMB ROUTER
C80: RT-MSR610 | D80: H3C MSR610 Enterprise 6-Port Gigabit Ethernet Router, 2x Gb Ethernet WAN (1GE+1SFP), 4x Gb Ethernet LAN/WAN | E80: 2396 | F80: 2246 | H80: PROMOTION 5 YEAR WARRANTY
C82: NEAT PROMOTION
C83: SKU | D83: DESCRIPTION | E83: PRICE | H83: COMMENTS
C84: NEATBAR-BYOD | D84: Neat BYOD BAR - All-in-one video device for Zoom/BYOD. Ideal for small to medium rooms up to 10 people within 15ft/5m. Features a 12MP camera, 120° FOV, 8x digital zoom, auto-framing, 5 mics, and opposing drivers. Mounting hardware included. | E84: 11809 | H84: PROMOTION
C85: NEATFRAME-SE | D85: Neat Frame personal video meeting device | E85: 10359 | H85: PROMOTION
C87: DNAKE PROMOTION
C88: SKU | D88: DESCRIPTION | E88: PRICE NOW | F88: OLD PRICE | H88: COMMENTS
C89: 280M-S8 | D89: Dnake 7" Indoor Monitor (Smart Lite App Version) | E89: 515 | F89: 1029 | H89: FINAL CLEARANCE PROMO
C90: 902M-S8 | D90: Dnake 7" Android Indoor Monitor | E90: 675 | F90: 1350 | H90: FINAL CLEARANCE PROMO
C91: 904M-S3 | D91: Dnake 10.1" Android Indoor Monitor | E91: 833 | F91: 1667 | H91: FINAL CLEARANCE PROMO
C92: 905D-Y4 | D92: Dnake 7" Android Doorhpone With Facial Recognition, DC 12V/2A, No PoE, 1 x RJ45, 10/100 Mbps adaptive | E92: 2795 | F92: 5589 | H92: FINAL CLEARANCE PROMO
C94: BLUETTI PROMOTION
C95: SKU | D95: DESCRIPTION | E95: PRICE | H95: COMMENTS
C96: PV120 | D96: Bluetti PV120 Solar Panel 120W | E96: 2899 | H96: PROMOTION
C98: NETOGY PROMOTION
C99: SKU | D99: DESCRIPTION | E99: PRICE | H99: COMMENTS
C100: UPS100-PLUS | D100: Netogy UPS100 Plus Mini DC UPS/Powerbank | E100: 599 | H100: PROMOTION
C102: MOTOROLA PROMOTION
C103: SKU | D103: DESCRIPTION | E103: PRICE | H103: COMMENTS
C104: MA1 | D104: Motorola MA1 Wireless Car Adapter For Android Auto™ | E104: 799 | H104: PROMOTION
C106: VILO PROMOTION
C107: SKU | D107: DESCRIPTION | E107: PRICE | H107: COMMENTS
C108: VILO-5-3 | D108: Vilo-5-3 Mesh Wi-Fi 5 System 3 Pack With Bark Parental Controls Included | E108: 1299 | H108: PROMOTION
C110: JABRA PROMOTION
C111: SKU | D111: DESCRIPTION | E111: PRICE NOW | F111: OLD PRICE | H111: COMMENTS
C112: EVOLVE 65-TE-ST | D112: Jabra Evolve 65 TE, Link 390a MS Stereo with Stand | E112: 3855 | F112: 4070 | H112: FINAL CLEARANCE PROMO
C113: EVOLVE-30 | D113: Jabra Evolve 30 Stereo Wired USB & 3.5mm MS | E113: 1169 | F113: 1235 | H113: FINAL CLEARANCE PROMO
C114: EVOLVE-40-MONO | D114: Jabra Evolve 40 Mono USB Headset | E114: 1159 | F114: 1223 | H114: FINAL CLEARANCE PROMO
C115: EVOLVE2-40-SE-MS | D115: Jabra Evolve2 40 SE STEREO USB-A Headset, Microsoft Version | E115: 2045 | F115: 2158 | H115: FINAL CLEARANCE PROMO
C116: PANACAST 50-VBS | D116: Jabra PanaCast 50 VBS (Android Video Bar System) Microsoft Version with Touch Control, USB C Charger | E116: 59699 | F116: 63105 | H116: FINAL CLEARANCE PROMO
...

Sheet New Products
G1: Return
B7: NEW PRODUCTS
B11: SKU | C11: DESCRIPTION | D11: PRICE | E11: Suggested advertising price | F11: MSRP | G11: COMMENTS
B12: IP DECT PHONES
B13: W59R PRO | C13: Yealink W59R PRO Rugged DECT Handset IP67 | D13: =_xlfn.XLOOKUP(B13,PRICING!A:A,PRICING!B:B,"No Record",0,1) -> 2069 | E13: =INDEX(PRICING!C:C,MATCH(B13,PRICING!A:A,0),1) -> 2940 | F13: =INDEX(PRICING!D:D,MATCH(B13,PRICING!A:A,0),1) -> 2940 | G13: COMING SOON 2 YEAR WARRANTY
B14: DECT WIRELESS HEADSETS
B15: WH63 E2 | C15: Yealink WH63 E2 DECT Wireless Convertible Headset, MS Teams Certified | D15: =_xlfn.XLOOKUP(B15,PRICING!A:A,PRICING!B:B,"No Record",0,1) -> 1886 | E15: =INDEX(PRICING!C:C,MATCH(B15,PRICING!A:A,0),1) -> 2695 | F15: =INDEX(PRICING!D:D,MATCH(B15,PRICING!A:A,0),1) -> 3305 | G15: NEW 2 YEAR WARRANTY
B16: WH68 HYBRID WITH CHARGE STAND | C16: Yealink WH68 Hybrid DECT Wireless Headset, Teams Certified, with Charging Stand | D16: =_xlfn.XLOOKUP(B16,PRICING!A:A,PRICING!B:B,"No Record",0,1) -> 2436 | E16: =INDEX(PRICING!C:C,MATCH(B16,PRICING!A:A,0),1) -> 3480 | F16: =INDEX(PRICING!D:D,MATCH(B16,PRICING!A:A,0),1) -> 4332 | G16: COMING SOON 2 YEAR WARRANTY
B17: TEAMS PHONES
B18: MP55 E2 | C18: Yealink MP55 E2 Phone For Microsoft Teams, Excludes PSU | D18: =_xlfn.XLOOKUP(B18,PRICING!A:A,PRICING!B:B,"No Record",0,1) -> 3788 | E18: =INDEX(PRICING!C:C,MATCH(B18,PRICING!A:A,0),1) -> 5412 | F18: =INDEX(PRICING!D:D,MATCH(B18,PRICING!A:A,0),1) -> 5550 | G18: COMING SOON 2 YEAR WARRANTY
B19: USB HEADSETS
B20: UH42 SE DUAL TEAMS USB-C/A | C20: Yealink UH42 SE Dual USB Headset, USB-C With USB-C/A Adapter, Teams Certified | D20: =_xlfn.XLOOKUP(B20,PRICING!A:A,PRICING!B:B,"No Record",0,1) -> 597 | E20: =INDEX(PRICING!C:C,MATCH(B20,PRICING!A:A,0),1) -> 852 | F20: =INDEX(PRICING!D:D,MATCH(B20,PRICING!A:A,0),1) -> N/A | G20: COMING SOON 2 YEAR WARRANTY
B21: UH42 SE MONO TEAMS USB-C/A | C21: Yealink UH42 SE Mono USB Headset, USB-C With USB-C/A Adapter, Teams Certified | D21: =_xlfn.XLOOKUP(B21,PRICING!A:A,PRICING!B:B,"No Record",0,1) -> 477 | E21: =INDEX(PRICING!C:C,MATCH(B21,PRICING!A:A,0),1) -> 682 | F21: =INDEX(PRICING!D:D,MATCH(B21,PRICING!A:A,0),1) -> N/A | G21: COMING SOON 2 YEAR WARRANTY
B22: VIDEO CONFERENCING DEVICES
B23: SKU | C23: DESCRIPTION | D23: PRICE | E23: Suggested advertising price | F23: MSRP | G23: COMMENTS
B24: A-SERIES ALL-IN-ONE VIDEO BARS FOR MICROSOFT TEAMS
B25: A25-010 | C25: Yealink A25 all-in-one Collaboration bar for focus rooms, Incl VCR11 Remote | D25: =INDEX(PRICING!B:B,MATCH(B25,PRICING!A:A,0),1) -> 20079 | E25: =INDEX(PRICING!C:C,MATCH(B25,PRICING!A:A,0),1) -> 27822 | F25: =INDEX(PRICING!D:D,MATCH(B25,PRICING!A:A,0),1) -> 27822 | G25: NEW 2 YEAR WARRANTY
B26: A25-031 | C26: Yealink A25 all-in-one Collaboration bar for focus rooms, incl. CTP25 touch console | D26: =INDEX(PRICING!B:B,MATCH(B26,PRICING!A:A,0),1) -> 27613 | E26: =INDEX(PRICING!C:C,MATCH(B26,PRICING!A:A,0),1) -> 40002 | F26: =INDEX(PRICING!D:D,MATCH(B26,PRICING!A:A,0),1) -> 40002 | G26: NEW 2 YEAR WARRANTY
B27: MEETINGBOARD
B28: MB65C-EDLA | C28: Yealink MeetingBoard 65C for Small and Medium Rooms, Manager Office - 65-inch all-in-one Collaboration Display, Google EDLA certified, Google Play, Supports casting, Whiteboard, USB-BYOD | D28: =INDEX(PRICING!B:B,MATCH(B28,PRICING!A:A,0),1) -> 38976 | E28: =INDEX(PRICING!C:C,MATCH(B28,PRICING!A:A,0),1) -> 52182 | F28: =INDEX(PRICING!D:D,MATCH(B28,PRICING!A:A,0),1) -> 52182 | G28: NEW 2 YEAR WARRANTY
B29: MB75C-EDLA | C29: Yealink MeetingBoard 75C for Small and Medium Rooms, Manager Office - 75-inch all-in-one Collaboration Display, Google EDLA certified, Google Play, Supports casting, Whiteboard, USB-BYOD | D29: =INDEX(PRICING!B:B,MATCH(B29,PRICING!A:A,0),1) -> 44000 | E29: =INDEX(PRICING!C:C,MATCH(B29,PRICING!A:A,0),1) -> 69582 | F29: =INDEX(PRICING!D:D,MATCH(B29,PRICING!A:A,0),1) -> 69582 | G29: NEW 2 YEAR WARRANTY
B30: ROOM AUDIO
B31: MSPEAKER PRO | C31: Yealink MSpeaker Pro Soundbar For Video Conferencing | D31: =INDEX(PRICING!B:B,MATCH(B31,PRICING!A:A,0),1) -> 4872 | E31: =INDEX(PRICING!C:C,MATCH(B31,PRICING!A:A,0),1) -> 6942 | F31: =INDEX(PRICING!D:D,MATCH(B31,PRICING!A:A,0),1) -> 6942 | G31: NEW 2 YEAR WARRANTY
B32: CPE40 | C32: Yealink CPE40 Speakerphone, works with CP50 | D32: =INDEX(PRICING!B:B,MATCH(B32,PRICING!A:A,0),1) -> 3654 | E32: =INDEX(PRICING!C:C,MATCH(B32,PRICING!A:A,0),1) -> 5481 | F32: =INDEX(PRICING!D:D,MATCH(B32,PRICING!A:A,0),1) -> 6072 | G32: NEW 2 YEAR WARRANTY
B33: CP50 | C33: Yealink CP50 Speaker for UVC85 Video Conferencing | D33: =INDEX(PRICING!B:B,MATCH(B33,PRICING!A:A,0),1) -> 5359 | E33: =INDEX(PRICING!C:C,MATCH(B33,PRICING!A:A,0),1) -> 8038 | F33: =INDEX(PRICING!D:D,MATCH(B33,PRICING!A:A,0),1) -> 8682 | G33: NEW 2 YEAR WARRANTY
B34: ACCESSORIES
B35: MB-12X PRO | C35: Yealink 12x PTZ Camera Module for MeetingBoard Pro Only | D35: =INDEX(PRICING!B:B,MATCH(B35,PRICING!A:A,0),1) -> 14128 | E35: =INDEX(PRICING!C:C,MATCH(B35,PRICING!A:A,0),1) -> 17382 | F35: =INDEX(PRICING!D:D,MATCH(B35,PRICING!A:A,0),1) -> 17382 | G35: NEW 2 YEAR WARRANTY
B36: ROOMSENSOR PRO | C36: Yealink RoomSensor Pro Multifunctional Wireless Sensor | D36: =INDEX(PRICING!B:B,MATCH(B36,PRICING!A:A,0),1) -> 4263 | E36: =INDEX(PRICING!C:C,MATCH(B36,PRICING!A:A,0),1) -> 6403 | F36: =INDEX(PRICING!D:D,MATCH(B36,PRICING!A:A,0),1) -> 6594 | G36: NEW 2 YEAR WARRANTY
B39: SKU | C39: DESCRIPTION | D39: PRICE | G39: COMMENTS
B40: ENTERPRISE POE ACCESS SWITCHES
B41: LS-5130S-28P-HPWR-EI-AC-GL | C41: H3C S5130S-28P-HPWR-EI-AC L2 Ethernet Switch with 24x 10/100/1000BASE-T PoE+ Ports (AC 370W), 4x 100/1000BASE-X SFP Ports, and 4x GE Combo Ports, (AC) | D41: P.O.R | G41: NOW IN STOCK
B42: LS-5130S-52P-PWR-EI-AC-GL | C42: H3C S5130S-52P-PWR-EI-AC L2 Ethernet Switch with 48x 10/100/1000BASE-T PoE+ Ports (AC 370W) and 4x 1000BASE-X SFP Ports, (AC) | D42: P.O.R | G42: NOW IN STOCK
B43: LS-5170-28S-HPWR-EI-GL | C43: H3C S5170-28S-HPWR-EI L2 Ethernet Switch with 24x 10/100/1000BASE-T Ports and 4x 1G/10G BASE-X SFP Plus Ports, (AC), PoE+ | D43: P.O.R | G43: NOW IN STOCK
B44: ENTERPRISE WIRELESS ACCESS POINTS
B45: EWP-WA6520-FIT | C45: H3C WA6520 Internal Antennas 4 Streams Dual Radio 802.11ax/ac/n Access Point,FIT | D45: P.O.R | G45: NOW IN STOCK
B46: EWP-WA6528I-FIT | C46: H3C WA6528i Internal Antennas 8 Streams Dual Radio 802.11ax/ac/n Access Point, FIT | D46: P.O.R | G46: NOW IN STOCK
B47: EWP-WA6620X-FIT | C47: H3C WA6620X Integrated Internal and External Antennas 4 Streams Dual Radio 802.11ax/ac/n External Access Point | D47: P.O.R | G47: NOW IN STOCK
B50: SKU | C50: DESCRIPTION | D50: PRICE | G50: COMMENTS
B51: RUTC41 | C51: Teltonika Teltonika RUTC41 4G LTE (Cat 4) Router, WIFI 6, 1 x WAN, 4 x LAN, eSIM | D51: 5426 | G51: Coming Soon
B52: RUT976 | C52: Teltonika RUT976 Redcap 5G LTE Cat 4 GNSS antenna OR DinRail Router, eSIM + Dual-SIM, 1 x WAN (100 Mbps), 3 x WAN (100 Mbps), MODUBUS RS232/RS485 | D52: 6150 | G52: Coming Soon
B53: EBD021 | C53: Teltonika EBD021 CALYX 4G LTE-FDD (Cat 4) embedded Raspberry Pi HAT+, 2 x SMA for Mobile, | D53: =INDEX(PRICING!BL:BL,MATCH(B53,PRICING!BK:BK,0),1) -> 693 | G53: Coming Soon
B57: SKU | C57: DESCRIPTION | D57: PRICE | G57: COMMENTS
B58: Neat BYOD
B59: NEATPADPRO10-SE | C59: Neat Pad Pro 10" touch-screen for Zoom/Teams/App Hub, serves as a room controller or scheduling display. Offers seamless video meeting management and room bookings. | D59: =INDEX(PRICING!AW:AW,MATCH(B59,PRICING!AV:AV,0),1) -> 20580 | G59: NEW Available from April 2026 ETA confirmed on Order 12 MONTH WARRANTY
B61: SKU | C61: DESCRIPTION | D61: PRICE | E61: Suggested advertising price | G61: COMMENTS
B62: Digital Canvas Series
B63: Spark2 | C63: Videri Digital Canvas Spark2 - 18.5" Digital Display (1920 x 1080 FHD), Wi-Fi enabled. Includes wall mount, power cable and power adapter | D63: =INDEX(PRICING!CP:CP,MATCH(B63,PRICING!CO:CO,0),1) -> 33630 | E63: 42037.168 | G63: NEW ETA confirmed on Order
B64: SparkQ+ | C64: Videri Digital Canvas SparkQ+ - 34" diagonal, 1920x1920 resolution, Wi-Fi enabled. Includes wall mount, power cable and power adapter | D64: =INDEX(PRICING!CP:CP,MATCH(B64,PRICING!CO:CO,0),1) -> 43985 | E64: 54981.639 | G64: NEW ETA confirmed on Order
B65: Spark3 | C65: Videri Digital Canvas Spark3 - 33" diagonal, 4K resolution, Wi-Fi enabled. Includes wall mount, power cable and power adapter | D65: =INDEX(PRICING!CP:CP,MATCH(B65,PRICING!CO:CO,0),1) -> 31040 | E65: 38801.051 | G65: NEW ETA confirmed on Order
B66: Spark4 | C66: Videri Digital Canvas Spark4 - 43" diagonal, 4K resolution, Wi-Fi enabled. Includes wall mount, power cable and power adapter | D66: =INDEX(PRICING!CP:CP,MATCH(B66,PRICING!CO:CO,0),1) -> 36219 | E66: 45273.286 | G66: NEW ETA confirmed on Order
B67: Spark5 | C67: Videri Digital Canvas Spark5 - 50" diagonal, 4K resolution, Wi-Fi enabled. Includes wall mount, power cable and power adapter | D67: =INDEX(PRICING!CP:CP,MATCH(B67,PRICING!CO:CO,0),1) -> 38809 | E67: 48509.404 | G67: NEW ETA confirmed on Order
B69: Workspace Management
B70: Worspace Management Licenses | C70: Refer to GoBright Brand Tab | G70: NEW ETA confirmed on Order
B71: Workspace Management Hardware | C71: On Request - Will be loaded soon | G71: NEW ETA confirmed on Order
B72: #VALUE!
B74: ZXHN-H3601P-INT | C74: ZTE H3601P Mesh Router, Wi-Fi 6 (3000Mbps) with Internal Aerials | D74: =INDEX(PRICING!BU:BU,MATCH(B74,PRICING!BT:BT,0),1) -> 525 | G74: NEW VOLUME DISCOUNTS AVAILABLE
B75: G5TS | C75: ZTE G5TS 5G Router, Wi-Fi 6 (1500Mbps), 2x RJ-45 1x RJ-11, nanoSIM, MTN FWA Approved | D75: =INDEX(PRICING!BU:BU,MATCH(B75,PRICING!BT:BT,0),1) -> 1650 | G75: NEW VOLUME DISCOUNTS AVAILABLE
B78: SHELLY FLOOD GEN4 | C78: Shelly Flood Gen4 Smart Battery Operated Water Leak Detector With 2m Cable Sensor | D78: =INDEX(PRICING!P:P,MATCH(B78,PRICING!O:O,0),1) -> 490.41455 | G78: NEW
B79: SHELLY LEAK SENSOR CABLE | C79: Shelly Leak Sensor Cable Extended Reach Coverage For Shelly Flood Gen4 | D79: =INDEX(PRICING!P:P,MATCH(B79,PRICING!O:O,0),1) -> 116.17143 | G79: NEW
B80: FRANKEVER SMART VALVE DN20 | C80: Frankever Smart Valve DN20 Powered By Shelly Smart Water Valve | D80: =INDEX(PRICING!P:P,MATCH(B80,PRICING!O:O,0),1) -> 2360.4727 | G80: NEW
B81: SHELLY WALL DISPLAY XL BLACK | C81: Shelly Wall Display XL - Smart Home Control Panel With a 10.1” Touch Display | D81: =INDEX(PRICING!P:P,MATCH(B81,PRICING!O:O,0),1) -> 5388.3653 | G81: NEW
B82: FRANKEVER SPRINKLER FK-06X | C82: 6-zone Wi-Fi Enabled Smart Sprinkler Controller – Powered by Shelly | D82: =INDEX(PRICING!P:P,MATCH(B82,PRICING!O:O,0),1) -> 1988.1901 | G82: NEW
B83: ECOWITT WEATHER STATION WS90 | C83: Ecowitt Weather Station WS90 Powered By Shelly 7-in-1 Weather Station | D83: =INDEX(PRICING!P:P,MATCH(B83,PRICING!O:O,0),1) -> 3493.0327 | G83: NEW
B84: SHELLY 2L GEN3 | C84: Shelly Two-Channel Smart Switch Tailored for Lighting Control in no Neutral Wire Installations. | D84: =INDEX(PRICING!P:P,MATCH(B84,PRICING!O:O,0),1) -> 708.37108 | G84: COMING SOON
B85: SHELLY WALL DISPLAY X2i BLACK | C85: Shelly Wall Display X2i Smart 6.95” Color Touchscreen (Black) | D85: =INDEX(PRICING!P:P,MATCH(B85,PRICING!O:O,0),1) -> 3283.5927 | G85: COMING SOON
B86: SHELLY WALL DISPLAY X2i SILVER | C86: Shelly Wall Display X2i Smart 6.95” Color Touchscreen (Silver) | D86: =INDEX(PRICING!P:P,MATCH(B86,PRICING!O:O,0),1) -> 3283.5927 | G86: COMING SOON
B88: HUAWEI
B89: IHS3-75SA | C89: Huawei Ideahub interactive 75" S3 Series | D89: 76917 | G89: NEW VOLUME DISCOUNTS AVAILABLE
B90: IHS3-65SA | C90: Huawei ideahub 65" S3 series | D90: 56268 | G90: NEW VOLUME DISCOUNTS AVAILABLE
D91: PRICE
B92: TP LINK TAPO
B93: Tapo H110 | C93: Smart IR & IoT Hub | D93: =INDEX(PRICING!AB:AB,MATCH(B93,PRICING!AA:AA,0),1) -> 292 | G93: NEW 2 YEAR WARRANTY
B94: Tapo P110 | C94: TP-Link Tapo P110(ZA) Mini Smart Wi-Fi Plug, Energy Monitoring | D94: =INDEX(PRICING!AB:AB,MATCH(B94,PRICING!AA:AA,0),1) -> 168 | G94: NEW 2 YEAR WARRANTY
B95: Tapo T310 V1.2 | C95: TP-Link Tapo T310 Smart Temp & Humidity Sensor with Alerts | D95: =INDEX(PRICING!AB:AB,MATCH(B95,PRICING!AA:AA,0),1) -> 194 | G95: NEW 2 YEAR WARRANTY
B96: Tapo T300 | C96: TP-Link Tapo T300 Smart 24/7 Water Drip & Leak 90dB Alert Sensor | D96: =INDEX(PRICING!AB:AB,MATCH(B96,PRICING!AA:AA,0),1) -> 214 | G96: NEW 2 YEAR WARRANTY
B97: Tapo T110 | C97: TP-Link Tapo T110 Smart Contact Sensor for Doors & Windows | D97: =INDEX(PRICING!AB:AB,MATCH(B97,PRICING!AA:AA,0),1) -> 162 | G97: NEW 2 YEAR WARRANTY
B98: Tapo T315 | C98: Tapo T315 Smart Temperature And Humidity Monitor | D98: =INDEX(PRICING!AB:AB,MATCH(B98,PRICING!AA:AA,0),1) -> 305 | G98: NEW 2 YEAR WARRANTY
B99: Tapo T100 | C99: TP-Link Tapo T100 Smart Motion Sensor with Alerts & Adjustable Sensitivity | D99: =INDEX(PRICING!AB:AB,MATCH(B99,PRICING!AA:AA,0),1) -> 194 | G99: NEW 2 YEAR WARRANTY
B100: Tapo S200B | C100: Tapo S200B Smart Button cooperate with Tapo Lights &Bulbs | D100: =INDEX(PRICING!AB:AB,MATCH(B100,PRICING!AA:AA,0),1) -> 181 | G100: NEW 2 YEAR WARRANTY
B101: Tapo S112 | C101: Smart Switch Module | D101: =INDEX(PRICING!AB:AB,MATCH(B101,PRICING!AA:AA,0),1) -> 260 | G101: NEW 2 YEAR WARRANTY
B102: Tapo L920-5 | C102: Smart Wi-Fi Light Strip, Multicolor | D102: =INDEX(PRICING!AB:AB,MATCH(B102,PRICING!AA:AA,0),1) -> 487 | G102: NEW 2 YEAR WARRANTY
B103: Tapo L920-10 | C103: Smart Wi-Fi Light Strip, Multicolor | D103: =INDEX(PRICING!AB:AB,MATCH(B103,PRICING!AA:AA,0),1) -> 812 | G103: NEW 2 YEAR WARRANTY
B104: Tapo C220 | C104: Pan/Tilt AI Home Security Wi-Fi Camera | D104: =INDEX(PRICING!AB:AB,MATCH(B104,PRICING!AA:AA,0),1) -> 455 | G104: NEW 2 YEAR WARRANTY
B105: Tapo C230 | C105: Pan/Tilt AI Home Security Wi-Fi Camera | D105: =INDEX(PRICING!AB:AB,MATCH(B105,PRICING!AA:AA,0),1) -> 585 | G105: NEW 2 YEAR WARRANTY
D106: PRICE
B107: G20 | C107: Mecool G20 Remote Compatible With Mecool ATV & GTV Devices | D107: =INDEX(PRICING!BO:BO,MATCH(B107,PRICING!BN:BN,0),1) -> 199 | G107: NEW 1 YEAR WARRANTY
B108: KS3 | C108: Mecool KS3 OTT Soundbar + Subwoofer | D108: =INDEX(PRICING!BO:BO,MATCH(B108,PRICING!BN:BN,0),1) -> 5999 | G108: NEW 1 YEAR WARRANTY
B109: GM1 | C109: Mecool GM1 Wireless Gamepad | D109: =INDEX(PRICING!BO:BO,MATCH(B109,PRICING!BN:BN,0),1) -> 599
D110: PRICE
B111: AIRNOVA | C111: NW01-S Tyre Inflator | D111: =INDEX(PRICING!Y:Y,MATCH(B111,PRICING!X:X,0),1) -> 799 | G111: NEW 1 YEAR WARRANTY
B112: AIRNOVAMAX | C112: KF03 Tyre Inflator & Jump Starter | D112: =INDEX(PRICING!Y:Y,MATCH(B112,PRICING!X:X,0),1) -> 1199 | G112: NEW 1 YEAR WARRANTY
B114: E & OE Terms & Conditions: Pricing valid from 1 April 2026 until 30 April 2026. All pricing is Exclusive of VAT and subject to stock availability and lead times. Pricing is subject to change without notice and is linked to the exchange rate. CLICK HERE to view our full Terms and Conditions.

Sheet Warehouse Clearance 
K1: Return
B6: WAREHOUSE CLEARANCE
D7: ** Please refer to the condition column for information about the products listed here.**
A10: Unified Communication
B11: Brand | C11: Code | D11: Product Description | E11: QTY Available | F11: Standard Price | G11: Warehouse Clearance Price | H11: Condition | I11: Warehouse | J11: Warranty | K11: Comments
B12: Jabra | C12: EVOLVE-40-MONO | D12: Jabra Evolve 40 Mono USB Headset | E12: 1 | F12: 1005 | G12: 905 | H12: Excellent / Sealed | I12: Gauteng | J12: Warranty expired | K12: Add Nology BB Warranty-12
B13: Yealink | C13: MB65-A001 | D13: Yealink MeetingBoard65 For Small And Medium Rooms: Includes 1X 65 Inch All-In-One Collaboration Display, Power Adapter, Wall Mount Bracket And Cables, 4 X Stylus Pen | E13: 1 | F13: =_xlfn.XLOOKUP(C13,PRICING!A181:A493,PRICING!D181:D493) -> 83502 | G13: 39755.55 | H13: Available on request | I13: Gauteng | J13: Warranty expired | K13: Clearance Price Add Nology BB Warranty-12
B14: Yealink | C14: MCOREKIT-C5-MS | D14: Yealink MCore Base Kit including mini-PC, MTouch Plus and RoomSensor | E14: 1 | F14: =_xlfn.XLOOKUP(C14,PRICING!A182:A494,PRICING!D182:D494) -> 43482 | G14: 29646.16 | H14: Available on request | I14: Gauteng | J14: Warranty expired | K14: Clearance Price Add Nology BB Warranty-12
B15: Yealink | C15: MD65 | D15: Yealink MeetingDisplay 65 inch | E15: 1 | F15: =_xlfn.XLOOKUP(C15,PRICING!A183:A495,PRICING!D183:D495) -> 29562 | G15: 13972.45 | H15: Available on request | I15: Gauteng | J15: Warranty expired | K15: Clearance Price Add Nology BB Warranty-12
B16: Yealink | C16: MVC S60-C5-000 | D16: Yealink MVC S60-C5-000 Teams Room System for Small to Medium Rooms incl. S60 Intelligent All-in-One Device, MCore Pro, MTouch Plus, RoomSensor | E16: 1 | F16: =_xlfn.XLOOKUP(C16,PRICING!A184:A496,PRICING!D184:D496) -> 93942 | G16: 66120.36 | H16: Available on request | I16: Gauteng | J16: Under warranty till 05-03-2026
B17: Yealink | C17: MVC300 | D17: Yealink MVC300, UVC30 Camera, MTouch | E17: 1 | F17: =_xlfn.XLOOKUP(C17,PRICING!A185:A497,PRICING!D185:D497) -> #N/A | G17: 27877 | H17: Available on request | I17: Gauteng | J17: Warranty expired | K17: Add Nology BB Warranty-12
B18: Yealink | C18: MVC640-C3-050 | D18: Yealink MVC640 Full HD Video Conferencing Solution Incl: UVC84 Camera, MTouch II, MSpeech AI Speakerphone And Mini-PC | E18: 2 | F18: 56706 | G18: 39338.01 | H18: Available on request | I18: Gauteng | J18: Warranty expired | K18: Add Nology BB Warranty-12
B19: Yealink | C19: MVC640-C4-F13 | D19: Yealink MVC640 Microsoft Teams Rooms System For Medium-To-Large Rooms, Incl. UVC84, MCore Pro Kit C4(MCore Pro Mini-PC, MTouch E2), VCR20, Mspeaker II, 2x CPW65, WPP30 | E19: 1 | F19: =_xlfn.XLOOKUP(C19,PRICING!A187:A499,PRICING!D187:D499) -> #N/A | G19: 39338.01 | H19: Available on request | I19: Gauteng | J19: No Warranty | K19: Add Nology BB Warranty-6
B20: Yealink | C20: UVC85 | D20: Yealink UVC85 4K 12X PTZ USB Camera | E20: 1 | F20: =_xlfn.XLOOKUP(C20,PRICING!A188:A500,PRICING!D188:D500) -> 14772 | G20: 9843.91 | H20: Available on request | I20: Gauteng | J20: Warranty expired | K20: Add Nology BB Warranty-12
B21: Yealink | C21: MP56 | D21: Yealink MP56 Android Phone, For MS Teams, Excludes PSU (EOL) | E21: 1 | F21: 3666 | G21: 1199 | H21: Available on request | I21: Cape Town | J21: Supplier warranty till 22-12-2025
B22: Yealink | C22: BH76-BLK-ST-USBA | D22: Yealink BH76 Headset, Black with Charging Stand, USB-A Connection, Teams Certified (EOL) | E22: 1 | F22: 2368 | G22: 1659 | H22: Available on request | I22: Gauteng | J22: Warranty expired | K22: Add Nology BB Warranty-12
B23: Yealink | C23: BT41 | D23: Yealink BT41 Bluetooth USB Dongle | E23: 2 | F23: 358 | G23: 249 | H23: Available on request | I23: Gauteng | J23: Warranty expired
B24: Yealink | C24: BT51-A-S | D24: Yealink BT51-A Bluetooth USB-A Dongle Compatible With BH72 Lite/BH72/BH76 | E24: 1 | F24: 358 | G24: 249 | H24: Available on request | I24: Gauteng | J24: Warranty expired
B25: Yealink | C25: CP965 | D25: Yealink CP965 Android IP Conference Phone (SIP ONLY) | E25: 1 | F25: 7399 | G25: 5179 | H25: Available on request | I25: Gauteng | J25: Supplier warranty till 02-01-2025 | K25: Add Nology BB Warranty-12
B26: Yealink | C26: CPE90 | D26: Yealink CPE90 Wired Expansion Microphones For CP960 | E26: 3 | F26: 1176 | G26: 829 | H26: Available on request | I26: Gauteng | J26: Warranty expired
B27: Yealink | C27: EHS60 | D27: Yealink EHS60 Wireless Headset Adapter For WH62, WH63, X1 Micro USB Port, X1 RJ45 (8P8C), X1 RJ9 (4P4C) Headset Jacks | E27: 8 | F27: 477 | G27: 339 | H27: Available on request | I27: Gauteng | J27: Supplier warranty till 03-08-2026
B28: Yealink | C28: EXP43 | D28: Yealink EXP43 LCD Expansion Module For T43U, T46U And T48U Phones | E28: 1 | F28: 1246 | G28: 879 | H28: Available on request | I28: Gauteng | J28: Warranty expired
B29: Yealink | C29: MP52 | D29: Yealink MP52 Basic Phone For MS Teams Excludes PSU (EOL) | E29: 10 | F29: 2550 | G29: 1109 | H29: Available on request | I29: Gauteng | J29: Under warranty till 22-12-2025
B30: Yealink | C30: PSU-COLOUR | D30: Yealink PSU Colour For 5V/2A PSU For T44W, T46U, T48U, T54W, T57W, T74W, T73U, T74U, T58W, T87W and MP5x Series | E30: 2 | F30: 129 | G30: 89 | H30: Available on request | I30: Gauteng | J30: Under warranty till 18-12-2025
B31: Yealink | C31: SIP-T30 | D31: Yealink T30 Single Line Entry Level IP Phone, No PoE, Includes PSU | E31: 2 | F31: 642 | G31: 449 | H31: Available on request | I31: Gauteng | J31: Under warranty till 04-01-2026
B32: Yealink | C32: SIP-T31P | D32: Yealink SIP-T31P 10/100 Desktop IP Phone, Excludes PSU | E32: 2 | F32: 752 | G32: 529 | H32: Available on request | I32: Gauteng | J32: Under warranty till 04-01-2026
B33: Yealink | C33: SIP-T31W | D33: Yealink T31W Desktop IP Phone With Built-In Wi-Fi, 10/100Mb Ethernet, Includes PSU | E33: 1 | F33: 940 | G33: 659 | H33: Available on request | I33: Gauteng | J33: Under warranty till 18-07-2026
B34: Yealink | C34: SIP-T33G | D34: Yealink SIP-T33G Gigabit Colour Screen Desktop IP Phone, Excludes PSU | E34: 10 | F34: 964 | G34: 759 | H34: Available on request | I34: Gauteng | J34: Warranty expired | K34: Add Nology BB Warranty-12
B35: Yealink | C35: SIP-T34W | D35: Yealink SIP-T34W Desktop IP Phone With Built-In Wi-Fi, Includes PSU | E35: 1 | F35: 1129 | G35: 789 | H35: Available on request | I35: Gauteng | J35: Warranty expired | K35: Add Nology BB Warranty-12
B36: Yealink | C36: SIP-T40P | D36: Yealink T40P Fe, Bw, IP Phone, Excludes PSU (EOL) | E36: 4 | F36: - | G36: 499 | H36: Available on request | I36: Gauteng | J36: Warranty expired | K36: Add Nology BB Warranty-12
B37: Yealink | C37: SIP-T46U | D37: Yealink T46U Gb IP Phone With Dual USB Ports And 4.3" Colour LCD, Excludes PSU | E37: 1 | F37: 2375 | G37: 1659 | H37: Available on request | I37: Gauteng | J37: Warranty expired | K37: Add Nology BB Warranty-12
B38: Yealink | C38: SIP-T48U | D38: Yealink T48U Gb IP Phone With 7" Touch LCD And Dual USB Ports, Excludes PSU (EOL) | E38: 1 | F38: 2849 | G38: 1999 | H38: Available on request | I38: Gauteng | J38: Warranty expired | K38: Add Nology BB Warranty-12
B39: Yealink | C39: SIP-T53W | D39: Yealink T53W Dual Band Wi-Fi IP Phone, Excludes PSU (EOL) | E39: 1 | F39: 2239 | G39: 1569 | H39: Available on request | I39: Gauteng | J39: Warranty expired | K39: Add Nology BB Warranty-12
B40: Yealink | C40: SIP-T57W | D40: Yealink T57W Dual Band IP Desktop Phone, Excludes PSU (EOL) | E40: 1 | F40: 3299 | G40: 2309 | H40: Available on request | I40: Gauteng | J40: Warranty expired | K40: Add Nology BB Warranty-12
B41: Yealink | C41: SIP-T58W | D41: Yealink T58W Smart Business Phone, Excl. Camera, Excl. PSU (EOL) | E41: 1 | F41: 5145 | G41: 3599 | H41: Available on request | I41: Gauteng | J41: Warranty expired
B42: Yealink | C42: UH34-LITE-DUAL | D42: Yealink UH34 Lite Dual Earpiece USB Headset With Foam Ear Cushions Teams Edition | E42: 3 | F42: 477 | G42: 329 | H42: Available on request | I42: Gauteng | J42: Warranty expired | K42: Add Nology BB Warranty-12
B43: Yealink | C43: W73P | D43: Yealink W73P IP DECT Phone And Base Station (Incl. W70B And W73H) | E43: 1 | F43: 1693 | G43: 1189 | H43: Available on request | I43: Gauteng | J43: Under warranty till 20-12-2024 | K43: Add Nology BB Warranty-12
B44: Yealink | C44: W78H | D44: Yealink W78H DECT Handset | E44: 1 | F44: 1552 | G44: 1089 | H44: Available on request | I44: Gauteng | J44: Warranty expired | K44: Add Nology BB Warranty-12
B45: Yealink | C45: W80B-DM | D45: Yealink W80B-DM Multi-Cell DECT Manager | E45: 1 | F45: 3293 | G45: 2309 | H45: Available on request | I45: Gauteng | J45: Warranty expired | K45: Add Nology BB Warranty-12
B46: Yealink | C46: WH66-DUAL | D46: Yealink WH66 Dual DECT Wireless On Ear Stereo Headset With Touch Screen Base Station | E46: 2 | F46: 3398 | G46: 2379 | H46: Available on request | I46: Gauteng | J46: Warranty expired | K46: Add Nology BB Warranty-12
B47: Yealink | C47: WH67 | D47: Yealink WH67 DECT Wireless Convertible Headset With Touch Screen Base Station (EOL) | E47: 1 | F47: 2999 | G47: 2099 | H47: Available on request | I47: Gauteng | J47: Warranty expired | K47: Add Nology BB Warranty-12
B48: Network
B49: Brand | C49: Code | D49: Product Description | E49: QTY Available | F49: Standard Price | G49: Bargain Bin Price | H49: Condition | I49: Warehouse | J49: Warranty | K49: Comments
B50: MikroTik | C50: CRS112-8P-4S-IN | D50: MikroTik Cloud Router Switch CRS112-8P-4S-IN, 8x GB LAN with POE-out, 4x SFP, desktop case, PSU | E50: 135 | F50: 3231 | G50: 2950 | H50: Excellent / Sealed | I50: Gauteng | J50: Warranty expired | K50: Add Nology BB Warranty-12
B51: MikroTik | C51: CRS310-1G-5S-4S+OUT | D51: MikroTik netFiber 9, 4x 10G SFP+ Ports, 5x 1G SFP Ports, 1x GB Ethernet Port (POE-IN), Outdoor Enclosure, Mounting Kit, PSU, POE Injector | E51: 4 | F51: 3891 | G51: 3614 | H51: New | I51: Gauteng | J51: Warranty expired | K51: Add Nology BB Warranty-12
B52: MikroTik | C52: CSS610-1GI-7R-2S+OUT | D52: MikroTik netPower Lite 7R with 8x GB Ethernet ports (7 with Reverse POE-in, 1 with POE-OUT), 2x SFP+ cages, SwitchOS, outdoor enclosure | E52: 2 | F52: 2674 | G52: 2095 | H52: Excellent / Sealed | I52: Gauteng | J52: Warranty expired | K52: Add Nology BB Warranty-12
B53: Zyxel CH | C53: GS1920-8HPV2 | D53: Zyxel GS1920-8HPv2 Web Managed 8 Port PoE Switch | E53: 8 | F53: 4800 | G53: 4165 | H53: New | I53: Gauteng | J53: Under warranty till 13-02-2028
B54: Zyxel CH | C54: GS1200-8HPV2 | D54: Zyxel GS1200-8HPv2 Switch, 8 Port Gigabit, 4 Port PoE, Web Managed | E54: 15 | F54: 1500 | G54: 1302 | H54: New | I54: Gauteng | J54: Under warranty till 31-05-2027
B55: Zyxel CH | C55: USGFLEX100 | D55: Zyxel USG Flex Firewall 10/100/1000,1*Wan, 1*SFP, 4*LAN/Dmz Ports, 1*USB With 1 Year UTM Bundle | E55: 5 | F55: 7450 | G55: 6236 | H55: New | I55: Gauteng | J55: Under warranty till 22-03-2026
B56: Zyxel CH | C56: GS1915-24E | D56: Zyxel GS1915-24E, 24-port GbE Smart hybrid mode Switch, standalone or NebulaFlex Cloud (NON-POE) | E56: 2 | F56: 3027 | G56: 2725 | H56: New | I56: Gauteng | J56: Under warranty till 15-05-2028
B57: Zyxel CH | C57: GS1915-8EP | D57: Zyxel GS1915-8EP, 8-port GbE PoE Smart hybrid mode Switch, standalone or NebulaFlex Cloud, 60 Watt 802.3at | E57: 15 | F57: 2775 | G57: 2398 | H57: New | I57: Gauteng | J57: Under warranty till 15-05-2028
B58: Zyxel CH | C58: GS1915-8 | D58: Zyxel GS1915-8, 8-port GbE Smart Hybrid Switch, standalone or NebulaFlex Cloud (NON-POE) | E58: 5 | F58: 1475 | G58: 1274 | H58: New | I58: Gauteng | J58: Under warranty till 15-05-2028
B59: Zyxel | C59: WX3100-T0 | D59: Zyxel WX3100 Dual-Band Wi-Fi 6 (1800Mbps) Mesh Node | E59: 247 | F59: 799 | G59: 629 | H59: New | I59: Gauteng | J59: 2 years
B61: Consumer
B62: Brand | C62: Code | D62: Product Description | E62: QTY Available | F62: Standard Price | G62: Bargain Bin Price | H62: Condition | I62: Warehouse | J62: Warranty | K62: Comments
B63: Shelly | C63: SHELLY BLU BUTTON1 (BLUE) | D63: Shelly Bluetooth Button for Operated Actions and Scene Activation (Blue) | E63: 11 | F63: 369 | G63: 299 | H63: New | I63: Gauteng | J63: 2 years
B64: Shelly | C64: SHELLY BLU BUTTON1 (RED) | D64: Shelly Bluetooth Button for Operated Actions and Scene Activation (Red) | E64: 21 | F64: 369 | G64: 299 | H64: New | I64: Gauteng | J64: 2 years
B65: Shelly | C65: SHELLY BLU BUTTON1 (BLACK) | D65: Shelly Bluetooth Button for Operated Actions and Scene Activation (Black) | E65: 4 | F65: 369 | G65: 299 | H65: New | I65: Gauteng | J65: 2 years

Sheet 3CX
E1: Return
B3: * 3CX QUOTES ARE BASED ON THE FEC AVAILABLE * | D3: LIST PRICE - $ PRICE EXCLUDING PARTNER LEVEL DISCOUNT
B4: BASIC | D4: Annual | E4: Comments
B5: BAS-8SCAN | C5: 3CX Basic V20 8SC license | D5: 300 | E5: NEW
B6: BAS-16SCAN | C6: 3CX Basic V20 16SC license | D6: 600 | E6: NEW
B7: BAS-24SCAN | C7: 3CX Basic V20 24SC license | D7: 825 | E7: NEW
B8: BAS-32SCAN | C8: 3CX Basic V20 32SC license | D8: 1015 | E8: NEW
B9: BAS-48SCAN | C9: 3CX Basic V20 48SC license | D9: 1500 | E9: NEW
B10: BAS-64SCAN | C10: 3CX Basic V20 64SC license | D10: 2025 | E10: NEW
B11: BAS-96SCAN | C11: 3CX Basic V20 96SC license | D11: 3000 | E11: NEW
B12: BAS-128SCAN | C12: 3CX Basic V20 128SC license | D12: 4125 | E12: NEW
B13: BAS-192SCAN | C13: 3CX Basic V20 192SC license | D13: 6190 | E13: NEW
B14: BAS-256SCAN | C14: 3CX Basic V20 256SC license | D14: 8250 | E14: NEW
B15: BAS-512SCAN | C15: 3CX Basic V20 512SC license | D15: 13500 | E15: NEW
B16: BAS-1024SCAN | C16: 3CX Basic V20 1024SC license | D16: 24750 | E16: NEW
B17: PROFESSIONAL | D17: Annual | E17: Comments
B18: PRO-8SCAN | C18: 3CX Professional V20 8SC license | D18: 395
B19: PRO-16SCAN | C19: 3CX Professional V20 16SC license | D19: 795
B20: PRO-24SCAN | C20: 3CX Professional V20 24SC license | D20: 1095
B21: PRO-32SCAN | C21: 3CX Professional V20 32SC license | D21: 1350
B22: PRO-48SCAN | C22: 3CX Professional V20 48SC license | D22: 1995
B23: PRO-64SCAN | C23: 3CX Professional V20 64SC license | D23: 2695
B24: PRO-96SCAN | C24: 3CX Professional V20 96SC license | D24: 3995
B25: PRO-128SCAN | C25: 3CX Professional V20 128SC license | D25: 5495
B26: PRO-192SCAN | C26: 3CX Professional V20 192SC license | D26: 8250
B27: PRO-256SCAN | C27: 3CX Professional V20 256SC license | D27: 10995
B28: PRO-512SCAN | C28: 3CX Professional V20 512SC license | D28: 17995
B29: PRO-1024SCAN | C29: 3CX Professional V20 1024SC license | D29: 32995
B30: ENTERPRISE | D30: Annual | E30: Comments
B31: ENT-8SCAN | C31: 3CX Enterprise V20 8SC license | D31: 575
B32: ENT-16SCAN | C32: 3CX Enterprise V20 16SC license | D32: 1095
B33: ENT-24SCAN | C33: 3CX Enterprise V20 24SC license | D33: 1495
B34: ENT-32SCAN | C34: 3CX Enterprise V20 32C license | D34: 1795
B35: ENT-48SCAN | C35: 3CX Enterprise V20 48SC license | D35: 2495
B36: ENT-64SCAN | C36: 3CX Enterprise V20 64SC license | D36: 3235
B37: ENT-96SCAN | C37: 3CX Enterprise V20 96SC license | D37: 4795
B38: ENT-128SCAN | C38: 3CX Enterprise V20 128SC license | D38: 6595
B39: ENT-192SCAN | C39: 3CX Enterprise V20 192SC license | D39: 9900
B40: ENT-256-SCAN | C40: 3CX Enterprise V20 256SC license | D40: 13195
B41: ENT-512SCAN | C41: 3CX Enterprise V20 512SC license | D41: 21915
B42: ENT-1024SCAN | C42: 3CX Enterprise V20 1024SC license | D42: 39595
B43: ENTERPRISE PLUS | D43: Annual | E43: Comments
B44: ENTPLUS-8SCAN | C44: 3CX Enterprise Plus V20 8SC license | D44: 750 | E44: NEW
B45: ENTPLUS-16SCAN | C45: 3CX Enterprise Plus V20 16SC license | D45: 1395 | E45: NEW
B46: ENTPLUS-24SCAN | C46: 3CX Enterprise Plus V20 24SC license | D46: 1895 | E46: NEW
B47: ENTPLUS-32SCAN | C47: 3CX Enterprise Plus V20 32SC license | D47: 2295 | E47: NEW
B48: ENTPLUS-48SCAN | C48: 3CX Enterprise Plus V20 48SC license | D48: 3250 | E48: NEW
B49: ENTPLUS-64SCAN | C49: 3CX Enterprise Plus V20 64SC license | D49: 4135 | E49: NEW
B51: E & OE Terms & Conditions: Pricing valid from 1 April 2026 until 30 April 2026. All pricing is Exclusive of VAT and subject to stock availability and lead times. Pricing is subject to change without notice and is linked to the exchange rate. CLICK HERE to view our full Terms and Conditions.

Sheet Apache Optics
E1: Return
B3: SKU | C3: DESCRIPTION | D3: PRICE | E3: COMMENTS
B4: APACHE OPTICS
B5: 1P-SFP1GESX | C5: Apache Optics 1G SFP - Multimode, 850nm, 550m reach, LC | D5: =INDEX(PRICING!AE:AE,MATCH(B5,PRICING!AD:AD,0),1) -> 431
B6: 1P-SFP1GELX | C6: Apache Optics 1G SFP - Single mode, 1310nm, 10km reach, LC | D6: =INDEX(PRICING!AE:AE,MATCH(B6,PRICING!AD:AD,0),1) -> 482
B7: 1P-SFP1GET | C7: Apache Optics 1000 baseT UTP SFP - RJ-45, 100m reach | D7: =INDEX(PRICING!AE:AE,MATCH(B7,PRICING!AD:AD,0),1) -> 1147
B8: 1P-SFP10GSR | C8: Apache Optics 10G SFP - Multimode, 850nm, 300m reach, LC | D8: =INDEX(PRICING!AE:AE,MATCH(B8,PRICING!AD:AD,0),1) -> 1017
B9: 1P-SFP10GLR | C9: Apache Optics 10G SFP - Single mode, 1310nm, 10km reach, LC | D9: =INDEX(PRICING!AE:AE,MATCH(B9,PRICING!AD:AD,0),1) -> 1448
B10: 1P-SFP10GUTP | C10: Apache Optics 10G UTP SFP - RJ-45, 100m reach | D10: =INDEX(PRICING!AE:AE,MATCH(B10,PRICING!AD:AD,0),1) -> 2954
B11: 1P-SFP25GSR | C11: Apache Optics 25G-SR SFP28 850nm 100m DOM Duplex LC MMF | D11: =INDEX(PRICING!AE:AE,MATCH(B11,PRICING!AD:AD,0),1) -> 1630
B12: 1P-SFP25GLR | C12: Apache Optics 25G-LR SFP28 1310nm 10km DOM Duplex LC SMF | D12: =INDEX(PRICING!AE:AE,MATCH(B12,PRICING!AD:AD,0),1) -> 2547
B13: 1P-SFP25GER | C13: Apache Optics 25G-ER SFP28 1310nm 40km DOM Duplex LC SMF | D13: =INDEX(PRICING!AE:AE,MATCH(B13,PRICING!AD:AD,0),1) -> 10700
B14: 1P-SFP25GZR | C14: Apache Optics 25G-ZR SFP28 1310nm 80km DOM Duplex LC SMF | D14: =INDEX(PRICING!AE:AE,MATCH(B14,PRICING!AD:AD,0),1) -> 101909
B15: 1P-QSFP40GSR | C15: Apache Optics 40G-SR QSFP 850nm 100m DOM Duplex LC MMF | D15: =INDEX(PRICING!AE:AE,MATCH(B15,PRICING!AD:AD,0),1) -> 2038
B16: 1P-QSFP40GLR | C16: Apache Optics 40G-LR QSFP 1310nm 10km DOM Duplex LC SMF | D16: =INDEX(PRICING!AE:AE,MATCH(B16,PRICING!AD:AD,0),1) -> 8152
... B24: 1P-BD1550131010KM | C24: Apache Optics 1G SFP Bi-Directional 1550/1310 Down | D24: =INDEX(PRICING!AE:AE,MATCH(B24,PRICING!AD:AD,0),1) -> 662
B26: SFP's are compatible with the following brands: Dell, Cisco, HP, Juniper, Huawei, Netgear, H3C, Palo Alto, Fortinet, Sophos, Mikrotik, Ubiquity, Zyxel and more. Please specify the brand of switch / router when requesting a quote or placing an order.
B28: E & OE Terms & Conditions: Pricing valid from 1 April 2026 until 30 April 2026. All pricing is Exclusive of VAT and subject to stock availability and lead times. Pricing is subject to change without notice and is linked to the exchange rate. CLICK HERE to view our full Terms and Conditions.

Sheet AudioCodes
B1: Return
B3: Nology is an official distributor of AudioCodes products and solutions
B4: For more information or assistance with the right solution for your requirements, please click HERE.
B30: E & OE Terms & Conditions: Pricing valid from 1 April 2026 until 30 April 2026. All pricing is Exclusive of VAT and subject to stock availability and lead times. Pricing is subject to change without notice and is linked to the exchange rate. CLICK HERE to view our full Terms and Conditions.

Sheet Bark
E1: Return
B3: SKU | C3: DESCRIPTION | D3: PRICE | E3: COMMENTS
B5: BARK HOME 5100-S | C5: Bark Home 5100 Internet Filter Hardware Device | D5: 1599
B7: E & OE Terms & Conditions: Pricing valid from 1 April 2026 until 30 April 2026. All pricing is Exclusive of VAT and subject to stock availability and lead times. Pricing is subject to change without notice and is linked to the exchange rate. CLICK HERE to view our full Terms and Conditions.

Sheet Bluetti
E1: Return
B3: SKU | C3: DESCRIPTION | D3: PRICE | E3: COMMENTS
B4: SOLAR PANELS
B5: PV120 | C5: Bluetti PV120 Solar Panel 120W | D5: =INDEX(PRICING!AN:AN,MATCH(B5,PRICING!AM:AM,0),1) -> 2899 | E5: Volume discounts available from 10+ units EOL (last stock)
B7: E & OE Terms & Conditions: Pricing valid from 1 April 2026 until 30 April 2026. All pricing is Exclusive of VAT and subject to stock availability and lead times. Pricing is subject to change without notice and is linked to the exchange rate. CLICK HERE to view our full Terms and Conditions.

Sheet DNAKE
E1: Return
B3: SKU | C3: DESCRIPTION | D3: PRICE | E3: COMMENTS
B4: INDOOR
B5: 280M-S8 | C5: DNAKE 7" Indoor Monitor (Smart Life App Version) | D5: =INDEX(PRICING!G:G,MATCH(B5,PRICING!F:F,0),1) -> 515 | E5: PROMOTION 2 YEAR WARRANTY
B6: 902M-S8 | C6: DNAKE 7" Android Indoor Monitor | D6: =INDEX(PRICING!G:G,MATCH(B6,PRICING!F:F,0),1) -> 675 | E6: PROMOTION 2 YEAR WARRANTY
B7: 904M-S3 | C7: DNAKE 10.1" Android Indoor Monitor | D7: =INDEX(PRICING!G:G,MATCH(B7,PRICING!F:F,0),1) -> 833 | E7: PROMOTION 2 YEAR WARRANTY
B8: OUTDOOR
B9: 905D-Y4 | C9: DNAKE 7" Android Door Phone with Facial Recognition | D9: =INDEX(PRICING!G:G,MATCH(B9,PRICING!F:F,0),1) -> 2795 | E9: PROMOTION 2 YEAR WARRANTY
B11: E & OE Terms & Conditions: Pricing valid from 1 April 2026 until 30 April 2026. All pricing is Exclusive of VAT and subject to stock availability and lead times. Pricing is subject to change without notice and is linked to the exchange rate. CLICK HERE to view our full Terms and Conditions.

Sheet GoBright
E1: Return
B3: Software Licenses
B4: SKU | C4: DESCRIPTION | D4: PRICE | E4: Amount
B5: Room Booking Licences
B6: GB-ROOM 1-9 | C6: GoBright Room Booking licence, per room (1-9 rooms) | D6: =INDEX(PRICING!CM:CM,MATCH(B6,PRICING!CL:CL,0),1) -> 3360 | E6: 1-9 rooms
B7: GB-ROOM 10-24 | C7: GoBright Room Booking licence, per room (10-24 rooms) | D7: =INDEX(PRICING!CM:CM,MATCH(B7,PRICING!CL:CL,0),1) -> 3150 | E7: 10-24 rooms
B8: GB-ROOM 25-49 | C8: GoBright Room Booking licence, per room (25-49 rooms) | D8: =INDEX(PRICING!CM:CM,MATCH(B8,PRICING!CL:CL,0),1) -> 2940 | E8: 25-49 rooms
B9: GB-ROOM 50+ | C9: GoBright Room Booking licence, per room (50+ rooms) | D9: =INDEX(PRICING!CM:CM,MATCH(B9,PRICING!CL:CL,0),1) -> 2730 | E9: 50+ rooms
B10: Room booking - Add on Licences
B11: GB-ROOMSIG 1-9 | C11: GoBright Digital Signage In-room and on room display licence, per room (1-9 rooms) | D11: =INDEX(PRICING!CM:CM,MATCH(B11,PRICING!CL:CL,0),1) -> 2520 | E11: 1-9 rooms
B12: GB-ROOMSIG 10-24 | C12: GoBright Digital Signage In-room and on room display licence, per room (10-24 rooms) | D12: =INDEX(PRICING!CM:CM,MATCH(B12,PRICING!CL:CL,0),1) -> 2363 | E12: 10-24 rooms
B13: GB-ROOM 25-49 | C13: GoBright Room Booking licence, per room (25-49 rooms) | D13: =INDEX(PRICING!CM:CM,MATCH(B13,PRICING!CL:CL,0),1) -> 2940 | E13: 25-49 rooms
B14: GB-ROOMSIG 50+ | C14: GoBright Digital Signage In-room and on room display licence, per room (50+ rooms) | D14: =INDEX(PRICING!CM:CM,MATCH(B14,PRICING!CL:CL,0),1) -> 2048 | E14: 50+ rooms
B15: GB-CATSERVL | C15: GoBright Catering & Services licence (Per Room) | D15: =INDEX(PRICING!CM:CM,MATCH(B15,PRICING!CL:CL,0),1) -> 1106 | E15: Per Room
B16: Desk Booking Licences
B17: GB-DESK 1-249 | C17: GoBright Desk Booking licence, per desk (1-249 Desks) | D17: =INDEX(PRICING!CM:CM,MATCH(B17,PRICING!CL:CL,0),1) -> 448 | E17: 1-249 desks
B18: GB-DESK 250-999 | C18: GoBright Desk Booking licence, per desk (250-999 Desks) | D18: =INDEX(PRICING!CM:CM,MATCH(B18,PRICING!CL:CL,0),1) -> 420 | E18: 250-999 desks
B19: GB-DESK 1000-1999 | C19: GoBright Desk Booking licence, per desk (1000-1999 Desks) | D19: =INDEX(PRICING!CM:CM,MATCH(B19,PRICING!CL:CL,0),1) -> 392 | E19: 1000-1999 desks
B20: GB-DESK 2000+ | C20: GoBright Desk Booking licence, per desk (2000+ Desks) | D20: =INDEX(PRICING!CM:CM,MATCH(B20,PRICING!CL:CL,0),1) -> 364 | E20: 2000+ desks
B21: Parking Space Licences
B22: GB-PARKING 1-249 | C22: GoBright Parking Space licence, per space (1-249) | D22: =INDEX(PRICING!CM:CM,MATCH(B22,PRICING!CL:CL,0),1) -> 448 | E22: 1-249 spaces
B23: GB-PARKING 250-999 | C23: GoBright Parking Space licence, per space (250-999) | D23: =INDEX(PRICING!CM:CM,MATCH(B23,PRICING!CL:CL,0),1) -> 420 | E23: 250-999 spaces
B24: GB-PARKING 1000-1999 | C24: GoBright Parking Space licence, per space (1000-1999) | D24: =INDEX(PRICING!CM:CM,MATCH(B24,PRICING!CL:CL,0),1) -> 392 | E24: 1000-1999 spaces
B25: GB-PARKING 2000+ | C25: GoBright Parking Space licence, per space (2000+) | D25: =INDEX(PRICING!CM:CM,MATCH(B25,PRICING!CL:CL,0),1) -> 364 | E25: 2000+ spaces
B26: Mapping Licenses
B27: GB-MAP 1-9 | C27: GoBright Mapping licence, per floorplan (1-9 Maps) | D27: =INDEX(PRICING!CM:CM,MATCH(B27,PRICING!CL:CL,0),1) -> 6286 | E27: 1-9 maps
B28: GP-MAP 10-24 | C28: GoBright Mapping licence, per floorplan (10-24 Maps) | D28: =INDEX(PRICING!CM:CM,MATCH(B28,PRICING!CL:CL,0),1) -> 5893 | E28: 10-24 maps
B29: GB-MAP 25-49 | C29: GoBright Mapping licence, per floorplan (25-49 Maps) | D29: =INDEX(PRICING!CM:CM,MATCH(B29,PRICING!CL:CL,0),1) -> 5500 | E29: 25-49 maps
B30: GB-MAP 50+ | C30: GoBright Mapping licence, per floorplan (50+ Maps) | D30: =INDEX(PRICING!CM:CM,MATCH(B30,PRICING!CL:CL,0),1) -> 5107 | E30: 50+ maps
B31: Visitor Registration Licences
B32: GB-VISITL | C32: GoBright Digital Self-registration licence (Per Location) | D32: =INDEX(PRICING!CM:CM,MATCH(B32,PRICING!CL:CL,0),1) -> 17500 | E32: per location
B33: Digital Signage Licences
B34: GB-VIEW-CORE 1-9 | C34: GoBright Digital Signage licence, per player (1-9 Players) | D34: =INDEX(PRICING!CM:CM,MATCH(B34,PRICING!CL:CL,0),1) -> 3486 | E34: 1-9 players
B35: GB-VIEW-CORE 10-24 | C35: GoBright Digital Signage licence, per player (10-24 Players) | D35: =INDEX(PRICING!CM:CM,MATCH(B35,PRICING!CL:CL,0),1) -> 3268 | E35: 10-24 players
B36: GB-VIEW-CORE 25-49 | C36: GoBright Digital Signage licence, per player (25-49 Players) | D36: =INDEX(PRICING!CM:CM,MATCH(B36,PRICING!CL:CL,0),1) -> 3050 | E36: 25-49 players
B37: GB-VIEW-CORE 50+ | C37: GoBright Digital Signage licence, per player (50+ Players) | D37: =INDEX(PRICING!CM:CM,MATCH(B37,PRICING!CL:CL,0),1) -> 2832 | E37: 50+ players
B38: Digital Signage - Add on Licences
B39: GB-VIEW-PREMIUM 1-9 | C39: GoBright Premium Digital Signage licence, per player (1-9 Players) | D39: =INDEX(PRICING!CM:CM,MATCH(B39,PRICING!CL:CL,0),1) -> 658 | E39: 1-9 players
B40: GB-VIEW-PREMIUM 10-24 | C40: GoBright Premium Digital Signage licence, per player (10-24 Players) | D40: =INDEX(PRICING!CM:CM,MATCH(B40,PRICING!CL:CL,0),1) -> 617 | E40: 10-24 players
B41: GB-VIEW-PREMIUM 25-49 | C41: GoBright Premium Digital Signage licence, per player (25-49 Players) | D41: =INDEX(PRICING!CM:CM,MATCH(B41,PRICING!CL:CL,0),1) -> 575 | E41: 25-49 players
B42: GB-VIEW-PREMIUM 50+ | C42: GoBright Premium Digital Signage licence, per player (50+ Players) | D42: =INDEX(PRICING!CM:CM,MATCH(B42,PRICING!CL:CL,0),1) -> 535 | E42: 50+ players
B43: Other Licences
B44: GB-WEEKPLANNER | C44: GoBright Week Planner licence (Per Location) | D44: =INDEX(PRICING!CM:CM,MATCH(B44,PRICING!CL:CL,0),1) -> 9086 | E44: per location
B45: GB-WAYFINDERL | C45: GoBright Wayfinding licence (Per Screen) | D45: =INDEX(PRICING!CM:CM,MATCH(B45,PRICING!CL:CL,0),1) -> 5586 | E45: per screen
B46: GB-LOCKERBANK | C46: GoBright Locker integration License (Per Lockerbank) | D46: =INDEX(PRICING!CM:CM,MATCH(B46,PRICING!CL:CL,0),1) -> 6286 | E46: per lockerbank
B47: GB-API-ACCESS | C47: GoBright Access to Desk & Room Booking API for integration or PowerBI analytics | D47: =INDEX(PRICING!CM:CM,MATCH(B47,PRICING!CL:CL,0),1) -> 16786
B48: GB-ANALYTICS-ADV | C48: GoBright Advanced Analytics licence (Per Customer) | D48: =INDEX(PRICING!CM:CM,MATCH(B48,PRICING!CL:CL,0),1) -> 9086 | E48: per customer
B50: E & OE Terms & Conditions: Pricing valid from 1 April 2026 until 30 April 2026. All pricing is Exclusive of VAT and subject to stock availability and lead times. Pricing is subject to change without notice and is linked to the exchange rate. CLICK HERE to view our full Terms and Conditions.

Sheet Call4tel
E1: Return
B3: SKU | C3: DESCRIPTION | D3: PRICE | E3: COMMENTS
B4: CALL4TEL
B5: NX32 LITE | C5: Call4Tel NX32 Lite - PBX Appliance Powered By 3CX (Incl. PSU) - Lightweight Casing | D5: =INDEX(PRICING!J:J,MATCH(B5,PRICING!I:I,0),1) -> 5299 | E5: 2 YEAR WARRANTY
B6: NX96(B) | C6: Call4Tel NX96 PBX Appliance Powered By 3CX Celeron CPU, 8GB Ram, 1TB SSD, 2X GB Ethernet | D6: =INDEX(PRICING!J:J,MATCH(B6,PRICING!I:I,0),1) -> 17499 | E6: 2 YEAR WARRANTY
B7: NX256 | C7: Call4Tel NX256 PBX Appliance Powered By 3CX I5 CPU, 16GB Ram, 1TB SSD, 2X Gb Ethernet, Includes PSU | D7: =INDEX(PRICING!J:J,MATCH(B7,PRICING!I:I,0),1) -> 44999 | E7: 2 YEAR WARRANTY - B2B ONLY Pricing dependent on ROE and shipping charges - please confirm pricing before placing an order
B9: E & OE Terms & Conditions: Pricing valid from 1 April 2026 until 30 April 2026. All pricing is Exclusive of VAT and subject to stock availability and lead times. Pricing is subject to change without notice and is linked to the exchange rate. CLICK HERE to view our full Terms and Conditions.

Sheet Inogeni
E1: Return
B3: SKU | C3: DESCRIPTION | D3: PRICE | E3: COMMENTS
B4: CONVERTORS
B5: 4KX-PLUS | C5: Inogeni Ultra HD HDMI to USB 3.0 camera converter with an HDMI loop | D5: =INDEX(PRICING!AZ:AZ,MATCH(B5,PRICING!AY:AY,0),1) -> 11385 | E5: ETA Confirmed on Order 2 YEAR WARRANTY
B6: 4KXUSB3 | C6: Inogeni Ultra HD to USB 3.0 professional camera converter with an HDMI loop and VISCA port | D6: =INDEX(PRICING!AZ:AZ,MATCH(B6,PRICING!AY:AY,0),1) -> 10893 | E6: ETA Confirmed on Order 2 YEAR WARRANTY
B7: 4K2USB3 | C7: Inogeni Ultra HD to USB 3.0 camera converter | D7: =INDEX(PRICING!AZ:AZ,MATCH(B7,PRICING!AY:AY,0),1) -> 7780 | E7: ETA Confirmed on Order 2 YEAR WARRANTY
B8: HD2USB3 | C8: Inogeni HDMI to USB 3.0 professional 1080p video converter | D8: =INDEX(PRICING!AZ:AZ,MATCH(B8,PRICING!AY:AY,0),1) -> 6306 | E8: ETA Confirmed on Order 2 YEAR WARRANTY
B9: HD2USB3UP | C9: Inogeni Upgrade HD2USB3 to 4k | D9: =INDEX(PRICING!AZ:AZ,MATCH(B9,PRICING!AY:AY,0),1) -> 1440 | E9: ETA Confirmed on Order 2 YEAR WARRANTY
B10: SDI2USB3 | C10: Inogeni Professional video converter to convert SDI to USB3 | D10: =INDEX(PRICING!AZ:AZ,MATCH(B10,PRICING!AY:AY,0),1) -> 8927 | E10: ETA Confirmed on Order 2 YEAR WARRANTY
B11: TOGGLE | C11: Inogeni Toggle - USB 3.0 PRO AV Switcher | D11: =INDEX(PRICING!AZ:AZ,MATCH(B11,PRICING!AY:AY,0),1) -> 8108 | E11: 2 YEAR WARRANTY
B12: TOGGLE ROOMS | C12: Inogeni Toggle Rooms - USB 3.0/HDMI Devices to 2 PCs Switcher (USB-C cable and PS included) | D12: =INDEX(PRICING!AZ:AZ,MATCH(B12,PRICING!AY:AY,0),1) -> 18755 | E12: NEW ETA Confirmed on Order 2 YEAR WARRANTY
B13: U-BRIDGE | C13: Inogeni USB 2.0 video camera and audio extender enables high-speed USB 2.0 connections up to 100 m /330 ft. over a single CAT 5e/6/7 cable | D13: =INDEX(PRICING!AZ:AZ,MATCH(B13,PRICING!AY:AY,0),1) -> 6306 | E13: ETA Confirmed on Order 2 YEAR WARRANTY
B14: U-BRIDGE3 | C14: Inogeni U-BRIDGE 3 - USB 3.2 Gen 1 camera and device extender | D14: =INDEX(PRICING!AZ:AZ,MATCH(B14,PRICING!AY:AY,0),1) -> 13227 | E14: NEW ETA Confirmed on Order 2 YEAR WARRANTY
B15: U-CAM | C15: Inogeni Camera converter converts USB cameras and audio to HDMI for CODECs, matrixes and displays | D15: =INDEX(PRICING!AZ:AZ,MATCH(B15,PRICING!AY:AY,0),1) -> 9746 | E15: ETA Confirmed on Order 2 YEAR WARRANTY
B16: INOGENI SHARE
B17: SHARE2U | C17: Inogeni Share2U Plug-and-Go Mixer for 2 USB or HDMI Cameras | D17: =INDEX(PRICING!AZ:AZ,MATCH(B17,PRICING!AY:AY,0),1) -> 34316 | E17: 2 YEAR WARRANTY
B18: SHARE2 | C18: Inogeni Dual HDMI/DVI to USB 3.0 camera mixer. 2 HDMI camera input to 1 x USB 3.0 | D18: =INDEX(PRICING!AZ:AZ,MATCH(B18,PRICING!AY:AY,0),1) -> 26126 | E18: ETA Confirmed on Order 2 YEAR WARRANTY
B19: INOGENI CAM
B20: CAM230 | C20: Inogeni USB and HDMI multi-camera switcher. Switch 3 sources (2 x USB 3.0/2.0 and 1 x HDMI to HDMI or USB | D20: =INDEX(PRICING!AZ:AZ,MATCH(B20,PRICING!AY:AY,0),1) -> 15970 | E20: ETA Confirmed on Order 2 YEAR WARRANTY
B21: CAM300 | C21: Inogeni Video switcher 4 sources. 2 x USB 2.0 and 2 x HDMI sources | D21: =INDEX(PRICING!AZ:AZ,MATCH(B21,PRICING!AY:AY,0),1) -> 29402 | E21: ETA Confirmed on Order 2 YEAR WARRANTY
B23: E & OE Terms & Conditions: Pricing valid from 1 April 2026 until 30 April 2026. All pricing is Exclusive of VAT and subject to stock availability and lead times. Pricing is subject to change without notice and is linked to the exchange rate. CLICK HERE to view our full Terms and Conditions.

Sheet H3C SMB
E1: Return
B3: SKU | C3: DESCRIPTION | D3: PRICE | E3: COMMENTS
B4: SOHO SWITCHES
B5: LS-1600V2-6P-HPWR-GL | C5: H3C S1600V2-6P-HPWR L2 Ethernet Switch with 5x 10/100/1000 BASE-T Ports (4x PoE+ Ports) and 1x 1G SFP Port, 73W PoE+ Capacity, AC PSU | D5: =INDEX(PRICING!BX:BX,MATCH(B5,PRICING!BW:BW,0),1) -> 997 | E5: 3 YEAR WARRANTY
B6: LS-1600V2-10P-HPWR-GL | C6: H3C S1600V2-10P-HPWR L2 Ethernet Switch with 9x 10/100/1000 BASE-T Ports (8x PoE+ Ports) and 1x 1G SFP Port, 125W PoE+ Capacity, AC PSU | D6: =INDEX(PRICING!BX:BX,MATCH(B6,PRICING!BW:BW,0),1) -> 1507 | E6: 3 YEAR WARRANTY
B7: LS-1600V2-18P-HPWR-GL | C7: H3C S1600V2-18P-HPWR L2 Ethernet Switch with 16x 10/100/1000 BASE-T PoE+ Ports and 2x 1G SFP Ports, 240W PoE+ Capacity, AC PSU | D7: =INDEX(PRICING!BX:BX,MATCH(B7,PRICING!BW:BW,0),1) -> 3194 | E7: 3 YEAR WARRANTY
B8: LS-1600V2-26P-HPWR-GL | C8: H3C S1600V2-26P-HPWR L2 Ethernet Switch with 24x 10/100/1000 BASE-T PoE+ Ports and 2x 1G SFP Ports, 370W PoE+ Capacity, AC PSU | D8: =INDEX(PRICING!BX:BX,MATCH(B8,PRICING!BW:BW,0),1) -> 4494 | E8: 3 YEAR WARRANTY
B9: LS-1600V2-26S-HPWR-GL | C9: H3C S1600V2-26S-HPWR L2 Ethernet Switch with 24x 10/100/1000 BASE-T PoE+ Ports and 2x 10G SFP+ Ports, 370W PoE+ Capacity, AC PSU | D9: =INDEX(PRICING!BX:BX,MATCH(B9,PRICING!BW:BW,0),1) -> 4672 | E9: 3 YEAR WARRANTY
B10: LS-1850V2-10P-EI-GL | C10: H3C S1850V2-10P-EI L2 Ethernet Switch with 8x 10/100/1000BASE-T Ports and 2x 1000BASE-X SFP Ports, AC PSU | D10: =INDEX(PRICING!BX:BX,MATCH(B10,PRICING!BW:BW,0),1) -> 1683 | E10: 5 YEAR WARRANTY
B11: LS-1850V2-10P-HPWR-EI-GL | C11: H3C S1850V2-10P-HPWR-EI L2 Ethernet Switch with 8x 10/100/1000 BASE-T PoE+ Ports and 2x 1000 BASE-X SFP Ports, 125W PoE Capacity, AC PSU | D11: =INDEX(PRICING!BX:BX,MATCH(B11,PRICING!BW:BW,0),1) -> 2540 | E11: H3C + YEALINK BUNDLE PROMOTION 5 YEAR WARRANTY
B12: LS-1850V2-28P-EI-GL | C12: H3C S1850V2-28P-EI Layer 2 Ethernet Switch 24x 10/100/1000Mbps Ports and 4x 1Gbps SFP Ports, AC PSU | D12: =INDEX(PRICING!BX:BX,MATCH(B12,PRICING!BW:BW,0),1) -> 2345 | E12: PROMOTION 5 YEAR WARRANTY
B13: LS-1850V2-28P-HPWR-EI-GL | C13: H3C S1850V2-28P-HPWR-EI L2 Ethernet Switch with 24x 10/100/1000BASE-T PoE+ Ports, 370W PoE Capacity and 4x 1000BASE-X SFP Ports, AC PSU | D13: =INDEX(PRICING!BX:BX,MATCH(B13,PRICING!BW:BW,0),1) -> 5398 | E13: 5 YEAR WARRANTY
B14: LS-1850V2-52P-EI-GL | C14: H3C S1850V2-52P-EI Layer 2 Ethernet Switch with 48x 10/100/1000Mbps Ethernet Ports and 4x 1Gbps SFP Ports, AC PSU | D14: =INDEX(PRICING!BX:BX,MATCH(B14,PRICING!BW:BW,0),1) -> 4459 | E14: 5 YEAR WARRANTY
B15: LS-1850V2-28X-HPWR-GL | C15: H3C SMB S1850V2-28X-HPWR Layer 2 Ethernet Switch with 24x 10/100/1000Mbps Ethernet PoE+ Ports and 4x 1Gbps/10Gbps SFP+ Ports, 370W PoE+ Capacity, AC PSU | D15: =INDEX(PRICING!BX:BX,MATCH(B15,PRICING!BW:BW,0),1) -> 7085 | E15: 5 YEAR WARRANTY
B16: LS-1850V2-52X-PWR-GL | C16: H3C S1850V2-52X-PWR L2 Ethernet Switch with 48x 10/100/1000 BASE-T PoE+ Ports and 4x 1G/10G BASE-X SFP Plus Ports, AC PSU | D16: =INDEX(PRICING!BX:BX,MATCH(B16,PRICING!BW:BW,0),1) -> 13689 | E16: 5 YEAR WARRANTY
B17: SMB SWITCHES
B18: LS-5120V3-28P-PWR-LI-GL | C18: H3C S5120V3-28P-PWR-LI L3 Ethernet Switch with 24x 10/100/1000 BASE-T PoE+ Ports and 4x1000 BASE-X SFP Ports, 240W PoE+ Capacity, AC PSU | D18: =INDEX(PRICING!BX:BX,MATCH(B18,PRICING!BW:BW,0),1) -> 5530 | E18: H3C + YEALINK BUNDLE PROMOTION 5 YEAR WARRANTY
B19: LS-5120V3-28P-HPWR-LI-GL | C19: H3C S5120V3-28P-HPWR-LI L3 Ethernet Switch with 24x 10/100/1000 BASE-T PoE+ Ports, 4x 100/1000 BASE-X SFP Ports, and 4x GE Combo Ports, 370W PoE+ Capacity, AC PSU | D19: =INDEX(PRICING!BX:BX,MATCH(B19,PRICING!BW:BW,0),1) -> 6199 | E19: H3C + YEALINK BUNDLE PROMOTION 5 YEAR WARRANTY
B20: LS-5120V3-52P-PWR-LI-GL | C20: H3C S5120V3-52P-PWR-LI L3 Ethernet Switch with 48x 10/100/1000 BASE-T PoE+ Ports and 4x 1000 BASE-X SFP Ports, 370W PoE+ Capacity, AC PSU | D20: =INDEX(PRICING!BX:BX,MATCH(B20,PRICING!BW:BW,0),1) -> 11502 | E20: 5 YEAR WARRANTY
B21: LS-5120V3-28S-PWR-LI-GL | C21: H3C S5120V3-28S-PWR-LI L3 Ethernet Switch with 24x 10/100/1000BASE-T PoE+ Ports and 4x 1G/10G BASE-X SFP Plus Ports, 240W PoE+ Capacity, AC PSU | D21: =INDEX(PRICING!BX:BX,MATCH(B21,PRICING!BW:BW,0),1) -> 7722 | E21: 5 YEAR WARRANTY
B22: LS-5120V3-28S-HPWR-LI-GL | C22: H3C S5120V3-28S-HPWR-LI L3 Ethernet Switch with 24x 10/100/1000 BASE-T PoE+ Ports, 4x 100/1000 BASE-X SFP Combo Ports, and 4x 1G/10G BASE-X SFP Plus Ports, 370W PoE+ Capacity, AC PSU | D22: =INDEX(PRICING!BX:BX,MATCH(B22,PRICING!BW:BW,0),1) -> 9865 | E22: 5 YEAR WARRANTY
B23: LS-5120V3-28F-LI-GL | C23: H3C S5120V3-28F-LI L3 Ethernet Switch with 24x 100/1000 Base-X Ports, 2x 10/100/1000 Base-T Combo Ports, 2x 1000 Base-X SFP Ports and 2*1G/10G Basse-X SFP+ Ports, AC PSU | D23: =INDEX(PRICING!BX:BX,MATCH(B23,PRICING!BW:BW,0),1) -> 6175 | E23: PROMOTION 5 YEAR WARRANTY
B24: LS-6520X-16ST-SI-GL | C24: H3C S6520X-16ST-SI L3 Ethernet Switch with 16x 1G/10G Base-X SFP+ Ports (2x Combo Ports), Excludes Power Supplies | D24: =INDEX(PRICING!BX:BX,MATCH(B24,PRICING!BW:BW,0),1) -> 15855 | E24: PROMOTION 3 YEAR WARRANTY
B25: LS-6520X-24ST-SI-GL | C25: H3C S6520X-24ST-SI L3 Ethernet Switch with 24x 1G/10G Base-X SFP+ Ports (2x Combo Ports), Excludes Power Supplies | D25: =INDEX(PRICING!BX:BX,MATCH(B25,PRICING!BW:BW,0),1) -> 19021 | E25: 3 YEAR WARRANTY
B26: WIRELESS ACCESS POINTS
B27: EWP-WA6020 | C27: H3C WA6020 Access Point, Dual Radio 802.11ax (1500Mbps), Internal Antennas, 4 Streams | D27: =INDEX(PRICING!BX:BX,MATCH(B27,PRICING!BW:BW,0),1) -> 1098 | E27: PROMOTION 5 YEAR WARRANTY
B28: EWP-WA6022H | C28: H3C WA6022H Wall-plate Access Point, Dual Radio 802.11ax (1500Mbps), Internal Antennas, 4 Streams, 2x Gb Ethernet Ports | D28: =INDEX(PRICING!BX:BX,MATCH(B28,PRICING!BW:BW,0),1) -> 966 | E28: PROMOTION 5 YEAR WARRANTY
B29: EWP-WA6120 | C29: H3C WA6120 Access Point, Dual Radio 802.11ax (3000Mbps), Internal Antennas, 4 Streams | D29: =INDEX(PRICING!BX:BX,MATCH(B29,PRICING!BW:BW,0),1) -> 1375 | E29: PROMOTION 5 YEAR WARRANTY
B30: EWP-WA6126 | C30: H3C WA6126 Access Point, Dual Radio 802.11ax (5300Mbps), Internal Antennas, 6 Streams | D30: =INDEX(PRICING!BX:BX,MATCH(B30,PRICING!BW:BW,0),1) -> 3162 | E30: 5 YEAR WARRANTY
B31: EWP-WA6120H | C31: H3C WA6120H Wall-plate Access Point, Dual Radio 802.11ax, Internal Antennas, 4 Streams | D31: =INDEX(PRICING!BX:BX,MATCH(B31,PRICING!BW:BW,0),1) -> 1881 | E31: 5 YEAR WARRANTY
B32: EWP-WA6120X | C32: H3C WA6120X Outdoor Access Point, Dual Radio 802.11ax, Internal Antennas, 4 Streams | D32: =INDEX(PRICING!BX:BX,MATCH(B32,PRICING!BW:BW,0),1) -> 3506 | E32: 5 YEAR WARRANTY
B33: WIRELESS CONTROLLERS
B34: EWP-WSG1812X-PWR | C34: H3C WSG1812X-PWR Wireless Service Gateway, 16-Port (12x 1000BASE-T PoE+, 2x GE WAN and 2x SFP Plus), 150W PoE Budget, Max. 64 Access Points | D34: =INDEX(PRICING!BX:BX,MATCH(B34,PRICING!BW:BW,0),1) -> 6087 | E34: 5 YEAR WARRANTY
B35: EWP-WSG1840X | C35: H3C WSG1840X Wireless Service Gateway, 8-Port (4x 1000BASE-T, 1x 5GE-T, 2x GE WAN and 1x SFP Plus), Max. 128 Access Points | D35: =INDEX(PRICING!BX:BX,MATCH(B35,PRICING!BW:BW,0),1) -> 6135 | E35: 5 YEAR WARRANTY
B36: FIREWALLS
B37: NS-SecPath F100-C-A1-I | C37: H3C SecPath F100-C-A1 Firewall Appliance | D37: =INDEX(PRICING!BX:BX,MATCH(B37,PRICING!BW:BW,0),1) -> 4741 | E37: 5 YEAR WARRANTY
B38: ROUTERS
B39: RT-MSR610 | C39: H3C MSR610 Enterprise 6-Port Gigabit Ethernet Router, 2x Gb Ethernet WAN (1GE+1SFP), 4x Gb Ethernet LAN/WAN | D39: =INDEX(PRICING!BX:BX,MATCH(B39,PRICING!BW:BW,0),1) -> 2246 | E39: PROMOTION 5 YEAR WARRANTY
B40: SFP MODULES
B41: SFP-GE-SX-MM850-A | C41: H3C 1000BASE-SX SFP Transceiver, Multi-Mode (850nm, 550m, LC) | D41: =INDEX(PRICING!BX:BX,MATCH(B41,PRICING!BW:BW,0),1) -> 1681 | E41: 1 YEAR WARRANTY
B42: SFP-GE-LX-SM1310-A | C42: H3C 1000BASE-LX SFP Transceiver, Single Mode (1310nm, 10km, LC) | D42: =INDEX(PRICING!BX:BX,MATCH(B42,PRICING!BW:BW,0),1) -> 3738 | E42: 1 YEAR WARRANTY
B43: SFP-XG-SX-MM850-E | C43: H3C SFP+ Module (850nm, 300m, LC) | D43: =INDEX(PRICING!BX:BX,MATCH(B43,PRICING!BW:BW,0),1) -> 814 | E43: 1 YEAR WARRANTY
B44: SFP-XG-LX-SM1310 | C44: H3C SFP+ Module (1310nm, 10km, LC) | D44: =INDEX(PRICING!BX:BX,MATCH(B44,PRICING!BW:BW,0),1) -> 1481 | E44: 1 YEAR WARRANTY
B45: ACCESSORIES
B46: EWPAM1HPOE-GL | C46: H3C EWPAM1HPOE 55V/30W Single port POE Injector | D46: =INDEX(PRICING!BX:BX,MATCH(B46,PRICING!BW:BW,0),1) -> 343 | E46: 1 YEAR WARRANTY
B47: SOHO-SWITCH-FL-02 | C47: H3C Angle Mount for H3C Switches (13-Inch Chassis) | D47: =INDEX(PRICING!BX:BX,MATCH(B47,PRICING!BW:BW,0),1) -> 26 | E47: 1 YEAR WARRANTY
B48: RTU-FL-F | C48: H3C Mounting Kit for MSR610and MSR810, (2 Brackets and 8 Screws) | D48: =INDEX(PRICING!BX:BX,MATCH(B48,PRICING!BW:BW,0),1) -> 56 | E48: 1 YEAR WARRANTY
B49: PSR75-12A-GL | C49: H3C 75W AC Pluggable Power Supply Module for LS-6520X switches | D49: =INDEX(PRICING!BX:BX,MATCH(B49,PRICING!BW:BW,0),1) -> 1102 | E49: 3 YEAR WARRANTY
B51: E & OE Terms & Conditions: Pricing valid from 1 April 2026 until 30 April 2026. All pricing is Exclusive of VAT and subject to stock availability and lead times. Pricing is subject to change without notice and is linked to the exchange rate. CLICK HERE to view our full Terms and Conditions.

Sheet H3C Enterprise
E1: Return
B3: SKU | C3: DESCRIPTION | E3: PRICE | F3: COMMENTS
B4: ENTERPRISE POE ACCESS SWITCHES
B5: LS-5130S-28P-HPWR-EI-AC-GL | C5: H3C S5130S-28P-HPWR-EI-AC L2 Ethernet Switch with 24x 10/100/1000BASE-T PoE+ Ports (AC 370W), 4x 100/1000BASE-X SFP Ports, and 4x GE Combo Ports, (AC) | E5: P.O.R | F5: NOW IN STOCK
B6: LS-5130S-52P-PWR-EI-AC-GL | C6: H3C S5130S-52P-PWR-EI-AC L2 Ethernet Switch with 48x 10/100/1000BASE-T PoE+ Ports (AC 370W) and 4x 1000BASE-X SFP Ports, (AC) | E6: P.O.R | F6: NOW IN STOCK
B7: LS-5170-28S-HPWR-EI-GL | C7: H3C S5170-28S-HPWR-EI L2 Ethernet Switch with 24x 10/100/1000BASE-T Ports and 4x 1G/10G BASE-X SFP Plus Ports, (AC), PoE+ | E7: P.O.R | F7: NOW IN STOCK
B8: ENTERPRISE WIRELESS ACCESS POINTS
B9: EWP-WA6520-FIT | C9: H3C WA6520 Internal Antennas 4 Streams Dual Radio 802.11ax/ac/n Access Point,FIT | E9: P.O.R | F9: NOW IN STOCK
B10: EWP-WA6528I-FIT | C10: H3C WA6528i Internal Antennas 8 Streams Dual Radio 802.11ax/ac/n Access Point, FIT | E10: P.O.R | F10: NOW IN STOCK
B11: EWP-WA6620X-FIT | C11: H3C WA6620X Integrated Internal and External Antennas 4 Streams Dual Radio 802.11ax/ac/n External Access Point | E11: P.O.R | F11: NOW IN STOCK
B13: Nology is an Official Distributor of H3C Enterprise Solutions
B38: E & OE Terms & Conditions: Pricing valid from 1 April 2026 until 30 April 2026. All pricing is Exclusive of VAT and subject to stock availability and lead times. Pricing is subject to change without notice and is linked to the exchange rate. CLICK HERE to view our full Terms and Conditions.

Sheet Huawei
E1: Return
B3: SKU | C3: DESCRIPTION | D3: PRICE | E3: COMMENTS
B4: HUAWEI ACCESS POINTS
B5: AP362 | C5: Huawei Wireless AP362 Wi-Fi 6, indoor, Dual Radio , 2*2 MU-MIMO, 1*GE Base-T, internal smart antennas | D5: =INDEX(PRICING!BI:BI,MATCH(B5,PRICING!BH:BH,0),1) -> 1843
B6: AP160 | C6: Huawei Wireless AP160 Wi-Fi 6, Indoor,2+2 dual bands,RJ45 x2, smart antenna | D6: =INDEX(PRICING!BI:BI,MATCH(B6,PRICING!BH:BH,0),1) -> 975
B7: AP761 | C7: Huawei Wireless AP761 Wif-Fi 6 outdoor,2+2 dual bands,built-in antenna | D7: =INDEX(PRICING!BI:BI,MATCH(B7,PRICING!BH:BH,0),1) -> 3099
B8: AP361 | C8: Huawei Wireless AP361 Wi-Fi 6, Indoor, Dual bands, RJ45 x 1,smart antenna | D8: =INDEX(PRICING!BI:BI,MATCH(B8,PRICING!BH:BH,0),1) -> 791
B9: AP371 | C9: Huawei eKit Wireless AP371 Wi-Fi 7, Indoor, Dual Radio , 2*2 MU-MIMO, 1*GE Base-T, internal smart antennas | D9: =INDEX(PRICING!BI:BI,MATCH(B9,PRICING!BH:BH,0),1) -> 1390
B10: HUAWEI WIRELESS ACCESS CONTROLLERS
B11: AC650-128AP | C11: Huawei AC650-128AP Wireless Access Controller 10 x GE ports, 2 x 10GE SFP+ ports, built-in 128 license | D11: =INDEX(PRICING!BI:BI,MATCH(B11,PRICING!BH:BH,0),1) -> 6037
B12: HUAWEI MULTI-SERVICE GATEWAY
B13: S380-L4T1T | C13: Huawei Multi-Service Gateway, 1 x GE WAN, 4 x GE LAN, up to 150 users,forwarding performance 2Gbps | D13: =INDEX(PRICING!BI:BI,MATCH(B13,PRICING!BH:BH,0),1) -> 1936
B14: S380-H8T3ST | C14: Huawei eKIT Multi-Service Gateway, 2 x GE WAN, 1*GE(SFP) WAN, 8 x GE LAN, up to 500 users, forwarding performance 2Gbps | D14: =INDEX(PRICING!BI:BI,MATCH(B14,PRICING!BH:BH,0),1) -> 6406
B15: S380-L4P1T | C15: Huawei eKIT Multi-Service Gateway 1 x GE WAN, 4 x GE LAN(PoE+, 50W), up to 150 users,forwarding performance 2Gbps | D15: =INDEX(PRICING!BI:BI,MATCH(B15,PRICING!BH:BH,0),1) -> 2788
B16: S380-S8P2T | C16: Huawei eKIT Multi-Service Gateway, 2 x GE WAN, 8 x GE LAN(PoE+, 124W), up to 350 users,forwarding performance 2Gbps | D16: =INDEX(PRICING!BI:BI,MATCH(B16,PRICING!BH:BH,0),1) -> 4468
B17: HUAWEI UNMANAGED SWITCH
B18: S110-8P2ST | C18: Huawei S110-8LP2ST Unmanaged Switch 8 x 10/100/1000BASE-T ports, 1 x GE SFP ports, 1 x 10/100/1000BASE-T port, PoE+ | D18: =INDEX(PRICING!BI:BI,MATCH(B18,PRICING!BH:BH,0),1) -> 733
B19: S110-16LP2SR | C19: Huawei S110-16LP2SR Unmanaged Switch 16 x 10/100/1000BASE-T ports, 2 x GE SFP ports, PoE+ | D19: =INDEX(PRICING!BI:BI,MATCH(B19,PRICING!BH:BH,0),1) -> 2951
B20: S110-24LP2SR | C20: Huawei S110-24LP2SR Unmanaged Switch 24 x 10/100/1000BASE-T ports, 2 x GE SFP ports, PoE+ | D20: =INDEX(PRICING!BI:BI,MATCH(B20,PRICING!BH:BH,0),1) -> 4250
B21: HUAWEI LAYER 2 MANAGED SWITCH
B22: S220-8P4S | C22: Huawei eKit S220-8P4S Layer 2 Managed Switch, 8 x 10/100/1000BASE-T(125W POE+) ports, 4 x 1GE SFP ports | D22: =INDEX(PRICING!BI:BI,MATCH(B22,PRICING!BH:BH,0),1) -> 2644
B23: S220-8T4S | C23: Huawei eKit S220-8T4S Layer 2 Managed Switch, 8 x 10/100/1000BASE-T ports, 4 x 1GE SFP ports | D23: =INDEX(PRICING!BI:BI,MATCH(B23,PRICING!BH:BH,0),1) -> 1756
B24: S220-24T4X | C24: Huawei S220-24T4X Layer 2 Managed Switch, 24 x 10/100/1000BASE-T ports, 4 x 10GE SFP+ ports | D24: =INDEX(PRICING!BI:BI,MATCH(B24,PRICING!BH:BH,0),1) -> 4474
B25: S220-24P4X | C25: Huawei S220-24P4X Layer 2 Managed Switch, 24 x 10/100/1000BASE-T ports(400W PoE+), 4 x 10GE SFP+ ports | D25: =INDEX(PRICING!BI:BI,MATCH(B25,PRICING!BH:BH,0),1) -> 5333
B26: S220-48T4X | C26: Huawei S220-48T4X Layer 2 Managed Switch, 48 x 10/100/1000BASE-T ports, 4 x 10GE SFP+ ports | D26: =INDEX(PRICING!BI:BI,MATCH(B26,PRICING!BH:BH,0),1) -> 7891
B27: S220-48T4S | C27: Huawei S220-48T4S Layer 2 Managed Switch, 48 x 10/100/1000BASE-T ports, 4 x GE SFP ports | D27: =INDEX(PRICING!BI:BI,MATCH(B27,PRICING!BH:BH,0),1) -> 5688
B28: S220-48P4X | C28: Huawei S220-48P4X Layer 2 Managed Switch, 48 x 10/100/1000BASE-T ports(380W PoE+), 4 x 10GE SFP+ ports | D28: =INDEX(PRICING!BI:BI,MATCH(B28,PRICING!BH:BH,0),1) -> 9471
B29: S220-48P4S | C29: Huawei S220-48P4S Layer 2 Managed Switch, 48 x 10/100/1000BASE-T ports(380W PoE+), 4 x GE SFP ports | D29: =INDEX(PRICING!BI:BI,MATCH(B29,PRICING!BH:BH,0),1) -> 8462
B30: HUAWEI LAYER 2 PLUS MANAGED SWITCH
B31: S310-24P4S | C31: Huawei S310-24P4S Layer 2+ Managed Switch, 24 x 10/100/1000BASE-T ports, 4 x GE SFP ports, POE+(370W) | D31: =INDEX(PRICING!BI:BI,MATCH(B31,PRICING!BH:BH,0),1) -> 5737
B32: S310-24T4X | C32: Huawei S310-24T4X Layer 2+ Managed Switch, 24 x 10/100/1000BASE-T ports, 4 x 10GE SFP+ ports | D32: =INDEX(PRICING!BI:BI,MATCH(B32,PRICING!BH:BH,0),1) -> 4663
B33: S310-24P4X | C33: Huawei S310-24P4X Layer 2+ Managed Switch, 24 x 10/100/1000BASE-T ports(400W PoE+), 4 x 10GE SFP+ ports | D33: =INDEX(PRICING!BI:BI,MATCH(B33,PRICING!BH:BH,0),1) -> 6628
B34: S310-48T4X | C34: Huawei S310-48T4X Layer 2+ Managed Switch, 48 x 10/100/1000BASE-T ports, 4 x 10GE SFP+ ports | D34: =INDEX(PRICING!BI:BI,MATCH(B34,PRICING!BH:BH,0),1) -> 10814
B35: S310-48P4X | C35: Huawei S310-48P4X Layer 2+ Managed Switch, 48 x 10/100/1000BASE-T ports(380W PoE+), 4 x 10GE SFP+ ports | D35: =INDEX(PRICING!BI:BI,MATCH(B35,PRICING!BH:BH,0),1) -> 10072
B36: S310-48P4S | C36: Huawei S310-48P4S Layer 2+ Managed Switch, 48 x 10/100/1000BASE-T ports(380W PoE+), 4 x GE SFP ports | D36: =INDEX(PRICING!BI:BI,MATCH(B36,PRICING!BH:BH,0),1) -> 10505
B37: HUAWEI LAYER 3 MANAGED SWITCH
B38: S530-24ST4XE | C38: Huawei S530-24ST4XE Layer 3 Managed Switch, 24 x 10/100/1000BASE-T ports, 8 x 1Gbps Ports Dual Purpose RJ45 or SFP, 4 x 10GE SFP+ ports, 2 x 12GE Stack ports | D38: =INDEX(PRICING!BI:BI,MATCH(B38,PRICING!BH:BH,0),1) -> 8124
B39: S530-24T4XE | C39: Huawei S530-24T4XE Layer 3 Managed Switch, 24 x 10/100/1000BASE-T ports, 4 x 10GE SFP+ ports, 2 x 12GE Stack ports | D39: =INDEX(PRICING!BI:BI,MATCH(B39,PRICING!BH:BH,0),1) -> 6773
B40: S530-48S4XE | C40: Huawei S530-48S4XE Layer 3 Managed Switch, 48 x 10/100/1000BASE-T ports, 4 x 10GE SFP+ ports, 2 x 12GE Stack ports | D40: =INDEX(PRICING!BI:BI,MATCH(B40,PRICING!BH:BH,0),1) -> 11809
B41: HUAWEI FIREWALLS
B42: USG6000E-S13 | C42: USG6000E-S13-AC,USG6000E-S13-AC,USG6000E-S13-AC Host(2*GE RJ45 + 8*GE COMBO + 2*10GE SFP+,1 AC power,Include SSL VPN 100 Users) | D42: =INDEX(PRICING!BI:BI,MATCH(B42,PRICING!BH:BH,0),1) -> 18678 | E42: License On Request
B43: HUAWEI INTERACTIVE DISPLAYS
B44: IHB2-65PU | C44: Huawei IdeaHub B2 IHB2-65PU Intelligent Collaboration Device 65-inch infrared screen Jade white | D44: =INDEX(PRICING!BI:BI,MATCH(B44,PRICING!BH:BH,0),1) -> 43763
B45: IHB2-75PU | C45: Huawei IdeaHub B2 IHB2-75PU Intelligent Collaboration Device 75-inch infrared screen Jade white | D45: =INDEX(PRICING!BI:BI,MATCH(B45,PRICING!BH:BH,0),1) -> 64152
B46: IHB2-86PU | C46: Huawei IdeaHub B2 IHB2-86PU Intelligent Collaboration Device 86-inch infrared screen Jade white | D46: =INDEX(PRICING!BI:BI,MATCH(B46,PRICING!BH:BH,0),1) -> 87694
B47: IHB3-65SA | C47: Huawei IdeaHub B3 IHB3-65PU Intelligent Collaboration Device 65-inch infrared screen Jade white | D47: =INDEX(PRICING!BI:BI,MATCH(B47,PRICING!BH:BH,0),1) -> 49455
B48: IHB3-75SA | C48: Huawei IdeaHub B3 IHB3-75SA Intelligent Collaboration Device 75-inch infrared screen Jade white | D48: =INDEX(PRICING!BI:BI,MATCH(B48,PRICING!BH:BH,0),1) -> 70038
B49: IHB3-86SA | C49: Huawei IdeaHub B3 IHB3-86PU Intelligent Collaboration Device 86-inch infrared screen Jade white | D49: =INDEX(PRICING!BI:BI,MATCH(B49,PRICING!BH:BH,0),1) -> 94070
B50: IHS2-65SA | C50: Huawei IdeaHub S2 Intelligent Collaboration Device 65-inch infrared screen Jade white | D50: =INDEX(PRICING!BI:BI,MATCH(B50,PRICING!BH:BH,0),1) -> 61363
B51: IHS2-75SA | C51: Huawei IdeaHub S2 IHS2-75SA Intelligent Collaboration Device 75-inch infrared screen Jade white | D51: =INDEX(PRICING!BI:BI,MATCH(B51,PRICING!BH:BH,0),1) -> 83881
B52: IHS2-86SA | C52: Huawei IdeaHub S2 Intelligent Collaboration Device 86-inch infrared screen Jade white | D52: =INDEX(PRICING!BI:BI,MATCH(B52,PRICING!BH:BH,0),1) -> 112030
B53: IHS3-75SA | C53: Huawei Ideahub interactive 75" S3 Series | D53: =INDEX(PRICING!BI:BI,MATCH(B53,PRICING!BH:BH,0),1) -> 76917
B54: IHS3-65SA | C54: Huawei ideahub 65" S3 series | D54: =INDEX(PRICING!BI:BI,MATCH(B54,PRICING!BH:BH,0),1) -> 56268
B55: IdeaPresence 138 | C55: Huawei 138-inch LED All-in-One Display | D55: P.O.A
B56: HUAWEI INTERACTIVE DISPLAYS ACCESSORIES
B57: ICD OPS i7 Z | C57: Huawei OPS i7-10700 D PC module | D57: =INDEX(PRICING!BI:BI,MATCH(B57,PRICING!BH:BH,0),1) -> 25237
B58: WB1M0IDEAHUB07 | C58: Huawei Ideahub White Rolling Stand II (65/75/86 inches) | D58: =INDEX(PRICING!BI:BI,MATCH(B58,PRICING!BH:BH,0),1) -> 5164
B59: WB1M0BRACKET01 | C59: Huawei Wall Mount Bracket | D59: =INDEX(PRICING!BI:BI,MATCH(B59,PRICING!BH:BH,0),1) -> 892
B60: HWA-01 | C60: Huawei Ideashare Key-typeC | D60: =INDEX(PRICING!BI:BI,MATCH(B60,PRICING!BH:BH,0),1) -> 2101
B61: IHC | C61: Huawei IdeaHub Controller | D61: =INDEX(PRICING!BI:BI,MATCH(B61,PRICING!BH:BH,0),1) -> 369
B62: HUAWEI INTERACTIVE DISPLAYS Maintenance card
B63: B2-65MC | C63: B2 65inch Maintenance card | D63: R1 412,00 | E63: License On Request
B64: B2-75/86MC | C64: B2 75/86inch Maintenance card | D64: R1 927,00 | E64: License On Request
B65: S2-65MC | C65: S2 65inch Maintenance card | D65: R1 927,00 | E65: License On Request
B66: S2-75/86MC | C66: S2 75/86inch Maintenance card | D66: R2 639,00 | E66: License On Request
B69: E & OE Terms & Conditions: Pricing valid from 1 April 2026 until 30 April 2026. All pricing is Exclusive of VAT and subject to stock availability and lead times. Pricing is subject to change without notice and is linked to the exchange rate. CLICK HERE to view our full Terms and Conditions.

Sheet LG
F1: Return
B3: Series | C3: SKU | D3: DESCRIPTION | E3: PRICE | F3: COMMENTS
B4: Professional Display
B5: FHD | C5: 22SM3G | D5: LG 22" FHD Signage Display, Brightness : 250nit, 16-hour duty cycle, Portrait / Landscape, Built-in Quad Core SoC, webOS 4.1 | E5: =_xlfn.XLOOKUP(C5,PRICING!L4:L20,PRICING!M4:M20) -> 6334 | F5: Spec Sheet
C6: 32SM5JB | D6: LG 32" FHD Signage Display, 400nit, 24-hour duty cycle, Portrait and Landscape, Haze 1%, SOC, Internal Memory 8GB, WebOS 6.0 | E6: =_xlfn.XLOOKUP(C6,PRICING!L5:L21,PRICING!M5:M21) -> 7205 | F6: Spec Sheet
B7: UHD | C7: 43UH5QE | D7: LG 43" 4K UHD Signage Display, ADS Panel, 500nit, 24-hour duty cycle, Portrait and Landscape, Haze 25%, SOC, Internal Memory 16GB, webOS 8.0 | E7: =_xlfn.XLOOKUP(C7,PRICING!L6:L22,PRICING!M6:M22) -> 10168 | F7: Spec Sheet
C8: 49UH5NM | D8: LG 49" UHD Signage Display, 4K UHD, 500nit, 24-hour duty cycle, Built-in Speaker, Portrait and Landscape, Haze 28%, SOC, Internal Memory 16GB, WebOS 6.0 | E8: =_xlfn.XLOOKUP(C8,PRICING!L7:L23,PRICING!M7:M23) -> 12317 | F8: Spec Sheet
C9: 55UH5Q-E | D9: LG 55" 4K UHD Signage Display, ADS Panel, 500nit, 24-hour duty cycle, Portrait and Landscape, Haze 25%, SOC, Internal Memory 16GB, webOS 8.0, Embedded IR | E9: =_xlfn.XLOOKUP(C9,PRICING!L8:L24,PRICING!M8:M24) -> 13250 | F9: Spec Sheet
C10: 65UL3Q-E | D10: LG 65" 4K UHD Signage Display, ADS Panel, Brightness: 350nit, 16-hour duty cycle, Portrait and Landscape, Haze 1%, Internal Memory 8GB, webOS 6.1 , Embedded IR | E10: =_xlfn.XLOOKUP(C10,PRICING!L9:L25,PRICING!M9:M25) -> 16676 | F10: Spec Sheet
C11: 65UH5Q-E | D11: LG 65" 4K UHD Signage Display, ADS Panel, 500nit, 24-hour duty cycle, Portrait and Landscape, Haze 25%, SOC, Internal Memory 16GB, webOS 8.0, Embedded IR | E11: =_xlfn.XLOOKUP(C11,PRICING!L10:L26,PRICING!M10:M26) -> 16676 | F11: Spec Sheet
C12: 75UH5N-M | D12: LG 75" UHD Signage Display, Brightness: 500nit, 24-hour duty cycle, Built-in Speaker, Portrait and Landscape, Haze 25%, SOC, Internal Memory 16GB, WebOS 6.0 | E12: 32608 | F12: Spec Sheet
C13: 86UL5Q-E | D13: LG 86" 4K UHD Signage Display, ADS Panel, Brightness: 500nit, 24-hour duty cycle, (30,000-hours lifespan), Portrait and Landscape, Haze 1%, Internal Memory 8GB, webOS 6.1 | E13: 40790 | F13: Spec Sheet
C14: 98UM5K | D14: LG 98" Professional Display, Resolution: 3840 x 2160 (UHD), Brightness: 500nit, 16-hour duty cycle, Haze 25%, Portrait and Landscape, Internal Memory 16GB, SOC, webOS 6.0 | E14: 89483 | F14: Spec Sheet
C15: 98UH5J-H | D15: LG 98" Professional Display, 3840 x 2160 (UHD), 500nit, 24-hour duty cycle, Built-in Speaker, Portrait and Landscape, Haze 28%, SOC, Internal Memory 16GB, WebOS 6.0 | E15: 114130 | F15: Spec Sheet
C16: 110UM5K | D16: LG 110" Professional Display, Resolution: 3840 x 2160 (UHD), Brightness: 500nit, 16-hour duty cycle, Haze 1%, Landscape only, Internal Memory 16GB, SOC, webOS 6.0 | E16: 209783 | F16: Spec Sheet
B17: Interative Touch
B18: TR3DK | C18: 55TR3DQ | D18: LG 55" CreateBoard: 4K UHD, 400 nit, 16/7 hour Duty Cycle, Ops Slot, Multi-Touch Point: 50 Points (Max), OS Version : Android 14(EDLA), Built-in speakers | E18: 24999 | F18: Spec Sheet
C19: 65TR3DQ | D19: LG 65" CreateBoard: 4K UHD, 400 nit, 16/7 hour Duty Cycle, Ops Slot, Multi-Touch Point: 50 Points (Max), OS Version : Android 14(EDLA), Built-in speakers | E19: 28260 | F19: Spec Sheet
C20: 75TR3DQ | D20: LG 75" CreateBoard: 4K UHD, 400 nit, 16/7 hour Duty Cycle, Ops Slot, Multi-Touch Point: 50 Points (Max), OS Version : Android 14(EDLA), Built-in speakers | E20: 32608 | F20: Spec Sheet
C21: 86TR3DQ | D21: LG 86" CreateBoard: 4K UHD, 400 nit, 16/7 hour Duty Cycle, Ops Slot, Multi-Touch Point: 50 Points (Max), OS Version : Android 14(EDLA), Built-in speakers | E21: 38042 | F21: Spec Sheet
B22: Commercial Lite TV Signage
B23: TV Signage | C23: 75UR640S | D23: LG 75" UHD TV Signage, Brightness: 400nits, Crestron Connect certified, 64MB storage, 16/7 duty cycle, SuperSign SW Compatible, Landscape only (SABC TV License Required) | E23: 18477 | F23: Spec Sheet
B25: E & OE Terms & Conditions: Pricing valid from 1 April 2026 until 30 April 2026. All pricing is Exclusive of VAT and subject to stock availability and lead times. Pricing is subject to change without notice and is linked to the exchange rate. CLICK HERE to view our full Terms and Conditions.

Sheet Logitech
E1: Return
B3: SKU | C3: DESCRIPTION | E3: COMMENTS
B4: Headsets
B5: 981-000406 | C5: Logitech H390 USB Computer Headset - USB- HYBRID ONLY | D5: =INDEX(PRICING!BC:BC,MATCH(B5,PRICING!BB:BB,0),1) -> 419 | E5: 2 YEAR WARRANTY
B6: 981-000575 | C6: Logitech H570e Stereo USB Headset | D6: =INDEX(PRICING!BC:BC,MATCH(B6,PRICING!BB:BB,0),1) -> 999 | E6: 2 YEAR WARRANTY
B7: 981-000519 | C7: Logitech H650e Professional USB Headset Stereo | D7: =INDEX(PRICING!BC:BC,MATCH(B7,PRICING!BB:BB,0),1) -> 1079 | E7: 2 YEAR WARRANTY
B8: 981-001451 | C8: Logitech Zone 305 Bluetooth Headset, inclucding Bluetooth Dongle, Midnight Black, MS Teams Certified | D8: =INDEX(PRICING!BC:BC,MATCH(B8,PRICING!BB:BB,0),1) -> 1699 | E8: 2 YEAR WARRANTY
B9: 981-001458 | C9: Logitech Zone 305 Bluetooth Headset, Midnight Black, MS Teams Certified | D9: =INDEX(PRICING!BC:BC,MATCH(B9,PRICING!BB:BB,0),1) -> 1259 | E9: 2 YEAR WARRANTY
B10: 981-001453 | C10: Logitech Zone 305 headset- MIDNIGHT BLACK - 2.4GHZ/BT | D10: =INDEX(PRICING!BC:BC,MATCH(B10,PRICING!BB:BB,0),1) -> 1829 | E10: 2 YEAR WARRANTY
B11: 985-001082 | C11: Logitech Zone True Wireless - GRAPHITE - 2.4GHZ/BT - PLUGC - EMEA-914 - BTC | D11: =INDEX(PRICING!BC:BC,MATCH(B11,PRICING!BB:BB,0),1) -> 5129 | E11: 2 YEAR WARRANTY
B12: 981-001157 | C12: Logitech Zone Vibe Wireless Bluetooth Headset, Microsoft Certified - Graphite | D12: =INDEX(PRICING!BC:BC,MATCH(B12,PRICING!BB:BB,0),1) -> 1709 | E12: 2 YEAR WARRANTY
B13: 981-001199 | C13: Logitech Zone Vibe Wireless UC - GRAPHITE,A00167/A00172,UC,MFI - BT - N/A - EMEA-914 | D13: =INDEX(PRICING!BC:BC,MATCH(B13,PRICING!BB:BB,0),1) -> 1879 | E13: 2 YEAR WARRANTY
B14: 981-001009 | C14: Logitech Zone Wired Earbuds Teams - GRAPHITE - USB - N/A - EMEA-914 | D14: =INDEX(PRICING!BC:BC,MATCH(B14,PRICING!BB:BB,0),1) -> 1589 | E14: 2 YEAR WARRANTY
B15: 981-000870 | C15: Logitech Zone Wired Teams - GRAPHITE - USB - N/A - EMEA-914 - TEAMS | D15: =INDEX(PRICING!BC:BC,MATCH(B15,PRICING!BB:BB,0),1) -> 1809 | E15: 2 YEAR WARRANTY
B16: 981-001593 | C16: Logitech Zone Wireless 2 ES for Business Bluetooth Headset, MS Teams Certified - Graphite | D16: =INDEX(PRICING!BC:BC,MATCH(B16,PRICING!BB:BB,0),1) -> 3309 | E16: 2 YEAR WARRANTY
... B18: 981-001311 | C18: Logitech Zone Wireless 2 UC - GRAPHITE,UC - 2.4GHZ/BT - N/A - EMEA-914 - A00174,A00172,NO STAND | D18: =INDEX(PRICING!BC:BC,MATCH(B18,PRICING!BB:BB,0),1) -> 5289 | E18: 2 YEAR WARRANTY
B19: WebCams
B20: 960-001592 | C20: Logitech Brio 105 Full HD 1080p USB Webcam - Graphite | D20: =INDEX(PRICING!BC:BC,MATCH(B20,PRICING!BB:BB,0),1) -> 449 | E20: 2 YEAR WARRANTY
B21: 960-001469 | C21: Logitech Brio 305 Full HD 1080p Business Webcam, USB-C - Graphite | D21: =INDEX(PRICING!BC:BC,MATCH(B21,PRICING!BB:BB,0),1) -> 899 | E21: 2 YEAR WARRANTY
B22: 960-001459 | C22: Logitech Brio 505 Full HD 1080p Business Webcam with Rightlight and Integrated privacy Shutter | D22: =INDEX(PRICING!BC:BC,MATCH(B22,PRICING!BB:BB,0),1) -> 2019 | E22: 2 YEAR WARRANTY
B23: 960-001360 | C23: Logitech C920e 1080p Webcam - Black | D23: =INDEX(PRICING!BC:BC,MATCH(B23,PRICING!BB:BB,0),1) -> 1659 | E23: 2 YEAR WARRANTY
B24: 960-001076 | C24: Logitech C925e Business Webcam - 1080p | D24: =INDEX(PRICING!BC:BC,MATCH(B24,PRICING!BB:BB,0),1) -> 1649 | E24: 2 YEAR WARRANTY
B25: 960-000972 | C25: Logitech C930e Business Webcam - 1080p | D25: =INDEX(PRICING!BC:BC,MATCH(B25,PRICING!BB:BB,0),1) -> 1849 | E25: 2 YEAR WARRANTY
B26: 960-001530 | C26: Logitech MX Brio 705 Premium Business Webcam with AI Image Enhancement | D26: =INDEX(PRICING!BC:BC,MATCH(B26,PRICING!BB:BB,0),1) -> 3079 | E26: 2 YEAR WARRANTY
B27: 960-001724 | C27: Logitech WEBCAM - Brio 4K - GRAPHITE - USB - | D27: =INDEX(PRICING!BC:BC,MATCH(B27,PRICING!BB:BB,0),1) -> 2609 | E27: 2 YEAR WARRANTY
B28: Personal Workspace B2B Mouse
B29: 910-003357 | C29: Logitech B100 Optical USB Mouse - BLACK-GREY - USB - HENDRIX WHITE BOX B100 | D29: =INDEX(PRICING!BC:BC,MATCH(B29,PRICING!BB:BB,0),1) -> 89 | E29: 2 YEAR WARRANTY
B30: 910-003357-S | C30: Logitech B100 Optical USB Mouse - BLACK-GREY - USB - HENDRIX WHITE BOX B100 SERIALISED | D30: =INDEX(PRICING!BC:BC,MATCH(B30,PRICING!BB:BB,0),1) -> #N/A | E30: 2 YEAR WARRANTY
B31: 910-006221 | C31: Logitech ERGO M575 for Business - GRAPHITE - BT | D31: =INDEX(PRICING!BC:BC,MATCH(B31,PRICING!BB:BB,0),1) -> 789 | E31: 2 YEAR WARRANTY
B32: 910-006494 | C32: Logitech Lift Vertical Ergonomic Mouse for Business - GRAPHITE / BLACK - 2.4GHZ/BT | D32: =INDEX(PRICING!BC:BC,MATCH(B32,PRICING!BB:BB,0),1) -> 1039 | E32: 2 YEAR WARRANTY
B33: 910-007182 | C33: Logitech M240 for Business - GRAPHITE - 2.4GHZ/BT | D33: =INDEX(PRICING!BC:BC,MATCH(B33,PRICING!BB:BB,0),1) -> 269 | E33: 2 YEAR WARRANTY
B34: 910-007511 | C34: Logitech M520 for Business - GRAPHITE - USB | D34: =INDEX(PRICING!BC:BC,MATCH(B34,PRICING!BB:BB,0),1) -> 449 | E34: 2 YEAR WARRANTY
B35: 910-006959 | C35: Logitech MX Anywhere 3S for Business - PALE GREY - 2.4GHZ/BT - N/A - EMEA28-935 | D35: =INDEX(PRICING!BC:BC,MATCH(B35,PRICING!BB:BB,0),1) -> 1319 | E35: 2 YEAR WARRANTY
B36: 910-006958 | C36: Logitech MX Anywhere 3S Wireless Mouse - 2.4GHZ/BT - N/A - EMEA28-935 | D36: =INDEX(PRICING!BC:BC,MATCH(B36,PRICING!BB:BB,0),1) -> 1359 | E36: 2 YEAR WARRANTY
B37: 910-006582 | C37: Logitech MX Master 3S for Business - GRAPHITE - BT | D37: =INDEX(PRICING!BC:BC,MATCH(B37,PRICING!BB:BB,0),1) -> 1899 | E37: 2 YEAR WARRANTY
B38: 910-006274 | C38: Logitech Signature M650 Wireless Mouse for Business - GRAPHITE - BT - N/A - EMEA-808 - M650 B2B | D38: =INDEX(PRICING!BC:BC,MATCH(B38,PRICING!BB:BB,0),1) -> 509 | E38: 2 YEAR WARRANTY
B39: Personal Workspace keyboard
B40: 920-002479 | C40: Logitech® Keyboard K120 for Business - BLK - US INT'L - USB - N/A - EMEA28-935 | D40: =INDEX(PRICING!BC:BC,MATCH(B40,PRICING!BB:BB,0),1) -> 229 | E40: 2 YEAR WARRANTY
B41: 920-002479-S | C41: Logitech Keyboard K120 for Business - BLK USB- EMEA28-935 SERIALISED | D41: =INDEX(PRICING!BC:BC,MATCH(B41,PRICING!BB:BB,0),1) -> #N/A | E41: 2 YEAR WARRANTY
B42: 920-013333 | C42: Logitech WIRED KB K620 FOR BUSINESS - GRAPHITE - USB | D42: =INDEX(PRICING!BC:BC,MATCH(B42,PRICING!BB:BB,0),1) -> 879 | E42: 2 YEAR WARRANTY
B43: 920-010352 | C43: Logitech ERGO K860 for Business - GRAPHITE - BT | D43: =INDEX(PRICING!BC:BC,MATCH(B43,PRICING!BB:BB,0),1) -> 2239 | E43: 2 YEAR WARRANTY
B44: 920-010251 | C44: Logitech MX KEYS FOR BUSINESS - GRAPHITE - BT | D44: =INDEX(PRICING!BC:BC,MATCH(B44,PRICING!BB:BB,0),1) -> 2059 | E44: 2 YEAR WARRANTY
B45: 920-010608 | C45: Logitech MX Keys Mini For Business - GRAPHITE - US INT'L - 2.4GHZ/BT - N/A - INTNL-973 | D45: =INDEX(PRICING!BC:BC,MATCH(B45,PRICING!BB:BB,0),1) -> 1859 | E45: 2 YEAR WARRANTY
B46: 920-012334 | C46: Logitech Wave Keys for Business - GRAPHITE - US INT'L - 2.4GHZ/BT - N/A - INTNL-973 - B2B | D46: =INDEX(PRICING!BC:BC,MATCH(B46,PRICING!BB:BB,0),1) -> 1029 | E46: 2 YEAR WARRANTY
B47: Personal Workspace Keyboard and Mouse Combo
B48: 920-012077 | C48: Logitech MK370 Combo for Business - GRAPHITE - BT - DONGLE | D48: =INDEX(PRICING!BC:BC,MATCH(B48,PRICING!BB:BB,0),1) -> 699 | E48: 2 YEAR WARRANTY
B49: 920-009204 | C49: Logitech MK470 Slim Keyboard and Mouse Combo - GRAPHITE - US INT'L - 2.4GHZ - N/A - INTNL-973 | D49: =INDEX(PRICING!BC:BC,MATCH(B49,PRICING!BB:BB,0),1) -> 879 | E49: 2 YEAR WARRANTY
B50: 920-013349 | C50: Logitech WIRED COMBO MK620 FOR BUSINESS - GRAPHITE - US INT'L - USB - - USB-C | D50: =INDEX(PRICING!BC:BC,MATCH(B50,PRICING!BB:BB,0),1) -> 1239 | E50: 2 YEAR WARRANTY
B51: 920-011004 | C51: Logitech Signature MK650 Combo for Business - GRAPHITE | D51: =INDEX(PRICING!BC:BC,MATCH(B51,PRICING!BB:BB,0),1) -> 1319 | E51: 2 YEAR WARRANTY
B52: 920-011032 | C52: Logitech Signature MK650 Combo for Business - Off White | D52: =INDEX(PRICING!BC:BC,MATCH(B52,PRICING!BB:BB,0),1) -> 1279 | E52: 2 YEAR WARRANTY
B53: 920-012508 | C53: Logitech Signature Slim Combo MK950 for Business - GRAPHITE | D53: =INDEX(PRICING!BC:BC,MATCH(B53,PRICING!BB:BB,0),1) -> 1629 | E53: 2 YEAR WARRANTY
B54: 920-010933 | C54: Logitech MX KEYS COMBO for BusinessGen2 - GRAPHITE | D54: =INDEX(PRICING!BC:BC,MATCH(B54,PRICING!BB:BB,0),1) -> 3539 | E54: 2 YEAR WARRANTY
B55: Logi Dock
B56: 986-000020-S | C56: Logitech Dock All-in-One USB-C Docking Station SERIALISED | D56: =INDEX(PRICING!BC:BC,MATCH(B56,PRICING!BB:BB,0),1) -> 6719 | E56: 2 YEAR WARRANTY
B57: Group
B58: 960-001057 | C58: Logitech Group Affordable Video Conferencing System for Mid to Large-sized Meeting Rooms | D58: =INDEX(PRICING!BC:BC,MATCH(B58,PRICING!BB:BB,0),1) -> 9789 | E58: 2 YEAR WARRANTY
B59: 989-000171 | C59: Logitech Group Expansion Microphones | D59: =INDEX(PRICING!BC:BC,MATCH(B59,PRICING!BB:BB,0),1) -> 3899 | E59: 2 YEAR WARRANTY
B60: 939-001487-S | C60: Logitech GROUP 10m Extended Cable - N/A - AMR-403 - 10M MINI-DIN CABLE SERIALISED | D60: =INDEX(PRICING!BC:BC,MATCH(B60,PRICING!BB:BB,0),1) -> #N/A | E60: 2 YEAR WARRANTY
B61: 939-001490-S | C61: Logitech Group 15M Extension Cable SERIALISED | D61: =INDEX(PRICING!BC:BC,MATCH(B61,PRICING!BB:BB,0),1) -> #N/A | E61: 2 YEAR WARRANTY
B62: MeetUp
B63: 960-001102 | C63: Logitech MeetUp All-in-one Conference Cam for Small Conference Rooms and Huddle rooms | D63: =INDEX(PRICING!BC:BC,MATCH(B63,PRICING!BB:BB,0),1) -> 9119 | E63: 2 YEAR WARRANTY
B64: 989-000405 | C64: Logitech MeetUp Expansion Mic | D64: =INDEX(PRICING!BC:BC,MATCH(B64,PRICING!BB:BB,0),1) -> 3249 | E64: 2 YEAR WARRANTY
B65: 939-001498 | C65: Logitech TV MOUNT FOR MEETUP - TV MOUNT | D65: =INDEX(PRICING!BC:BC,MATCH(B65,PRICING!BB:BB,0),1) -> 1719 | E65: 2 YEAR WARRANTY
B66: 950-000005-S | C66: Logitech MeetUp Mic Extension Cable, 10m - Graphite SERIALISED | D66: =INDEX(PRICING!BC:BC,MATCH(B66,PRICING!BB:BB,0),1) -> #N/A | E66: 2 YEAR WARRANTY
B67: MeetUp 2
B68: 960-001681 | C68: Logitech MeetUp 2 All-in-one Conference Cam for Small Conference Rooms and Huddle rooms | D68: =INDEX(PRICING!BC:BC,MATCH(B68,PRICING!BB:BB,0),1) -> 16359 | E68: 2 YEAR WARRANTY
B69: 952-000195 | C69: Logitech Active USB Cable for MeetUp 2, 5m | D69: =INDEX(PRICING!BC:BC,MATCH(B69,PRICING!BB:BB,0),1) -> 3629 | E69: 2 YEAR WARRANTY
B70: Rally
B71: 960-001313 | C71: Logitech Rally Bar All-in-one Video Bar for Medium to Large Rooms - Graphite | D71: =INDEX(PRICING!BC:BC,MATCH(B71,PRICING!BB:BB,0),1) -> 64289 | E71: 2 YEAR WARRANTY
B72: 960-001572 | C72: Logitech Rally Bar Huddle for Small and Huddle Rooms | D72: =INDEX(PRICING!BC:BC,MATCH(B72,PRICING!BB:BB,0),1) -> 27219 | E72: 2 YEAR WARRANTY
B73: 960-001341 | C73: Logitech Rally Bar Mini All-in-one Video Bar for Small to Medium Rooms - Graphite | D73: =INDEX(PRICING!BC:BC,MATCH(B73,PRICING!BB:BB,0),1) -> 47639 | E73: 2 YEAR WARRANTY
B74: 960-001227 | C74: Logitech Rally Camera, Premium PTZ Camera With Ultra-HD Imaging and Automatic Camera Control | D74: =INDEX(PRICING!BC:BC,MATCH(B74,PRICING!BB:BB,0),1) -> 17729 | E74: 2 YEAR WARRANTY
B75: 960-001242 | C75: Logitech Rally Plus Premier Modular Video Conferencing System for Large and Extra Large Rooms, incl. Rally Cam, 2x Speakers, 2x Mic Pods, Rally Display Hub, Rally Table Hub - Black | D75: =INDEX(PRICING!BC:BC,MATCH(B75,PRICING!BB:BB,0),1) -> 45639 | E75: 2 YEAR WARRANTY
B76: 960-001240 | C76: Logitech Rally Premier Modular Video Conferencing System for Large and Extra Large Rooms, incl. Rally Cam, 1x Speaker, 1x Mic Pod, Rally Display Hub, Rally Table Hub - Black | D76: =INDEX(PRICING!BC:BC,MATCH(B76,PRICING!BB:BB,0),1) -> 40089 | E76: 2 YEAR WARRANTY
B77: 960-001237 | C77: Logitech WEBCAM - Logitech Rally Ultra-HD ConferenceCam - BLACK - USB - PLUGG - EMEA-914 - UK HONG KONG | D77: =INDEX(PRICING!BC:BC,MATCH(B77,PRICING!BB:BB,0),1) -> 37809 | E77: 2 YEAR WARRANTY
B78: Rally Accessories
B79: 952-000041 | C79: Logitech Rally Bar and Rally Bar Mini TV Mount | D79: =INDEX(PRICING!BC:BC,MATCH(B79,PRICING!BB:BB,0),1) -> 3669 | E79: 2 YEAR WARRANTY
B80: 952-000057-S | C80: Logitech RALLY BAR REMOTE CONTROL - GRAPHITE - BT SERIALISED | D80: =INDEX(PRICING!BC:BC,MATCH(B80,PRICING!BB:BB,0),1) -> 1179 | E80: 2 YEAR WARRANTY
B81: 952-000044 | C81: Logitech Rally Bar Wall Mount Bracket | D81: =INDEX(PRICING!BC:BC,MATCH(B81,PRICING!BB:BB,0),1) -> 2039 | E81: 2 YEAR WARRANTY
B82: 993-002153 | C82: Logitech Rally Cable (USB-C to USB-C) SERIALISED | D82: =INDEX(PRICING!BC:BC,MATCH(B82,PRICING!BB:BB,0),1) -> 539 | E82: 2 YEAR WARRANTY
B83: 989-000430 | C83: Logitech Rally Mic Pod - Graphite | D83: =INDEX(PRICING!BC:BC,MATCH(B83,PRICING!BB:BB,0),1) -> 5829 | E83: 2 YEAR WARRANTY
B84: 952-000038 | C84: Logitech Rally Mic Pod - White | D84: =INDEX(PRICING!BC:BC,MATCH(B84,PRICING!BB:BB,0),1) -> 6189 | E84: 2 YEAR WARRANTY
B85: 952-000181-S | C85: Logitech Rally Mic Pod CAT Coupler- Extension Cable SERIALISED | D85: =INDEX(PRICING!BC:BC,MATCH(B85,PRICING!BB:BB,0),1) -> #N/A | E85: 2 YEAR WARRANTY
B86: 952-000047-S | C86: Logitech Rally Mic Pod Extension Cable, 10m - White SERIALISED | D86: =INDEX(PRICING!BC:BC,MATCH(B86,PRICING!BB:BB,0),1) -> #N/A | E86: 2 YEAR WARRANTY
B87: 939-001647 | C87: Logitech Rally Mic Pod Hub for the Logitech Rally Conference Cam - Graphite | D87: =INDEX(PRICING!BC:BC,MATCH(B87,PRICING!BB:BB,0),1) -> 5169 | E87: 2 YEAR WARRANTY
B88: 952-000020 | C88: Logitech Rally Mic Pod Mount - White | D88: =INDEX(PRICING!BC:BC,MATCH(B88,PRICING!BB:BB,0),1) -> 1479 | E88: 2 YEAR WARRANTY
B89: 952-000002 | C89: Logitech Rally Mic Pod Table Mount - Graphite | D89: =INDEX(PRICING!BC:BC,MATCH(B89,PRICING!BB:BB,0),1) -> 1669 | E89: 2 YEAR WARRANTY
B90: 939-001644 | C90: Logitech Rally Mounting Kit for the Logitech Rally Conference Cam | D90: =INDEX(PRICING!BC:BC,MATCH(B90,PRICING!BB:BB,0),1) -> 4579 | E90: 2 YEAR WARRANTY
... B94: 993-001952 | C94: Logitech TABLE HUB for Rally Ultra-HD ConferenceCam - BLACK - USB - N/A - WW-9004 | D94: =INDEX(PRICING!BC:BC,MATCH(B94,PRICING!BB:BB,0),1) -> 9369 | E94: 2 YEAR WARRANTY
B95: Rally Board
B96: 960-001751 | C96: Logitech Rally Board 65 - GRAPHITE - N/A - PLUGM - WWi-9006 - SOUTH AFRICA | D96: =INDEX(PRICING!BC:BC,MATCH(B96,PRICING!BB:BB,0),1) -> 131119 | E96: 2 YEAR WARRANTY
B97: 952-000251 | C97: Rally Board 65 Cart - WHITE - N/A - N/A - WWi-9006 - CART,WW | D97: =INDEX(PRICING!BC:BC,MATCH(B97,PRICING!BB:BB,0),1) -> 48709 | E97: 2 YEAR WARRANTY
B98: MTR Bundles on Windows
B99: RALLY PLUS V2 | C99: Rally Plus Bundle INCL Rally System, Rally Speaker, Rally Mic Pod | D99: =INDEX(PRICING!BC:BC,MATCH(B99,PRICING!BB:BB,0),1) -> 47999 | E99: 2 YEAR WARRANTY
B100: TAPRBGMSTLNV | C100: LOGITECH - MTR ON WINDOWS RALLY BAR BUNDLE - INCLUDES: RALLY BAR GRAPHITE, TAP+CAT5E, LENOVO THINKSMART CORE, + 1YR Essential | D100: =INDEX(PRICING!BC:BC,MATCH(B100,PRICING!BB:BB,0),1) -> 106380 | E100: 2 YEAR WARRANTY
B101: TAPRMGMSTLNV | C101: LOGITECH - MTR ON WINDOWS RALLY BAR MINI BUNDLE - INCLUDES: RALLY BAR MINI GRAPHITE, TAP+CAT5E, LENOVO THINKSMART CORE, + 1YR Essential | D101: =INDEX(PRICING!BC:BC,MATCH(B101,PRICING!BB:BB,0),1) -> 89725 | E101: 2 YEAR WARRANTY
B102: TAPMSTBASELNV | C102: Logitech MTR on Windows Base Kit, including Tap+Cat5e, Lenovo ThinkSmart Core, + 1YR Essential | D102: =INDEX(PRICING!BC:BC,MATCH(B102,PRICING!BB:BB,0),1) -> 42597 | E102: 2 YEAR WARRANTY
B103: TAPMUPMSTLNV | C103: LOGITECH - MTR ON WINDOWS SMALL BUNDLE - INCLUDES: MEETUP, TAP+CAT5E, LENOVO THINKSMART CORE,+ 1YR Essential | D103: =INDEX(PRICING!BC:BC,MATCH(B103,PRICING!BB:BB,0),1) -> 51488 | E103: 2 YEAR WARRANTY
B104: TAPMUPMSTLNV2 | C104: LOGITECH - MTR ON WINDOWS SMALL BUNDLE - INCLUDES: MEETUP, TAP+CAT5E, LENOVO THINKSMART CORE,+ 1YR Essential | D104: =INDEX(PRICING!BC:BC,MATCH(B104,PRICING!BB:BB,0),1) -> 58866 | E104: 2 YEAR WARRANTY
B105: TAPRALMSLNV2 | C105: Logitech MTR on Windows Medium Bundle, including Rally, Rally Mounting Kit, Tap+Cat5e,Rally Speaker, Rally Mic Pod, Lenovo ThinkSmart Core, Rally Mic Pod Hub,+ 1YR Essential | D105: =INDEX(PRICING!BC:BC,MATCH(B105,PRICING!BB:BB,0),1) -> 98031 | E105: 2 YEAR WARRANTY
...

Sheet Mecool
E1: Return
B3: SKU | C3: DESCRIPTION | D3: PRICE | E3: COMMENTS
B5: KD3 | C5: Mecool KD3 Android TV Dongle | D5: =INDEX(PRICING!BO:BO,MATCH(B5,PRICING!BN:BN,0),1) -> 799 | E5: Bulk Pricing for 50+
B6: KM7 PLUS | C6: Mecool KM7 Plus Android 11.0 Google TV Box | D6: =INDEX(PRICING!BO:BO,MATCH(B6,PRICING!BN:BN,0),1) -> 899 | E6: Bulk Pricing for 50+
B7: KS3 | C7: Mecool KS3 OTT Soundbar + Subwoofer | D7: =INDEX(PRICING!BO:BO,MATCH(B7,PRICING!BN:BN,0),1) -> 5999 | E7: Bulk Pricing for 50+
B8: G20 | C8: Mecool G20 Remote Compatible With Mecool ATV & GTV Devices | D8: =INDEX(PRICING!BO:BO,MATCH(B8,PRICING!BN:BN,0),1) -> 199 | E8: Bulk Pricing for 50+
B9: GM1 | C9: Mecool GM1 Wireless Gamepad | D9: =INDEX(PRICING!BO:BO,MATCH(B9,PRICING!BN:BN,0),1) -> 599 | E9: Bulk Pricing for 50+
B12: E & OE Terms & Conditions: Pricing valid from 1 April 2026 until 30 April 2026. All pricing is Exclusive of VAT and subject to stock availability and lead times. Pricing is subject to change without notice and is linked to the exchange rate. CLICK HERE to view our full Terms and Conditions.

Sheet Minix
E1: Return
B3: SKU | C3: DESCRIPTION | D3: PRICE | E3: COMMENTS
B5: C1-NS | C5: Minix C1 Wireless USB-C to 1080P HDMI Dongle | D5: =INDEX(PRICING!BR:BR,MATCH(B5,PRICING!BQ:BQ,0),1) -> 969
B6: H1-NS | C6: Minix H1 Wireless HDMI to HDMI Dongle (1080P) | D6: =INDEX(PRICING!BR:BR,MATCH(B6,PRICING!BQ:BQ,0),1) -> 969
B7: CP86-CP-NS | C7: Minix CP86-CP CarPlay Dongle stick | D7: =INDEX(PRICING!BR:BR,MATCH(B7,PRICING!BQ:BQ,0),1) -> 769
B8: CP86-AA-NS | C8: Minix CP86-AA Android Auto Dongle stick | D8: =INDEX(PRICING!BR:BR,MATCH(B8,PRICING!BQ:BQ,0),1) -> 769
B9: CP89-HD-NS | C9: Minix CP89-HD Portable Wireless CarPlay & Android Auto High-Definition Touchscreen | D9: =INDEX(PRICING!BR:BR,MATCH(B9,PRICING!BQ:BQ,0),1) -> 3799
B11: E & OE Terms & Conditions: Pricing valid from 1 April 2026 until 30 April 2026. All pricing is Exclusive of VAT and subject to stock availability and lead times. Pricing is subject to change without notice and is linked to the exchange rate. CLICK HERE to view our full Terms and Conditions.

Sheet MikroTik
E1: Return
B3: SKU | C3: DESCRIPTION | D3: PRICE | E3: COMMENTS
B4: SWITCHES
B5: CSS610-1Gi-7R-2S+OUT | C5: MikroTik netPower Lite 7R with 8x Gb Ethernet ports (7 with Reverse PoE-in, 1 with PoE-OUT), 2x SFP+ cages, SwitchOS, outdoor enclosure | D5: =INDEX(PRICING!S:S,MATCH(B5,PRICING!R:R,0),1) -> 2114
B6: CRS310-1G-5S-4S+OUT | C6: MikroTik netFiber 9, 4x 10G SFP+ Ports, 5x 1G SFP Ports, 1x Gb Ethernet Port (PoE-IN), Outdoor Enclosure, Mounting Kit, PSU, PoE Injector | D6: =INDEX(PRICING!S:S,MATCH(B6,PRICING!R:R,0),1) -> 3655
B7: CRS112-8P-4S-IN | C7: MikroTik Cloud Router Switch CRS112-8P-4S-IN, 8x Gb LAN with PoE-out, 4x SFP, RouterOS L5, desktop case, PSU | D7: =INDEX(PRICING!S:S,MATCH(B7,PRICING!R:R,0),1) -> 3182
B8: CSS326-24G-2S+RM | C8: MikroTik Cloud Smart Switch CSS326-24G-2S+RM, 24x Gb Ethernet ports, 2x SFP+ cages, SwOS, 1U rackmount case | D8: =INDEX(PRICING!S:S,MATCH(B8,PRICING!R:R,0),1) -> 2413
B9: CSS610-8P-2S+IN | C9: MikroTik Cloud Smart Switch CSS610-8P-2S+IN, 8x Gb 802.3af/at PoE-out ports, 2x SFP+ cages | D9: =INDEX(PRICING!S:S,MATCH(B9,PRICING!R:R,0),1) -> 3396
B10: CRS106-1C-5S | C10: Mikrotik Cloud Router Switch 106-1C-5S with QCA8511 400MHz CPU, 128MB RAM, 1x Combo port (Gigabit Ethernet or SFP), 5 x SFP cages, RouterOS L5, desktop case, PSU | D10: =INDEX(PRICING!S:S,MATCH(B10,PRICING!R:R,0),1) -> 870
B11: CRS309-1G-8S+IN | C11: MikroTik Cloud Router Switch CRS309-1G-8S+IN, 1x Gb Ethernet, 8x SFP+ Cages, RouterOS L5 Or SwitchOS (Dual Boot), Passive Desktop Case, Rackmount Ears, PSU | D11: =INDEX(PRICING!S:S,MATCH(B11,PRICING!R:R,0),1) -> 4058
B12: CRS310-1G-5S-4S+IN | C12: MikroTik Cloud Router Switch CRS310-1G-5S-4S+IN, 4x SFP+, 5x SFP cages, 1x Gb LAN port, RouterOS L5, desktop case | D12: =INDEX(PRICING!S:S,MATCH(B12,PRICING!R:R,0),1) -> 2966
B13: CRS318-16P-2S+OUT | C13: MikroTik netPower 16P, 16x Gb LAN with PoE-out, 2x SFP+ cages, RouterOS L5 or SwitchOS (dual boot), outdoor enclosure, Excludes PSU | D13: =INDEX(PRICING!S:S,MATCH(B13,PRICING!R:R,0),1) -> 4165
B14: CRS328-24P-4S+RM | C14: MikroTik Cloud Router Switch CRS328-24P-4S+RM, 24xGb LAN (all PoE-out), 4x SFP+ cages, RouterOS L5 or SwitchOS (dual boot), 1U rackmount case, 500W built-in PSU | D14: =INDEX(PRICING!S:S,MATCH(B14,PRICING!R:R,0),1) -> 7419
B15: CRS328-4C-20S-4S+RM | C15: MikroTik Cloud Router Switch CRS328-4C-20S-4S+RM, 20x SFP cages, 4x SFP+ cages, 4x Combo ports (1x Gb LAN or SFP), RouterOS L5 or SwitchOS (dual boot), 1U rackmount case, Dual PSU | D15: =INDEX(PRICING!S:S,MATCH(B15,PRICING!R:R,0),1) -> 6354
B16: CRS317-1G-16S+RM | C16: MikroTik Cloud Router Switch CRS317-1G-16S+RM, 1x Gb LAN, 16x SFP+ Cages, RouterOS L6 OR SwitchOS (Dual Boot), Passive Cooling 1U Rackmount Enclosure, Dual Redundant PSU | D16: =INDEX(PRICING!S:S,MATCH(B16,PRICING!R:R,0),1) -> 7917
... B20: CRS518-16XS-2XQ-RM | C20: MikroTik Cloud Router Switch CRS518-16XS-2XQ-RM, 2x 100G QSFP28 Ports, 16x 25G SFP28 Ports, 1x 100M Ethernet Port for Management, USB Type A, 1U Rackmount Enclosure, Dual Hot-Swap PSU, 4x Hot-Swap Fans | D20: =INDEX(PRICING!S:S,MATCH(B20,PRICING!R:R,0),1) -> 25857
B21: IOT RANGE
B22: RB924I-2ND-BT5&BG77 | C22: Mikrotik KNOT -IoT Gateway with 650MHz CPU, 64MB RAM, 2 x 10/100Mbps Ethernet ports (PoE-in and PoE-out), built-in 2.4Ghz 802.11b/g/n Dual Chain wireless with integrated antenna, Bluetooth v5.2 with integrated antenna, built-in GPS, CAT-M and NarrowBand | D22: =INDEX(PRICING!S:S,MATCH(B22,PRICING!R:R,0),1) -> 1503
B23: TG-BT5-IN | C23: MikroTik Indoor BLE 5.2 tag with built-in accelerometer for KNOT or other IoT asset-tracking/telemetry setups, iBeacon, Eddystone, MikroTik telemetry support, magnet activation, contains LiMnO2 battery | D23: =INDEX(PRICING!S:S,MATCH(B23,PRICING!R:R,0),1) -> 149
B24: WIRELESS SYSTEMS (OUTDOOR)
B25: RBWAPG-60AD-A | C25: MikroTik wAP 60G AP with Phase array 60 degree 60GHz antenna, 802.11ad wireless, 1x Gb LAN, PoE, RouterOS L4 (AP) | D25: =INDEX(PRICING!S:S,MATCH(B25,PRICING!R:R,0),1) -> 2114 | E25: ETA Confirmed on Order
B26: RBWAPG-60AD | C26: MikroTik wAP 60G with Phase array 60 degree 60GHz antenna, 802.11ad wireless, 1x Gb LAN, PoE, RouterOS L3 (CPE) for use as CPE in Point -to-Multipoint setups for connections up to 200m | D26: =INDEX(PRICING!S:S,MATCH(B26,PRICING!R:R,0),1) -> 1730 | E26: ETA Confirmed on Order
B27: ETHERNET ROUTERS
B28: RBD53IG-5HACD2HND | C28: MikroTik hAP ac³ Dual Band Wireless Router, 5x Gb LAN (PoE-out on port #5), two wireless interfaces (built-in 2.4Ghz 802.11b/g/n two chain, built-in 5Ghz 802.11ac two chain), 3dBi 2.4GHz external antenna, 5.5dBi 5GHz external antenna, tower/desktop case, USB, PSU, RouterOS L4 | D28: =INDEX(PRICING!S:S,MATCH(B28,PRICING!R:R,0),1) -> 1644
B29: RBD52G-5HACD2HND-TC | C29: MikroTik hAP ac² Dual Band Access Point, 5x Gb LAN, built-in 2.4Ghz 802.11b/g/n Dual Chain wireless with integrated antenna, built-in 5GHz 802.11an/ac Dual Chain wireless with integrated antenna, USB, RouterOS L4, desktop/tower case, PSU | D29: =INDEX(PRICING!S:S,MATCH(B29,PRICING!R:R,0),1) -> 1061
B30: E50UG | C30: MikroTik hEX (2024 version) with Dual Core 950MHz CPU, 512MB RAM, 5 x Gigabit LAN ports, USB, RouterOS v7 L4, plastic case, PSU | D30: =INDEX(PRICING!S:S,MATCH(B30,PRICING!R:R,0),1) -> 831
B31: E60iUGS | C31: Mikrotik hEX S (2025 version) with Dual Core 950MHz CPU, 512MB RAM, 2.5G SFP cage, 5 x Gigabit Eth ports, USB, RouterOS v7 L4, plastic case, PSU | D31: =INDEX(PRICING!S:S,MATCH(B31,PRICING!R:R,0),1) -> 950
B32: RB760IGS | C32: Mikrotik hEX S, 5x Gb LAN ports, SFP, USB, PoE-out on port #5, RouterOS L4, plastic case, PSU, IPSEC Hardware Encryption | D32: =INDEX(PRICING!S:S,MATCH(B32,PRICING!R:R,0),1) -> 1090
B33: RB4011IGS+RM | C33: MikroTik RouterBOARD RB4011iGS+, 10x Gb LAN, 1x SFP+ port, RouterOS L5, desktop case, rackmount ears, PSU | D33: =INDEX(PRICING!S:S,MATCH(B33,PRICING!R:R,0),1) -> 3010
B34: RB750R2 | C34: MikroTik hEX Lite - Desktop Router with 5x 10/100 Ports - ViBE COMPATIBLE (ViBE Base License not included) | D34: =INDEX(PRICING!S:S,MATCH(B34,PRICING!R:R,0),1) -> 639
B35: ACT-NVD | C35: ViBE Base License for MikroTik RB750 | D35: =INDEX(PRICING!S:S,MATCH(B35,PRICING!R:R,0),1) -> 409
B36: RB750GR3 | C36: MikroTik hEX, Desktop Router, 5x Gb LAN ports, USB, RouterOS L4, plastic case, PSU | D36: =INDEX(PRICING!S:S,MATCH(B36,PRICING!R:R,0),1) -> 896
B37: RB750UPR2 | C37: MikroTik hEX PoE lite, Desktop Router, 5x LAN (four with PoE out), USB, RouterOS L4, plastic case and PSU | D37: =INDEX(PRICING!S:S,MATCH(B37,PRICING!R:R,0),1) -> 896
B38: RB960PGS | C38: MikroTik hEX PoE, Desktop Router, 5x Gb LAN (four with PoE out), SFP, USB, RouterOS L4, plastic case and PSU | D38: =INDEX(PRICING!S:S,MATCH(B38,PRICING!R:R,0),1) -> 1345
B39: RB1100AHX4 | C39: MikroTik RouterBOARD RB1100AHx4, 13x Gb LAN, RouterOS L6, 1U rackmount case, Dual PSU | D39: =INDEX(PRICING!S:S,MATCH(B39,PRICING!R:R,0),1) -> 4837
... B47: CCR2116-12G-4S+ | C47: MikroTik Cloud Core Router CCR2116-12G-4S+, 4x SFP+ cage, 13x Gb LAN, M.2 PCIe slot, RouterOS L6, 1U rackmount case, Dual PSU | D47: =INDEX(PRICING!S:S,MATCH(B47,PRICING!R:R,0),1) -> 15209
B48: WIRELESS FOR HOME & OFFICE (INDOOR)
B49: RBCAPGI-5ACD2ND | C49: MikroTik cAP ac, 2x Gb LAN (one with PoE-out), built-in 2.4Ghz 802.11b/g/n Dual Chain wireless, built-in 5GHz 802.11an/ac Dual Chain wireless, RouterOS L4, ceiling enclosure, wall-mount enclosure, PSU, PoE injector | D49: =INDEX(PRICING!S:S,MATCH(B49,PRICING!R:R,0),1) -> 1312
B50: RB941-2ND-TC | C50: MikroTik hAP lite, 4x LAN, built-in 2.4Ghz 802.11b/g/n 2x2 two chain wireless with integrated antennas, RouterOS L4, tower case, PSU | D50: =INDEX(PRICING!S:S,MATCH(B50,PRICING!R:R,0),1) -> 368
B51: RB951UI-2ND | C51: MikroTik hAP SOHO Access Point, 5x LAN, built-in 2.4Ghz 802.11b/g/n 2x2 two chain wireless with integrated antennas, USB, RouterOS L4, desktop case, PSU | D51: =INDEX(PRICING!S:S,MATCH(B51,PRICING!R:R,0),1) -> 662
B52: RB951UI-2HND | C52: MikroTik RouterBOARD RB951Ui-2HnD, 5x LAN, built-in 2.4Ghz 802b/g/n 2x2 two chain wireless with integrated antennas, desktop case, PSU, RouterOS L4 | D52: =INDEX(PRICING!S:S,MATCH(B52,PRICING!R:R,0),1) -> 896
B53: RB952UI-5AC2ND | C53: MikroTik hAP ac lite, 5x LAN, built-in 2.4Ghz 802.11b/g/n two chain wireless with integrated antennas, built-in 5Ghz 802.11ac single chain wireless with integrated antenna, USB, desktop case, PSU, RouterOS L4 | D53: =INDEX(PRICING!S:S,MATCH(B53,PRICING!R:R,0),1) -> 854
B54: RB952UI-5AC2ND-TC | C54: MikroTik hAP ac lite, 5x LAN, built-in 2.4Ghz 802.11b/g/n two chain wireless with integrated antennas, built-in 5Ghz 802.11ac single chain wireless with integrated antenna, USB, tower case, PSU, RouterOS L4 | D54: =INDEX(PRICING!S:S,MATCH(B54,PRICING!R:R,0),1) -> 854
B55: RB962UIGS-5HACT2HNT | C55: MikroTik hAP ac Desktop Access Point, 5x Gb LAN, built-in 2.4Ghz 802.11b/g/n three chain wireless with integrated antennas, built-in 5Ghz 802.11ac three chain wireless with integrated antenna, SFP cage, USB, desktop case, PSU, RouterOS L4 | D55: =INDEX(PRICING!S:S,MATCH(B55,PRICING!R:R,0),1) -> 2023
B56: C52IG-5HAXD2HAXD-TC | C56: MikroTik hAP ax² Wi-Fi 6 Access Point, 5x Gb LAN (1 with PoE OUT), built-in 2.4GHz 802.11ax Dual Chain wireless with integrated antenna, built-in 5GHz 802.11ax Dual Chain wireless with integrated antenna, RouterOS L4, desktop/tower case, PSU | D56: =INDEX(PRICING!S:S,MATCH(B56,PRICING!R:R,0),1) -> 1431
B57: RBD25G-5HPACQD2HPND | C57: MikroTik Audience, 2x Gb LAN, three wireless interfaces (built-in 2.4Ghz 802.11b/g/n two chain wireless with integrated antennas, built-in 5Ghz 802.11ac four chain wireless with integrated antennas, built-in 5Ghz 802.11ac two chain wireless with integrated antennas), desktop/tower case, Ethernet cable, PSU, RouterOS L4 | D57: =INDEX(PRICING!S:S,MATCH(B57,PRICING!R:R,0),1) -> 2520
B58: L009UIGS-2HAXD-IN | C58: MikroTik L009UiGS-2HaxD, 8x Gb LAN, 1x 2.5 Gb SFP port, 2.4 GHz 802.11b/g/n/ax dual-chain wireless, 4dBi 2.4GHz external antennas, USB, desktop case, PSU, RouterOS L5 | D58: =INDEX(PRICING!S:S,MATCH(B58,PRICING!R:R,0),1) -> 1922
B59: RBCAPGI-5ACD2ND | C59: MikroTik cAP ac Dual Band Indoor Access Point, 2x Gb LAN (one with PoE-out), built-in 2.4Ghz 802.11b/g/n Dual Chain wireless, built-in 5GHz 802.11an/ac Dual Chain wireless, RouterOS L4, ceiling enclosure, wall-mount enclosure, PSU, PoE injector | D59: =INDEX(PRICING!S:S,MATCH(B59,PRICING!R:R,0),1) -> 1312
B60: L41G-2axD | C60: hAP ax lite with 800MHz CPU, 256MB RAM, 4 x Gbit LAN, 2.4 GHz 802.11b/g/n/ax two chain wireless with integrated antennas, RouterOS L4, tower case, PSU | D60: =INDEX(PRICING!S:S,MATCH(B60,PRICING!R:R,0),1) -> 854
B61: LTE PRODUCTS
B62: S53UG+5HaxD2HaxD-TC&FG621-EA | C62: Chateau LTE6 ax with 1.8GHz four core CPU, 1GB RAM, 1 x 2.5 Gigabit LAN, 4 x Gigabit LAN, two wireless interfaces (built-in 2.4Ghz 802.11b/g/n/ax two chain wireless, built-in 5Ghz 802.11a/n/ac/ax two chain wireless) with external antennas, LTE CAT6 modem for International bands 1/3/5/7/8/20/28/38/40/41 with integrated antennas, SMA connectors for external antennas, tower case, USB, PSU, RouterOS L4, International version | D62: =INDEX(PRICING!S:S,MATCH(B62,PRICING!R:R,0),1) -> 2814
B63: ATLGM&EG18-EA | C63: MikroTik ATL LTE18 kit with 1.2GHz dual-core ARM CPU, 256MB RAM, 1 x Gigabit Ethernet port with PoE-in for powering, 1.2 Gbps LTE CAT18 modem for International bands 1/3/5/7/8/20/28/38/40/41, 4 high-gain middle band (1.7-2.7GHz) and 2 high-gain low band | D63: =INDEX(PRICING!S:S,MATCH(B63,PRICING!R:R,0),1) -> 4522
B64: D53G-5HacD2HnD-TC&EG120K-EA | C64: Mikrotik Chateau LTE12 (2025) kit with 716MHz four core CPU, 256MB RAM, 5 x Gbit Eth ports, two wireless interfaces (built-in 2.4Ghz 802.11b/g/n two chain wireless with integrated antennas, built-in 5Ghz 802.11ac two chain wireless with integrated antennas), LTE CAT12 modem for International bands 1/3/5/7/8/20/28/32/38/40/41 with integrated antennas, SMA connectors for external antennas, tower case, USB, PSU, RouterOS L4 | D64: =INDEX(PRICING!S:S,MATCH(B64,PRICING!R:R,0),1) -> 2776
B65: SFP MODULES
B66: S-85DLC05D | C66: MikroTik SFP (1.25G) module, 550m, multi-mode | D66: =INDEX(PRICING!S:S,MATCH(B66,PRICING!R:R,0),1) -> 256 | E66: ETA Confirmed on Order MOQ Applies
B67: S+85DLC03D | C67: MikroTik SFP (1.25G) module, 550m, multi-mode, 850nm | D67: =INDEX(PRICING!S:S,MATCH(B67,PRICING!R:R,0),1) -> 854 | E67: ETA Confirmed on Order MOQ Applies
B68: S-31DLC20D | C68: MikroTik SFP (1.25G) module, 20KM, Single Mode, 1310nm | D68: =INDEX(PRICING!S:S,MATCH(B68,PRICING!R:R,0),1) -> 341 | E68: ETA Confirmed on Order MOQ Applies
B69: S-RJ01 | C69: MikroTik SFP (1.25G) module, 100M, RJ45 Copper | D69: =INDEX(PRICING!S:S,MATCH(B69,PRICING!R:R,0),1) -> 427 | E69: ETA Confirmed on Order MOQ Applies
B70: S-3553LC20D | C70: MikroTik Two x SFP (1.25G) module kit, 20Km, single mode | D70: =INDEX(PRICING!S:S,MATCH(B70,PRICING!R:R,0),1) -> 1046 | E70: ETA Confirmed on Order MOQ Applies
B71: ACCESSORIES
B72: 48POW | C72: MikroTik Power Supply 48V 1.46A Straight DC plug | D72: =INDEX(PRICING!S:S,MATCH(B72,PRICING!R:R,0),1) -> 249
B73: RBPOE | C73: MikroTik Passive PoE Base Unit | D73: =INDEX(PRICING!S:S,MATCH(B73,PRICING!R:R,0),1) -> 46
B74: RBGPOE | C74: MikroTik Gigabit PoE Injector | D74: =INDEX(PRICING!S:S,MATCH(B74,PRICING!R:R,0),1) -> 85
B75: RBFTC11 | C75: MikroTik Fiber to Copper Converter in Outdoor enclosure, PoE injector, power supply | D75: =INDEX(PRICING!S:S,MATCH(B75,PRICING!R:R,0),1) -> 576
B76: QMP-LHG | C76: MikroTik quickMOUNT Pro Wall Mount for LHG antennas | D76: =INDEX(PRICING!S:S,MATCH(B76,PRICING!R:R,0),1) -> 96
B77: QMP | C77: MikroTik quickMOUNT Pro Wall Mount for small antennas | D77: =INDEX(PRICING!S:S,MATCH(B77,PRICING!R:R,0),1) -> 96
B79: E & OE Terms & Conditions: Pricing valid from 1 April 2026 until 30 April 2026. All pricing is Exclusive of VAT and subject to stock availability and lead times. Pricing is subject to change without notice and is linked to the exchange rate. CLICK HERE to view our full Terms and Conditions.

Sheet Motorola
E1: Return
B3: SKU | C3: DESCRIPTION | D3: PRICE | E3: COMMENTS
B4: WIRELESS CAR ADAPTER FOR ANDROID AUTO
B5: MA1 | C5: Motorola MA1 Wireless Car Adapter For Android Auto™ | D5: =INDEX(PRICING!AT:AT,MATCH(B5,PRICING!AS:AS,0),1) -> 799 | E5: PROMOTION
B6: TURBOPOWER CHARGERS
B7: SJMC302 | C7: Motorola SJMC302 TurboPower 30W USB-C Charger | D7: =INDEX(PRICING!AT:AT,MATCH(B7,PRICING!AS:AS,0),1) -> 199 | E7: Volume discounts available from 20+ units
B8: SJMC502 | C8: Motorola SJMC502 TurboPower 50W Dual USB-C And USB-A Charger | D8: =INDEX(PRICING!AT:AT,MATCH(B8,PRICING!AS:AS,0),1) -> 349 | E8: Volume discounts available from 20+ units
B9: SJMC682 | C9: Motorola SJMC682 TurboPower 68W USB-C Charger | D9: =INDEX(PRICING!AT:AT,MATCH(B9,PRICING!AS:AS,0),1) -> 399 | E9: Volume discounts available from 20+ units
B11: E & OE Terms & Conditions: Pricing valid from 1 April 2026 until 30 April 2026. All pricing is Exclusive of VAT and subject to stock availability and lead times. Pricing is subject to change without notice and is linked to the exchange rate. CLICK HERE to view our full Terms and Conditions.

Sheet Neat
E1: Return
B3: SKU | C3: DESCRIPTION | D3: PRICE | E3: COMMENTS
B4: Neat Pad
B5: NEATPAD-SE | C5: Neat Pad - Controller / Scheduling Display | D5: =INDEX(PRICING!AW:AW,MATCH(B5,PRICING!AV:AV,0),1) -> 14181 | E5: 12 MONTH WARRANTY
B6: Add-on
B7: NEATPAD-GLASSMOUNT | C7: Neat Pad Glass Mount | D7: =INDEX(PRICING!AW:AW,MATCH(B7,PRICING!AV:AV,0),1) -> 1020
B8: NEATPAD-HEX8-4 | C8: Neat Screws (x4) for Neat Pad Mount Adapter | D8: =INDEX(PRICING!AW:AW,MATCH(B8,PRICING!AV:AV,0),1) -> 156
B9: NEATPAD-WALLADAPT | C9: Neat Pad mount adapter | D9: =INDEX(PRICING!AW:AW,MATCH(B9,PRICING!AV:AV,0),1) -> 502
B10: NEATPAD-SIDEMOUNT | C10: Neat Pad side mount bracket | D10: =INDEX(PRICING!AW:AW,MATCH(B10,PRICING!AV:AV,0),1) -> 597
B11: NEATPAD-WALLBRACK | C11: Neat Pad wall bracket | D11: =INDEX(PRICING!AW:AW,MATCH(B11,PRICING!AV:AV,0),1) -> 674
B12: Neat Pulse
B13: PULSE-PLUS-PAD1 | C13: Neat Pulse Plus for Neat Pad, including Control [Management and Monitoring] and Care [Support] for 1 year | D13: =INDEX(PRICING!AW:AW,MATCH(B13,PRICING!AV:AV,0),1) -> 951 | E13: Pulse Plus
B14: PULSE-PLUS-PAD3 | C14: Neat Pulse Plus for Neat Pad, including Control [Management and Monitoring] and Care [Support] for 3 years | D14: =INDEX(PRICING!AW:AW,MATCH(B14,PRICING!AV:AV,0),1) -> 1888 | E14: Pulse Plus
B15: PULSE-PRO-PAD1 | C15: Neat Pulse Pro for Neat Pad, including Control [Management and Monitoring], Care [Support], and Cover [Advanced Replacement] for 1 year | D15: =INDEX(PRICING!AW:AW,MATCH(B15,PRICING!AV:AV,0),1) -> 1427 | E15: Pulse Pro
B16: PULSE-PRO-PAD3 | C16: NeatPulse Pro for Neat Pad, including Control [Management and Monitoring], Care [Support], and Cover [Advanced Replacement] for 3 years | D16: =INDEX(PRICING!AW:AW,MATCH(B16,PRICING!AV:AV,0),1) -> 3545 | E16: Pulse Pro
B17: Neat Pad Pro
B18: NEATPADPRO10-SE | C18: Neat Pad Pro 10" touch-screen for Zoom/Teams/App Hub, serves as a room controller or scheduling display. Offers seamless video meeting management and room bookings. | D18: =INDEX(PRICING!AW:AW,MATCH(B18,PRICING!AV:AV,0),1) -> 20580 | E18: NEW Available from April 2026 ETA confirmed on Order 12 MONTH WARRANTY
B19: Neat Pulse
B20: PULSE-PLUS-PADPRO1 | C20: Pulse Plus for Neat Pad Pro 10" including advanced software platform and premium support for 1 year | D20: =INDEX(PRICING!AW:AW,MATCH(B20,PRICING!AV:AV,0),1) -> 1484 | E20: Pulse Plus
B21: PULSE-PLUS-PADPRO3 | C21: Pulse Plus for Neat Pad Pro 10", including advanced software platform and premium support for 3 years | D21: =INDEX(PRICING!AW:AW,MATCH(B21,PRICING!AV:AV,0),1) -> 3343 | E21: Pulse Plus
B22: PULSE-PRO-PADPRO1 | C22: Pulse Pro for Neat Pad Pro 10", including advanced software platform, premium support, and extended warranty for 1 year | D22: =INDEX(PRICING!AW:AW,MATCH(B22,PRICING!AV:AV,0),1) -> 2234 | E22: Pulse Pro
B23: PULSE-PRO-PADPRO3 | C23: Pulse Pro for Neat Pad Pro 10", including advanced software platform, premium support, and extended warranty for 3 years | D23: =INDEX(PRICING!AW:AW,MATCH(B23,PRICING!AV:AV,0),1) -> 5577 | E23: Pulse Pro
B24: Neat Board
B25: NEATBOARD32-SE | C25: Neat 32" All-In-One Touch Screen Video Device 140-degree Field Of View Ultra HD 4K, Power Delivery With USB, 4 Beamforming Microphones, 2-way Loudspeaker System, Table Stand Included (Adaptive Stand and Clamp Sold separately) | D25: =INDEX(PRICING!AW:AW,MATCH(B25,PRICING!AV:AV,0),1) -> 71163 | E25: NEW ETA Confirmed on Order 12 MONTH WARRANTY
B26: Add-on
B27: NB32-TBLST | C27: Neat Fixed table stand designed for simple tabletop placement of Neat Board 32. Provides a fixed 4° tilt and integrated cable management | D27: =INDEX(PRICING!AW:AW,MATCH(B27,PRICING!AV:AV,0),1) -> 7206 | E27: ETA Confirmed on Order
B28: NB32-WALL-MNT | C28: Neat Slim, fixed wall mount for securely attaching Neat Board 32 to a wall with minimal wall gap. Designed for clean, ADA-compliant installations and includes a locking mechanism for added security | D28: =INDEX(PRICING!AW:AW,MATCH(B28,PRICING!AV:AV,0),1) -> 5147 | E28: ETA Confirmed on Order
B29: NB32-AD-TBLST | C29: Neat Freestanding adaptive table stand supporting height adjustment, tilt, and swivel for flexible table placement and ergonomic positioning for Neat Board 32 | D29: =INDEX(PRICING!AW:AW,MATCH(B29,PRICING!AV:AV,0),1) -> 16265 | E29: ETA Confirmed on Order
B30: NB32-AD-TBLST-B | C30: Neat Base kit for configuring the Neat Board 32 adaptive table stand system. Can be used as a replacement base or to convert an adaptive table clamp into a table stand by swapping the base component. Does not include full stand | D30: =INDEX(PRICING!AW:AW,MATCH(B30,PRICING!AV:AV,0),1) -> 5015 | E30: ETA Confirmed on Order
B31: NB32-AD-TBLCL | C31: Neat Board 32 Table clamp mounting solution fixed to the edge of a table. Supports height adjustment, tilt, and swivel while saving table space | D31: =INDEX(PRICING!AW:AW,MATCH(B31,PRICING!AV:AV,0),1) -> 16265 | E31: ETA Confirmed on Order
B32: NB32-AD-TBLCL-B | C32: Neat Base kit for the Neat Board 32 adaptive mounting system. Enables conversion between adaptive table stand and clamp configurations without replacing the full assembly. Does not include full stand. | D32: =INDEX(PRICING!AW:AW,MATCH(B32,PRICING!AV:AV,0),1) -> 5015 | E32: ETA Confirmed on Order
B33: NB32-AD-TBL-BLT | C33: Neat Optional accessory enabling the Neat Board 32 adaptive table stand or clamp to be bolted directly to a table for secure, permanent installations. Does not include stand or clamp. | D33: =INDEX(PRICING!AW:AW,MATCH(B33,PRICING!AV:AV,0),1) -> 5015 | E33: ETA Confirmed on Order
B34: NB32-PRIV | C34: Neat Magnetic camera privacy cover that attaches over the Neat Board 32 camera to ensure visual privacy when not in use. Includes a magnetic docking plate with adhesive mounting. | D34: =INDEX(PRICING!AW:AW,MATCH(B34,PRICING!AV:AV,0),1) -> 2594 | E34: ETA Confirmed on Order
B35: NB32-CBL-LOCK | C35: Neat Cable security and management cover that secures and conceals cables connected to the back of Neat Board 32. Attaches using two screws with a 2.5 mm hex key to prevent cable removal or tampering. | D35: =INDEX(PRICING!AW:AW,MATCH(B35,PRICING!AV:AV,0),1) -> 2594 | E35: ETA Confirmed on Order
B36: Neat Pulse
B37: PULSE-PLUS-BOARD32-1 | C37: Pulse Plus for Neat Board 32, including advanced software platform and premium support for 1 years | D37: =INDEX(PRICING!AW:AW,MATCH(B37,PRICING!AV:AV,0),1) -> 4367 | E37: Pulse Plus
B38: PULSE-PLUS-BOARD32-3 | C38: Pulse Plus for Neat Board 32, including advanced software platform and premium support for 3 years | D38: =INDEX(PRICING!AW:AW,MATCH(B38,PRICING!AV:AV,0),1) -> 9829 | E38: Pulse Plus
B39: PULSE-PRO-BOARD32-1 | C39: Pulse Pro for Neat Board 32, including advanced software platform and premium support for 1 year | D39: =INDEX(PRICING!AW:AW,MATCH(B39,PRICING!AV:AV,0),1) -> 6557 | E39: Pulse Pro
B40: PULSE-PRO-BOARD32-3 | C40: Pulse Pro for Neat Board 32, including advanced software platform and premium support for 3 years | D40: =INDEX(PRICING!AW:AW,MATCH(B40,PRICING!AV:AV,0),1) -> 16386 | E40: Pulse Pro
B41: NEATBOARD50-SE | C41: Neat Board50 - 50" Collaboration & Active Touch Screen Device/50mp camera, integrated camera & Mics with table stand | D41: =INDEX(PRICING!AW:AW,MATCH(B41,PRICING!AV:AV,0),1) -> 112471 | E41: ETA Confirmed on Order 12 MONTH WARRANTY
B42: Add-on
B43: NEATBOARD50-ADAPTIVEMOUNT | C43: NeatBoard50 - Flexible Mount | D43: =INDEX(PRICING!AW:AW,MATCH(B43,PRICING!AV:AV,0),1) -> 24706 | E43: ETA Confirmed on Order 12 MONTH WARRANTY
B44: NEATBOARD50-WALLMOUNT | C44: NeatBoard50 - Wallmount | D44: =INDEX(PRICING!AW:AW,MATCH(B44,PRICING!AV:AV,0),1) -> 6382 | E44: ETA Confirmed on Order 12 MONTH WARRANTY
B45: NEATBOARD50-ADAPTIVESTAND | C45: NeatBoard50 - Flexible Accoustic stand | D45: =INDEX(PRICING!AW:AW,MATCH(B45,PRICING!AV:AV,0),1) -> 40970 | E45: ETA Confirmed on Order 12 MONTH WARRANTY
B46: NEATBOARD-STYLUS-2PK | C46: Neat Board - STYLUS + PACKAGING (packaged in sets of 2) | D46: =INDEX(PRICING!AW:AW,MATCH(B46,PRICING!AV:AV,0),1) -> 2352
B47: NEAT-ACTIVE-MARKER | C47: Neat Active Marker - pressure sensitive active marker for Board 50 and Board Pro. 1 stylus in each package. | D47: =INDEX(PRICING!AW:AW,MATCH(B47,PRICING!AV:AV,0),1) -> 1712
B48: Neat Pulse
B49: PULSE-PLUS-BOARD50-1 | C49: Pulse Plus for Neat Board 50, including Control [Management and Monitoring] and Care [Support] for 1 year | D49: =INDEX(PRICING!AW:AW,MATCH(B49,PRICING!AV:AV,0),1) -> 6903 | E49: Pulse Plus
B50: PULSE-PLUS-BOARD50-3 | C50: Pulse Plus for Neat Board 50, including Control [Management and Monitoring] and Care [Support] for 3 years | D50: =INDEX(PRICING!AW:AW,MATCH(B50,PRICING!AV:AV,0),1) -> 15536 | E50: Pulse Plus
B51: PULSE-PRO-BOARD50-1 | C51: Pulse Pro for Neat Board 50, including Control [Management and Monitoring], Care [Support], and Cover [Advanced Replacement] for 1 year | D51: =INDEX(PRICING!AW:AW,MATCH(B51,PRICING!AV:AV,0),1) -> 10376 | E51: Pulse Pro
B52: PULSE-PRO-BOARD50-3 | C52: Pulse Pro for Neat Board 50, including Control [Management and Monitoring], Care [Support], and Cover [Advanced Replacement] for 3 years | D52: =INDEX(PRICING!AW:AW,MATCH(B52,PRICING!AV:AV,0),1) -> 25898 | E52: Pulse Pro
B53: NEATBOARDPRO-SE | C53: Neat Board Pro - 65” Collaboration & Touch Screen Device designed for Zoom and Microsoft Teams | D53: =INDEX(PRICING!AW:AW,MATCH(B53,PRICING!AV:AV,0),1) -> 140636 | E53: 12 MONTH WARRANTY
B54: Add-on
B55: NEATBOARDPRO-ADAPTIVE-STAND | C55: Neat Adaptive stand offers flexibility with easy movement between spaces and adjustable screen height, ensuring comfortable viewing and efficient meetings | D55: =INDEX(PRICING!AW:AW,MATCH(B55,PRICING!AV:AV,0),1) -> 61559 | E55: 12 MONTH WARRANTY
B56: NEATBOARDPRO-ADAPTIVE-MOUNT | C56: Neat Adaptive Mount Securely position the Board Pro close to the wall for a sleek look. Easy vertical adjustment ensures optimal viewing angles and comfort in any room setup. | D56: =INDEX(PRICING!AW:AW,MATCH(B56,PRICING!AV:AV,0),1) -> 26765 | E56: ETA Confirmed on Order 12 MONTH WARRANTY
B57: NEATBOARDPRO-WALLMOUNT | C57: Neat Wall Mount for Board Pro. VESA compatible | D57: =INDEX(PRICING!AW:AW,MATCH(B57,PRICING!AV:AV,0),1) -> 7206 | E57: ETA Confirmed on Order 12 MONTH WARRANTY
B58: NEATBOARD-STYLUS-2PK | C58: Neat Board - STYLUS + PACKAGING (packaged in sets of 2) | D58: =INDEX(PRICING!AW:AW,MATCH(B58,PRICING!AV:AV,0),1) -> 2352
B59: NEAT-ACTIVE-MARKER | C59: Neat Active Marker - pressure sensitive active marker for Board 50 and Board Pro. 1 stylus in each package. | D59: =INDEX(PRICING!AW:AW,MATCH(B59,PRICING!AV:AV,0),1) -> 1712
B60: Neat Pulse
B61: PULSE-PLUS-BOARDPRO-1 | C61: Neat Pulse Plus for Neat Board Pro including Control and Care for 1 year | D61: =INDEX(PRICING!AW:AW,MATCH(B61,PRICING!AV:AV,0),1) -> 8647 | E61: Pulse Plus
B62: PULSE-PLUS-BOARDPRO-3 | C62: Neat Pulse Plus for Neat Board Pro, including Control and Care for 3 years | D62: =INDEX(PRICING!AW:AW,MATCH(B62,PRICING!AV:AV,0),1) -> 19456 | E62: Pulse Plus
B63: PULSE-PRO-BOARDPRO-1 | C63: Neat Pulse Pro for Neat Board Pro-SE, including Control Management and Monitoring, Care Support, and Cover Advanced Replacement for 1 year | D63: =INDEX(PRICING!AW:AW,MATCH(B63,PRICING!AV:AV,0),1) -> 12971 | E63: Pulse Pro
B64: PULSE-PRO-BOARDPRO-3 | C64: Neat Pulse Pro for Neat Board Pro-SE, including Control Management and Monitoring, Care Support, and Cover Advanced Replacement for 3 years | D64: =INDEX(PRICING!AW:AW,MATCH(B64,PRICING!AV:AV,0),1) -> 32426 | E64: Pulse Pro
B65: Neat Bar
B66: NEATBAR2-SE | C66: Neat Bar 2 - 2nd Generation Collaboration Bar with Integrated 50mp camera, 113 FOV, Microphones and wall, table, and display mounts | D66: =INDEX(PRICING!AW:AW,MATCH(B66,PRICING!AV:AV,0),1) -> 59521 | E66: ETA Confirmed on Order 12 MONTH WARRANTY
B67: Neat Pulse
B68: PULSE-PLUS-BAR2-1 | C68: Pulse Plus for Neat Bar2 and Neat Pad, including Control and Care for 1 year | D68: =INDEX(PRICING!AW:AW,MATCH(B68,PRICING!AV:AV,0),1) -> 4597 | E68: Pulse Plus
B69: PULSE-PLUS-BAR2-3 | C69: Pulse Plus for Neat Bar2 and Neat Pad, including Control and Care for 3 years | D69: =INDEX(PRICING!AW:AW,MATCH(B69,PRICING!AV:AV,0),1) -> 10348 | E69: Pulse Plus
B70: PULSE-PRO-BAR2-1 | C70: Pulse Pro for Neat Bar2 and Neat Pad, including Control, Care, and Cover for 1 year | D70: =INDEX(PRICING!AW:AW,MATCH(B70,PRICING!AV:AV,0),1) -> 6903 | E70: Pulse Pro
B71: PULSE-PRO-BAR2-3 | C71: Pulse Pro for Neat Bar2 and Neat Pad, including Control, Care, and Cover for 3 years | D71: =INDEX(PRICING!AW:AW,MATCH(B71,PRICING!AV:AV,0),1) -> 17251 | E71: Pulse Pro
B72: Neat BYOD
B73: NEATBAR-BYOD | C73: Neat BYOD BAR - All-in-one video device for Zoom/BYOD. Ideal for small to medium rooms up to 10 people within 15ft/5m. Features a 12MP camera, 120° FOV, 8x digital zoom, auto-framing, 5 mics, and opposing drivers. Mounting hardware included. | D73: =INDEX(PRICING!AW:AW,MATCH(B73,PRICING!AV:AV,0),1) -> 11805 | E73: PROMOTION ETA Confirmed on Order 12 MONTH WARRANTY
B74: Neat Pulse
B75: PULSE-PLUS-BARB-PLUS1 | C75: Neat Pulse Plus 1-year for Neat Bar BYOD | D75: =INDEX(PRICING!AW:AW,MATCH(B75,PRICING!AV:AV,0),1) -> 1153 | E75: Pulse Plus
B76: PULSE-PLUS-BARB-PLUS3 | C76: Neat Pulse Plus 3-year for Neat Bar BYOD | D76: =INDEX(PRICING!AW:AW,MATCH(B76,PRICING!AV:AV,0),1) -> 2565 | E76: Pulse Plus
B77: PULSE-PRO-BARB-PRO1 | C77: Neat Pulse Pro 1-year for Neat Bar BYOD | D77: =INDEX(PRICING!AW:AW,MATCH(B77,PRICING!AV:AV,0),1) -> 1700 | E77: Pulse Pro
B78: PULSE-PRO-BARB-PRO3 | C78: Neat Pulse Pro 3-year for Neat Bar BYOD | D78: =INDEX(PRICING!AW:AW,MATCH(B78,PRICING!AV:AV,0),1) -> 4280 | E78: Pulse Pro
B79: Neat Bar Pro
B80: NEATBARPRO-SE | C80: Neat Bar Pro - Collaboration Bar designed for MS TEAMS and Zoom. Includes Bar Pro, integrated camera, microphones and wall, table, and display mounts. | D80: =INDEX(PRICING!AW:AW,MATCH(B80,PRICING!AV:AV,0),1) -> 94445 | E80: 12 MONTH WARRANTY
B81: Add-on
B82: BARPRO-MOUNT-ADAPTER | C82: Neat Mounting interface between Neat Bar Pro and mounting brackets | D82: =INDEX(PRICING!AW:AW,MATCH(B82,PRICING!AV:AV,0),1) -> 1626
B83: BARPRO-SCREENMOUNT-HORIZONTALBAR | C83: Neat Horizontal Neat Bar Pro VESA attachment, covers up to 600 mm VESA interface, only horizontal bar is included | D83: =INDEX(PRICING!AW:AW,MATCH(B83,PRICING!AV:AV,0),1) -> 1193
B84: BARPRO-SCREENMOUNT-VERTICALBAR | C84: Neat Vertical Neat Bar Pro VESA attachment, covers up to 600 mm VESA interface, only vertical bar is included | D84: =INDEX(PRICING!AW:AW,MATCH(B84,PRICING!AV:AV,0),1) -> 1193
B85: BARPRO-TABLESTAND | C85: Neat BarPro Table Stand | D85: =INDEX(PRICING!AW:AW,MATCH(B85,PRICING!AV:AV,0),1) -> 1420
B86: BARPRO-WALLMOUNT | C86: Neat BarPro Wall mount | D86: =INDEX(PRICING!AW:AW,MATCH(B86,PRICING!AV:AV,0),1) -> 1029
B87: Neat Pulse
B88: PULSE-PLUS-BARPRO1 | C88: Pulse Plus for Neat Bar Pro with Neat Pad, including Control [Management and Monitoring] and Care [Support] for 1 year | D88: =INDEX(PRICING!AW:AW,MATCH(B88,PRICING!AV:AV,0),1) -> 6745 | E88: Pulse Plus
B89: PULSE-PLUS-BARPRO3 | C89: Pulse Plus for Neat Bar Pro with Neat Pad, including Control [Management and Monitoring] and Care [Support] for 3 years | D89: =INDEX(PRICING!AW:AW,MATCH(B89,PRICING!AV:AV,0),1) -> 15176 | E89: Pulse Plus
B90: PULSE-PRO-BARPRO1 | C90: Pulse Pro for Neat Bar Pro with Neat Pad, including Control [Management and Monitoring], Care [Support], and Cover [Advanced Replacement] for 1 year | D90: =INDEX(PRICING!AW:AW,MATCH(B90,PRICING!AV:AV,0),1) -> 10117 | E90: Pulse Pro
B91: PULSE-PRO-BARPRO3 | C91: Pulse Pro for Neat Bar Pro with Neat Pad, including Control [Management and Monitoring], Care [Support], and Cover [Advanced Replacement] for 3 years | D91: =INDEX(PRICING!AW:AW,MATCH(B91,PRICING!AV:AV,0),1) -> 25293 | E91: Pulse Pro
B92: Neat Frame
B93: NEATFRAME-SE | C93: Neat Frame personal video meeting device designed for MS TEAMS and ZOOM | D93: =INDEX(PRICING!AW:AW,MATCH(B93,PRICING!AV:AV,0),1) -> 10359 | E93: PROMOTION 12 MONTH WARRANTY
B94: Neat Pulse
B95: PULSE-PLUS-FRAME1 | C95: Pulse Plus for Neat Frame including Control [Management and Monitoring] and Care [Support] for 1 year | D95: =INDEX(PRICING!AW:AW,MATCH(B95,PRICING!AV:AV,0),1) -> 692 | E95: Pulse Plus
B96: PULSE-PLUS-FRAME3 | C96: Pulse Plus for Frame including Control [Management and Monitoring] and Care [Support] for 3 years | D96: =INDEX(PRICING!AW:AW,MATCH(B96,PRICING!AV:AV,0),1) -> 1556 | E96: Pulse Plus
B97: PULSE-PRO-FRAME1 | C97: Pulse Pro for Neat Frame, including Control [Management and Monitoring], Care [Support], and Cover [Advanced Replacement] for 1 year | D97: =INDEX(PRICING!AW:AW,MATCH(B97,PRICING!AV:AV,0),1) -> 1038 | E97: Pulse Pro
B98: PULSE-PRO-FRAME3 | C98: Pulse Pro for Neat Frame, including Control [Management and Monitoring], Care [Support], and Cover [Advanced Replacement] for 3 years | D98: =INDEX(PRICING!AW:AW,MATCH(B98,PRICING!AV:AV,0),1) -> 2594 | E98: Pulse Pro
B99: Neat Center
B100: NEATCENTER-SE | C100: Neat 360° companion device extending Neat Symmetry, providing optimal sound and views of meeting room participants. For placement on a table, mounted or hung from above. Ethernet cable incl. Does not incl POE (sold separately) | D100: =INDEX(PRICING!AW:AW,MATCH(B100,PRICING!AV:AV,0),1) -> 39604 | E100: 12 MONTH WARRANTY
B101: Add-on
...

Sheet Netogy
E1: Return
B3: CLICK HERE TO VISIT OUR NETOGY WEBSITE FOR MORE INFO
B4: SKU | C4: DESCRIPTION | D4: PRICE | E4: COMMENTS
B5: BACKUP POWER
B6: UPS100-PLUS | C6: Netogy UPS100 Plus Mini DC UPS/Powerbank | D6: =INDEX(PRICING!Y:Y,MATCH(B6,PRICING!X:X,0),1) -> 599 | E6: PROMOTION
B7: ANDROID TV BOX
B8: NOVA10 | C8: Netogy Nova10 Android TV Box | D8: =INDEX(PRICING!Y:Y,MATCH(B8,PRICING!X:X,0),1) -> 849 | E8: Volume discounts available from 50+ units
B9: GOOGLE TV BOX
B10: NOVA PRO | C10: Netogy Nova Pro Google TV Box | D10: =INDEX(PRICING!Y:Y,MATCH(B10,PRICING!X:X,0),1) -> 1099
B11: YCABLE | C11: Netogy Nova Pro Y-Cable | D11: =INDEX(PRICING!Y:Y,MATCH(B11,PRICING!X:X,0),1) -> 59
B12: TV BOX REMOTE
B13: NOVA10 BLUETOOTH RCU | C13: Netogy Nova10 Bluetooth Remote Control | D13: =INDEX(PRICING!Y:Y,MATCH(B13,PRICING!X:X,0),1) -> 129
B14: NOVA PRO BLUETOOTH RCU | C14: Netogy Nova Pro Bluetooth Remote Control | D14: =INDEX(PRICING!Y:Y,MATCH(B14,PRICING!X:X,0),1) -> 129
B15: TYRE INFLATORS
B16: AIRNOVA | C16: NW01-S Tyre Inflator | D16: =INDEX(PRICING!Y:Y,MATCH(B16,PRICING!X:X,0),1) -> 799
B17: AIRNOVAMAX | C17: KF03 Tyre Inflator & Jump Starter | D17: =INDEX(PRICING!Y:Y,MATCH(B17,PRICING!X:X,0),1) -> 1199
B19: E & OE Terms & Conditions: Pricing valid from 1 April 2026 until 30 April 2026. All pricing is Exclusive of VAT and subject to stock availability and lead times. Pricing is subject to change without notice and is linked to the exchange rate. CLICK HERE to view our full Terms and Conditions.

Sheet Samsung
E1: Return
B3: SKU | C3: DESCRIPTION | D3: PRICE | E3: SPECIFICATIONS
B4: LARGE FORMAT DISPLAYS
B5: 58-QB65C | C5: 65" Professional Display - UHD, 16/7 Usage, 350nit Brightness, SoC Media Player: SSSP 10 Tizen 7 | D5: =INDEX(PRICING!CA:CA,MATCH(B5,PRICING!BZ:BZ,0),1) -> 14565 | E5: QB65C
B6: 58-QB75C | C6: 75" Professional Display - UHD, 16/7 Usage, 350nit Brightness, SoC Media Player: SSSP 10 Tizen 7 | D6: =INDEX(PRICING!CA:CA,MATCH(B6,PRICING!BZ:BZ,0),1) -> 24999 | E6: QB75C
B7: 58-QB85C | C7: 85" Professional Display - UHD, 16/7 Usage, 350nit Brightness, SoC Media Player: SSSP Tizen 7 | D7: =INDEX(PRICING!CA:CA,MATCH(B7,PRICING!BZ:BZ,0),1) -> 33152 | E7: QB85C
B8: 58-QM50C | C8: 50" Professional Display - UHD, 24/7 Usage, 500nit Brightness, SoC Media Player: SSSP 10 Tizen 7 | D8: =INDEX(PRICING!CA:CA,MATCH(B8,PRICING!BZ:BZ,0),1) -> 10653 | E8: QM50C
B9: 58-QM55C | C9: 55" Professional Display - UHD, 24/7 Usage, 500nit Brightness, SoC Media Player: SSSP 10 Tizen 7 | D9: =INDEX(PRICING!CA:CA,MATCH(B9,PRICING!BZ:BZ,0),1) -> 13586 | E9: QM55C
B10: 58-QM65C | C10: 65" Professional Display - UHD, 24/7 Usage, 500nit Brightness, SoC Media Player: SSSP 10 Tizen 7 | D10: =INDEX(PRICING!CA:CA,MATCH(B10,PRICING!BZ:BZ,0),1) -> 16847 | E10: QM65C
B11: 58-QM75C | C11: 75" Professional Display - UHD, 24/7 Usage, 500nit Brightness, SoC Media Player: SSSP 10 Tizen 7 | D11: =INDEX(PRICING!CA:CA,MATCH(B11,PRICING!BZ:BZ,0),1) -> 33695 | E11: QM75C
B12: 58-QM85C | C12: 85" Professional Display - UHD, 24/7 Usage, 500nit Brightness, SoC Media Player: SSSP 10 Tizen 7 | D12: =INDEX(PRICING!CA:CA,MATCH(B12,PRICING!BZ:BZ,0),1) -> 41303 | E12: QM85C
B14: E & OE Terms & Conditions: Pricing valid from 1 April 2026 until 30 April 2026. All pricing is Exclusive of VAT and subject to stock availability and lead times. Pricing is subject to change without notice and is linked to the exchange rate. CLICK HERE to view our full Terms and Conditions.

Sheet Shelly
E1: Return
B3: CLICK HERE TO VISIT OUR SHELLY WEBSITE FOR MORE INFO
B4: SKU | C4: DESCRIPTION | D4: PRICE | E4: COMMENTS
B5: SMART SWITCHES AND DIMMERS
B6: SHELLY PM MINI GEN3 | C6: Shelly PM Mini Gen3 Offers One-Channel Power Metering | D6: =INDEX(PRICING!P:P,MATCH(B6,PRICING!O:O,0),1) -> 273.47074
B7: SHELLY 1 MINI GEN3 | C7: Shelly 1 Mini Gen3 Smart Mini One-Channel 8A Wi-Fi Relay | D7: =INDEX(PRICING!P:P,MATCH(B7,PRICING!O:O,0),1) -> 253.12684
B8: SHELLY 1PM MINI GEN3 | C8: Shelly 1PM Mini Gen3 One-Channel Wi-Fi Relay With Power Monitoring | D8: =INDEX(PRICING!P:P,MATCH(B8,PRICING!O:O,0),1) -> 287.05733
B9: SHELLY 1 GEN3 | C9: Shelly 1 Gen3 Wi-Fi Operated Smart Switch To Remotely Control A Wide Range Of Home Appliances And Office Equipment | D9: =INDEX(PRICING!P:P,MATCH(B9,PRICING!O:O,0),1) -> 306.66128
B10: SHELLY 1PM GEN3 | C10: Shelly 1PM Gen3 Wi-Fi Operated Smart Switch With Power Monitoring | D10: =INDEX(PRICING!P:P,MATCH(B10,PRICING!O:O,0),1) -> 365.60807
B11: SHELLY 1PM GEN4 | C11: Shelly 1PM Gen4 Compact Smart Switch With Power Monitoring & Multiprotocol Support | D11: =INDEX(PRICING!P:P,MATCH(B11,PRICING!O:O,0),1) -> 431.67358
B12: SHELLY 2PM GEN3 | C12: Shelly 2PM Gen3 Two-Channel Smart Switch With Power Monitoring And Cover Control | D12: =INDEX(PRICING!P:P,MATCH(B12,PRICING!O:O,0),1) -> 533.44057
B13: SHELLY 2PM GEN4 | C13: Shelly 2PM Gen4 Two-Channel Smart Switch With Power Metering And Multiprotocol Support | D13: =INDEX(PRICING!P:P,MATCH(B13,PRICING!O:O,0),1) -> 674.40727
B14: SHELLY PRO 1PM | C14: Shelly Pro 1PM DIN-Rail Mountable Wi-Fi Relay For One Channel Of 16A | D14: =INDEX(PRICING!P:P,MATCH(B14,PRICING!O:O,0),1) -> 1177.0088
B15: SHELLY PRO 2PM | C15: Shelly Pro 2PM DIN-Rail Mountable Wi-Fi Relay With Power Monitoring Of Two 16A Channels 25A In Total | D15: =INDEX(PRICING!P:P,MATCH(B15,PRICING!O:O,0),1) -> 1566.7834
B16: SHELLY PRO 4PM | C16: Shelly Pro 4PM DIN-Rail Mountable Wi-Fi Relay For 4 Channels of 16A Each 40A In Total | D16: =INDEX(PRICING!P:P,MATCH(B16,PRICING!O:O,0),1) -> 1856.7965
B17: SHELLY DIMMER 0/1-10V GEN3 | C17: Shelly Dimmer 0/1-10V PM Gen3 Smart Dimming Controller With Power Measurement | D17: =INDEX(PRICING!P:P,MATCH(B17,PRICING!O:O,0),1) -> 320.52106
... B23: SHELLY PRO 3 | C23: Shelly Pro 3 - Three-Channel Relay With Potential-Free Outputs Supporting A Total Of 48A | D23: =INDEX(PRICING!P:P,MATCH(B23,PRICING!O:O,0),1) -> 1426.7418
B24: SHELLY 2L GEN3 | C24: Shelly Two-Channel Smart Switch Tailored for Lighting Control in no Neutral Wire Installations | D24: =INDEX(PRICING!P:P,MATCH(B24,PRICING!O:O,0),1) -> 708.37108 | E24: COMING SOON
B25: ENERGY METERS
B26: SHELLY PRO EM - 50 | C26: Shelly Pro EM-50 DIN-Rail Mountable Two-Channel Single Phase Energy Meter With Integrated Switch For Contactor Control | D26: =INDEX(PRICING!P:P,MATCH(B26,PRICING!O:O,0),1) -> 1442.0024
B27: SHELLY EM GEN3 | C27: Shelly EM Gen3 + 50A Clamp Provides Real-Time Insights Into The Power Consumption Of Your Connected Devices | D27: =INDEX(PRICING!P:P,MATCH(B27,PRICING!O:O,0),1) -> 1129.5856
B28: SHELLY 50A CLAMP | C28: Shelly 50A Clamp Split Core Current Transformer ONLY Compatible With Shelly EM | D28: =INDEX(PRICING!P:P,MATCH(B28,PRICING!O:O,0),1) -> 252.44364
B29: SHELLY 50A CLAMP EM GEN3 | C29: Shelly 50A Clamp Split Core Current Transformer ONLY Compatible With Shelly EM Gen3 & PRO EM-50 | D29: =INDEX(PRICING!P:P,MATCH(B29,PRICING!O:O,0),1) -> 237.77358
B30: SHELLY 80A CLAMP | C30: Shelly 80A Clamp Current Transformer With Connector For Shelly EM Gen3 | D30: =INDEX(PRICING!P:P,MATCH(B30,PRICING!O:O,0),1) -> 266.87564
B31: SHELLY 120A CLAMP | C31: Shelly 120A Clamp Split Core Current Transformer ONLY Compatible With Shelly EM | D31: =INDEX(PRICING!P:P,MATCH(B31,PRICING!O:O,0),1) -> 340.78815
B32: SHELLY PRO 3EM-120A | C32: Shelly Pro 3EM-120A DIN-Rail Mountable Single Or Three-Phase Energy Meter With 3-Phase Current Transformers | D32: =INDEX(PRICING!P:P,MATCH(B32,PRICING!O:O,0),1) -> 2254.0553
B33: SHELLY PRO 3EM-400A | C33: Shelly Pro 3EM-400A DIN-Rail Mountable Single Or Three-Phase Energy Meter With 3-Phase Current Transformers | D33: =INDEX(PRICING!P:P,MATCH(B33,PRICING!O:O,0),1) -> 4447.517
B34: SHELLY 120A CT PRO 3EM | C34: Shelly 120A CT Pro 3EM Split Core Current Transformer For Shelly Pro 3EM | D34: =INDEX(PRICING!P:P,MATCH(B34,PRICING!O:O,0),1) -> 346.38751
B35: SHELLY 400A CT PRO 3EM | C35: Shelly 400A CT Pro 3EM Split Core Current Transformer For Shelly Pro 3EM | D35: =INDEX(PRICING!P:P,MATCH(B35,PRICING!O:O,0),1) -> 1133.9825
B36: SMART LIGHTNING
B37: SHELLY DUO CW/WW (E27) | C37: Shelly Duo CW/WW (E27) Smart Cool Or Warm White Dimmable Bulb | D37: =INDEX(PRICING!P:P,MATCH(B37,PRICING!O:O,0),1) -> 229 | E37: EOL (last stock & promotion)
B38: SHELLY VINTAGE A60 (E27) | C38: Shelly Vintage A60 (E27) Dimmable Smart Bulb | D38: =INDEX(PRICING!P:P,MATCH(B38,PRICING!O:O,0),1) -> 229 | E38: EOL (last stock & promotion)
B39: SHELLY VINTAGE G125 (E27) | C39: Shelly Vintage G125 (E27) Dimmable Smart Bulb | D39: =INDEX(PRICING!P:P,MATCH(B39,PRICING!O:O,0),1) -> 359 | E39: EOL (last stock & promotion)
B40: SMART HEATING AND CLIMATE CONTROL
B41: SHELLY H&T GEN3 (BLACK) | C41: Shelly H&T Gen3 Wi-Fi Temperature & Humidity Sensor With An E-Paper Display (Matte Black) | D41: =INDEX(PRICING!P:P,MATCH(B41,PRICING!O:O,0),1) -> 622.21972
B42: SHELLY BLU H&T (BLACK) | C42: Shelly BLU H&T (Black) Bluetooth Humidity And Temperature Sensor | D42: =INDEX(PRICING!P:P,MATCH(B42,PRICING!O:O,0),1) -> 340.93091
B43: SHELLY TEMP SENSOR (DS18B20) | C43: Shelly Temp Sensor DS18B20 1m Temperature Sensing Cable | D43: =INDEX(PRICING!P:P,MATCH(B43,PRICING!O:O,0),1) -> 74.510909
B44: SHELLY TEMP SENSOR DS18B20 3M | C44: Shelly Temp Sensor DS18B20 3m Temperature Sensing Cable | D44: =INDEX(PRICING!P:P,MATCH(B44,PRICING!O:O,0),1) -> 137.34611
B45: SAFETY AND SECURITY
B46: SHELLY PLUS SMOKE ALARM | C46: Shelly Plus Smoke Alarm Is A Wire-Free Battery Operated Smart Photoelectric Smoke Alarm | D46: =INDEX(PRICING!P:P,MATCH(B46,PRICING!O:O,0),1) -> 841.26098
B47: SHELLY BLU MOTION | C47: Shelly BLU Motion Smart Bluetooth Motion Detection Sensor Featuring A Lux Meter | D47: 371
B48: SHELLY BLU DOOR WINDOW BLACK | C48: Shelly BLU Door Window (Black) Bluetooth Sensor Designed To Detect The Opening And Closing Of A Door Or Window | D48: =INDEX(PRICING!P:P,MATCH(B48,PRICING!O:O,0),1) -> 310.11188
B49: SHELLY BLU DOOR WINDOW WHITE | C49: Shelly BLU Door Window (White) Bluetooth Sensor Designed To Detect The Opening And Closing Of A Door Or Window | D49: =INDEX(PRICING!P:P,MATCH(B49,PRICING!O:O,0),1) -> 323.41527
B50: SHELLY FLOOD GEN4 | C50: Shelly Flood Gen4 Smart Battery Operated Water Leak Detector With 2m Cable Sensor | D50: =INDEX(PRICING!P:P,MATCH(B50,PRICING!O:O,0),1) -> 490.41455 | E50: NEW
B51: SHELLY LEAK SENSOR CABLE | C51: Shelly Leak Sensor Cable Extended Reach Coverage For Shelly Flood Gen4 | D51: =INDEX(PRICING!P:P,MATCH(B51,PRICING!O:O,0),1) -> 116.17143 | E51: NEW
B52: CONTROL AND SCENE ACTIVATION
B53: SHELLY WALL DISPLAY + BLU H&T | C53: Shelly Wall Display + Blu H&T (Black) Smart Control Panel With Temperature, Humidity & LUX Sensors | D53: =INDEX(PRICING!P:P,MATCH(B53,PRICING!O:O,0),1) -> 2472.906
B54: SHELLY WALL DISPLAY+BLU H&T(W) | C54: Shelly Wall Display + Blu H&T (White) Smart Control Panel With Temperature, Humidity & LUX Sensors | D54: =INDEX(PRICING!P:P,MATCH(B54,PRICING!O:O,0),1) -> 2571.3964
B55: SHELLY WALL DISPLAY XL BLACK | C55: Shelly Wall Display XL - Smart Home Control Panel With a 10.1” Touch Display | D55: =INDEX(PRICING!P:P,MATCH(B55,PRICING!O:O,0),1) -> 5388.3653 | E55: NEW
B56: SHELLY WALL DISPLAY X2i BLACK | C56: Shelly Wall Display X2i Smart 6.95” Color Touchscreen (Black) | D56: =INDEX(PRICING!P:P,MATCH(B56,PRICING!O:O,0),1) -> 3283.5927 | E56: COMING SOON
B57: SHELLY WALL DISPLAY X2i SILVER | C57: Shelly Wall Display X2i Smart 6.95” Color Touchscreen (Silver) | D57: =INDEX(PRICING!P:P,MATCH(B57,PRICING!O:O,0),1) -> 3283.5927 | E57: COMING SOON
B58: SHELLY BLU BUTTON1 (BLACK) | C58: Shelly BLU Button1 (Black) Bluetooth Button For Operated Actions And Scene Activation | D58: =INDEX(PRICING!P:P,MATCH(B58,PRICING!O:O,0),1) -> 299 | E58: EOL (last stock & promotion)
B59: SHELLY BLU BUTTON1 (BLUE) | C59: Shelly BLU Button1 (Blue) Bluetooth Button For Operated Actions And Scene Activation | D59: =INDEX(PRICING!P:P,MATCH(B59,PRICING!O:O,0),1) -> 299 | E59: EOL (last stock & promotion)
B60: SHELLY BLU BUTTON1 (RED) | C60: Shelly BLU Button1 (Red) Bluetooth Button For Operated Actions And Scene Activation | D60: =INDEX(PRICING!P:P,MATCH(B60,PRICING!O:O,0),1) -> 299 | E60: EOL (last stock & promotion)
B61: SHELLY BLU BUTTON TOUGH 1 BLACK | C61: Shelly BLU Button Tough1 (Black) Smart Shock, Water And Dust-Resistant Bluetooth Button Of A Compact Size | D61: 331
B62: SHELLY BLU BUTTON TOUGH 1 MOCH | C62: Shelly BLU Button Tough1 (Mocha) Smart Shock, Water And Dust-Resistant Bluetooth Button Of A Compact Size | D62: =INDEX(PRICING!P:P,MATCH(B62,PRICING!O:O,0),1) -> 309.13547
B63: SHELLY BLU RC BUTTON 4 | C63: Shelly BLU RC Button 4 Smart Four-Button Bluetooth Remote Controller | D63: =INDEX(PRICING!P:P,MATCH(B63,PRICING!O:O,0),1) -> 292.01711
B64: IRRIGATION, WATER CONTROL & WEATHER TRACKING
B65: FRANKEVER SMART VALVE DN20 | C65: Frankever Smart Valve DN20 Powered By Shelly Smart Water Valve | D65: =INDEX(PRICING!P:P,MATCH(B65,PRICING!O:O,0),1) -> 2360.4727 | E65: NEW
B66: FRANKEVER SPRINKLER FK-06X | C66: 6-zone Wi-Fi Enabled Smart Sprinkler Controller – Powered by Shelly | D66: =INDEX(PRICING!P:P,MATCH(B66,PRICING!O:O,0),1) -> 1988.1901 | E66: NEW
B67: ECOWITT WEATHER STATION WS90 | C67: Ecowitt Weather Station WS90 Powered By Shelly 7-in-1 Weather Station | D67: =INDEX(PRICING!P:P,MATCH(B67,PRICING!O:O,0),1) -> 3493.0327 | E67: NEW
B68: ACCESSORIES
B69: SHELLY BLU GATEWAY | C69: Shelly BLU Gateway Smart BLE To Wi-Fi Gateway In A USB-A Dongle | D69: =INDEX(PRICING!P:P,MATCH(B69,PRICING!O:O,0),1) -> 272.69355
B70: SHELLY PLUS ADD-ON | C70: Shelly Plus Add-On For Shelly Gen3 And Gen4 Devices | D70: =INDEX(PRICING!P:P,MATCH(B70,PRICING!O:O,0),1) -> 271.32435
B71: SHELLY PRO 3EM SWITCH ADD-ON | C71: Shelly Pro 3EM Switch Add-On Extends The Possibilities Of The Shelly Pro 3EM | D71: =INDEX(PRICING!P:P,MATCH(B71,PRICING!O:O,0),1) -> 385.45818
B72: SHELLY BYPASS | C72: Shelly Bypass For Dimmer 2 Needed If Dimmer 2 Is Used With No Neutral Has Less Than 10W Load | D72: =INDEX(PRICING!P:P,MATCH(B72,PRICING!O:O,0),1) -> 53.865974
B73: SHELLY BYPASS FOR DIMMER GEN3 | C73: Shelly Bypass For Dimmer Gen3 Small Bypass To Operate In Installations Without A Neutral Wire | D73: =INDEX(PRICING!P:P,MATCH(B73,PRICING!O:O,0),1) -> 77.218723
B74: SHELLY PLUS UNI | C74: Shelly Plus Uni Small Form Factor Smart Universal Module | D74: =INDEX(PRICING!P:P,MATCH(B74,PRICING!O:O,0),1) -> 281.79394
B76: E & OE Terms & Conditions: Pricing valid from 1 April 2026 until 30 April 2026. All pricing is Exclusive of VAT and subject to stock availability and lead times. Pricing is subject to change without notice and is linked to the exchange rate. CLICK HERE to view our full Terms and Conditions.

Sheet Telrad
E1: Return
B3: SKU | C3: DESCRIPTION | D3: PRICE | E3: COMMENTS
B4: POINT-TO-MULTI POINT
B5: BreezeAIR AXE-L 5-200-17-PTMP-CPE | C5: BreezeAIR AXE-L 5.x GHz 200Mbps PTMP CPE, integrated 17.5 dBi dual polarization antenna | D5: =INDEX(PRICING!BF:BF,MATCH(B5,PRICING!BE:BE,0),1) -> 6469
B6: BreezeAIR AXE-L 5-200-23-PTMP-CPE | C6: BreezeAIR AXE-L 5.x GHz 200Mbps PTMP CPE, integrated 23 dBi dual polarization antenna | D6: =INDEX(PRICING!BF:BF,MATCH(B6,PRICING!BE:BE,0),1) -> 7255
B7: BreezeAIR AXE-L 5-500-17-PTMP-CPE | C7: BreezeAIR AXE-L 5.x GHz 500Mbps PTMP CPE, integrated 17.5 dBi dual polarization antenna | D7: =INDEX(PRICING!BF:BF,MATCH(B7,PRICING!BE:BE,0),1) -> 7299
B8: BreezeAIR AXE-L 5-500-23-PTMP-CPE | C8: BreezeAIR AXE-L 5.x GHz 500Mbps PTMP CPE, integrated 23 dBi dual polarization antenna | D8: =INDEX(PRICING!BF:BF,MATCH(B8,PRICING!BE:BE,0),1) -> 7998
B9: BreezeAirAXE-5-1G-17-PTMP-CPE | C9: BreezeAir AXE 5.x GHz 1Gbps PTMP CPE, integrated 17.5 dBi dual polarization antenna | D9: =INDEX(PRICING!BF:BF,MATCH(B9,PRICING!BE:BE,0),1) -> 8125
B10: BreezeAirAXE-5-1G-23-PTMP-CPE | C10: BreezeAir AXE 5.x GHz 1Gbps PTMP CPE, integrated 23 dBi dual polarization antenna | D10: =INDEX(PRICING!BF:BF,MATCH(B10,PRICING!BE:BE,0),1) -> 8738.9957
B11: BreezeAirAXE-5-2G-PTMP | C11: BreezeAir AXE 5.x GHz 2Gbps PTMP Master Unit, external antenna ports, synchronized | D11: =INDEX(PRICING!BF:BF,MATCH(B11,PRICING!BE:BE,0),1) -> 29475
