Workbook

Sheet Progress
B1: Total | C1: Processed | D1: Difference | E1: Rate% | G1: 45548 | I1: OVERVIEW | J1: Agents tasked to assist | K1: Total | L1: Processed | M1: Difference | N1: Rate%
A2: Clients (A - D) | B2: ='Clients (A - D)'!B1 -> 3294 | C2: =COUNTIFS('Clients (A - D)'!A$4:A1003,$A1,'Clients (A - D)'!C$4:C1003,"?*") -> 0 | D2: =B2-C2 -> 3294 | E2: =C2/B2 -> 0 | G2: 120 | I2: Clients (A - D) | J2: Marisa + Darne | K2: ='Clients (A - D)'!B1 -> 3294 | L2: ='Clients (A - D)'!C1 -> 645 | M2: =K2-L2 -> 2649 | N2: =L2/K2 -> 0.19581056
A3: Clients (E - H) | B3: ='Clients (E - H)'!B1 -> 1532 | C3: =COUNTIFS('Clients (E - H)'!A$4:A1003,$A1,'Clients (E - H)'!C$4:C1003,"?*") -> 0 | D3: =B3-C3 -> 1532 | E3: =C3/B3 -> 0 | G3: 76 | I3: Clients (E - H) | J3: Farren | K3: ='Clients (E - H)'!B1 -> 1532 | L3: ='Clients (E - H)'!C1 -> 159 | M3: =K3-L3 -> 1373 | N3: =L3/K3 -> 0.1037859
A4: Clients (I - L) | B4: ='Clients (I - L)'!B1 -> 1814 | C4: =COUNTIFS('Clients (I - L)'!A$4:A1003,$A1,'Clients (I - L)'!C$4:C1003,"?*") -> 0 | D4: =B4-C4 -> 1814 | E4: =C4/B4 -> 0 | G4: 52 | I4: Clients (I - L) | J4: Larinda + Kayla | K4: ='Clients (I - L)'!B1 -> 1814 | L4: ='Clients (I - L)'!C1 -> 1076 | M4: =K4-L4 -> 738 | N4: =L4/K4 -> 0.59316428
A5: Clients (M - P) | B5: ='Clients (M - P)'!B1 -> 2150 | C5: =COUNTIFS('Clients (M - P)'!A$4:A1003,$A1,'Clients (M - P)'!C$4:C1003,"?*") -> 0 | D5: =B5-C5 -> 2150 | E5: =C5/B5 -> 0 | G5: 64 | I5: Clients (M - P) | J5: Jessica | K5: ='Clients (M - P)'!B1 -> 2150 | L5: ='Clients (M - P)'!C1 -> 1239 | M5: =K5-L5 -> 911 | N5: =L5/K5 -> 0.57627907
A6: Clients (Q - T) | B6: ='Clients (Q - T)'!B1 -> 1974 | C6: =COUNTIFS('Clients (Q - T)'!A$4:A1003,$A1,'Clients (Q - T)'!C$4:C1003,"?*") -> 0 | D6: =B6-C6 -> 1974 | E6: =C6/B6 -> 0 | G6: 3 | I6: Clients (Q - T) | J6: Ryanicea & Adele | K6: ='Clients (Q - T)'!B1 -> 1974 | L6: ='Clients (Q - T)'!C1 -> 1033 | M6: =K6-L6 -> 941 | N6: =L6/K6 -> 0.52330294
A7: Clients (U - V) | B7: ='Clients (U - V)'!B1 -> 1101 | C7: =COUNTIFS('Clients (U - V)'!A$4:A1003,$A1,'Clients (U - V)'!C$4:C1003,"?*") -> 0 | D7: =B7-C7 -> 1101 | E7: =C7/B7 -> 0 | G7: 29 | I7: Clients (U - V) | J7: Charlize | K7: ='Clients (U - V)'!B1 -> 1101 | L7: ='Clients (U - V)'!C1 -> 117 | M7: =K7-L7 -> 984 | N7: =L7/K7 -> 0.10626703
A8: Clients (W - Z) | B8: ='Clients (W - Z)'!B1 -> 556 | C8: =COUNTIFS('Clients (W - Z)'!A$4:A1003,$A1,'Clients (W - Z)'!C$4:C1003,"?*") -> 0 | D8: =B8-C8 -> 556 | E8: =C8/B8 -> 0 | G8: 76 | I8: Clients (W - Z) | J8: Cassidy | K8: ='Clients (W - Z)'!B1 -> 556 | L8: ='Clients (W - Z)'!C1 -> 378 | M8: =K8-L8 -> 178 | N8: =L8/K8 -> 0.67985612
B10: =SUM(B2:B8) -> 12421 | C10: =SUM(C2:C8) -> 0 | D10: =SUM(D2:D8) -> 12421 | E10: =C10/B10 -> 0 | K10: =SUM(K2:K8) -> 12421 | L10: =SUM(L2:L8) -> 4647 | M10: =SUM(M2:M8) -> 7774 | N10: =L10/K10 -> 0.37412447
B12: =SUM(B2:B8) -> 12421 | C12: =SUM(C2:C8) -> 0 | D12: =SUM(D2:D8) -> 12421 | E12: =C12/B12 -> 0
A13: 45551 | B13: Total | C13: Processed | D13: Difference | E13: Rate% | G13: 45551
A14: Clients (A - D) | B14: =D2 -> 3294 | C14: =COUNTIFS('Clients (A - D)'!A$4:A1003,$A13,'Clients (A - D)'!C$4:C1003,"?*") -> 0 | D14: =B14-C14 -> 3294 | E14: =C14/B14 -> 0 | G14: 124
A15: Clients (E - H) | B15: =D3 -> 1532 | C15: =COUNTIFS('Clients (E - H)'!A$4:A1003,$A13,'Clients (E - H)'!C$4:C1003,"?*") -> 0 | D15: =B15-C15 -> 1532 | E15: =C15/B15 -> 0 | G15: 125
A16: Clients (I - L) | B16: =D4 -> 1814 | C16: =COUNTIFS('Clients (I - L)'!A$4:A1003,$A13,'Clients (I - L)'!C$4:C1003,"?*") -> 0 | D16: =B16-C16 -> 1814 | E16: =C16/B16 -> 0 | G16: 52
A17: Clients (M - P) | B17: =D5 -> 2150 | C17: =COUNTIFS('Clients (M - P)'!A$4:A1003,$A13,'Clients (M - P)'!C$4:C1003,"?*") -> 9 | D17: =B17-C17 -> 2141 | E17: =C17/B17 -> 0.0041860465 | G17: 64
A18: Clients (Q - T) | B18: =D6 -> 1974 | C18: =COUNTIFS('Clients (Q - T)'!A$4:A1003,$A13,'Clients (Q - T)'!C$4:C1003,"?*") -> 0 | D18: =B18-C18 -> 1974 | E18: =C18/B18 -> 0 | G18: 8
A19: Clients (U - V) | B19: =D7 -> 1101 | C19: =COUNTIFS('Clients (U - V)'!A$4:A1003,$A13,'Clients (U - V)'!C$4:C1003,"?*") -> 0 | D19: =B19-C19 -> 1101 | E19: =C19/B19 -> 0 | G19: 30
A20: Clients (W - Z) | B20: =D8 -> 556 | C20: =COUNTIFS('Clients (W - Z)'!A$4:A1003,$A13,'Clients (W - Z)'!C$4:C1003,"?*") -> 0 | D20: =B20-C20 -> 556 | E20: =C20/B20 -> 0 | G20: 98
B22: =SUM(B14:B20) -> 12421 | C22: =SUM(C14:C20) -> 9 | D22: =SUM(D14:D20) -> 12412 | E22: =C22/B22 -> 0.00072457934
A24: 45552 | B24: Total | C24: Processed | D24: Difference | E24: Rate% | G24: 45552
A25: Clients (A - D) | B25: =D14 -> 3294 | C25: =COUNTIFS('Clients (A - D)'!A$4:A1003,$A24,'Clients (A - D)'!C$4:C1003,"?*") -> 0 | D25: =B25-C25 -> 3294 | E25: =C25/B25 -> 0 | G25: 124
A26: Clients (E - H) | B26: =D15 -> 1532 | C26: =COUNTIFS('Clients (E - H)'!A$4:A1003,$A24,'Clients (E - H)'!C$4:C1003,"?*") -> 0 | D26: =B26-C26 -> 1532 | E26: =C26/B26 -> 0 | G26: 141
A27: Clients (I - L) | B27: =D16 -> 1814 | C27: =COUNTIFS('Clients (I - L)'!A$4:A1003,$A24,'Clients (I - L)'!C$4:C1003,"?*") -> 0 | D27: =B27-C27 -> 1814 | E27: =C27/B27 -> 0 | G27: 52
A28: Clients (M - P) | B28: =D17 -> 2141 | C28: =COUNTIFS('Clients (M - P)'!A$4:A1003,$A24,'Clients (M - P)'!C$4:C1003,"?*") -> 102 | D28: =B28-C28 -> 2039 | E28: =C28/B28 -> 0.047641289 | G28: 117
A29: Clients (Q - T) | B29: =D18 -> 1974 | C29: =COUNTIFS('Clients (Q - T)'!A$4:A1003,$A24,'Clients (Q - T)'!C$4:C1003,"?*") -> 0 | D29: =B29-C29 -> 1974 | E29: =C29/B29 -> 0 | G29: 28
A30: Clients (U - V) | B30: =D19 -> 1101 | C30: =COUNTIFS('Clients (U - V)'!A$4:A1003,$A24,'Clients (U - V)'!C$4:C1003,"?*") -> 0 | D30: =B30-C30 -> 1101 | E30: =C30/B30 -> 0 | G30: 30
A31: Clients (W - Z) | B31: =D20 -> 556 | C31: =COUNTIFS('Clients (W - Z)'!A$4:A1003,$A24,'Clients (W - Z)'!C$4:C1003,"?*") -> 0 | D31: =B31-C31 -> 556 | E31: =C31/B31 -> 0 | G31: 98
B33: =SUM(B25:B31) -> 12412 | C33: =SUM(C25:C31) -> 102 | D33: =SUM(D25:D31) -> 12310 | E33: =C33/B33 -> 0.0082178537
A35: 45553 | B35: Total | C35: Processed | D35: Difference | E35: Rate% | G35: 45553
A36: Clients (A - D) | B36: =D25 -> 3294 | C36: =COUNTIFS('Clients (A - D)'!A$4:A1003,$A35,'Clients (A - D)'!C$4:C1003,"?*") -> 73 | D36: =B36-C36 -> 3221 | E36: =C36/B36 -> 0.022161506 | G36: 166
A37: Clients (E - H) | B37: =D26 -> 1532 | C37: =COUNTIFS('Clients (E - H)'!A$4:A1003,$A35,'Clients (E - H)'!C$4:C1003,"?*") -> 0 | D37: =B37-C37 -> 1532 | E37: =C37/B37 -> 0 | G37: 144
A38: Clients (I - L) | B38: =D27 -> 1814 | C38: =COUNTIFS('Clients (I - L)'!A$4:A1003,$A35,'Clients (I - L)'!C$4:C1003,"?*") -> 58 | D38: =B38-C38 -> 1756 | E38: =C38/B38 -> 0.031973539 | G38: 53
A39: Clients (M - P) | B39: =D28 -> 2039 | C39: =COUNTIFS('Clients (M - P)'!A$4:A1003,$A35,'Clients (M - P)'!C$4:C1003,"?*") -> 0 | D39: =B39-C39 -> 2039 | E39: =C39/B39 -> 0 | G39: 186
A40: Clients (Q - T) | B40: =D29 -> 1974 | C40: =COUNTIFS('Clients (Q - T)'!A$4:A1003,$A35,'Clients (Q - T)'!C$4:C1003,"?*") -> 0 | D40: =B40-C40 -> 1974 | E40: =C40/B40 -> 0 | G40: 57
A41: Clients (U - V) | B41: =D30 -> 1101 | C41: =COUNTIFS('Clients (U - V)'!A$4:A1003,$A35,'Clients (U - V)'!C$4:C1003,"?*") -> 0 | D41: =B41-C41 -> 1101 | E41: =C41/B41 -> 0 | G41: 37
A42: Clients (W - Z) | B42: =D31 -> 556 | C42: =COUNTIFS('Clients (W - Z)'!A$4:A1003,$A35,'Clients (W - Z)'!C$4:C1003,"?*") -> 20 | D42: =B42-C42 -> 536 | E42: =C42/B42 -> 0.035971223 | G42: 98
B43: =D32 -> 0
B44: =SUM(B36:B42) -> 12310 | C44: =SUM(C36:C42) -> 151 | D44: =SUM(D36:D42) -> 12159 | E44: =C44/B44 -> 0.01226645
A46: 45554 | B46: Total | C46: Processed | D46: Difference | E46: Rate% | G46: 45554
A47: Clients (A - D) | B47: =D36 -> 3221 | C47: =COUNTIFS('Clients (A - D)'!A$4:A1003,$A46,'Clients (A - D)'!C$4:C1003,"?*") -> 0 | D47: =B47-C47 -> 3221 | E47: =C47/B47 -> 0 | G47: 240
A48: Clients (E - H) | B48: =D37 -> 1532 | C48: =COUNTIFS('Clients (E - H)'!A$4:A1003,$A46,'Clients (E - H)'!C$4:C1003,"?*") -> 1 | D48: =B48-C48 -> 1531 | E48: =C48/B48 -> 0.00065274151 | G48: 144
A49: Clients (I - L) | B49: =D38 -> 1756 | C49: =COUNTIFS('Clients (I - L)'!A$4:A1003,$A46,'Clients (I - L)'!C$4:C1003,"?*") -> 63 | D49: =B49-C49 -> 1693 | E49: =C49/B49 -> 0.035876993 | G49: 111
A50: Clients (M - P) | B50: =D39 -> 2039 | C50: =COUNTIFS('Clients (M - P)'!A$4:A1003,$A46,'Clients (M - P)'!C$4:C1003,"?*") -> 3 | D50: =B50-C50 -> 2036 | E50: =C50/B50 -> 0.0014713095 | G50: 243
A51: Clients (Q - T) | B51: =D40 -> 1974 | C51: =COUNTIFS('Clients (Q - T)'!A$4:A1003,$A46,'Clients (Q - T)'!C$4:C1003,"?*") -> 1 | D51: =B51-C51 -> 1973 | E51: =C51/B51 -> 0.00050658561 | G51: 77
A52: Clients (U - V) | B52: =D41 -> 1101 | C52: =COUNTIFS('Clients (U - V)'!A$4:A1003,$A46,'Clients (U - V)'!C$4:C1003,"?*") -> 0 | D52: =B52-C52 -> 1101 | E52: =C52/B52 -> 0 | G52: 37
A53: Clients (W - Z) | B53: =D42 -> 536 | C53: =COUNTIFS('Clients (W - Z)'!A$4:A1003,$A46,'Clients (W - Z)'!C$4:C1003,"?*") -> 0 | D53: =B53-C53 -> 536 | E53: =C53/B53 -> 0 | G53: 113
B55: =SUM(B47:B53) -> 12159 | C55: =SUM(C47:C53) -> 68 | D55: =SUM(D47:D53) -> 12091 | E55: =C55/B55 -> 0.0055925652
A57: 45555 | B57: Total | C57: Processed | D57: Difference | E57: Rate%
A58: Clients (A - D) | B58: =D47 -> 3221 | C58: =COUNTIFS('Clients (A - D)'!A$4:A1003,$A57,'Clients (A - D)'!C$4:C1003,"?*") -> 0 | D58: =B58-C58 -> 3221 | E58: =C58/B58 -> 0
A59: Clients (E - H) | B59: =D48 -> 1531 | C59: =COUNTIFS('Clients (E - H)'!A$4:A1003,$A57,'Clients (E - H)'!C$4:C1003,"?*") -> 0 | D59: =B59-C59 -> 1531 | E59: =C59/B59 -> 0
A60: Clients (I - L) | B60: =D49 -> 1693 | C60: =COUNTIFS('Clients (I - L)'!A$4:A1003,$A57,'Clients (I - L)'!C$4:C1003,"?*") -> 13 | D60: =B60-C60 -> 1680 | E60: =C60/B60 -> 0.0076786769
A61: Clients (M - P) | B61: =D50 -> 2036 | C61: =COUNTIFS('Clients (M - P)'!A$4:A1003,$A57,'Clients (M - P)'!C$4:C1003,"?*") -> 0 | D61: =B61-C61 -> 2036 | E61: =C61/B61 -> 0
A62: Clients (Q - T) | B62: =D51 -> 1973 | C62: =COUNTIFS('Clients (Q - T)'!A$4:A1003,$A57,'Clients (Q - T)'!C$4:C1003,"?*") -> 0 | D62: =B62-C62 -> 1973 | E62: =C62/B62 -> 0
A63: Clients (U - V) | B63: =D52 -> 1101 | C63: =COUNTIFS('Clients (U - V)'!A$4:A1003,$A57,'Clients (U - V)'!C$4:C1003,"?*") -> 0 | D63: =B63-C63 -> 1101 | E63: =C63/B63 -> 0
A64: Clients (W - Z) | B64: =D53 -> 536 | C64: =COUNTIFS('Clients (W - Z)'!A$4:A1003,$A57,'Clients (W - Z)'!C$4:C1003,"?*") -> 6 | D64: =B64-C64 -> 530 | E64: =C64/B64 -> 0.01119403
B66: =SUM(B58:B64) -> 12091 | C66: =SUM(C58:C64) -> 19 | D66: =SUM(D58:D64) -> 12072 | E66: =C66/B66 -> 0.0015714168
A68: 45556 | B68: Total | C68: Processed | D68: Difference | E68: Rate%
A69: Clients (A - D) | B69: =D58 -> 3221 | C69: =COUNTIFS('Clients (A - D)'!A$4:A1003,$A68,'Clients (A - D)'!C$4:C1003,"?*") -> 0 | D69: =B69-C69 -> 3221 | E69: =C69/B69 -> 0
A70: Clients (E - H) | B70: =D59 -> 1531 | C70: =COUNTIFS('Clients (E - H)'!A$4:A1003,$A68,'Clients (E - H)'!C$4:C1003,"?*") -> 0 | D70: =B70-C70 -> 1531 | E70: =C70/B70 -> 0
A71: Clients (I - L) | B71: =D60 -> 1680 | C71: =COUNTIFS('Clients (I - L)'!A$4:A1003,$A68,'Clients (I - L)'!C$4:C1003,"?*") -> 19 | D71: =B71-C71 -> 1661 | E71: =C71/B71 -> 0.011309524
A72: Clients (M - P) | B72: =D61 -> 2036 | C72: =COUNTIFS('Clients (M - P)'!A$4:A1003,$A68,'Clients (M - P)'!C$4:C1003,"?*") -> 0 | D72: =B72-C72 -> 2036 | E72: =C72/B72 -> 0
A73: Clients (Q - T) | B73: =D62 -> 1973 | C73: =COUNTIFS('Clients (Q - T)'!A$4:A1003,$A68,'Clients (Q - T)'!C$4:C1003,"?*") -> 0 | D73: =B73-C73 -> 1973 | E73: =C73/B73 -> 0
A74: Clients (U - V) | B74: =D63 -> 1101 | C74: =COUNTIFS('Clients (U - V)'!A$4:A1003,$A68,'Clients (U - V)'!C$4:C1003,"?*") -> 0 | D74: =B74-C74 -> 1101 | E74: =C74/B74 -> 0
A75: Clients (W - Z) | B75: =D64 -> 530 | C75: =COUNTIFS('Clients (W - Z)'!A$4:A1003,$A68,'Clients (W - Z)'!C$4:C1003,"?*") -> 0 | D75: =B75-C75 -> 530 | E75: =C75/B75 -> 0
B77: =SUM(B69:B75) -> 12072 | C77: =SUM(C69:C75) -> 19 | D77: =SUM(D69:D75) -> 12053 | E77: =C77/B77 -> 0.00157389
A79: 45557 | B79: Total | C79: Processed | D79: Difference | E79: Rate%
A80: Clients (A - D) | B80: =D69 -> 3221 | C80: =COUNTIFS('Clients (A - D)'!A$4:A1003,$A79,'Clients (A - D)'!C$4:C1003,"?*") -> 0 | D80: =B80-C80 -> 3221 | E80: =C80/B80 -> 0
A81: Clients (E - H) | B81: =D70 -> 1531 | C81: =COUNTIFS('Clients (E - H)'!A$4:A1003,$A79,'Clients (E - H)'!C$4:C1003,"?*") -> 0 | D81: =B81-C81 -> 1531 | E81: =C81/B81 -> 0
A82: Clients (I - L) | B82: =D71 -> 1661 | C82: =COUNTIFS('Clients (I - L)'!A$4:A1003,$A79,'Clients (I - L)'!C$4:C1003,"?*") -> 0 | D82: =B82-C82 -> 1661 | E82: =C82/B82 -> 0
A83: Clients (M - P) | B83: =D72 -> 2036 | C83: =COUNTIFS('Clients (M - P)'!A$4:A1003,$A79,'Clients (M - P)'!C$4:C1003,"?*") -> 0 | D83: =B83-C83 -> 2036 | E83: =C83/B83 -> 0
A84: Clients (Q - T) | B84: =D73 -> 1973 | C84: =COUNTIFS('Clients (Q - T)'!A$4:A1003,$A79,'Clients (Q - T)'!C$4:C1003,"?*") -> 0 | D84: =B84-C84 -> 1973 | E84: =C84/B84 -> 0
A85: Clients (U - V) | B85: =D74 -> 1101 | C85: =COUNTIFS('Clients (U - V)'!A$4:A1003,$A79,'Clients (U - V)'!C$4:C1003,"?*") -> 0 | D85: =B85-C85 -> 1101 | E85: =C85/B85 -> 0
A86: Clients (W - Z) | B86: =D75 -> 530 | C86: =COUNTIFS('Clients (W - Z)'!A$4:A1003,$A79,'Clients (W - Z)'!C$4:C1003,"?*") -> 0 | D86: =B86-C86 -> 530 | E86: =C86/B86 -> 0
B88: =SUM(B80:B86) -> 12053 | C88: =SUM(C80:C86) -> 0 | D88: =SUM(D80:D86) -> 12053 | E88: =C88/B88 -> 0
A90: 45558 | B90: Total | C90: Processed | D90: Difference | E90: Rate%
A91: Clients (A - D) | B91: =D80 -> 3221 | C91: =COUNTIFS('Clients (A - D)'!A$4:A1003,$A90,'Clients (A - D)'!C$4:C1003,"?*") -> 0 | D91: =B91-C91 -> 3221 | E91: =C91/B91 -> 0
A92: Clients (E - H) | B92: =D81 -> 1531 | C92: =COUNTIFS('Clients (E - H)'!A$4:A1003,$A90,'Clients (E - H)'!C$4:C1003,"?*") -> 0 | D92: =B92-C92 -> 1531 | E92: =C92/B92 -> 0
A93: Clients (I - L) | B93: =D82 -> 1661 | C93: =COUNTIFS('Clients (I - L)'!A$4:A1003,$A90,'Clients (I - L)'!C$4:C1003,"?*") -> 45 | D93: =B93-C93 -> 1616 | E93: =C93/B93 -> 0.027092113
A94: Clients (M - P) | B94: =D83 -> 2036 | C94: =COUNTIFS('Clients (M - P)'!A$4:A1003,$A90,'Clients (M - P)'!C$4:C1003,"?*") -> 0 | D94: =B94-C94 -> 2036 | E94: =C94/B94 -> 0
A95: Clients (Q - T) | B95: =D84 -> 1973 | C95: =COUNTIFS('Clients (Q - T)'!A$4:A1003,$A90,'Clients (Q - T)'!C$4:C1003,"?*") -> 37 | D95: =B95-C95 -> 1936 | E95: =C95/B95 -> 0.018753168
A96: Clients (U - V) | B96: =D85 -> 1101 | C96: =COUNTIFS('Clients (U - V)'!A$4:A1003,$A90,'Clients (U - V)'!C$4:C1003,"?*") -> 0 | D96: =B96-C96 -> 1101 | E96: =C96/B96 -> 0
A97: Clients (W - Z) | B97: =D86 -> 530 | C97: =COUNTIFS('Clients (W - Z)'!A$4:A1003,$A90,'Clients (W - Z)'!C$4:C1003,"?*") -> 0 | D97: =B97-C97 -> 530 | E97: =C97/B97 -> 0
B98: =D87 -> 0
B99: =SUM(B91:B97) -> 12053 | C99: =SUM(C91:C97) -> 82 | D99: =SUM(D91:D97) -> 11971 | E99: =C99/B99 -> 0.0068032855
A101: 45561 | B101: Total | C101: Processed | D101: Difference | E101: Rate% | G101: 45561
A102: Clients (A - D) | B102: =D91 -> 3221 | C102: =COUNTIFS('Clients (A - D)'!A$4:A1003,$A101,'Clients (A - D)'!C$4:C1003,"?*") -> 64 | D102: =B102-C102 -> 3157 | E102: =C102/B102 -> 0.019869606 | G102: 24
A103: Clients (E - H) | B103: =D92 -> 1531 | C103: =COUNTIFS('Clients (E - H)'!A$4:A1003,$A101,'Clients (E - H)'!C$4:C1003,"?*") -> 0 | D103: =B103-C103 -> 1531 | E103: =C103/B103 -> 0 | G103: 145
A104: Clients (I - L) | B104: =D93 -> 1616 | C104: =COUNTIFS('Clients (I - L)'!A$4:A1003,$A101,'Clients (I - L)'!C$4:C1003,"?*") -> 24 | D104: =B104-C104 -> 1592 | E104: =C104/B104 -> 0.014851485 | G104: 263
A105: Clients (M - P) | B105: =D94 -> 2036 | C105: =COUNTIFS('Clients (M - P)'!A$4:A1003,$A101,'Clients (M - P)'!C$4:C1003,"?*") -> 0 | D105: =B105-C105 -> 2036 | E105: =C105/B105 -> 0 | G105: 368
A106: Clients (Q - T) | B106: =D95 -> 1936 | C106: =COUNTIFS('Clients (Q - T)'!A$4:A1003,$A101,'Clients (Q - T)'!C$4:C1003,"?*") -> 37 | D106: =B106-C106 -> 1899 | E106: =C106/B106 -> 0.01911157 | G106: 274
A107: Clients (U - V) | B107: =D96 -> 1101 | C107: =COUNTIFS('Clients (U - V)'!A$4:A1003,$A101,'Clients (U - V)'!C$4:C1003,"?*") -> 1 | D107: =B107-C107 -> 1100 | E107: =C107/B107 -> 0.00090826521 | G107: 37
A108: Clients (W - Z) | B108: =D97 -> 530 | C108: =COUNTIFS('Clients (W - Z)'!A$4:A1003,$A101,'Clients (W - Z)'!C$4:C1003,"?*") -> 3 | D108: =B108-C108 -> 527 | E108: =C108/B108 -> 0.0056603774 | G108: 117
B110: =SUM(B102:B108) -> 11971 | C110: =SUM(C102:C108) -> 129 | D110: =SUM(D102:D108) -> 11842 | E110: =C110/B110 -> 0.010776042
A112: 45565 | B112: Total | C112: Processed | D112: Difference | E112: Rate% | G112: 45565
A113: Clients (A - D) | B113: =D102 -> 3157 | C113: =COUNTIFS('Clients (A - D)'!A$4:A1003,$A112,'Clients (A - D)'!C$4:C1003,"?*") -> 0 | D113: =B113-C113 -> 3157 | E113: =C113/B113 -> 0 | G113: 312
A114: Clients (E - H) | B114: =D103 -> 1531 | C114: =COUNTIFS('Clients (E - H)'!A$4:A1003,$A112,'Clients (E - H)'!C$4:C1003,"?*") -> 1 | D114: =B114-C114 -> 1530 | E114: =C114/B114 -> 0.00065316786 | G114: 145
A115: Clients (I - L) | B115: =D104 -> 1592 | C115: =COUNTIFS('Clients (I - L)'!A$4:A1003,$A112,'Clients (I - L)'!C$4:C1003,"?*") -> 0 | D115: =B115-C115 -> 1592 | E115: =C115/B115 -> 0 | G115: 292
A116: Clients (M - P) | B116: =D105 -> 2036 | C116: =COUNTIFS('Clients (M - P)'!A$4:A1003,$A112,'Clients (M - P)'!C$4:C1003,"?*") -> 12 | D116: =B116-C116 -> 2024 | E116: =C116/B116 -> 0.0058939096 | G116: 372
A117: Clients (Q - T) | B117: =D106 -> 1899 | C117: =COUNTIFS('Clients (Q - T)'!A$4:A1003,$A112,'Clients (Q - T)'!C$4:C1003,"?*") -> 9 | D117: =B117-C117 -> 1890 | E117: =C117/B117 -> 0.0047393365 | G117: 325
A118: Clients (U - V) | B118: =D107 -> 1100 | C118: =COUNTIFS('Clients (U - V)'!A$4:A1003,$A112,'Clients (U - V)'!C$4:C1003,"?*") -> 0 | D118: =B118-C118 -> 1100 | E118: =C118/B118 -> 0 | G118: 38
...

Sheet Clients (A - D)
B1: =COUNTA(B4:B3298) -> 3294 | C1: =COUNTIF(C4:C3298,"?*") -> 645
A2: Date | B2: Client Account | C2: Client Reference | D2: Client name | E2: Highsite / SC | F2: Type | G2: ISPMan Premium | H2: ISPMan EFT Fee | I2: Contract Duration | J2: Install Date | K2: Contract Expiry | L2: Have Contract | M2: Notes
B3: ABC001 | C3: ABC001-12345 | D3: Mr Joe Soap | E3: Dwarskersbos S/C | F3: Trusc Wireless | I3: 1 Year | K3: 45626 | L3: TRUE | M3: Example line
A4: 45548 | B4: AAD001 | C4: AAD001-11532 | D4: AA Aadan | E4: Oranjefontein | F4: Trusc Wireless | G4: 344 | H4: 35 | I4: 2 year | J4: 44900 | K4: 46361 | L4: TRUE
A5: 45548 | B5: AAL001 | C5: AAL001-13068 | D5: F Aaltge | E5: Koringberg | F5: Trusc Wireless | G5: 574 | H5: 0 | I5: 2 year | J5: 44606 | K5: 45336 | L5: TRUE
A6: 45548 | B6: AAN001 | C6: AAN001-5829 | D6: Aands Managed Services | E6: Dwarskersbos S/C | F6: Trusc Wireless | G6: 574 | H6: 0 | I6: 2 year | J6: 44168 | K6: 44898 | L6: TRUE
A7: 45548 | B7: AAR001 | C7: AAR001-23350 | D7: Aardwolf Security Solution (PTY) Ltd | E7: None | F7: Trusc Fibre | G7: 399 | H7: 58 | I7: 2 year | J7: 45182 | K7: 45913 | L7: TRUE
A8: 45548 | B8: ABA003 | C8: ABA003-7674 | D8: NT Abata | E8: Windpomp | F8: Trusc Wireless | G8: 298 | H8: 0 | I8: 2 year | J8: 43701 | K8: 44432 | L8: TRUE
A9: 45548 | B9: ABB004 | C9: ABB004-22168 | D9: B Abbott | E9: Bulshoek | F9: Trusc Wireless | G9: 574 | H9: 0 | I9: 2 year | J9: 44988 | K9: 45719 | L9: TRUE
A10: 45548 | B10: ABC001 | C10: ABC001-18852 | D10: ABCO Ingenieurs Werke (Edms) Bpk | E10: None | F10: Openserve | G10: 1375 | H10: 0 | I10: 2 year | J10: 44712 | K10: 45443 | L10: TRUE
A11: 45548 | B11: ABC001 | C11: ABC001-5746 | D11: ABCO Ingenieurs Werke (Edms) Bpk | E11: Springbok | F11: Trusc Wireless | G11: 1609 | H11: 0 | I11: 2 year | J11: 43399 | K11: 44130 | L11: TRUE
A12: 45548 | B12: ABD002 | C12: ABD002-4931 | D12: LS Abdol | E12: Koraan | F12: Trusc Wireless | G12: 574 | H12: 0 | I12: 2 year | J12: 44110 | K12: 44840 | L12: TRUE
A13: 45548 | B13: ABD005 | C13: ABD005-7802 | D13: AM Abdulahi | E13: Clan | F13: Trusc Wireless | G13: 459 | H13: 0 | I13: 2 year | J13: 43728 | K13: 44459 | L13: TRUE
A14: 45548 | B14: ABD005 | C14: ABD005-9116 | D14: AM Abdulahi | E14: Synott | F14: Trusc Wireless | G14: 459 | H14: 0 | I14: 2 year | J14: 43879 | K14: 44610 | L14: TRUE
A15: 45548 | B15: ABD009 | C15: ABD009-8564 | D15: WC Abdol | E15: Koraan | F15: Trusc Wireless | G15: 350 | H15: 35 | I15: 2 year | J15: 45243 | K15: 45974 | L15: TRUE
... A50: 45548 | B50: ABR064 | C50: ABR064-20558 | D50: I Abrahams | E50: None | F50: Trusc Fibre | G50: 344 | H50: 0 | I50: 2 year | J50: 44856 | K50: 45587 | L50: TRUE
A51: 45548 | B51: ABR065 | C51: ABR065-21098 | D51: JW Abrahams | E51: Klawer-Res | F51: Trusc Wireless | G51: 574 | H51: 0 | I51: 2 year | J51: To be processed | K51: To be processed | L51: TRUE
A52: 45548 | B52: ABR066 | C52: ABR066-21260 | D52: NJP Abrahams | E52: Klawer-Res | F52: Trusc Wireless | G52: 574 | H52: 0 | I52: 2 year | J52: 44904 | K52: 45635 | L52: TRUE
A53: 45548 | B53: ABR069 | C53: ABR069-21477 | D53: RB Abrahams | E53: Modderfontein | F53: Trusc Wireless | G53: 574 | H53: 0 | I53: 2 year | J53: 44925 | K53: 45656 | L53: TRUE
A54: 45548 | B54: ABR074 | C54: ABR074-22847 | D54: DD Abrahams | E54: Piketberg | F54: Trusc Wireless | G54: 344 | H54: 0 | I54: 2 year | J54: 45343 | K54: 46074 | L54: TRUE
A55: 45548 | B55: ABR075 | C55: ABR075-23073 | D55: TI Abrahams | E55: Paardeberg | F55: Trusc Wireless | G55: 344 | H55: 35 | I55: 2 year | J55: 45119 | K55: 45850 | L55: TRUE
A56: 45548 | B56: ABR076 | C56: ABR076-23099 | D56: BB Abrahams | E56: Okiep | F56: Trusc Wireless | G56: 344 | H56: 0 | I56: 2 year | J56: 45124 | K56: 45856 | L56: TRUE
A57: 45548 | B57: ABR077 | C57: ABR077-23133 | D57: MB Abrahamse | E57: None | F57: Trusc Fibre | G57: 344 | H57: 0 | I57: 2 year | J57: 45129 | K57: 45860 | L57: TRUE
A58: 45548 | B58: ABR078 | C58: ABR078-23163 | D58: P Abrahams | E58: Koringberg | F58: Trusc Wireless | G58: 574 | H58: 0 | I58: 2 year | J58: 45132 | K58: 45863 | L58: TRUE
A59: 45548 | B59: ABR080 | C59: ABR080-23741 | D59: ZL Abrahams | E59: Heuningberg | F59: Trusc Wireless | G59: 350 | H59: 0 | I59: 2 year | J59: 45206 | K59: 45937 | L59: TRUE
A60: 45548 | B60: ABR083 | C60: ABR083-24481 | D60: AG Abrahams | E60: Doornbaai | F60: Trusc Wireless | G60: 350 | H60: 0 | I60: 2 year | J60: 45262 | K60: 45993 | L60: TRUE
A61: 45548 | B61: ABR084 | C61: ABR084-24887 | D61: B Abrahams | E61: Klawer | F61: Trusc Wireless | G61: 350 | H61: 0 | I61: 2 year | J61: 45307 | K61: 46038 | L61: TRUE
A62: 45548 | B62: ABR085 | C62: ABR085-25059 | D62: CA Abrahams | E62: Aurora | F62: Trusc Wireless | G62: 350 | H62: 0 | I62: 2 year | J62: 45315 | K62: 46046 | L62: TRUE
A63: 45548 | B63: ABR086 | C63: ABR086-25142 | D63: WZ Abrahams | E63: Oranjefontein | F63: Trusc Wireless | G63: 350 | H63: 0 | I63: 2 year | J63: 45323 | K63: 46054 | L63: TRUE
... A68: 45548 | B68: ABR092 | C68: ABR092-27488 | D68: MEJ Abrahams | E68: Graafwater | F68: Trusc Wireless | G68: 299 | H68: 0 | I68: 2 year | J68: 45505 | K68: 46235 | L68: TRUE
A69: 45548 | B69: ABR093 | C69: ABR093-27693 | D69: R Abrahams | E69: Kalbaskraal | F69: Trusc Wireless | G69: 299 | H69: 0 | I69: 2 year | J69: 45534 | K69: 46264 | L69: TRUE | M69: Still to be installed
A70: 45548 | B70: ABR094 | C70: ABR094-27823 | D70: H Abrahams | E70: Doornbaai | F70: Trusc Wireless | G70: 299 | H70: 0 | I70: 2 year | J70: 45169 | K70: 45900 | L70: TRUE
A71: 45548 | B71: ABR095 | C71: ABR095-27849 | D71: S Abrahams | E71: Synott | F71: Trusc Wireless | G71: 299 | H71: 0 | I71: 2 year | J71: 45168 | K71: 45899 | L71: TRUE
A72: 45548 | B72: ABS002 | C72: ABS002-19999 | D72: AM Absolon | E72: Piketberg | F72: Trusc Wireless | G72: 574 | H72: 0 | I72: 2 year | J72: 44810 | K72: 45541 | L72: TRUE
A73: 45553 | B73: ABS003 | C73: ABS003-27884 | D73: AE Absolom | E73: Steelwater | F73: Trusc Wireless | G73: 299 | H73: 0 | I73: 2 year | J73: 45542 | K73: 46272 | L73: TRUE
A74: 45548 | B74: ACA001 | C74: ACA001-15428 | D74: Academy of Diving and Offshore Medicine PTY Ltd | E74: Masada | F74: Trusc Wireless | G74: 977 | H74: 0 | I74: 2 year | J74: 44454 | K74: 45184 | L74: TRUE
A75: 45548 | B75: ACA002 | C75: ACA002-26022 | D75: Acacia Marketing | E75: Dwarskersbos S/C | F75: Trusc Fibre | G75: 399 | H75: 0 | I75: 2 year | J75: 45393 | K75: 46123 | L75: TRUE
A76: 45548 | B76: ACH003 | C76: ACH003-13776 | D76: CA Achilles | E76: Tallie Marine | F76: Trusc Wireless | G76: 402 | H76: 0 | J76: 44377 | L76: FALSE | M76: No signed SLA
A77: 45548 | B77: ACH006 | C77: ACH006-17019 | D77: TC Achilles | E77: Tallie Marine | F77: Trusc Wireless | G77: 402 | H77: 0 | I77: 2 year | J77: 44548 | K77: 45278 | L77: TRUE
A78: 45548 | B78: ACK006 | C78: ACK006-18736 | D78: PL Ackeer | E78: Duiwelskop | F78: Trusc Wireless | G78: 574 | H78: 0 | I78: 2 year | J78: 44691 | K78: 45422 | L78: TRUE
A79: 45548 | B79: ACT002 | C79: ACT002-10056 | D79: Gonnas | E79: jacobsbaai | F79: Trusc Wireless | G79: 2184 | H79: 0 | I79: 2 year | J79: 44700 | K79: 45431 | L79: TRUE
A80: 45548 | B80: ACT005 | C80: ACT005-23230 | D80: Actophambili Roads PTY Ltd | E80: None | F80: Trusc Fibre | G80: 804 | H80: 0 | I80: 2 year | J80: 45140 | K80: 45871 | L80: TRUE
A81: 45548 | B81: ADA002 | C81: ADA002-2764 | D81: AI Adan | E81: Clan | F81: Trusc Wireless | G81: 528 | H81: 0 | I81: 2 year | J81: 42577 | K81: 43307 | L81: TRUE
A82: 45548 | B82: ADA002 | C82: ADA002-2765 | D82: AI Adan | E82: Clan | F82: Trusc Wireless | G82: 528 | H82: 0 | I82: 2 year | J82: 42577 | K82: 43307
A83: 45548 | B83: ADA007 | C83: ADA007-3915 | D83: SR Adams | E83: Maskam | F83: Trusc Wireless | G83: 574 | H83: 0 | I83: 2 year | J83: 43802 | K83: 44533 | L83: TRUE
A84: 45548 | B84: ADA008 | C84: ADA008-4624 | D84: UB Adams | E84: Doornbaai | F84: Trusc Wireless | G84: 574 | H84: 0 | I84: 2 year | J84: 44907 | K84: 45638 | L84: TRUE
A85: 45548 | B85: ADA010 | C85: ADA010-4932 | D85: FV Adams | E85: Kapteins | F85: Trusc Wireless | G85: 632 | H85: 0 | I85: 2 year | J85: 43186 | K85: 43917 | L85: TRUE
A86: 45548 | B86: ADA016 | C86: ADA016-6512 | D86: MJ Adams | E86: Rooidraai | F86: Trusc Wireless | G86: 350 | H86: 35 | I86: 2 year | J86: 45303 | K86: 46034 | L86: TRUE
A87: 45548 | B87: ADA018 | C87: ADA018-7550 | D87: M Adams | E87: Olifantskop | F87: Trusc Wireless | G87: 459 | H87: 0 | I87: 2 year | J87: 43689 | K87: 44420 | L87: TRUE
A88: 45548 | B88: ADA023 | C88: ADA023-9089 | D88: AM Adam | E88: Synott | F88: Trusc Wireless | G88: 574 | H88: 0 | I88: 2 year | J88: 43874 | K88: 44605 | L88: TRUE
A89: 45548 | B89: ADA027 | C89: ADA027-11254 | D89: WML Adams | E89: Koringberg | F89: Trusc Wireless | G89: 350 | H89: 0 | I89: 2 year | J89: 45187 | K89: 45918 | L89: TRUE
A90: 45548 | B90: ADA028 | C90: ADA028-11416 | D90: JEM Adams | E90: Bergstraat | F90: Trusc Wireless | G90: 574 | H90: 0 | I90: 2 year | J90: 44156 | K90: 44886 | L90: TRUE
A91: 45548 | B91: ADA030 | C91: ADA030-11699 | D91: FD Adams | E91: Clan | F91: Trusc Wireless | G91: 689 | H91: 0 | I91: 2 year | J91: 44175 | K91: 44905 | L91: TRUE
A92: 45548 | B92: ADA031 | C92: ADA031-11877 | D92: LP Adams | E92: None | F92: Openserve | G92: 699 | H92: 0 | I92: 1 Year | J92: 44592 | K92: 44957 | L92: TRUE
A93: 45548 | B93: ADA033 | C93: ADA033-11947 | D93: A Adams | E93: Rooidraai | F93: Trusc Wireless | G93: 350 | H93: 35 | I93: 2 year | J93: 45209 | K93: 45940 | L93: TRUE
A94: 45548 | B94: ADA034 | C94: ADA034-12053 | D94: G Adams | E94: Vdal North | F94: Trusc Wireless | G94: 350 | H94: 35 | I94: 1 Year | J94: 45292 | K94: 45658 | L94: TRUE
... A167: 45553 | B167: ADM002 | C167: ADM002-22095 | D167: HOA Admiral Island | E167: Admiral Island | F167: Trusc Fibre | G167: 399 | H167: 0 | I167: 2 year | J167: 44987 | K167: 45718 | L167: TRUE
A168: 45553 | B168: ADM002 | C168: ADM002-22808 | D168: HOA Admiral Island | E168: Admiral Island | F168: Trusc Fibre | G168: N/A | H168: 0 | L168: FALSE
A169: 45553 | B169: ADO003 | C169: ADO003-6649 | D169: EJ Adonis | E169: Rooidraai | F169: Trusc Wireless | G169: 350 | H169: 35 | I169: 2 year | J169: 45287 | K169: 46018 | L169: TRUE
A170: 45553 | B170: ADO004 | C170: ADO004-8089 | D170: KJE Adonis | E170: Rooidraai | F170: Trusc Wireless | G170: 574 | H170: 0 | I170: 2 year | J170: 44676 | K170: 45407 | L170: TRUE
A171: 45553 | B171: ADO005 | C171: ADO005-8594 | D171: ER Adonis | E171: Modderfontein | F171: Trusc Wireless | G171: 250 | H171: 0 | I171: 2 year | J171: 45328 | K171: 46059 | L171: TRUE
A172: 45553 | B172: ADO007 | C172: ADO007-14673 | D172: AWJ Adonis | E172: Octotel - Moorreesburg | F172: Octotel | G172: 850 | H172: 0 | I172: 1 Year | J172: 44503 | K172: 44868 | L172: TRUE
A173: 45553 | B173: ADO008 | C173: ADO008-10949 | D173: AM Adow | E173: Synott | F173: Trusc Wireless | G173: 459 | H173: 0 | I173: 2 year | J173: 44077 | K173: 44807 | L173: TRUE
A174: 45553 | B174: ADO009 | C174: ADO009-24315 | D174: BB Adonis | E174: Octotel - Moorreesburg | F174: Octotel | G174: 599 | H174: 35 | I174: 1 Year | J174: 45259 | K174: 45625 | L174: TRUE
A175: 45553 | B175: ADO011 | C175: ADO011-11552 | D175: AM Adonis | E175: Goudmyn | F175: Trusc Wireless | G175: 287 | H175: 0 | I175: 2 year | J175: 44546 | K175: 45276 | L175: TRUE
A176: 45553 | B176: ADO012 | C176: ADO012-11805 | D176: A Adonis | E176: Rooidraai | F176: Trusc Wireless | G176: 574 | H176: 0 | I176: 2 year | J176: 44189 | K176: 44919 | L176: TRUE
A177: 45553 | B177: ADO012 | C177: ADO012-11837 | D177: A Adonis | E177: Rooidraai | F177: Trusc Wireless | G177: 344 | H177: 0 | I177: 2 year | J177: 44194 | K177: 44924 | L177: TRUE
A178: 45553 | B178: ADO018 | C178: ADO018-16593 | D178: EAA Adonis | E178: Octotel - Moorreesburg | F178: Octotel | G178: 699 | H178: 0 | I178: 2 year | J178: 45391 | K178: 46121 | L178: TRUE
A179: 45553 | B179: ADO026 | C179: ADO026-14247 | D179: NR Adonis | E179: Nababeep | F179: Trusc Wireless | G179: 449 | H179: 0 | I179: 2 year | J179: 45450 | K179: 46180 | L179: TRUE
A180: 45553 | B180: ADO028 | C180: ADO028-14528 | D180: CR Adonis | E180: Koringberg | F180: Trusc Wireless | G180: 459 | H180: 0 | I180: 2 year | J180: 44551 | K180: 45281 | L180: TRUE
... A272: 45574 | B272: AGU001 | C272: AGU001-6679 | D272: ME De Klerk | E272: Goudmyn | F272: Trusc Wireless | G272: 574 | H272: 0 | I272: 2 year | J272: 44993 | K272: 45724 | L272: TRUE
A273: 45574 | B273: AGU006 | C273: AGU006-20757 | D273: JJ Agulhas | E273: Oranjefontein | F273: Trusc Wireless | G273: 689 | H273: 0 | L273: FALSE
A274: 45574 | B274: AGU007 | C274: AGU007-22410 | D274: S Agulhas | E274: Kalbaskraal | F274: Trusc Wireless | G274: 804 | H274: 0 | L274: FALSE
A275: 45574 | B275: AGU008 | C275: AGU008-22971 | D275: A Agulhas | E275: Kalbaskraal | F275: Trusc Wireless | G275: 459 | H275: 0 | L275: FALSE
A276: 45574 | B276: AHM001 | C276: AHM001-16514 | D276: Mamun Ahmed | E276: turner | F276: Trusc Wireless | G276: 574 | H276: 0 | L276: FALSE
A277: 45574 | B277: AHM001 | C277: AHM001-17078 | D277: Mamun Ahmed | E277: Vdal_res | F277: Trusc Wireless | G277: 574 | H277: 0 | L277: FALSE
A278: 45574 | B278: AHM001 | C278: AHM001-3914 | D278: Mamun Ahmed | E278: Koekenaap | F278: Trusc Wireless | G278: 574 | H278: 0 | L278: FALSE
A279: 45561 | B279: AHM003 | C279: AHM003-21653 | D279: IM Ahmed | E279: Vredendal-Resevoir | F279: Trusc Wireless | G279: 344 | H279: 35 | I279: 2 year | J279: 44939 | K279: 45670 | L279: TRUE
A280: 45561 | B280: AHM003 | C280: AHM003-5800 | D280: IM Ahmed | E280: Vredendal-Resevoir | F280: Trusc Wireless | G280: 344 | H280: 0 | I280: 2 year | J280: 44936 | K280: 45667 | L280: TRUE
A281: 45561 | B281: AHM004 | C281: AHM004-6366 | D281: YA Ahmed | E281: Graafwater | F281: Trusc Wireless | G281: 459 | H281: 35 | I281: 2 year | J281: 43550 | K281: 44281 | L281: TRUE
A282: 45561 | B282: AHM011 | C282: AHM011-26708 | D282: SP Ahmed | E282: Nababeep | F282: Trusc Wireless | G282: 344 | H282: 0 | I282: 2 year | J282: 45428 | K282: 46158 | L282: TRUE
A283: 45561 | B283: AIR001 | C283: AIR001-12610 | D283: Airplant CC t a Plant Services | E283: Octotel-Cape Gate | F283: Octotel | G283: 1609 | H283: 0 | I283: 1 Year | J283: 44341 | K283: 46167 | L283: TRUE
A284: 45561 | B284: AIR002 | C284: AIR002-19135 | D284: R Airoldi | E284: Admiral Island | F284: Trusc Fibre | G284: 399 | H284: 0 | I284: 2 year | J284: 44952 | K284: 45683 | L284: TRUE
A285: 45561 | B285: AJD001 | C285: AJD001-3927 | D285: AJ De Klerk BK | E285: Water Tower | F285: Trusc Fibre | G285: 172 | H285: 0 | I285: 2 year | J285: 44121 | K285: 44851 | L285: TRUE
A286: 45561 | B286: AJW001 | C286: AJW001-22882 | D286: AJW Boerdery Pty Ltd | E286: Biedouw | F286: Trusc Wireless | G286: 689 | H286: 0 | I286: 2 year | J286: 45086 | K286: 45817 | L286: TRUE
A287: 45561 | B287: AKD001 | C287: AKD001-3356 | D287: K Akdemir | E287: St Helena | F287: Trusc Wireless | G287: 804 | H287: 0 | I287: 2 year | J287: 43506 | K287: 44237 | L287: TRUE
A288: 45561 | B288: AKK001 | C288: AKK001-25616 | D288: M Akker | E288: De Punt | F288: Trusc Wireless | G288: 804 | H288: 0 | I288: 2 year | J288: 45353 | K288: 46083 | L288: TRUE
A289: 45561 | B289: ALA001 | C289: ALA001-23083 | D289: DC Alard | E289: Goudmyn | F289: Trusc Wireless | G289: 574 | H289: 0 | I289: 2 year | J289: 45126 | K289: 45857 | L289: TRUE
A290: 45561 | B290: ALB003 | C290: ALB003-2818 | D290: G Alberts | E290: Rilau | F290: Trusc Wireless | G290: 599 | H290: 0 | I290: 1 Year | J290: 45519 | K290: 45884 | L290: TRUE
... A349: 45573 | B349: ALO003 | C349: ALO003-28362 | D349: GS Aloto | E349: Ramskop | F349: Trusc Wireless | G349: 399 | H349: 0 | I349: 2 year | J349: 45559 | K349: 46289 | L349: TRUE
A350: 45573 | B350: ALO003 | C350: ALO003-28363 | D350: GS Aloto | E350: Aasvoelkop SC | F350: Trusc Wireless | L350: FALSE | M350: Scheduling
A351: 45573 | B351: ALO003 | C351: ALO003-28365 | D351: GS Aloto | E351: Aasvoelkop SC | F351: Trusc Wireless | L351: FALSE | M351: Scheduling
A352: 45573 | B352: ALO004 | C352: ALO004-24907 | D352: SS Aloto | E352: Ramskop | F352: Trusc Wireless | G352: 250 | H352: 35 | I352: 2 year | J352: 45310 | K352: 46041 | L352: TRUE
A353: 45573 | B353: ALZ001 | C353: ALZ001-22916 | D353: Alzanne Boerdery | E353: Admiral Island | F353: Trusc Fibre | G353: 574 | H353: 0 | I353: 2 year | J353: 45101 | K353: 45832 | L353: TRUE
A354: 45573 | B354: AMA004 | C354: AMA004-22986 | D354: Amalanda Restaurant (PTY) LTD T/A Homespun By Matt | E354: octotel_blouberg | F354: Octotel | G354: 689 | H354: 0 | I354: 1 Year | J354: 45108 | K354: 45474 | L354: TRUE
A355: 45573 | B355: AMA004 | C355: AMA004-9276 | D355: Amalanda Restaurant (PTY) LTD T/A Homespun By Matt | E355: Aasvoelkop SC | F355: Frogfoot | G355: 1161 | H355: 0 | I355: 1 Year | J355: 44445 | K355: 44810 | L355: TRUE
A356: 45573 | B356: AMA006 | C356: AMA006-18500 | D356: Homespun Andros T/A Homespun @ The Andros | E356: Aasvoelkop SC | F356: Openserve | G356: 1145 | H356: 0 | I356: 1 Year | J356: 44593 | K356: 44958 | L356: TRUE
A357: 45573 | B357: AMB002 | C357: AMB002-21199 | D357: Ambatha Pty Ltd | E357: Dwarskersbos S/C | F357: Trusc Fibre | G357: 459 | H357: 35 | I357: 2 year | J357: 45241 | K357: 45972 | L357: TRUE
A358: 45573 | B358: AMB003 | C358: AMB003-23780 | D358: A Ambraal | E358: Koringberg | F358: Trusc Wireless | G358: 350 | H358: 0 | I358: 2 year | J358: 45269 | K358: 46000 | L358: TRUE
A359: 45573 | B359: AMI001 | C359: AMI001-19704 | D359: MD Ruhul Amin | E359: Elandsbay | F359: Trusc Wireless | G359: 574 | H359: 35 | I359: 2 year | J359: 44779 | K359: 45510 | L359: TRUE
...

Sheet Clients (E - H)
B1: =COUNTA(B4:B1535) -> 1532 | C1: =COUNTIF(C4:C1535,"?*") -> 159
A2: Date | B2: Client Account | C2: Client Reference | D2: Client name | E2: Highsite / SC | F2: Type | G2: ISPMan Premium | H2: ISPMan EFT Fee | I2: Contract Duration | J2: Install Date | K2: Contract Expiry | L2: Have Contract
B3: ABC001 | C3: ABC001-12345 | D3: Mr Joe Soap | E3: Dwarskersbos S/C | F3: Trusc Wireless | I3: 1 Year | K3: 45626 | L3: TRUE | M3: Example line
A4: 45548 | B4: EAL001 | C4: EAL001-24642 | D4: EA Lombard Family Trust ta | E4: Strand | F4: Trusc Wireless | G4: 350 | H4: 0 | I4: 2 year | J4: 45279 | K4: 46023 | L4: TRUE
A5: 45548 | B5: EAR002 | C5: EAR002-15529 | D5: Earth Hero Movement NPC | E5: vlan179 | F5: Trusc Wireless | G5: 1149 | H5: 0 | I5: 2 year | J5: 44858 | K5: 45597 | L5: TRUE
A6: 45548 | B6: EAS001 | C6: EAS001-17797 | D6: Easygram CC t/a Easygram Telegram Services | E6: Aasvoelkop-aasvoelkop-switch1 | F6: Openserve | G6: 699 | H6: 0 | I6: 2 year | J6: 45271 | K6: 46003 | L6: TRUE
A7: 45548 | B7: EBE001 | C7: EBE001-1274 | D7: Ebenhaeser VGK | E7: Eben | F7: Trusc Wireless | G7: 344 | H7: 0 | I7: 2 year | J7: 44947 | K7: 45689 | L7: TRUE
A8: 45548 | B8: EBE003 | C8: EBE003-16720 | D8: Ebenhaezer Primary School | E8: ebenheazer-apa11 | F8: Trusc Wireless | G8: 0 | H8: 0 | I8: Sponsorship Agreement | J8: 44616 | K8: 45261 | L8: TRUE
A9: 45548 | B9: EBE005 | C9: EBE005-26157 | D9: WJ Ebersohn | E9: vdal_north-apa2 | F9: Trusc Wireless | G9: 350 | H9: 35 | I9: 2 year | J9: 45406 | K9: 46143 | L9: TRUE
A10: 45548 | B10: EBI003 | C10: EBI003-11327 | D10: JL Ebing | E10: rooidraai-apa12 | F10: Trusc Wireless | G10: 804 | H10: 0 | I10: 2 year | J10: 44132 | K10: 44866 | L10: TRUE
A11: 45548 | B11: EBI004 | C11: EBI004-11354 | D11: JL Ebing | E11: rooidraai-apa18 | F11: Trusc Wireless | G11: 804 | H11: 0 | I11: 2 year | J11: 44959 | K11: 45717 | L11: TRUE
A12: 45548 | B12: EBS002 | C12: EBS002-5429 | D12: EBS Civils CC | E12: langebaan-apa14 | F12: Trusc Wireless | G12: 0 | H12: 0 | I12: 2 year | J12: 45051 | K12: 45809 | L12: TRUE
A13: 45548 | B13: ECK002 | C13: ECK002-27590 | D13: L Eckardt | E13: Aasvoelkop-aasvoelkop-switch1 | F13: Trusc Wireless | G13: 350 | H13: 0 | I13: 2 year | J13: Still need to Install | K13: 45495 | L13: TRUE
A14: 45548 | B14: EDA003 | C14: EDA003-14380 | D14: MR Edas | E14: meisies_koshuis-apa1 | F14: Trusc Wireless | G14: 574 | H14: 0 | I14: 2 year | J14: 44404 | K14: 45139 | L14: TRUE
A15: 45548 | B15: EDA004 | C15: EDA004-27611 | D15: E Edas | E15: Aasvoelkop-aasvoelkop-switch1 | F15: Openserve | G15: 599 | H15: 0 | I15: 2 year | J15: 45497 | K15: 46227 | L15: TRUE
A16: 45548 | B16: EDA005 | C16: EDA005-16368 | D16: CJ Edas | E16: meisies_koshuis-apa1 | F16: Trusc Wireless | G16: 574 | H16: 0 | I16: 2 year | J16: 44524 | K16: 45261 | L16: TRUE
A17: 45548 | B17: EDA006 | C17: EDA006-19535 | D17: JS Edas | E17: oranjefontein-apa14 | F17: Trusc Wireless | G17: 574 | H17: 0 | I17: 2 year | J17: 44765 | K17: 45505 | L17: TRUE
A18: 45548 | B18: EDE002 | C18: EDE002-20096 | D18: Eden Primary School | E18: ether3 - lm_bakwerke-apa24 | F18: Trusc Wireless | G18: 0 | H18: 0 | I18: Sponsorship Agreement | J18: 44813 | K18: 45536 | L18: TRUE
A19: 45548 | B19: EDR001 | C19: EDR001-16862 | D19: MR Edries | E19: oranjefontein-apa7 | F19: Trusc Wireless | G19: 599 | H19: 0 | I19: 2 year | J19: 45520 | K19: 46250 | L19: TRUE
A20: 45548 | B20: EDW002 | C20: EDW002-10905 | D20: B Edwards | E20: wittedrift-apa4 | F20: Trusc Wireless | G20: 804 | H20: 0 | I20: 2 year | J20: 44076 | K20: 44805 | L20: TRUE
A21: 45548 | B21: EDW003 | C21: EDW003-11378 | D21: RG Edwards | E21: olifantskop-apa1 | F21: Trusc Wireless | G21: 574 | H21: 0 | I21: 2 year | J21: 44148 | K21: 44866 | L21: TRUE
A22: 45548 | B22: EEN001 | C22: EEN001-25581 | D22: Eensgezind Boerdery | E22: koringberg-apa14 | F22: Trusc Wireless | G22: 350 | H22: 0 | I22: 2 year | J22: 45357 | K22: 46068 | L22: TRUE
A23: 45548 | B23: EFF002 | C23: EFF002-8755 | D23: Effective Human Intervention PTY Ltd | E23: rilau-apa11 | F23: Trusc Wireless | G23: 689 | H23: 0 | I23: 2 year | J23: 43469 | K23: 44531 | L23: TRUE
A24: 45548 | B24: EFR001 | C24: EFR001-6488 | D24: L Efraim | E24: rooidraai-apa20 | F24: Trusc Wireless | G24: 350 | H24: 35 | I24: 2 year | J24: 45209 | K24: 45962 | L24: TRUE
A25: 45548 | B25: EGL001 | C25: EGL001-6038 | D25: W Egli | E25: eagle-apa1 | F25: Trusc Wireless | G25: 632 | H25: 0 | I25: 2 year | J25: 43524 | K25: 44228 | L25: TRUE
... A79: 45548 | B79: ENG003 | C79: ENG003-1588 | D79: JA Engelbrecht | E79: kapel-apa1 | F79: Trusc Wireless | G79: 574 | H79: 0 | I79: 2 year | J79: 44423 | K79: 45170 | L79: TRUE
B80: ENG009 | C80: ENG009-758 | D80: JHA Engelbrecht | E80: retshof-apa6 | F80: Trusc Wireless | G80: 574 | H80: 0 | I80: 2 year | J80: 44105 | K80: 44835 | L80: TRUE
B81: ENG013 | C81: ENG013-20158 | D81: JA Engelbrecht | E81: Vredendal-exchange-vredex-acc-switch1 | F81: Trusc Fibre | G81: 574 | H81: 0 | I81: 2 year | J81: 44849 | K81: 45566 | L81: TRUE
B82: ENG014 | C82: ENG014-1029 | D82: JF Engelbrecht | E82: lang-apa6 | F82: Trusc Wireless | G82: 299 | H82: 0 | I82: 2 year | J82: 45524 | K82: 46255 | L82: TRUE
B83: ENG014 | C83: ENG014-2221 | D83: JF Engelbrecht | E83: Lambertsbay | F83: Trusc Wireless | G83: 299 | H83: 0 | I83: 2 year | J83: 45532 | K83: 46255 | L83: TRUE
B84: ENG015 | C84: ENG015-1190 | D84: JC Engelbrecht | E84: rooirand-apa6 | F84: Trusc Wireless | G84: 804 | H84: 0 | I84: 2 year | J84: 45126 | K84: 45839 | L84: TRUE
B85: ENG023 | C85: ENG023-1565 | D85: SA Engelbrecht | E85: kapel_rep-apa1 | F85: Trusc Wireless | G85: 1149 | H85: 0 | I85: 2 year | J85: 44055 | K85: 44805 | L85: TRUE
B86: ENG023 | C86: ENG023-1580 | D86: SA Engelbrecht | E86: kapel_repeater | F86: Trusc Wireless | G86: 632 | H86: 0 | I86: 2 year | J86: 42761 | K86: 44805 | L86: TRUE
B87: ENG027 | C87: ENG027-1761 | D87: FC Engelbrecht | E87: koekrep-apa2 | F87: Trusc Wireless | G87: 402 | H87: 0 | I87: 2 year | J87: 43536 | K87: 44287 | L87: TRUE
B88: ENG028 | C88: ENG028-1941 | D88: HB Engelbrecht | E88: steelwater-apa5 | F88: Trusc Wireless | G88: 632 | H88: 35 | I88: 2 year | J88: 43263 | K88: 46059 | L88: TRUE
B89: ENG028 | C89: ENG028-5286 | D89: HB Engelbrecht | E89: steelwater-apa5 | F89: Trusc Wireless | G89: 350 | H89: 35 | I89: 2 year | J89: 45327 | K89: 46059 | L89: TRUE
B90: ENG035 | C90: ENG035-2453 | D90: AF Engelbrecht | E90: kransvlei-apa1 | F90: Trusc Wireless | G90: 699 | H90: 0 | I90: 2 year | J90: 45302 | K90: 46033 | L90: TRUE
B91: ENG043 | C91: ENG043-3581 | D91: AJ Engelbrecht | E91: lutzville-apa11 | F91: Trusc Wireless | G91: 574 | H91: 0 | I91: 2 year | J91: 44167 | K91: 44531 | L91: TRUE
B92: ENG045 | C92: ENG045-20924 | D92: N Engelbrecht | E92: Aasvoelkop-aasvoelkop-switch1 | F92: Trusc Fibre | G92: 0 | H92: 0 | I92: 2 year | J92: Still need to Install | K92: 45627 | L92: TRUE
B93: ENG045 | C93: ENG045-3912 | D93: N Engelbrecht | E93: watertower-apa1 | F93: Trusc Wireless | G93: 574 | H93: 0 | I93: 2 year | J93: 43894 | K93: 45627 | L93: TRUE
B94: ENG046 | C94: ENG046-12839 | D94: H Engelbrecht | E94: lambertsbay-apa5 | F94: Trusc Wireless | G94: 574 | H94: 0 | I94: 2 year | J94: 6690427 | K94: 43744 | L94: TRUE
B95: ENG047 | C95: ENG047-4399 | D95: PP Engelbrecht | E95: piketberg-apa3 | F95: Trusc Wireless | G95: 632 | H95: 0 | I95: 2 year | J95: 43040 | K95: 43800 | L95: TRUE
B96: ENG051 | C96: ENG051-4933 | D96: CJ Engelbrecht | E96: koraan-apa4 | F96: Trusc Wireless | G96: 804 | H96: 0 | I96: 2 year | J96: 44901 | K96: 45658 | L96: TRUE
B97: ENG053 | C97: ENG053-5002 | D97: NM Engelbrecht | E97: watertower-apa3 | F97: Trusc Wireless | G97: 350 | H97: 0 | I97: 2 year | J97: 45292 | K97: 46027 | L97: TRUE
B98: ENG055 | C98: ENG055-5031 | D98: JM Engelbrecht | E98: vdal_res-apa2 | F98: Trusc Wireless | G98: 350 | H98: 35 | I98: 2 year | J98: 45187 | K98: 45931 | L98: TRUE
B99: ENG058 | C99: ENG058-9526 | D99: USJ Engineering (Pty) Ltd | E99: springbok2-apa6 | F99: Trusc Wireless | G99: 804 | H99: 0 | I99: 2 year | J99: 43984 | K99: 44652 | L99: TRUE
B100: ENG060 | C100: ENG060-6069 | D100: AC Engelbrecht | E100: vdal_north-apa2 | F100: Trusc Wireless | G100: 804 | H100: 0 | I100: 2 year | J100: 44216 | K100: 44958 | L100: TRUE
B101: ENG065 | C101: ENG065-7048 | D101: AE Engelbrecht | E101: saron | F101: Trusc Wireless | G101: 459 | H101: 0 | I101: 2 year | J101: 43665 | K101: 44348 | L101: TRUE
B102: ENG067 | C102: ENG067-7064 | D102: JJH Engelbrecht | E102: olifantskop-apa11 | F102: Trusc Wireless | G102: 574 | H102: 0 | I102: 2 year | J102: 44700 | K102: 45444 | L102: TRUE
B103: ENG068 | C103: ENG068-23543 | D103: L Engelbrecht | E103: goudmyn-apa6 | F103: Trusc Wireless | G103: 350 | H103: 0 | I103: 2 year | J103: 45186 | K103: 45931 | L103: TRUE
B104: ENG076 | C104: ENG076-8097 | D104: NA Engelbrecht | E104: retshof | F104: Trusc Wireless | G104: 399 | H104: 0 | I104: 2 year | J104: 45527 | K104: 46258 | L104: TRUE
... B139: ENG164 | C139: ENG164-19262 | D139: C Engelbrecht | E139: Steelwater | F139: Trusc Wireless | G139: 344 | H139: 0 | I139: 2 year | J139: 45197 | K139: 45931 | L139: TRUE
B140: ENG168 | C140: ENG168-20350 | D140: A Engelbrecht | E140: Aasvoelkop-aasvoelkop-switch1 | F140: Trusc Fibre | G140: 459 | H140: 0 | I140: 2 year | J140: Still need to Install | K140: 45566 | L140: TRUE
B141: ENG169 | C141: ENG169-20395 | D141: A Engelbrecht | E141: Clan | F141: Trusc Wireless | G141: 574 | H141: 0 | I141: 2 year | J141: 44852 | K141: 45566 | L141: TRUE
B142: ENG171 | C142: ENG171-20936 | D142: W Engelbrecht | E142: Heuningberg | F142: Trusc Wireless | G142: 574 | H142: 0 | I142: 2 year | J142: 44887 | K142: 45627 | L142: TRUE
B143: ENG172 | C143: ENG172-27020 | D143: HW Engelbrecht | E143: voight | F143: Trusc Wireless | G143: 349 | H143: 0 | I143: 2 year | J143: 45456 | K143: 46186 | L143: TRUE
B144: ENG173 | C144: ENG173-21090 | D144: NH Engelbrecht | E144: Klawer | F144: Trusc Wireless | G144: 574 | H144: 0 | I144: 2 year | J144: 44895 | K144: 45627 | L144: TRUE
B145: ENG175 | C145: ENG175-21265 | D145: SY Engelbrecht | E145: springbok2-apa20 | F145: Trusc Wireless | G145: 402 | H145: 0 | I145: 2 year | J145: 44905 | K145: 45658 | L145: TRUE
A146: 45581 | B146: ENG179 | C146: ENG179-21745 | D146: JMJ Engelbrecht | E146: grootfontein | F146: Trusc Wireless | G146: 459 | H146: 0 | I146: 2 year | J146: 45028 | K146: 45759 | L146: TRUE
A147: 45576 | B147: ENG185 | C147: ENG185-22263 | D147: E Engelbrecht | E147: Laaiplek | F147: Trusc Wireless | G147: 344 | H147: 0 | I147: 2 year | J147: 45149 | K147: 45880 | L147: TRUE
A148: 45575 | B148: ECH001 | C148: ECH001-28464 | D148: Echo Edge Pty Ltd | E148: vredenburg1-apa4 | F148: Trusc Wireless | G148: 1999 | H148: 0 | I148: 2 year | J148: 45563 | K148: 46293 | L148: TRUE
A149: 45581 | B149: ENG189 | C149: ENG189-22881 | D149: SJ Engelbrecht | E149: Nababeep | F149: Trusc Wireless | G149: 574 | H149: 0 | I149: 2 year | J149: 45085 | K149: 45816 | L149: TRUE
B150: ENG190 | D150: Z Engelbrecht | L150: FALSE
B151: ENG191 | D151: N Engelbrecht | L151: FALSE
B152: ENG193 | D152: J Engelbrecht | L152: FALSE
B153: ENG194 | D153: S Engelbrecht | L153: FALSE
B154: ENG196 | D154: L Engelbrecht | L154: FALSE
B155: ENG197 | D155: CR Engel | L155: FALSE
B156: ENG198 | D156: WJ Engelbrecht | L156: FALSE
B157: ENG199 | D157: J Engelbrecht | L157: FALSE
B158: ENG200 | D158: EM Engelbrecht | L158: FALSE
B159: ENG202 | D159: HL Engelbrecht | L159: FALSE
B160: ENG204 | D160: TA Engelbrecht | L160: FALSE
B161: ENG205 | D161: J Engelbrecht | L161: FALSE
... B163: ENG207 | D163: WH Engelbrecht | L163: FALSE
A164: 45581 | B164: ENG209 | C164: ENG209-25350 | D164: MG Engelbrecht | E164: Klipberg | F164: Trusc Wireless | G164: 350 | H164: 35 | I164: 2 year | J164: 44973 | K164: 45704 | L164: TRUE
A165: 45576 | B165: ENG239 | C165: ENG239-28385 | D165: M Engelbrecht | E165: Vredendal-Resevoir | F165: Trusc Wireless | G165: 299 | H165: 35 | I165: 2 year | J165: 45573 | K165: 46303 | L165: TRUE
A166: 45581 | B166: ENG210 | C166: ENG210-25449 | D166: DM Engelbrecht | E166: Synott | F166: Trusc Wireless | G166: 250 | H166: 0 | I166: 2 year | J166: 45344 | K166: 46075 | L166: TRUE
B167: ENG211 | D167: J Engelbrecht | L167: FALSE
B168: ENG212 | D168: C Engelbrecht | L168: FALSE
B169: ENG213 | D169: J Engelbrecht | L169: FALSE
B170: ENG215 | D170: P Engelbrecht | L170: FALSE
B171: ENG216 | D171: M Engelbrecht | L171: FALSE
B172: ENG217 | D172: JE Engelbrecht | L172: FALSE
B173: ENG218 | D173: G Engelbrecht | L173: FALSE
B174: ENG219 | D174: DJV Engelbrecht | L174: FALSE
B175: ENG221 | D175: J Engelbrecht | L175: FALSE
B176: ENG222 | D176: GE Engelbrecht | L176: FALSE
B177: ENG223 | D177: RN Engelbrecht | L177: FALSE
B178: ENG225 | D178: LP Engelbrecht | L178: FALSE
... B238: ERE003 | D238: M Erentze | L238: FALSE
A239: 45581 | B239: ERE004 | C239: ERE004-24777 | D239: LM Erentzen | E239: Dwarskersbos S/C | F239: Trusc Fibre | G239: 399 | H239: 0 | I239: 2 year | J239: 45315 | K239: 46046 | L239: TRUE
A240: 45581 | B240: ERF001 | C240: ERE004-24784 | D240: Erf 419 Halfway House Ext 48 CC | E240: Dwarskersbos S/C | F240: Trusc Fibre | G240: 399 | H240: 0 | I240: 2 year | J240: 45314 | K240: 46045 | L240: TRUE
B241: ERF002 | D241: Erf 2966 Brackenfell CC | L241: FALSE
B242: ERN001 | D242: BE Ernstzen | L242: FALSE
B243: ERN003 | D243: E Ernstzen | L243: FALSE
B244: ERN004 | D244: BM Ernstzen | L244: FALSE
B245: ESA008 | D245: AH Esau | L245: FALSE
B246: ESA014 | D246: MJ Esau | L246: FALSE
B247: ESA015 | D247: WER Esau | L247: FALSE
...

Sheet Clients (I - L)
B1: =COUNTA(B4:B3290) -> 1814 | C1: =COUNTIF(C4:C3290,"?*") -> 1076
A2: Date | B2: Client Account | C2: Client Reference | D2: Client name | E2: Highsite / SC | F2: Type | G2: ISPMan Premium | H2: ISPMan EFT Fee | I2: Contract Duration | J2: Install Date | K2: Contract Expiry | L2: Have Contract
B3: ABC001 | C3: ABC001-12345 | D3: Mr Joe Soap | E3: Dwarskersbos S/C | F3: Trusc Wireless | I3: 1 Year | K3: 45626 | L3: TRUE | M3: Example line
A4: 45548 | B4: IBG001 | C4: IBG001-22189 | D4: IBG Sureinvest An Independant Group cc | E4: Admiral Island | F4: Trusc Fibre | G4: 799 | H4: 0 | I4: 2 year | J4: 45022 | K4: 45753 | L4: TRUE
A5: 45548 | B5: IBR001 | C5: IBR001-5680 | D5: SJ Ibrahim | E5: vdal_north-apa5 | F5: Trusc Wireless | G5: 350 | H5: 35 | I5: 2 year | J5: 44867 | K5: 45598 | L5: TRUE
A6: 45548 | B6: IBR001 | C6: IBR001-24701 | D6: SJ Ibrahim | E6: vdal_res-apa14_c | F6: Trusc Wireless | G6: 350 | H6: 35 | I6: 2 year | J6: 45284 | K6: 46015 | L6: TRUE
A7: 45548 | B7: ICE001 | C7: ICE001-26438 | D7: SS Burger | E7: Dwarskersbos S/C | F7: Trusc Fibre | G7: 599 | H7: 0 | I7: 2 year | J7: 45409 | K7: 46139 | L7: FALSE | M7: no signed SLA for Fibre
A8: 45548 | B8: IGN001 | C8: - | D8: Ignite | G8: - | H8: - | L8: FALSE
A9: 45548 | B9: IKA002 | C9: IKA002-14573 | D9: C Ikaneng | E9: voorberg-apa6 | F9: Trusc Wireless | G9: 349 | H9: 0 | I9: 2 year | J9: 45442 | K9: 46172 | L9: TRUE
A10: 45548 | B10: ILL001 | C10: ILL001-11233 | D10: Ilingelethu Secondary School | E10: vlan109_oranjefontein-ap10_C-ppp | F10: Trusc Wireless | G10: 0 | H10: 0 | J10: 44138 | K10: 44868 | L10: FALSE
A11: 45548 | B11: IMA001 | C11: IMA001-23541 | D11: SI Iman | E11: malms_gh-apa4 | F11: Trusc Wireless | G11: 350 | H11: 35 | I11: 2 year | J11: 45189 | K11: 45920 | L11: TRUE
A12: 45548 | B12: IMI001 | C12: IMI001-12140 | D12: Imibala Orchards | E12: Heuningberg | F12: Trusc Wireless | G12: 977 | H12: 0 | I12: 2 year | J12: 44210 | K12: 44940 | L12: TRUE
A13: 45548 | B13: IMM002 | C13: IMM002-3115 | D13: GC Immelman | E13: kapel | F13: Trusc Wireless | G13: 599 | H13: 0 | I13: 2 year | J13: 45547 | K13: 46277 | L13: TRUE
A14: 45548 | B14: IMM005 | C14: IMM005-21919 | D14: WFE Immelman | E14: Admiral Island | F14: Trusc Fibre | G14: 229 | H14: 0 | I14: 2 year | J14: 45072 | K14: 45803 | L14: TRUE
A15: 45548 | B15: IMP001 | C15: IMP001-16736 | D15: Impinda Investments 27 CC | E15: Melkboom | F15: Trusc Wireless | G15: N/A on ISPman | H15: 0 | I15: 2 year | J15: 45467 | K15: 46197 | L15: FALSE
A16: 45548 | B16: IMV002 | C16: IMV002-27148 | D16: Imvusa Trading 546 CC | E16: Melkboom | F16: Trusc Wireless | G16: 449 | H16: 35 | I16: 2 year | J16: 45467 | K16: 46197 | L16: TRUE
A17: 45548 | B17: INC001 | C17: N/A | D17: Incorporated Beauty | G17: N/A on ISPman | H17: - | I17: 1 Year | J17: 43378 | K17: 43743 | L17: TRUE
A18: 45548 | B18: IND002 | C18: IND002-11240 | D18: Indo Trust | E18: elandshotel | F18: Trusc Wireless | G18: 799 | H18: 0 | I18: 2 year | J18: 45439 | K18: 45804 | L18: TRUE
A19: 45548 | B19: IND004 | C19: IND004-22498 | D19: Indian Princess Pty Ltd | E19: octotel_cbd-vredehoek | F19: Octotel | G19: 2874 | H19: 0 | I19: 2 year | J19: 45037 | K19: 45768 | L19: TRUE
A20: 45548 | B20: IND005 | C20: IND005-28192 | D20: Indiscape CC | E20: Admiral Island | F20: Trusc Fibre | G20: 629 | H20: 0 | I20: 2 year | J20: 45546 | K20: 46276 | L20: TRUE
A21: 45548 | B21: ING002 | C21: ING002-25097 | D21: Ingodwe Trust | E21: Dwarskersbos S/C | F21: Trusc Fibre | G21: 399 | H21: 0 | I21: 2 year | J21: 45337 | K21: 46068 | L21: TRUE
A22: 45548 | B22: INK001 | C22: INK001-19303 | D22: D Inkeld | E22: kabiscouw | F22: Trusc Wireless | G22: 349 | H22: 0 | I22: 2 year | J22: 45492 | K22: 46222 | L22: TRUE
A23: 45548 | B23: INN002 | C23: INN002-12548 | D23: Innovative Recruitment | E23: Jacobsbaai | F23: Trusc Wireless | G23: 689 | H23: 0 | I23: 2 year | J23: 44252 | K23: 44982 | L23: TRUE
A24: 45548 | B24: INT003 | C24: INT003-12832 | D24: Intellego Wines Pty Ltd | E24: Paardeberg | F24: Trusc Wireless | G24: 1149 | H24: 0 | I24: 2 year | J24: 44280 | K24: 45010 | L24: TRUE
A25: 45548 | B25: INT003 | C25: INT003-12837 | D25: Intellego Wines Pty Ltd | E25: Paardeberg | F25: Trusc Wireless | G25: 689 | H25: 0 | I25: 2 year | J25: 44281 | K25: 45011 | L25: TRUE
A26: 45548 | B26: INT004 | C26: INT004-19609 | D26: Intergro Technologies PTY LTD | E26: Veldrift S/C | F26: Trusc Fibre | G26: 649 | H26: 0 | I26: 1 Year | J26: 45189 | K26: 45555 | L26: TRUE
A27: 45548 | B27: INT005 | C27: INT005-25256 | D27: Interworks Wireless Solutions | E27: vlan59 | F27: Trusc Wireless | G27: 5499 | H27: 0 | I27: 2 year | J27: 45282 | K27: 46013 | L27: TRUE
A28: 45548 | B28: INT005 | C28: INT005-25257 | D28: Interworks Wireless Solutions | E28: vlan20_maanberg | F28: Trusc Wireless | G28: 1149 | H28: 0 | I28: 2 year | J28: 45337 | K28: 46068 | L28: TRUE
A29: 45548 | B29: IOB001 | C29: IOB001-24542 | D29: Iobase Software and Applications | E29: Admiral Island | F29: Trusc Fibre | G29: 399 | H29: 0 | I29: 2 year | J29: 45294 | K29: 46025 | L29: TRUE
... A66: 45553 | B66: ISO001 | C66: ISO001-24801 | D66: ISOQAR Africa PTY Ltd | E66: Veldrift S/C | F66: Trusc Fibre | G66: 399 | H66: 0 | I66: 2 year | J66: 45315 | K66: 46046 | L66: TRUE
A67: 45553 | B67: ISS001 | C67: ISS001-18542 | D67: VA Issel | E67: Aasvoelkop SC | F67: Trusc Fibre | G67: 0 | H67: 0 | I67: 2 year | L67: TRUE
A68: 45553 | B68: ISS001 | C68: ISS001-20134 | D68: VA Issel | E68: Tallie Marine | F68: Trusc Wireless | G68: 574 | H68: 0 | I68: 2 year | J68: 44835 | K68: 45566 | L68: TRUE
A69: 45553 | B69: ISS001 | C69: ISS001-3449 | D69: VA Issel | E69: vredex-apa5 | F69: Trusc Wireless | G69: 689 | H69: 0 | I69: 2 year | J69: 44129 | K69: 44617 | L69: TRUE | M69: Has to be removed still
A70: 45553 | B70: IVE001 | C70: IVE001-20532 | D70: TC Ives | E70: Admiral Island | F70: Trusc Fibre | G70: 689 | H70: 0 | I70: 2 year | J70: 45104 | K70: 45835 | L70: TRUE
A71: 45553 | B71: IZA001 | C71: IZA001-2671 | D71: J Izaaks | E71: Lutzville | F71: Trusc Wireless | G71: 528 | H71: 0 | I71: 2 year | J71: 42542 | K71: 43272 | L71: TRUE
A72: 45553 | B72: IZA002 | C72: IZA002-3530 | D72: CA Izaks | E72: vredenburg1-apa4 | F72: Trusc Wireless | G72: 459 | H72: 0 | I72: 2 year | J72: 44931 | K72: 45662 | L72: TRUE
A73: 45553 | B73: IZA003 | C73: IZA003-6253 | D73: AJ Izaks | E73: Vdal North | F73: Trusc Wireless | G73: 599 | H73: 0 | I73: 2 year | J73: 45518 | K73: 46248 | L73: TRUE
A74: 45553 | B74: IZA004 | C74: IZA004-7972 | D74: CR Izaks | E74: Melkboom | F74: Trusc Wireless | G74: 350 | H74: 35 | I74: 2 year | J74: 43781 | K74: 44512 | L74: TRUE
A75: 45553 | B75: IZA005 | C75: IZA005-8311 | D75: JJA Izaks | E75: Vdal North | F75: Trusc Wireless | G75: 350 | H75: 35 | I75: 2 year | J75: 43809 | K75: 44540 | L75: TRUE
A76: 45553 | B76: IZA006 | C76: IZA006-9643 | D76: MD Izaks | E76: Klawer-Res | F76: Trusc Wireless | G76: 449 | H76: 35 | I76: 2 year | J76: 45432 | K76: 46162 | L76: TRUE
A77: 45553 | B77: IZA007 | C77: IZA007-24433 | D77: B Izaaks | E77: Nababeep | F77: Trusc Wireless | G77: 350 | H77: 0 | I77: 2 year | J77: 45259 | K77: 45990 | L77: TRUE
A78: 45553 | B78: IZA008 | C78: IZA008-28142 | D78: NC Izaks | E78: Klawer-Res | F78: Trusc Wireless | G78: 250 | H78: 0 | I78: 2 year | J78: 44970 | K78: 45701 | L78: TRUE
A79: 45553 | B79: IZA009 | C79: IZA009-26344 | D79: M Izaacs | E79: Heuningberg | F79: Trusc Wireless | G79: 250 | H79: 0 | I79: 2 year | J79: 45416 | K79: 46146 | L79: TRUE
A80: 45553 | B80: JAA002 | C80: JAA002-11893 | D80: DM Jaars | E80: Nababeep | F80: Trusc Wireless | G80: 287 | H80: 0 | I80: 2 year | J80: 45193 | K80: 45924 | L80: TRUE
A81: 45553 | B81: JAA004 | C81: JAA004-14400 | D81: L Jaars | E81: Lutzville | F81: Trusc Wireless | G81: 350 | H81: 35 | I81: 2 year | J81: 45261 | K81: 45992 | L81: TRUE
... A154: 45554 | B154: JAC141 | C154: JAC141-25753 | D154: V Jack | E154: Engels | F154: Trusc Wireless | G154: 250 | H154: 35 | I154: 2 year | J154: 45370 | K154: 46100 | L154: TRUE
A155: 45554 | B155: JAC142 | C155: JAC142-25772 | D155: Q Jacobs | E155: Laguna Hills | F155: Trusc Fibre | G155: 689 | H155: 0 | I155: 2 year | J155: 44999 | K155: 45730 | L155: FALSE | M155: Billing Needed #683130
A156: 45554 | B156: JAC143 | C156: JAC143-25821 | D156: TC Jacobs | E156: Oranjefontein | F156: Trusc Wireless | G156: 350 | H156: 0 | I156: 2 year | J156: 45377 | K156: 46107 | L156: TRUE
A157: 45554 | B157: JAC144 | C157: JAC144-26271 | D157: CE Jacobs | E157: saron | F157: Trusc Wireless | G157: 350 | H157: 0 | I157: 2 year | J157: 45419 | K157: 46149 | L157: TRUE
A158: 45554 | B158: JAC145 | C158: JAC145-26644 | D158: GN Jacobs | E158: Okiep | F158: Trusc Wireless | G158: 350 | H158: 0 | I158: 2 year | J158: 45443 | K158: 46173 | L158: TRUE
A159: 45554 | B159: JAC146 | C159: JAC146-27015 | D159: DJ Jacobs | E159: Goudmyn | F159: Trusc Wireless | G159: 349 | H159: 0 | I159: 2 year | J159: 45470 | K159: 46200 | L159: TRUE
A160: 45554 | B160: JAC147 | C160: JAC147-27651 | D160: P Jacobs | E160: Oranjefontein | F160: Trusc Wireless | G160: 799 | H160: 0 | I160: 2 year | J160: 45527 | K160: 46257 | L160: TRUE
A161: 45554 | B161: JAC148 | C161: JAC148-27687 | D161: RL Jacobs | E161: saron | F161: Trusc Wireless | G161: 399 | H161: 0 | I161: 2 year | J161: 45531 | K161: 46261 | L161: TRUE
A162: 45554 | B162: JAC149 | C162: JAC149-27856 | D162: LH Jacobs | E162: Kalbaskraal | F162: Trusc Wireless | G162: 799 | H162: 0 | I162: 2 year | L162: FALSE | M162: Billing Needed #686392
A163: 45554 | B163: JAC150 | C163: JAC150-28117 | D163: NJ Jacobs | E163: Aasvoelkop-aasvoelkop-switch1 | F163: Trusc Wireless | G163: 299 | H163: 0 | I163: 2 year | L163: FALSE | M163: Still to be installed #692286
A164: 45554 | B164: JAE001 | C164: JAE001-17091 | D164: C Jaers | E164: lm_bakwerke | F164: Trusc Wireless | G164: 350 | H164: 0 | I164: 2 year | J164: 45304 | K164: 46035 | L164: TRUE
A165: 45554 | B165: JAE002 | C165: JAE002-25138 | D165: WA Jaers | E165: Oranjefontein | F165: Trusc Wireless | G165: 250 | H165: 0 | I165: 2 year | J165: 45333 | K165: 46064 | L165: TRUE
A166: 45554 | B166: JAF004 | C166: JAF004-8408 | D166: FD Jafta | E166: Vdal_res | F166: Trusc Wireless | G166: 574 | H166: 0 | I166: 2 year | L166: FALSE | M166: Billing Needed #702107
A167: 45554 | B167: JAF007 | C167: JAF007-10450 | D167: JM Jaftha | E167: Lutzville | F167: Trusc Wireless | G167: 459 | H167: 0 | I167: 2 year | J167: 44750 | K167: 45481 | L167: TRUE
A168: 45554 | B168: JAF009 | C168: JAF009-15380 | D168: HA Jaftha | E168: Bitterfontein | F168: Trusc Wireless | G168: 350 | H168: 0 | I168: 2 year | J168: 45243 | K168: 45974 | L168: TRUE
A169: 45554 | B169: JAF010 | C169: JAF010-16421 | D169: A Jaftha | E169: Duiwelskop | F169: Trusc Wireless | G169: 350 | H169: 0 | I169: 2 year | J169: 45341 | K169: 46072 | L169: TRUE
A170: 45554 | B170: JAF018 | C170: JAF018-27489 | D170: AJ Jafta | E170: Synott | F170: Trusc Wireless | G170: 399 | H170: 0 | I170: 2 year | J170: 45503 | K170: 46233 | L170: TRUE
A171: 45554 | B171: JAG002 | C171: JAG002-6509 | D171: LP Jagers | E171: Voorberg | F171: Trusc Wireless | G171: 350 | H171: 35 | I171: 2 year | J171: 45344 | K171: 46075 | L171: TRUE
A172: 45554 | B172: JAG004 | C172: JAG004-11407 | D172: BL Jagers | E172: Voorberg | F172: Trusc Wireless | G172: 250 | H172: 0 | I172: 2 year | J172: 45310 | K172: 46041 | L172: TRUE
A173: 45554 | B173: JAG009 | C173: JAG009-23387 | D173: T Jagers | E173: Koringberg | F173: Trusc Wireless | G173: 350 | H173: 0 | I173: 2 year | J173: 45174 | K173: 45905 | L173: TRUE
A174: 45554 | B174: JAG011 | C174: JAG011-24761 | D174: RDG Jaghtman | E174: vlan10_graafwater-apa1 | F174: Trusc Wireless | G174: 350 | H174: 0 | I174: 2 year | J174: 45294 | K174: 46025 | L174: TRUE
A175: 45555 | B175: JAG012 | C175: JAG012-24898 | D175: AT Jagers | E175: Kalbaskraal | F175: Trusc Wireless | G175: 350 | H175: 0 | I175: 2 year | J175: 45317 | K175: 46048 | L175: TRUE
A176: 45555 | B176: JAG013 | C176: JAG013-25068 | D176: C Jagers | E176: Heuningberg | F176: Trusc Wireless | G176: 350 | H176: 0 | I176: 2 year | J176: 45342 | K176: 46073 | L176: TRUE
A177: 45555 | B177: JAG014 | C177: JAG014-25949 | D177: MJ Jagers | E177: Koringberg | F177: Trusc Wireless | G177: 350 | H177: 0 | I177: 2 year | J177: 45385 | K177: 46115 | L177: TRUE
A178: 45555 | B178: JAG015 | C178: JAG015-27165 | D178: S Jagers | E178: Paardeberg | F178: Trusc Wireless | G178: 449 | H178: 0 | I178: 2 year | J178: 45478 | K178: 46208 | L178: TRUE
... A182: 45555 | B182: JAK005 | C182: JAK005-22557 | D182: Hendrik Botha Family Trust/Jakkalswater Guest Farm | E182: Nababeep | F182: Trusc Wireless | G182: 1379 | H182: 0 | I182: 2 year | J182: 44979 | K182: 45710 | L182: TRUE
A183: 45555 | B183: JAK006 | C183: JAK006-28229 | D183: A Jakobs | E183: Goudmyn | F183: Trusc Wireless | G183: 299 | H183: 0 | I183: 2 year | L183: FALSE | M183: Billing Needed #696861
A184: 45555 | B184: JAM007 | C184: JAM007-21729 | D184: MG James | E184: Bulshoek | F184: Trusc Wireless | G184: 459 | H184: 0 | I184: 2 year | J184: 44946 | K184: 45677 | L184: TRUE
A185: 45555 | B185: JAM008 | C185: JAM008-25797 | D185: AA Jamal | E185: bottlefontein | F185: Trusc Wireless | G185: 350 | H185: 35 | I185: 2 year | J185: 45371 | K185: 46101 | L185: TRUE
A186: 45555 | B186: JAN009 | C186: JAN009-5516 | D186: LC Jansen van Rensburg | E186: Doornbaai | F186: Trusc Wireless | G186: 977 | H186: 0 | I186: 2 year | J186: 44887 | K186: 45618 | L186: TRUE
A187: 45555 | B187: JAN016 | C187: JAN016-3165 | D187: C Jantjies | E187: Maskam | F187: Trusc Wireless | G187: 574 | H187: 0 | I187: 2 year | L187: FALSE
A188: 45556 | B188: JAN017 | C188: JAN017-15506 | D188: GFS Janse van Rensburg | E188: paleis-apa2 | F188: Trusc Wireless | G188: 1149 | H188: 58 | I188: 2 year | J188: 44491 | K188: 45221 | L188: TRUE
A189: 45556 | B189: JAN017 | C189: JAN017-3318 | D189: GFS Janse van Rensburg | E189: paleis-apa2 | F189: Trusc Wireless | G189: 1149 | H189: 58 | I189: 2 year | L189: FALSE | M189: Billing Needed #682750
A190: 45556 | B190: JAN018 | C190: JAN018-3451 | D190: M Jansen van Vuren | E190: St Helena | F190: Trusc Wireless | G190: 344 | H190: 0 | I190: 2 year | J190: 42805 | K190: 43535 | L190: TRUE
A191: 45556 | B191: JAN022 | C191: JAN022-6344 | D191: J Jantjies | E191: Lutzville | F191: Trusc Wireless | G191: 350 | H191: 0 | I191: 2 year | J191: 45238 | K191: 45969 | L191: TRUE
A192: 45556 | B192: JAN028 | C192: JAN028-19596 | D192: AC Janse van Rensburg | E192: Veldrift S/C | F192: Trusc Fibre | G192: 399 | H192: 0 | I192: 2 year | J192: 45275 | K192: 46006 | L192: TRUE
A193: 45556 | B193: JAN033 | C193: JAN033-17966 | D193: B Janse Van Rensburg | E193: Aasvoelkop-aasvoelkop-switch1 | F193: Trusc Wireless | G193: 103 | H193: 0 | I193: 2 year | J193: 44616 | K193: 45346 | L193: TRUE
A194: 45556 | B194: JAN048 | C194: JAN048-7516 | D194: MS Jantjies | E194: kliprand-apa1 | F194: Trusc Wireless | G194: 350 | H194: 35 | I194: 2 year | J194: 45278 | K194: 46009 | L194: TRUE
A195: 45556 | B195: JAN050 | C195: JAN050-8084 | D195: CA Janse van Rensburg | E195: turner | F195: Trusc Wireless | G195: 632 | H195: 0 | I195: 2 year | J195: 43769 | K195: 44500 | L195: TRUE
A196: 45556 | B196: JAN052 | C196: JAN052-8457 | D196: S Jantjies | E196: Rooidraai | F196: Trusc Wireless | G196: 574 | H196: 35 | I196: 2 year | J196: 44981 | K196: 45712 | L196: TRUE
A197: 45556 | B197: JAN056 | C197: JAN056-8643 | D197: A Janse Van Rensburg | E197: Rooidraai | F197: Trusc Wireless | G197: 689 | H197: 0 | I197: 2 year | J197: 43823 | K197: 44554 | L197: TRUE
A198: 45556 | B198: JAN059 | C198: JAN059-23334 | D198: XMJ Januarie | E198: Windpomp | F198: Trusc Wireless | G198: 459 | H198: 0 | I198: 2 year | J198: 45164 | K198: 45895 | L198: TRUE
A199: 45556 | B199: JAN059 | C199: JAN059-8972 | D199: XMJ Januarie | E199: Windpomp | F199: Trusc Wireless | G199: 1199 | H199: 0 | I199: 2 year | J199: 45159 | K199: 45890 | L199: TRUE
A200: 45556 | B200: JAN063 | C200: JAN063-9680 | D200: CA Jansen | E200: Melkboom | F200: Trusc Wireless | G200: 574 | H200: 35 | I200: Current Terms | J200: 45451 | L200: TRUE
A201: 45556 | B201: JAN065 | C201: JAN065-9857 | D201: RM Jantjies | E201: grootfontein | F201: Trusc Wireless | G201: 574 | H201: 35 | I201: 2 year | J201: 44784 | K201: 45515 | L201: TRUE
A202: 45556 | B202: JAN074 | C202: JAN074-10485 | D202: DA Jantjies | E202: Klawer-Res | F202: Trusc Wireless | G202: 449 | H202: 35 | I202: 2 year | J202: 45463 | K202: 46193 | L202: TRUE
A203: 45556 | B203: JAN076 | C203: JAN076-26483 | D203: GJ Janse van Nieuwenhuizen | E203: Dwarskersbos S/C | F203: Trusc Fibre | G203: 499 | H203: 0 | L203: FALSE | M203: No Signed Contract #649781
A204: 45556 | B204: JAN079 | C204: JAN079-10844 | D204: F Jantjies | E204: vlan20_maanberg | F204: Trusc Wireless | G204: 459 | H204: 0 | I204: 2 year | J204: 44068 | K204: 44798 | L204: TRUE
A205: 45556 | B205: JAN080 | C205: JAN080-10932 | D205: AJ Janse | E205: Bergstraat | F205: Trusc Wireless | G205: 574 | H205: 0 | I205: 2 year | J205: 44092 | K205: 44822 | L205: TRUE
A206: 45556 | B206: JAN083 | C206: JAN083-11005 | D206: JM Januarie | E206: vlan110 - paardeberg_apa11 | F206: Trusc Wireless | G206: 599 | H206: 0 | I206: 2 year | L206: FALSE
A207: 45558 | B207: JAN084 | C207: JAN084-11177 | D207: RG Jansen | E207: Lewerberg | F207: Trusc Wireless | G207: 350 | H207: 0 | I207: 2 year | J207: 45254 | K207: 45985 | L207: TRUE
A208: 45558 | B208: JAN086 | C208: JAN086-11282 | D208: Jannie Kiep Familie Trust | E208: Rooidraai | F208: Trusc Wireless | G208: 1149 | H208: 0 | I208: 2 year | J208: 44131 | K208: 44861 | L208: TRUE
A209: 45558 | B209: JAN087 | C209: JAN087-11284 | D209: C Janse Van Rensburg | E209: kapel | F209: Trusc Wireless | G209: 350 | H209: 0 | I209: 2 year | J209: 45247 | K209: 45978 | L209: TRUE
A210: 45558 | B210: JAN088 | C210: JAN088-11818 | D210: E Jantjies | E210: Clanwilliam | F210: Trusc Wireless | G210: 344 | H210: 0 | I210: 2 year | J210: 44183 | K210: 44913 | L210: TRUE
A211: 45558 | B211: JAN089 | C211: JAN089-12008 | D211: BR Jantjies | E211: Steelwater | F211: Trusc Wireless | G211: 350 | H211: 0 | I211: 2 year | J211: 45302 | K211: 46033 | L211: TRUE
...

Sheet Clients (M - P)
B1: =COUNTA(B4:B2153) -> 2150 | C1: =COUNTIF(C4:C2153,"?*") -> 1239
A2: Date | B2: Client Account | C2: Client Reference | D2: Client name | E2: Highsite / SC | F2: Type | G2: ISPMan Premium | H2: ISPMan EFT Fee | I2: Contract Duration | J2: Install Date | K2: Contract Expiry | L2: Have Contract
B3: ABC001 | C3: ABC001-12345 | D3: Mr Joe Soap | E3: Dwarskersbos S/C | F3: Trusc Wireless | I3: 1 Year | K3: 45626 | L3: TRUE | M3: Example line
A4: 45545 | B4: MAA002 | C4: MAA002-1019 | D4: GM Maas | E4: heeren-apa | F4: Trusc Wireless | G4: 229 | H4: 0 | I4: 2 year | J4: 43567 | K4: 45394 | L4: TRUE
A5: 45545 | B5: MAA004 | C5: MAA004-2885 | D5: GJJ Maass | E5: AP10039 | F5: Trusc Wireless | G5: 350 | H5: 0 | I5: 2 year | J5: 45232 | K5: 45963 | L5: TRUE
A6: 45545 | B6: MAA007 | C6: MAA007-4511 | D6: ER Maarman | E6: Klawer | F6: Trusc Wireless | G6: 350 | H6: 0 | I6: 2 year | J6: 45257 | K6: 45988 | L6: TRUE
A7: 45545 | B7: MAA008 | C7: MAA008-5096 | D7: K Maarman | E7: Lambertsbay | F7: Trusc Wireless | G7: 402 | H7: 0 | I7: 2 year | J7: 43742 | K7: 44473 | L7: TRUE
A8: 45545 | B8: MAA009 | C8: MAA009-5411 | D8: FG Maass | E8: Klawer | F8: Trusc Wireless | G8: 689 | H8: 0 | I8: 2 year | J8: 45024 | K8: 45024 | L8: TRUE
A9: 45545 | B9: MAA015 | C9: MAA015-7711 | D9: GS Maarman | E9: Lutzville | F9: Trusc Wireless | G9: 574 | H9: 0 | I9: 2 year | J9: 44618 | K9: 45348 | L9: TRUE
A10: 45545 | B10: MAA017 | C10: MAA017-8406 | D10: MM Maasdorp | E10: Lutzville | F10: Trusc Wireless | G10: 574 | H10: 0 | J10: 44608 | K10: 45338 | L10: FALSE
A11: 45545 | B11: MAA021 | C11: MAA021-18225 | D11: AJ Maasdorp | E11: Vredendal-exchange-vredex-acc-switch2 | F11: Trusc Fibre | G11: 574 | H11: 0 | I11: 2 year | J11: 45023 | K11: 45754 | L11: TRUE
A12: 45545 | B12: MAA026 | C12: MAA026-17576 | D12: P Maarman | E12: octotel_moorreesburg | F12: Octotel | G12: 804 | H12: 0 | I12: 1 Year | J12: 44601 | K12: 44966 | L12: TRUE
A13: 45545 | B13: MAA028 | C13: MAA028-11576 | D13: V Maass | E13: Olifantskop | F13: Trusc Wireless | G13: 344 | H13: 0 | I13: 2 year | J13: 44177 | K13: 45638 | L13: TRUE
A14: 45545 | B14: MAA028 | C14: MAA028-14245 | D14: V Maass | E14: Aasvoelkop-aasvoelkop-switch1 | F14: Frogfoot | G14: 1092 | H14: 0 | I14: 1 Year | J14: 44414 | K14: 44779 | L14: TRUE
A15: 45545 | B15: MAA032 | C15: MAA032-25561 | D15: D Maarman | E15: malms_gh-apa5 | F15: Trusc Wireless | G15: 350 | H15: 35 | I15: 2 year | J15: 45349 | K15: 46080 | L15: TRUE
A16: 45545 | B16: MAA035 | C16: MAA035-13601 | D16: AJH Maasdorp | E16: Okiep | F16: Trusc Wireless | G16: 574.5 | H16: 0 | I16: 2 year | J16: 45071 | K16: 45802 | L16: TRUE
A17: 45545 | B17: MAA037 | C17: MAA037-13667 | D17: W Maasdorp | E17: vdal_res-apa8 | F17: Trusc Wireless | G17: 574 | H17: 0 | I17: 2 year | J17: 44357 | K17: 45087 | L17: TRUE
A18: 45545 | B18: MAA038 | C18: MAA038-13918 | D18: S Maass | E18: vdal_north-apa1 | F18: Trusc Wireless | G18: 172 | H18: 0 | I18: 2 year | J18: 44382 | K18: 45112 | L18: TRUE
A19: 45546 | B19: MAA042 | C19: MAA042-14090 | D19: EM Maarman | E19: vdal_res-apa16 | F19: Trusc Wireless | G19: 399 | H19: 0 | I19: 2 year | J19: 45504 | K19: 46234 | L19: TRUE
A20: 45546 | B20: MAA044 | C20: MAA044-14271 | D20: W Maarman | E20: vlan10_graafwater-apa1 | F20: Trusc Wireless | G20: 250 | H20: 0 | I20: 2 year | J20: 45316 | K20: 46047 | L20: TRUE
A21: 45546 | B21: MAA046 | C21: MAA046-14594 | D21: JN Maarman | E21: Koekenaap | F21: Trusc Wireless | G21: 250 | H21: 0 | I21: 2 year | J21: 45186 | K21: 45917 | L21: TRUE
A22: 45546 | B22: MAA046 | C22: MAA046-26595 | D22: JN Maarman | E22: bitterfontein-apa4 | F22: Trusc Wireless | G22: 250 | H22: 0 | I22: 2 year | J22: 45411 | K22: 46141 | L22: TRUE
... A35: 45547 | B35: MAA066 | C35: MAA066-17304 | D35: CD Maarman | E35: kalbaskraal-apa1 | F35: Trusc Wireless | G35: 574 | H35: 0 | I35: 2 year | J35: 44572 | K35: 45302 | L35: TRUE
A36: 45547 | B36: MAA067 | C36: MAA067-17677 | D36: JL Maarman | E36: Vdal_res | F36: Trusc Wireless | G36: 574 | H36: 0 | I36: 2 year | J36: 28 Okt 2022 | K36: 28 Okt 2024 | L36: TRUE
A37: 45547 | B37: MAA068 | C37: MAA068-17808 | D37: J Maarman | E37: vlan10_graafwater-apa1 | F37: Trusc Wireless | G37: 574 | H37: 0 | I37: 2 year | J37: 44602 | K37: 45332 | L37: TRUE
A38: 45547 | B38: MAA070 | C38: MAA070-18094 | D38: LH Maarman | E38: vlan110 - paardeberg_apa11 | F38: Trusc Wireless | G38: 689 | H38: 0 | I38: 2 year | J38: 44890 | K38: 45621 | L38: TRUE
A39: 45547 | B39: MAA071 | C39: MAA071-18120 | D39: G Maarman | E39: Oranjefontein | F39: Trusc Wireless | G39: 299 | H39: 0 | I39: 2 year | J39: 45359 | K39: 46089 | L39: TRUE
A40: 45547 | B40: MAA073 | C40: MAA073-18867 | D40: A Maarman | E40: springbok2-apa20 | F40: Trusc Wireless | G40: 574 | H40: 0 | I40: 2 year | J40: 44700 | K40: 45431 | L40: TRUE
A41: 45547 | B41: MAA075 | C41: MAA075-19194 | D41: LJ Maarman | E41: Maskam | F41: Trusc Wireless | G41: 689 | H41: 0 | I41: 2 year | J41: 44734 | K41: 45465 | L41: TRUE
A42: 45547 | B42: MAA076 | C42: MAA076-19779 | D42: PJ Maarman | E42: eben-apa4 | F42: Trusc Wireless | G42: 459 | H42: 0 | I42: 2 year | J42: 44781 | K42: 45512 | L42: TRUE
A43: 45547 | B43: MAA077 | C43: MAA077-26455 | D43: ZC Maarman | E43: boberg-apa2 | F43: Trusc Wireless | G43: 350 | H43: 0 | I43: 2 year | J43: 45455 | K43: 45455 | L43: TRUE
A44: 45548 | B44: MAA078 | C44: MAA078-19988 | D44: FC Maarman | E44: Springbok 1 | F44: Trusc Wireless | G44: 574 | H44: 0 | I44: 2 year | J44: 44805 | K44: 45536 | L44: TRUE
A45: 45548 | B45: MAA079 | C45: MAA079-20602 | D45: M Maartens | E45: Dwarskersbos S/C | F45: Trusc Fibre | G45: 459 | H45: 0 | I45: 2 year | J45: 20 Okt 2022 | K45: 20 Okt 2024 | L45: TRUE
A46: 45548 | B46: MAA081 | C46: MAA081-21179 | D46: VSC Maasdorp | E46: Vdal North | F46: Trusc Wireless | G46: 459 | H46: 0 | I46: 2 year | J46: 44890 | K46: 45621 | L46: TRUE
A47: 45548 | B47: MAA082 | C47: MAA082-21415 | D47: R Maarman | E47: Lambex | F47: Trusc Wireless | G47: 574 | H47: 0 | I47: 2 year | J47: 44930 | K47: 45661 | L47: TRUE
A48: 45548 | B48: MAA084 | C48: MAA084-21507 | D48: CP Maarman | E48: Sishen | F48: Trusc Wireless | G48: 459 | H48: 0 | I48: 2 year | J48: 44935 | K48: 45666 | L48: TRUE
A49: 45548 | B49: MAA086 | C49: MAA086-21808 | D49: NT Maarman | E49: boberg-apa2 | F49: Trusc Wireless | G49: 459 | H49: 0 | I49: 2 year | J49: 44959 | K49: 45690 | L49: TRUE
A50: 45548 | B50: MAA087 | C50: MAA087-21879 | D50: M Maarman | E50: Synott | F50: Trusc Wireless | G50: 459 | H50: 0 | I50: 2 year | J50: 44964 | K50: 45695 | L50: TRUE
A51: 45548 | B51: MAA088 | C51: MAA088-22162 | D51: DJ Maarman | E51: Oranjefontein | F51: Trusc Wireless | G51: 574 | H51: 0 | I51: 2 year | J51: 44987 | K51: 45718 | L51: TRUE
A52: 45548 | B52: MAA089 | C52: MAA089-22176 | D52: JH Maarman | E52: piketberg-apa13 | F52: Trusc Wireless | G52: 574 | H52: 0 | I52: 2 year | J52: 44991 | K52: 45722 | L52: TRUE
A53: 45548 | B53: MAA091 | C53: MAA091-22500 | D53: R Maarman | E53: Maskam | F53: Trusc Wireless | G53: 344 | H53: 0 | I53: 2 year | J53: 45021 | K53: 45752 | L53: TRUE
A54: 45548 | B54: MAA094 | C54: MAA094-23810 | D54: DM Maarman | E54: Windpomp | F54: Trusc Wireless | G54: 350 | H54: 0 | I54: 2 year | J54: 22 Sept 2023 | K54: 22 Sept 2025 | L54: TRUE
A55: 45548 | B55: MAA095 | C55: MAA095-23927 | D55: SR Maartens | E55: wheatfields-switch1-ppp | F55: Trusc Fibre | G55: 574 | H55: 0 | I55: Current Terms | J55: 12 Okt 2023 | K55: 12 Okt 2023 | L55: TRUE
A56: 45548 | B56: MAA096 | C56: MAA096-24033 | D56: EN Maarman | E56: Oranjefontein | F56: Trusc Wireless | G56: 350 | H56: 0 | I56: 2 year | J56: 45258 | K56: 45989 | L56: TRUE
A57: 45548 | B57: MAA097 | C57: MAA097-24130 | D57: G Maarman | E57: piketberg-apa13 | F57: Trusc Wireless | G57: 250 | H57: 0 | I57: 2 year | J57: 45269 | K57: 46000 | L57: TRUE
A58: 45548 | B58: MAA098 | C58: MAA098-24228 | D58: RR Maarman | E58: Oranjefontein | F58: Trusc Wireless | G58: 350 | H58: 0 | I58: 2 year | J58: 45233 | K58: 45964 | L58: TRUE
A59: 45548 | B59: MAA100 | C59: MAA100-24343 | D59: RD Maarman | E59: Steelwater | F59: Trusc Wireless | G59: 350 | H59: 0 | I59: 2 year | J59: 45257 | K59: 45988 | L59: TRUE
A60: 45548 | B60: MAA102 | C60: MAA102-24901 | D60: M J Maarman | E60: bottlefontein-apa8 | F60: Trusc Wireless | G60: 350 | H60: 0 | I60: 2 year | J60: 45310 | K60: 46041 | L60: TRUE
A61: 45548 | B61: MAA103 | C61: MAA103-25189 | D61: PL Maarman | E61: goudmyn | F61: Trusc Wireless | G61: 350 | H61: 0 | I61: 2 year | J61: 45328 | K61: 46059 | L61: TRUE
A62: 45548 | B62: MAA104 | C62: MAA104-25434 | D62: L Maasdorp | E62: Graafwater | F62: Trusc Wireless | G62: 250 | H62: 0 | I62: 2 year | J62: 45343 | K62: 46074 | L62: TRUE
A63: 45548 | B63: MAA105 | C63: MAA105-25713 | D63: NK Maarman | E63: Eben | F63: Trusc Wireless | G63: 350 | H63: 0 | I63: 2 year | J63: 45362 | K63: 46092 | L63: TRUE
A64: 45548 | B64: MAA106 | C64: MAA106-25767 | D64: A Maarman | E64: boberg | F64: Trusc Wireless | G64: 250 | H64: 0 | I64: 2 year | J64: 45371 | K64: 46101 | L64: TRUE
A65: 45551 | B65: MAA107 | C65: MAA107-26054 | D65: YO Maarman | E65: Klipberg | F65: Trusc Wireless | G65: 350 | H65: 0 | I65: 2 year | J65: 45392 | K65: 46122 | L65: TRUE
A66: 45551 | B66: MAA108 | C66: MAA108-26201 | D66: CJ Maarman | E66: Duiwelskop | F66: Trusc Wireless | G66: 350 | H66: 0 | I66: 2 year | J66: 45406 | K66: 46136 | L66: TRUE
A67: 45551 | B67: MAA109 | C67: MAA109-26349 | D67: RJ Maarman | E67: Kalbaskraal | F67: Trusc Wireless | G67: 350 | H67: 0 | I67: 2 year | J67: 45421 | K67: 46151 | L67: TRUE
... A72: 45551 | B72: MAA116 | C72: MAA116-27977 | D72: MJ Maarman | E72: Vdal North | F72: Trusc Wireless | G72: 399 | H72: 35 | I72: 2 year | J72: 45534 | K72: 46264 | L72: TRUE
A73: 45551 | B73: MAA117 | C73: MAA117-28233 | D73: C Maarman | E73: Lambertsbay | F73: Trusc Wireless | G73: 399 | H73: 0 | I73: 2 year | J73: 45547 | K73: 46277 | L73: TRUE | M73: Sla saved billing still needed
A74: 45552 | B74: MAB006 | C74: MAB006-24021 | D74: DJ Mabank | E74: Oranjefontein | F74: Trusc Wireless | G74: 350 | H74: 0 | I74: 2 year | J74: 45248 | K74: 45979 | L74: TRUE
A75: 45552 | B75: MAB007 | C75: MAB007-26030 | D75: EA Mabona | E75: Oranjefontein | F75: Trusc Wireless | G75: 350 | H75: 0 | I75: 2 year | J75: 45403 | K75: 46133 | L75: TRUE
A76: 45552 | B76: MAB008 | C76: MAB008-26985 | D76: NS Mabuto | E76: Vdal North | F76: Trusc Wireless | G76: 349 | H76: 0 | I76: 2 year | J76: 45458 | K76: 46188 | L76: TRUE
A77: 45552 | B77: MAC004 | C77: MAC004-3272 | D77: AC Maclachlan | E77: deklip | F77: Trusc Wireless | G77: 804 | H77: 0 | I77: 2 year | J77: 44042 | K77: 44772 | L77: TRUE
A78: 45552 | B78: MAC005 | C78: MAC005-3493 | D78: CL Maclean | E78: anemone-apa8 | F78: Trusc Wireless | G78: 459 | H78: 0 | I78: 2 year | J78: 45028 | K78: 45759 | L78: TRUE
A79: 45552 | B79: MAC009 | C79: MAC009-19661 | D79: GA Maclachlan | E79: Bulshoek | F79: Trusc Wireless | G79: 2644 | H79: 0 | I79: 2 year | J79: 44775 | K79: 45506 | L79: TRUE
A80: 45552 | B80: MAC011 | C80: MAC011-4956 | D80: A Machelm | E80: Vdal North | F80: Trusc Wireless | G80: 495 | H80: 0 | I80: 2 year | J80: 43784 | K80: 44515 | L80: TRUE
A81: 45552 | B81: MAC013 | C81: MAC013-6913 | D81: CL Mackay | E81: Piketberg | F81: Trusc Wireless | G81: 1356 | H81: 0 | I81: 2 year | J81: 43594 | K81: 44325 | L81: TRUE
A82: 45552 | B82: MAC014 | C82: MAC014-10076 | D82: F Macgregor | E82: wittedrift-apa4 | F82: Trusc Wireless | G82: 574 | H82: 0 | I82: 2 year | J82: 44713 | K82: 45444 | L82: TRUE
A83: 45552 | B83: MAC015 | C83: MAC015-12078 | D83: NP Macilikishi | E83: Vdal North | F83: Trusc Wireless | G83: 574 | H83: 0 | I83: 2 year | J83: 44207 | K83: 44937 | L83: TRUE
A84: 45552 | B84: MAC017 | C84: MAC017-13276 | D84: N Macilikishi | E84: Vdal_res | F84: Trusc Wireless | G84: 250 | H84: 0 | I84: 2 year | J84: 45243 | K84: 45974 | L84: TRUE
A85: 45552 | B85: MAC020 | C85: MAC020-15574 | D85: SM Macart | E85: Nababeep | F85: Trusc Wireless | G85: 350 | H85: 0 | I85: 1 Year | J85: 45281 | K85: 46012 | L85: TRUE
... A88: 45552 | B88: MAC026 | C88: MAC026-20049 | D88: DA Macgregor | E88: Admiral Island-admiral-acc-switch5 | F88: Trusc Fibre | G88: 399 | H88: 0 | I88: 2 year | J88: 44803 | K88: 45534 | L88: TRUE
A89: 45552 | B89: MAC027 | C89: MAC027-20301 | D89: J Macmillan | E89: Veldrift Switching Centre-veldrift_sc-olt1_pon7 | F89: Trusc Fibre | G89: 399 | H89: 0 | I89: 2 year | J89: 01 Sept 2023 | K89: 01 Sept 2025 | L89: TRUE
A90: 45552 | B90: MAC030 | C90: MAC030-21395 | D90: A Mac Gregor | E90: Doornbaai | F90: Trusc Wireless | G90: 574 | H90: 0 | I90: 2 year | J90: 44917 | K90: 45648 | L90: TRUE
A91: 45552 | B91: MAC032 | C91: MAC032-23873 | D91: CL Macdonald | E91: Okiep | F91: Trusc Wireless | G91: 250 | H91: 0 | I91: 2 year | J91: 16 Okt 2023 | K91: 16 Okt 2025 | L91: TRUE
A92: 45552 | B92: MAC033 | C92: MAC033-24409 | D92: JM Machelm | E92: kalbaskraal-apa6 | F92: Trusc Wireless | G92: 350 | H92: 35 | I92: 2 year | J92: 45264 | K92: 45995 | L92: TRUE
A93: 45552 | B93: MAC034 | C93: MAC034-24535 | D93: PI Mactobi | E93: springbok1-apa10 | F93: Trusc Wireless | G93: 350 | H93: 0 | I93: 2 year | J93: 45271 | K93: 46002 | L93: TRUE
A94: 45552 | B94: MAC035 | C94: MAC035-24606 | D94: Kenneth Mackenzie Accounting PTY LTD | E94: Nivica-nivica-acc-switch3 | F94: Trusc Fibre | G94: 449 | H94: 0 | I94: 1 Year | J94: 45473 | K94: 45838 | L94: TRUE
A95: 45552 | B95: MAC036 | C95: MAC036-25719 | D95: LJ Machikie | E95: lutz-apa1 | F95: Trusc Wireless | G95: 350 | H95: 0 | I95: 2 year | J95: 45362 | K95: 46092 | L95: TRUE
A96: 45552 | B96: MAC037 | C96: MAC037-25792 | D96: ME Machabe | E96: Synott | F96: Trusc Wireless | G96: 250 | H96: 0 | I96: 2 year | J96: 45369 | K96: 46099 | L96: TRUE
A97: 45552 | B97: MAC038 | C97: MAC038-26020 | D97: T Macheli | E97: Engels | F97: Trusc Wireless | G97: 250 | H97: 0 | I97: 2 year | J97: 45407 | K97: 46137 | L97: TRUE
A98: 45552 | B98: MAC039 | C98: MAC039-26680 | D98: SE Mac Gregor | E98: Admiral Island | F98: Trusc Fibre | G98: 399 | H98: 0 | I98: 1 Year | J98: 45434 | K98: 46164 | L98: TRUE
A99: 45552 | B99: MAC040 | C99: MAC040-26870 | D99: N Machakaire | E99: Oranjefontein | F99: Trusc Wireless | G99: 449 | H99: 35 | I99: 2 year | J99: 45446 | K99: 46176 | L99: TRUE
A100: 45552 | B100: MAD003 | C100: MAD003-16151 | D100: MLC Madini | E100: Nababeep | F100: Trusc Wireless | G100: 350 | H100: 0 | I100: 2 year | J100: 45252 | K100: 45983 | L100: TRUE
A101: 45552 | B101: MAD006 | C101: MAD006-20774 | D101: LA Madoena | E101: Clan | F101: Trusc Wireless | G101: 574 | H101: 0 | I101: 2 year | J101: 44879 | K101: 45610 | L101: TRUE
A102: 45552 | B102: MAD007 | C102: MAD007-22938 | D102: S Madikane | E102: Vdal_res | F102: Trusc Wireless | G102: 459 | H102: 0 | I102: 2 year | J102: 45097 | K102: 45828 | L102: TRUE
A103: 45552 | B103: MAD008 | C103: MAD008-25226 | D103: N Madlebe | E103: Rooidraai | F103: Trusc Wireless | G103: 350 | H103: 0 | I103: 2 year | J103: 45329 | K103: 46060 | L103: TRUE
... A106: 45552 | B106: MAD012 | C106: MAD012-28215 | D106: A Madrae | E106: Aasvoelkop SC | F106: Trusc Wireless | G106: 399 | H106: 0 | I106: 2 year | J106: 45556 | K106: 46286 | L106: TRUE
A107: 45552 | B107: MAE001 | C107: MAE001-15909 | D107: G Maerman | E107: Maskam | F107: Trusc Wireless | G107: 350 | H107: 0 | I107: 2 year | J107: 12 Okt 2023 | K107: 12 Okt 2025 | L107: TRUE
A108: 45552 | B108: MAE002 | C108: MAE002-24723 | D108: A Maerman | E108: Klawer-Res | F108: Trusc Wireless | G108: 350 | H108: 0 | I108: 2 year | J108: 45292 | K108: 46023 | L108: TRUE
A109: 45552 | B109: MAF001 | C109: MAF001-26864 | D109: K Mafuxwana | E109: kalbaskraal-apa6 | F109: Trusc Wireless | G109: 349 | H109: 0 | I109: 2 year | J109: 45453 | K109: 46183 | L109: TRUE
A110: 45552 | B110: MAG003 | C110: MAG003-5348 | D110: D Magerman | E110: Koraan | F110: Trusc Wireless | G110: 459 | H110: 0 | I110: 2 year | J110: 43679 | K110: 44410 | L110: TRUE | M110: Recovery
A111: 45552 | B111: MAG004 | C111: MAG004-7144 | D111: IC Magerman | E111: Nababeep | F111: Trusc Wireless | G111: 804 | H111: 0 | I111: 2 year | J111: 43630 | K111: 44361 | L111: TRUE
A112: 45552 | B112: MAG005 | C112: MAG005-7208 | D112: BL Magadla | E112: voorberg-apa6 | F112: Trusc Wireless | G112: 229 | H112: 0 | I112: 2 year | J112: 43699 | K112: 44430 | L112: TRUE
A113: 45552 | B113: MAG006 | C113: MAG006-9646 | D113: WV Magerman | E113: Nababeep | F113: Trusc Wireless | G113: 350 | H113: 0 | I113: 2 year | J113: 45236 | K113: 45967 | L113: TRUE
A114: 45552 | B114: MAG007 | C114: MAG007-10198 | D114: MS Maggot | E114: Nababeep | F114: Trusc Wireless | G114: 349 | H114: 0 | I114: 2 year | J114: 45449 | K114: 46179 | L114: TRUE
A115: 45552 | B115: MAG009 | C115: MAG009-13998 | D115: AR Magerman | E115: Koraan | F115: Trusc Wireless | G115: 459 | H115: 0 | I115: 2 year | J115: 44389 | K115: 45119 | L115: TRUE
A116: 45552 | B116: MAG012 | C116: MAG012-17465 | D116: S Maggott | E116: Nababeep | F116: Trusc Wireless | G116: 344 | H116: 0 | I116: 2 year | J116: 44575 | K116: 45305 | L116: TRUE
A117: 45552 | B117: MAG013 | C117: MAG013-17574 | D117: CR Maggott | E117: Nababeep | F117: Trusc Wireless | G117: 574 | H117: 0 | I117: 2 year | J117: 44581 | K117: 45311 | L117: TRUE
A118: 45552 | B118: MAG016 | C118: MAG016-19640 | D118: WV Magerman | E118: Nababeep | F118: Trusc Wireless | G118: 250 | H118: 0 | I118: 2 year | J118: 45238 | K118: 45969 | L118: TRUE
A119: 45552 | B119: MAG017 | C119: MAG017-19724 | D119: SD Magerman | E119: Goudmyn | F119: Trusc Wireless | G119: 574 | H119: 0 | I119: 2 year | J119: 44781 | K119: 45512 | L119: TRUE
A120: 45552 | B120: MAG018 | C120: MAG018-19745 | D120: VJ Magerman | E120: Okiep | F120: Trusc Wireless | G120: 574 | H120: 0 | I120: 2 year | J120: 44783 | K120: 45514 | L120: TRUE
...

Sheet Clients (Q - T)
B1: =COUNTA(B4:B1977) -> 1974 | C1: =COUNTIF(C4:C1977,"?*") -> 1033
A2: Date | B2: Client Account | C2: Client Reference | D2: Client name | E2: Highsite / SC | F2: Type | G2: ISPMan Premium | H2: ISPMan EFT Fee | I2: Contract Duration | J2: Install Date | K2: Contract Expiry | L2: Have Contract
B3: ABC001 | C3: ABC001-12345 | D3: Mr Joe Soap | E3: Dwarskersbos S/C | F3: Trusc Wireless | I3: 1 Year | K3: 45626 | L3: TRUE | M3: Example line
A4: 45558 | B4: QAN001 | C4: QAN001-25743 | D4: RP Qanetsi | E4: Oranjefontein | F4: Trusc Wireless | G4: 350 | H4: 0 | I4: 2 year | J4: 45364 | K4: 46094 | L4: TRUE
A5: 45558 | B5: QHA001 | C5: QHA001-1039 | D5: Qhayisa en Richmond Pre School | E5: Vdal_res | F5: Trusc Wireless | G5: 350 | H5: 0 | I5: 2 year | J5: 1 Desember 2023 | K5: 1 Desember 2025 | L5: TRUE
A6: 45558 | B6: QHI001 | C6: QHI001-27778 | D6: BJ Qhive | E6: mekano-apa7 | F6: Trusc Wireless | G6: 399 | H6: 0 | I6: 2 year | J6: 45511 | K6: 46241 | L6: TRUE
A7: 45558 | B7: QHU001 | C7: QHU001-25093 | D7: N Qhuza | E7: vlan109_oranjefontein-ap10_C-ppp | F7: Trusc Wireless | G7: 350 | H7: 0 | I7: 2 year | J7: 45334 | K7: 45334 | L7: TRUE
A8: 45558 | B8: QOM002 | C8: QOM002-26027 | D8: SG Qomoyi | E8: kabiscouw | F8: Trusc Wireless | G8: 575 | H8: 0 | I8: 2 year | J8: 45396 | K8: 46126 | L8: TRUE
A9: 45558 | B9: QUA002 | C9: QUA002-19352 | D9: Quantum Forklifts | E9: Steelwater | F9: Trusc Wireless | G9: 1149 | H9: 0 | I9: 2 year | J9: 44743 | K9: 45474 | L9: FALSE
A10: 45558 | B10: QUA005 | C10: QUA005-20670 | D10: BA Quayle | E10: Veldrift S/C | F10: Trusc Fibre | G10: 399 | H10: 0 | I10: 2 year | J10: 45155 | K10: 45886 | L10: TRUE
A11: 45558 | B11: QUI002 | C11: QUI002-13083 | D11: CC Quill | E11: Tallie Marine | F11: Trusc Wireless | G11: 399 | H11: 0 | I11: 2 year | J11: 45517 | K11: 46247 | L11: TRUE
A12: 45558 | B12: QUI003 | C12: QUI003-19476 | D12: Quickstep 668(PTY)Ltd | E12: St Helena | F12: Trusc Wireless | G12: 574 | H12: 0 | I12: 1 Year | J12: 44774 | K12: 45139 | L12: FALSE
A13: 45558 | B13: QUI004 | C13: QUI004-19814 | D13: DD Quill | E13: Octotel_Ruyterwacht | F13: Octotel | G13: 804 | H13: 0 | I13: 1 Year | J13: 44799 | K13: 45164 | L13: FALSE
A14: 45558 | B14: QUI006 | C14: QUI006-23070 | D14: W Quickfall | E14: Nababeep | F14: Trusc Wireless | G14: 574 | H14: 0 | I14: 2 year | J14: 45115 | K14: 45846 | L14: TRUE
A15: 45558 | B15: QUN001 | C15: QUN001-24508 | D15: CY Qunya | E15: retshof | F15: Trusc Wireless | G15: 350 | H15: 0 | I15: 2 year | J15: 45270 | K15: 46001 | L15: TRUE
A16: 45558 | B16: QUP001 | C16: QUP001-17080 | D16: NV Qupe | E16: Vdal_res | F16: Trusc Wireless | G16: 344 | H16: 35 | I16: 2 year | J16: 44549 | K16: 45279 | L16: FALSE
A17: 45579 | B17: QUI007 | C17: QUI007-28333 | D17: AJ Quirinano | E17: Kalbaskraal | F17: Trusc Wireless | G17: 399 | H17: 35 | I17: 2 year | J17: 45564 | K17: 46294 | L17: TRUE
A18: 45558 | B18: RAA002 | C18: RAA002-1297 | D18: PS Raad | E18: Synott | F18: Trusc Wireless | G18: 344 | H18: 0 | I18: Month to Month | J18: 44132 | K18: 28 Oct 0222 | L18: FALSE
A19: 45558 | B19: RAA003 | C19: RAA003-2448 | D19: VE Raath | E19: Rilau | F19: Trusc Wireless | G19: 298 | H19: 0 | I19: 2 year | J19: 47295 | K19: 44373 | L19: FALSE
A20: 45558 | B20: RAA005 | C20: RAA005-5146 | D20: HJ Raage | E20: Koekenaap | F20: Trusc Wireless | G20: 0 | H20: 0 | I20: 2 year | J20: 44396 | K20: 45126 | L20: FALSE | M20: No pricing in ispman
A21: 45558 | B21: RAA005 | C21: RAA005-14536 | D21: HJ Raage | E21: Koekenaap | F21: Trusc Wireless | G21: 574 | H21: 0 | I21: 2 year | J21: 44412 | K21: 45142 | L21: FALSE
A22: 45558 | B22: RAA006 | C22: RAA006-5501 | D22: S Raad | E22: Clan | F22: Trusc Wireless | G22: 288 | I22: 2 year | J22: 44092 | K22: 44822 | L22: FALSE
A23: 45558 | B23: RAA007 | C23: RAA007-9888 | D23: ZK Raatus | E23: Koraan | F23: Trusc Wireless | G23: 459 | H23: 0 | I23: 2 year | J23: 44736 | K23: 45467 | L23: FALSE
A24: 45558 | B24: RAA012 | C24: RAA012-16269 | D24: GJ Raaths | E24: olive_place-SC | F24: Trusc Fibre | G24: 632 | H24: 0 | I24: 1 Year | J24: 44525 | K24: 45255 | L24: FALSE
A25: 45558 | B25: RAB008 | C25: RAB008-26170 | D25: CJ Martin | E25: Vdal North | F25: Trusc Wireless | G25: 350 | H25: 0 | I25: 2 year | J25: 45410 | K25: 46140 | L25: TRUE
A26: 45558 | B26: RAB009 | C26: RAB009-17076 | D26: J Rabie | E26: Goudmyn | F26: Trusc Wireless | G26: 350 | H26: 35 | I26: 2 year | J26: 45399 | K26: 46129 | L26: TRUE
A27: 45558 | B27: RAB010 | C27: RAB010-17208 | D27: AA Rabe | E27: Goudmyn | F27: Trusc Wireless | G27: 350 | H27: 0 | I27: 1 Year | J27: 45281 | K27: 45647 | L27: TRUE
A28: 45558 | B28: RAB012 | C28: RAB012-25314 | D28: C Rabie | E28: lm_bakwerke | F28: Trusc Wireless | G28: 350 | H28: 0 | I28: 2 year | J28: 45336 | K28: 46067 | L28: TRUE
A29: 45558 | B29: RAB013 | C29: RAB013-26845 | D29: ES Rabe | E29: Klipberg | F29: Trusc Wireless | G29: 449 | H29: 0 | I29: 2 year | J29: 45438 | K29: 46168 | L29: TRUE
A30: 45558 | B30: RAC001 | C30: RAC001-3767 | D30: SP Rack | E30: Laaiplek | F30: Trusc Fibre | G30: 1149 | H30: 0 | I30: 2 year | J30: 44616 | K30: 45346 | L30: FALSE
A31: 45558 | B31: RAD007 | C31: RAD007-14606 | D31: AF Rademeyer | E31: Bitterfontein | F31: Trusc Wireless | G31: 977 | H31: 0 | I31: 2 year | J31: 44538 | K31: 45268 | L31: FALSE
A32: 45558 | B32: RAD008 | C32: RAD008-14690 | D32: D Radloff | E32: Vdal North | F32: Trusc Wireless | G32: 459 | H32: 0 | I32: 2 year | J32: 44427 | K32: 45157 | L32: FALSE
A33: 45558 | B33: RAD009 | C33: RAD009-15087 | D33: J Radyn | E33: Blouwater | F33: Trusc Wireless | G33: 804 | H33: 0 | I33: 2 year | J33: 44447 | K33: 45177 | L33: FALSE
A34: 45558 | B34: RAD011 | C34: RAD011-17945 | D34: TN Radebe | E34: Voorberg | F34: Trusc Wireless | G34: 804 | H34: 0 | I34: 2 year | J34: 44622 | K34: 45353 | L34: FALSE
... A60: 45560 | B60: RAS011 | C60: RAS011-25775 | D60: JM Ras | E60: lag-21:115.1280196.43.47.2 | F60: Openserve | G60: 699 | H60: 0 | I60: 2 year | J60: 45370 | K60: 46100 | L60: TRUE
A61: 45560 | B61: RAU003 | C61: RAU003-4773 | D61: JN Raubenheimer | E61: lutzkerk-apa3 | F61: Trusc Wireless | G61: 804 | H61: 0 | I61: 2 year | J61: 45359 | K61: 0/03/2026 | L61: TRUE
A62: 45560 | B62: RAU005 | C62: RAU005-26723 | D62: IG Rautenbach | E62: Piketberg | F62: Openserve | G62: 699 | H62: 0 | I62: 1 Year | J62: 45452 | K62: 46182 | L62: TRUE
A63: 45560 | B63: RAU008 | C63: RAU008-20098 | D63: CV Rauch | E63: Paardeberg | F63: Trusc Wireless | G63: 689 | H63: 0 | I63: 2 year | J63: 44820 | K63: 45551 | L63: TRUE
A64: 45560 | B64: RAU009 | C64: RAU009-27096 | D64: R Rautenbach | E64: Nivica | F64: Trusc Fibre | G64: 499 | H64: 0 | I64: 1 Year | J64: 45456 | K64: 45821 | L64: TRUE
A65: 45560 | B65: RAY003 | C65: RAY003-15896 | D65: BK Raymond | E65: Okiep | F65: Trusc Wireless | G65: 399 | H65: 0 | I65: 2 Year | J65: 45477 | K65: 46207 | L65: TRUE
A66: 45560 | B66: RAY004 | C66: RAY004-16371 | D66: TC Raymond | E66: Okiep | F66: Trusc Wireless | G66: 350 | H66: 35 | I66: 2 year | J66: 45264 | K66: 45995 | L66: TRUE
A67: 45560 | B67: RAY006 | C67: RAY006-19464 | D67: JH Raymond | E67: Okiep | F67: Trusc Wireless | G67: 799 | H67: 0 | I67: 2 year | J67: 45491 | K67: 46221 | L67: TRUE
A68: 45560 | B68: RAY007 | C68: RAY007-25801 | D68: JJ Raymond | E68: Springbok | F68: Trusc Wireless | G68: 350 | H68: 0 | I68: 2 year | J68: 45372 | K68: 46102 | L68: TRUE
A69: 45560 | B69: RAY008 | C69: RAY008-26986 | D69: ZR Raymond | E69: Lewerberg | F69: Trusc Wireless | G69: 349 | H69: 0 | I69: 2 year | J69: 45462 | K69: 46192 | L69: TRUE
A70: 45560 | B70: RED001 | C70: RED001-2318 | D70: Red Sage Properties | E70: urionskraal | F70: Trusc Wireless | G70: 977 | H70: 0 | I70: 2 year | J70: 44732 | K70: 45463 | L70: TRUE
A71: 45561 | B71: RED002 | C71: RED002-17741 | D71: Red Ribbon Communications CC | E71: Koringberg | F71: Trusc Wireless | G71: 1149 | H71: 35 | I71: 2 year | J71: 44593 | K71: 45323 | L71: TRUE
A72: 45561 | B72: RED007 | C72: RED007-15709 | D72: VG Redpath | E72: Clan | F72: Trusc Wireless | G72: 344 | H72: 0 | I72: 2 year | J72: 44495 | K72: 45225 | L72: TRUE
A73: 45561 | B73: RED009 | C73: RED009-19505 | D73: CC Reddy | E73: vlan601_innidippie-switch1-PPP | F73: Trusc Fibre | G73: 574 | H73: 0 | I73: 1 Year | J73: 44763 | K73: 45128 | L73: TRUE
... A83: 45561 | B83: REI013 | C83: REI013-23678 | D83: H Reinders | E83: Nivica | F83: Trusc Fibre | G83: 399 | H83: 0 | I83: 1 Year | J83: 45476 | K83: 46206 | L83: TRUE
A84: 45561 | B84: REL001 | C84: REL001-28059 | D84: JA Relf | E84: Velddrift | F84: Trusc Fibre | G84: 449 | H84: 0 | I84: 2 year | L84: TRUE | M84: Client still need to be installed
A85: 45561 | B85: REN002 | C85: REN002-22608 | D85: M Rensburg | E85: Oranjefontein | F85: Trusc Wireless | G85: 574 | H85: 35 | I85: 2 year | J85: 45411 | K85: 45776 | L85: TRUE
A86: 45561 | B86: RES002 | C86: RES002-9929 | D86: C Resandt | E86: Modderfontein | F86: Trusc Wireless | G86: 574 | H86: 0 | I86: 2 year | J86: 44740 | K86: 45471 | L86: TRUE
A87: 45561 | B87: RES004 | C87: RES004-10588 | D87: HP Resandt | E87: Modderfontein | F87: Trusc Wireless | G87: 574 | H87: 0 | I87: 2 year | J87: 44036 | K87: 44766 | L87: TRUE
A88: 45561 | B88: RET001 | C88: RET001-451 | D88: Monotonka Boerdery | E88: koekrep-apa2 | F88: Trusc Wireless | G88: 816 | H88: 0 | I88: 2 year | J88: 43363 | K88: 44094 | L88: TRUE
A89: 45561 | B89: RET006 | C89: RET006-4043 | D89: PJ Retief Trust | E89: Doornbaai | F89: Trusc Wireless | G89: 344 | H89: 0 | I89: 2 year | J89: 44105 | K89: 44835 | L89: TRUE
A90: 45561 | B90: RET007 | C90: RET007-7352 | D90: E Retief | E90: watertower-apa3 | F90: Trusc Wireless | G90: 229 | H90: 0 | I90: 2 year | J90: 43649 | K90: 44442 | L90: TRUE
A91: 45561 | B91: RET008 | C91: RET008-18461 | D91: T Retief | E91: Rilau | F91: Trusc Wireless | G91: 350 | H91: 0 | I91: 2 year | J91: 45334 | K91: 46065 | L91: TRUE
A92: 45561 | B92: RET009 | C92: RET009-22948 | D92: Venkorp Retailers CC | E92: Velddrift | F92: Trusc Fibre | G92: 344 | H92: 0 | I92: 2 year | J92: 45100 | K92: 45831 | L92: TRUE
A93: 45561 | B93: REY005 | C93: REY005-10093 | D93: JJ Reynolds | E93: Clan | F93: Trusc Wireless | G93: 804 | H93: 0 | I93: 2 year | J93: 44763 | K93: 45494 | L93: TRUE
A94: 45561 | B94: REY006 | C94: REY006-14906 | D94: MJ Reyneke | E94: rooiheuwel-apa7 | F94: Trusc Wireless | G94: 799 | H94: 0 | I94: 2 year | J94: 45448 | K94: 46178 | L94: TRUE
A95: 45561 | B95: REY008 | C95: REY008-21276 | D95: J Reyneke | E95: Windpomp | F95: Trusc Wireless | G95: 499.5 | H95: 0 | I95: 2 year | J95: 45552 | K95: 46282 | L95: TRUE
A96: 45561 | B96: REY008 | C96: REY008-23151 | D96: J Reyneke | E96: Lambertsbay | F96: Trusc Wireless | G96: 399.5 | H96: 0 | I96: 2 year | J96: 45547 | K96: 45547 | L96: TRUE
... A118: 45565 | B118: RIC010 | C118: RIC010-10424 | D118: Rick Brown Associates | E118: Jacobsbaai | F118: Trusc Wireless | G118: 804 | H118: 0 | I118: 2 year | J118: 44016 | K118: 44746 | L118: TRUE
A119: 45565 | B119: RIC012 | C119: RIC012-10615 | D119: M Richard | E119: Vdal_res | F119: Trusc Wireless | G119: 349 | H119: 35 | I119: 2 year | J119: 24 Jul 0202 | K119: 44766 | L119: TRUE
A120: 45565 | B120: RIC013 | C120: RIC013-17417 | D120: NM Rickert | E120: eben | F120: Trusc Wireless | G120: 350 | H120: 0 | I120: 2 year | J120: 45321 | K120: 46052 | L120: TRUE
A121: 45565 | B121: RIC014 | C121: RIC014-13082 | D121: RI Richens | E121: Piketberg | F121: Trusc Wireless | G121: 1149 | H121: 0 | I121: 2 year | J121: 44333 | K121: 45063 | L121: TRUE
A122: 45565 | B122: RIC018 | C122: RIC018-17748 | D122: JM Richards | E122: Lutzville | F122: Trusc Wireless | G122: 689 | H122: 0 | I122: 2 year | J122: 44601 | K122: 45331 | L122: TRUE
A123: 45566 | B123: RIC020 | C123: RIC020-18752 | D123: C Richards | E123: Okiep | F123: Trusc Wireless | G123: 574 | H123: 0 | I123: 2 year | J123: 44691 | K123: 45422 | L123: TRUE
A124: 45566 | B124: RIC021 | C124: RIC021-20177 | D124: CA Richards | E124: Okiep | F124: Trusc Wireless | G124: 350 | H124: 0 | I124: 2 year | J124: 44659 | K124: 45390 | L124: TRUE
A125: 45566 | B125: RIC022 | C125: RIC022-22324 | D125: J Rich | E125: Nababeep | F125: Trusc Wireless | G125: 574 | H125: 0 | I125: 2 year | J125: 45003 | K125: 45734 | L125: TRUE
A126: 45566 | B126: RIC023 | C126: RIC023-23417 | D126: MJ Richard | E126: Maskam | F126: Trusc Wireless | G126: 350 | H126: 0 | I126: 2 year | J126: 45179 | K126: 45910 | L126: TRUE
A127: 45566 | B127: RIC024 | C127: RIC024-25823 | D127: BS Richards | E127: Lutzville | F127: Trusc Wireless | G127: 350 | H127: 35 | I127: 2 year | J127: 45366 | K127: 46096 | L127: TRUE
A128: 45568 | B128: RIC025 | C128: RIC025-26246 | D128: CG Richards | E128: Clan | F128: Trusc Wireless | G128: 350 | H128: 0 | I128: 2 year | J128: 45428 | K128: 46158 | L128: TRUE
A129: 45568 | B129: RID002 | C129: RID002-14298 | D129: JJ Riddles | E129: Maskam | F129: Trusc Wireless | G129: 350 | H129: 0 | I129: 2 year | J129: 45309 | K129: 46040 | L129: TRUE
A130: 45568 | B130: RIE006 | C130: RIE006-10767 | D130: AJ Riedemann | E130: eland | F130: Trusc Wireless | G130: 344 | H130: 35 | I130: 2 year | J130: 44833 | K130: 45564 | L130: TRUE
A131: 45568 | B131: RIE007 | C131: RIE007-12478 | D131: EM Riekert | E131: langebaan | F131: Openserve | G131: 977 | H131: 0 | I131: 1 Year | J131: 44247 | K131: 44977 | L131: TRUE
... A141: 45568 | B141: ROB018 | C141: ROB018-27607 | D141: GL Robinson | E141: saron | F141: Trusc Wireless | G141: 299 | H141: 0 | I141: 2 year | J141: 45503 | K141: 46233 | L141: TRUE
A142: 45568 | B142: ROB024 | C142: ROB024-22276 | D142: D Robinson | E142: Velddrift | F142: Trusc Fibre | G142: 399 | H142: 0 | I142: 2 year | J142: 6 Aug 0202 | K142: 46240 | L142: TRUE
A143: 45569 | B143: ROB027 | C143: ROB027-15979 | D143: AM Robinson-Blankenberg | E143: bottlefontein | F143: Trusc Wireless | G143: 344 | H143: 0 | I143: 2 year | J143: 44503 | K143: 45233 | L143: TRUE
A144: 45569 | B144: ROB028 | C144: ROB028-17222 | D144: YN Robyn | E144: voight | F144: Trusc Wireless | G144: 574 | H144: 0 | I144: 2 year | J144: 44574 | K144: 45304 | L144: TRUE
A145: 45569 | B145: ROB031 | C145: ROB031-20328 | D145: CM Robinson | E145: Laaiplek | F145: Trusc Fibre | G145: 249 | H145: 0 | I145: 2 year | J145: 45562 | K145: 46292 | L145: TRUE
A146: 45569 | B146: ROB033 | C146: ROB033-21986 | D146: RC Robinson | E146: Rooidraai | F146: Trusc Wireless | G146: 344 | H146: 0 | I146: 2 year | J146: 44968 | K146: 45699 | L146: TRUE
A147: 45569 | B147: ROB035 | C147: ROB035-24172 | D147: HF Robinson | E147: bottlefontein | F147: Trusc Wireless | G147: 350 | H147: 0 | I147: 2 year | J147: 45244 | K147: 45975 | L147: TRUE
A148: 45569 | B148: ROB036 | C148: ROB036-24696 | D148: K S Robertson | E148: Kransvlei | F148: Trusc Wireless | G148: 350 | H148: 0 | I148: 2 year | J148: 45295 | K148: 46026 | L148: TRUE
A149: 45572 | B149: ROB037 | C149: ROB037-24842 | D149: JJ Roberts | E149: Okiep | F149: Trusc Wireless | G149: 250 | H149: 35 | I149: 2 year | J149: 45301 | K149: 46063 | L149: TRUE
A150: 45572 | B150: ROC003 | C150: ROC003-3432 | D150: Rock Ridge Manor PTY Ltd | E150: turner | F150: Trusc Wireless | G150: 1149 | H150: 0 | I150: 2 year | J150: 45315 | K150: 46046 | L150: TRUE
A151: 45572 | B151: ROC003 | C151: ROC003-4076 | D151: Rock Ridge Manor PTY Ltd | E151: kabiscouw | F151: Trusc Wireless | G151: 350 | H151: 0 | I151: 2 year | J151: 45315 | K151: 46046 | L151: TRUE
A152: 45572 | B152: ROC004 | C152: ROC004-6951 | D152: N Rocher | E152: vlan229-rooidraai-apa22_C-ppp | F152: Trusc Wireless | G152: 804 | H152: 0 | I152: 2 year | J152: 44803 | K152: 45534 | L152: TRUE
A153: 45572 | B153: ROC005 | C153: ROC005-26546 | D153: BF Rocher | E153: Dwarskersbos S/C | F153: Trusc Fibre | G153: 499 | H153: 0 | I153: 2 year | J153: 44485 | K153: 45215 | L153: TRUE
A154: 45572 | B154: ROC005 | C154: ROC005-7261 | D154: BF Rocher | E154: Rooidraai | F154: Trusc Wireless | G154: 459 | H154: 0 | I154: 2 year | J154: 43622 | K154: 44353 | L154: TRUE
... A167: 45572 | B167: ROE016 | C167: ROE016-22711 | D167: WA Roems | E167: Vdal_res | F167: Trusc Wireless | G167: 689 | H167: 0 | I167: 2 year | J167: 45057 | K167: 45788 | L167: TRUE
A168: 45572 | B168: ROE017 | D168: RJ Roestof | L168: FALSE | M168: CLIENT LEGALLED
A169: 45572 | B169: ROE019 | C169: ROE019-27887 | D169: M Roelofse | E169: Dwarskersbos S/C | F169: Trusc Wireless | G169: 449 | H169: 0 | I169: 1 Year | J169: 45526 | K169: 46256 | L169: TRUE
A170: 45572 | B170: ROH002 | C170: ROH002-19057 | D170: M Rohm | E170: Water Tower | F170: Trusc Wireless | G170: 689 | H170: 0 | I170: 2 year | J170: 44720 | K170: 45451 | L170: TRUE
A171: 45572 | B171: ROL001 | C171: ROL001-20797 | D171: MB Rollison | E171: Oranjefontein | F171: Trusc Wireless | G171: 574 | H171: 0 | I171: 2 year | J171: 44876 | K171: 44876 | L171: TRUE
A172: 45572 | B172: ROM004 | C172: ROM004-28113 | D172: CJ Romain | E172: Aasvoelkop SC | F172: Openserve | G172: 804 | H172: 0 | I172: 2 year | J172: 45533 | K172: 46263 | L172: TRUE
A173: 45572 | B173: ROM005 | D173: GC Roman | L173: FALSE | M173: Client in Recovery
A174: 45572 | B174: ROM011 | C174: ROM011-21649 | D174: R Romani | E174: Velddrift | F174: Trusc Wireless | G174: 399 | H174: 0 | I174: 2 year | J174: 45157 | K174: 45157 | L174: TRUE
A175: 45573 | B175: ROM012 | C175: ROM012-23617 | D175: LR Roman | E175: Duiwelskop | F175: Trusc Wireless | G175: 350 | H175: 0 | I175: 2 year | J175: 45209 | K175: 45940 | L175: TRUE
A176: 45573 | B176: ROM014 | C176: ROM014-23850 | D176: J Roman | E176: saron | F176: Trusc Wireless | G176: 350 | H176: 0 | I176: 2 year | J176: 45219 | K176: 45950 | L176: TRUE
...

Sheet Clients (U - V)
B1: =COUNTA(B4:B1104) -> 1101 | C1: =COUNTIF(C4:C1104,"?*") -> 117
A2: Date | B2: Client Account | C2: Client Reference | D2: Client name | E2: Highsite / SC | F2: Type | G2: ISPMan Premium | H2: ISPMan EFT Fee | I2: Contract Duration | J2: Install Date | K2: Contract Expiry | L2: Have Contract
B3: ABC001 | C3: ABC001-12345 | D3: Mr Joe Soap | E3: Dwarskersbos S/C | F3: Trusc Wireless | I3: 1 Year | K3: 45626 | L3: TRUE | M3: Example line
A4: 45548 | B4: UDD001 | C4: UDD001-14796 | D4: J Uddin | E4: Nababeep | F4: Trusc Wireless | G4: 350 | H4: 0 | I4: 2 year | J4: 45338 | K4: 46069 | L4: TRUE
A5: 45548 | B5: UDD001 | C5: UDD001-25436 | D5: J Uddin | E5: Nababeep | F5: Trusc Wireless | G5: 350 | H5: 0 | I5: 2 year | J5: 45343 | K5: 46074 | L5: TRUE
A6: 45548 | B6: UDD003 | C6: UDD003-27636 | D6: M Uddin | E6: Okiep | F6: Trusc Wireless | G6: 299 | H6: 0 | I6: 2 year | J6: 45524 | K6: 46254 | L6: TRUE
A7: 45548 | B7: UIL001 | C7: UIL001-6618 | D7: Uilenkraal Pty Ltd | E7: Klipberg | F7: Trusc Wireless | G7: 689 | H7: 0 | I7: 2 year | J7: 43572 | K7: 44303 | L7: TRUE
A8: 45548 | B8: UIL001 | C8: UIL001-6632 | D8: Uilenkraal Pty Ltd | E8: Klipberg | F8: Trusc Wireless | G8: 1207 | H8: 0 | I8: 2 year | J8: 43629 | K8: 44360 | L8: TRUE
A9: 45548 | B9: UIL002 | C9: UIL002-24726 | D9: Uilenkraal Pty Ltd | E9: koringberg | F9: Trusc Wireless | G9: 350 | H9: 0 | I9: 2 year | J9: 45284 | K9: 45650 | L9: TRUE
A10: 45548 | B10: UIT004 | C10: UIT004-11046 | D10: Uitkyk Boerdery | E10: klipberg | F10: Trusc Wireless | G10: 804 | H10: 0 | I10: 2 year | J10: 44862 | K10: 45593 | L10: TRUE
A11: 45548 | B11: ULT001 | C11: ULT001-10437 | D11: 3 Ts Media Pty Ltd ta Ultimate Media | E11: koringberg | F11: Trusc Wireless | G11: 804 | H11: 0 | I11: 2 year | J11: 44778 | K11: 45509 | L11: TRUE
A12: 45548 | B12: UMA001 | C12: UMA001-13237 | D12: A Umans | E12: sh (saldanha Heights) | F12: Trusc Wireless | G12: 574 | H12: 0 | I12: 2 year | J12: 44320 | K12: 45050 | L12: TRUE
A13: 45548 | B13: UMA002 | C13: UMA002-17601 | D13: Marlene Umans | E13: deklip | F13: Trusc Wireless | G13: 449 | H13: 0 | I13: 2 year | J13: 45429 | K13: 46159 | L13: TRUE
A14: 45548 | B14: UMO001 | C14: UMO001-3900 | D14: Umoya Energy (RF)(PTY) LTD | E14: vlan200_umoya-fibre-ppp | F14: Trusc Wireless | G14: 11250.04 | H14: 0 | I14: Corporate Billing | L14: TRUE
A15: 45548 | B15: UMZ001 | C15: UMZ001-3617 | D15: Umzamani Fishing cc | E15: None | F15: Trusc Wireless | G15: 816 | H15: 0 | I15: 2 year | J15: 42846 | K15: 43576 | L15: TRUE
A16: 45548 | B16: UND001 | C16: UND001-26871 | D16: CCG Underwood | E16: None | F16: Trusc Fibre | G16: 499 | H16: 0 | I16: 2 year | J16: 45445 | K16: 46175 | L16: TRUE
A17: 45548 | B17: UNE001 | C17: UNE001-658 | D17: Uniekum Contracting PTY LTD | E17: leipoldtvillepop | F17: Trusc Wireless | G17: 344 | H17: 35 | I17: 2 year | J17: 44998 | K17: 45729 | L17: TRUE
A18: 45548 | B18: UNG001 | C18: UNG001-26415 | D18: M Ungerer | E18: None | F18: Trusc Fibre | G18: 399 | H18: 0 | I18: 2 year | J18: 45409 | K18: 46139 | L18: TRUE
A19: 45548 | B19: UNI005 | C19: UNI005-4801 | D19: UNI-SERV DPC Pty Ltd | E19: Masada | F19: Trusc Wireless | G19: 632 | H19: 0 | I19: 2 year | J19: 43134 | K19: 43864 | L19: TRUE
A20: 45548 | B20: UNI006 | C20: UNI006-15043 | D20: Unik Group of Companies (Pty) Ltd | E20: None | F20: Openserve | G20: 1375 | H20: 0 | I20: 2 year | J20: 44469 | K20: 45199 | L20: TRUE
A21: 45548 | B21: UNI007 | C21: UNI007-8615 | D21: Unifrutti SA (Pty) Ltd | E21: tafelberg | F21: Trusc Wireless | G21: 7474 | H21: 0 | I21: 2 year | J21: 44974 | K21: 45705 | L21: TRUE
A22: 45548 | B22: UNI008 | C22: UNI008-10034 | D22: Unique Premium Beverages | E22: retshof | F22: Trusc Wireless | G22: 599 | H22: 35 | I22: 2 year | J22: 45505 | K22: 46235 | L22: TRUE
A23: 45548 | B23: UNI009 | C23: UNI009-15407 | D23: Uniting Reformed Church | E23: deklip | F23: Trusc Wireless | G23: 350 | H23: 0 | I23: 2 year | J23: 45626 | K23: 46356 | L23: TRUE
A24: 45548 | B24: UPT007 | C24: UPT007-21509 | D24: A Upton | E24: vlan130-koraan | F24: Trusc Wireless | G24: 344 | H24: 0 | I24: 2 year | J24: 44933 | K24: 45664 | L24: TRUE
A25: 45548 | B25: URB003 | C25: URB003-27146 | D25: Urban Eye Planning and Development Pty Ltd | E25: Tallie Marine | F25: Trusc Wireless | G25: 799 | H25: 0 | I25: 2 year | J25: 45463 | K25: 46193 | L25: TRUE
A26: 45548 | B26: URI001 | C26: URI001-2485 | D26: Urionskraal Boerdery | E26: vlan3236_URI001-2485-SpecialLink | F26: Trusc Wireless | G26: 459 | H26: 0 | I26: 2 year | J26: 43725 | K26: 44456 | L26: TRUE
... A28: 45548 | B28: UYS004 | C28: UYS004-7480 | D28: S Uys | E28: De Hoek | F28: Trusc Wireless | G28: 350 | H28: 0 | I28: 2 year | J28: 45282 | K28: 46013 | L28: TRUE
A29: 45548 | B29: UYS005 | C29: UYS005-8853 | D29: SM Uys | L29: FALSE
A30: 45548 | B30: UYS007 | C30: UYS007-9950 | D30: E Uys | E30: ether1 - sh | F30: Trusc Wireless | G30: 804 | H30: 0 | I30: 2 year | J30: 44827 | K30: 45558 | L30: TRUE
A31: 45548 | B31: UYS008 | C31: UYS008-10355 | D31: JG Uys | E31: goudmyn | F31: Trusc Wireless | G31: 230 | H31: 0 | I31: 2 year | J31: 44009 | K31: 44739 | L31: TRUE
A32: 45548 | B32: UYS009 | C32: UYS009-13102 | D32: M Uys | E32: olive_place-SC | F32: Trusc Fibre | G32: 399 | H32: 0 | I32: 1 Year | J32: 45441 | K32: 46171 | L32: TRUE
A33: 45574 | B33: UYS013 | C33: UYS013-25598 | D33: S Uys | E33: goudmyn | F33: Trusc Wireless | G33: 350 | H33: 0 | I33: 2 year | J33: 45352 | K33: 46082 | L33: TRUE
A34: 45574 | B34: VAA006 | C34: VAA006-19070 | D34: PJ Vaas | E34: Vdal_res | F34: Trusc Wireless | G34: 349 | H34: 0 | I34: 2 year | J34: 45475 | K34: 46205 | L34: TRUE
A35: 45574 | B35: VAA008 | C35: VAA008-24585 | D35: Vaalvlei Boerdery Pty Ltd | E35: Strand | F35: Trusc Wireless | G35: 250 | H35: 0 | I35: 2 year | J35: 45273 | K35: 46004 | L35: TRUE
A36: 45574 | B36: VAL001 | C36: VAL001-804 | D36: LP Valentine | E36: Spioenkop | F36: Trusc Wireless | G36: 1552 | H36: 0 | I36: 2 year | J36: 43630 | K36: 44361 | L36: TRUE
A37: 45574 | B37: VAL002 | C37: VAL002-1774 | D37: GAH Traveho PTY LTD | E37: langebaan | F37: Trusc Wireless | G37: 673 | H37: 0 | I37: 2 year | J37: 44665 | K37: 45396 | L37: TRUE
A38: 45574 | B38: VAL006 | C38: VAL006-5487 | D38: Valskuil Boerdery | E38: paleis-apa2 | F38: Trusc Wireless | G38: 804 | H38: 35 | I38: 2 year | J38: 44833 | K38: 45564 | L38: TRUE
A39: 45574 | B39: VAL008 | C39: VAL008-7976 | D39: B Vallentyn | E39: Modderfontein | F39: Trusc Wireless | G39: 574 | H39: 0 | I39: 2 year | J39: 44480 | K39: 45210 | L39: TRUE
A40: 45574 | B40: VAL010 | C40: VAL010-10044 | D40: NP Valentyn | E40: Maskam | F40: Trusc Wireless | G40: 350 | H40: 0 | I40: 2 year | J40: 45288 | K40: 46019 | L40: TRUE
A41: 45574 | B41: VAL011 | C41: VAL011-23714 | D41: J Valentyn | E41: Koringberg | F41: Trusc Wireless | G41: 350 | H41: 0 | I41: 2 year | J41: 45204 | K41: 45935 | L41: TRUE
... A55: 45574 | B55: VAM001 | C55: VAM001-9423 | D55: Vaalplasie Trust | E55: Koringberg | F55: Trusc Wireless | G55: 804 | H55: 0 | I55: 2 year | J55: 44301 | K55: 45031 | L55: TRUE
A56: 45574 | B56: VAN009 | C56: VAN009-1810 | D56: Frederick Daniel Jacobus van Zyl | L56: FALSE
A57: 45574 | B57: VAN010 | C57: VAN010-5451 | D57: HJ Van Zyl | E57: Lutzville | F57: Trusc Wireless | G57: 344 | H57: 0 | I57: 2 year | J57: 44097 | K57: 44827 | L57: TRUE
A58: 45574 | B58: VAN019 | C58: VAN019-262 | D58: C van Wyk | E58: kapel | F58: Trusc Wireless | G58: 649 | H58: 35 | I58: 2 year | J58: 45490 | K58: 46220 | L58: TRUE
A59: 45574 | B59: VAN032 | C59: VAN032-463 | D59: Die Wiese CC | E59: Lambertsbay | F59: Trusc Wireless | G59: 574 | H59: 0 | I59: 2 year | J59: 44676 | K59: 45407 | L59: TRUE
A60: 45574 | B60: VAN035 | C60: VAN035-491 | D60: JEA van Zyl | E60: Strand | F60: Trusc Wireless | G60: 574 | H60: 0 | I60: 2 year | J60: 44111 | K60: 44841 | L60: TRUE
A61: 45575 | B61: VAN038 | C61: VAN038-549 | D61: J van Rhyn | E61: Heuningberg | F61: Trusc Wireless | G61: 976 | H61: 35 | I61: 2 year | J61: 45106 | K61: 45837 | L61: TRUE | M61: Running on current terms
A62: 45575 | B62: VAN040 | C62: VAN040-568 | D62: Sandberg Flora PTY LTD | E62: rond | F62: Trusc Wireless | G62: 799 | H62: 0 | I62: 2 year | J62: 45439 | K62: 46169 | L62: TRUE
A63: 45575 | B63: VAN041 | C63: VAN041-11807 | D63: JH van Zyl Boerdery (EDMS) Bpk | E63: Strand | F63: Trusc Wireless | G63: 0 | H63: 0 | I63: 2 year | J63: 44183 | K63: 44913 | L63: TRUE
A64: 45575 | B64: VAN041 | C64: VAN041-583 | D64: JH van Zyl Boerdery (EDMS) Bpk | E64: Spioenkop | F64: Trusc Wireless | G64: 1149 | H64: 0 | I64: 2 year | J64: 45224 | K64: 45955 | L64: TRUE
A65: 45575 | B65: VAN045 | C65: VAN045-713 | D65: HA van Rensburg | E65: Strand | F65: Trusc Wireless | G65: 350 | H65: 0 | I65: 2 year | J65: 45251 | K65: 45982 | L65: TRUE
A66: 45575 | B66: VAN046 | C66: VAN046-761 | D66: CP Van Der Merwe | E66: Kransvlei | F66: Trusc Wireless | G66: 459 | H66: 0 | I66: 2 year | J66: 43445 | K66: 44176 | L66: TRUE
A67: 45575 | B67: VAN048 | C67: VAN048-792 | D67: PJ van Zyl Boerdery | E67: Spioenkop | F67: Trusc Wireless | G67: 799 | H67: 0 | I67: 2 year | J67: 45526 | K67: 46256 | L67: TRUE
A68: 45575 | B68: VAN050 | C68: VAN050-801 | D68: C van Zyl | E68: Melkboom | F68: Trusc Wireless | G68: 799 | H68: 0 | I68: 2 year | J68: 45422 | K68: 46152 | L68: TRUE
A69: 45575 | B69: VAN050 | C69: VAN050-22367 | D69: C van Zyl | E69: Melkboom | F69: Trusc Wireless | G69: 349 | H69: 0 | I69: 2 year | J69: 45422 | K69: 46152 | L69: TRUE
A70: 45575 | B70: VAN055 | C70: VAN055-899 | D70: Rietvlei Boerdery Clanwilliam | E70: Bulshoek | F70: Trusc Wireless | G70: 574 | H70: 0 | I70: 2 year | J70: 44582 | K70: 45312 | L70: TRUE
A71: 45575 | B71: VAN056 | C71: VAN056-922 | D71: Biedouw Valley Rooibos | E71: Biedouw | F71: Trusc Wireless | G71: 799 | H71: 0 | I71: 2 year | J71: 45512 | K71: 46242 | L71: TRUE
A72: 45575 | B72: VAN057 | C72: VAN057-21351 | D72: Van Rhyn Werda Boerdery | E72: Strand | F72: Trusc Wireless | G72: 689 | H72: 0 | I72: 2 year | J72: 44910 | K72: 45641 | L72: TRUE
A73: 45575 | B73: VAN058 | C73: VAN058-956 | D73: HW van Niekerk | E73: Strand | F73: Trusc Wireless | G73: 350 | H73: 35 | I73: 2 year | J73: 45225 | K73: 45956 | L73: TRUE
... A108: 45576 | B108: VAN1039 | C108: VAN1039-22807 | D108: AJB van Heerden | E108: Bulshoek | F108: Trusc Wireless | G108: 344 | H108: 0 | I108: 2 year | J108: 45076 | K108: 45807 | L108: TRUE
A109: 45576 | B109: VAN1041 | C109: VAN1041-13148 | D109: E van Zyl | E109: Tallie Marine | F109: Trusc Wireless | G109: 689 | H109: 0 | I109: 2 year | J109: 44302 | K109: 16 Apr 0202 | L109: TRUE
A110: 45576 | B110: VAN1045 | C110: VAN1045-13212 | D110: H van der Westhuizen | E110: malms_gh | F110: Trusc Wireless | G110: 344 | H110: 0 | I110: 2 year | J110: 45096 | K110: 45827 | L110: TRUE
A111: 45576 | B111: VAN1047 | C111: VAN1047-13213 | D111: AL van der Merwe | E111: lamberts | F111: Trusc Wireless | G111: 459 | H111: 0 | I111: 2 year | J111: 44727 | K111: 45458 | L111: TRUE
A112: 45576 | B112: VAN1050 | C112: VAN1050-27733 | D112: ME van Schalkwyk | E112: None | F112: Trusc Fibre | G112: 249 | H112: 0 | I112: 2 year | J112: 45504 | K112: 46234 | L112: TRUE
A113: 45576 | B113: VAN1057 | C113: VAN1057-13503 | D113: Wydeman J van der Merwe | E113: Klipberg | F113: Trusc Wireless | G113: 689 | H113: 0 | I113: 2 year | J113: 44341 | K113: 45071 | L113: TRUE
A114: 45576 | B114: VAN106 | C114: VAN106-1577 | D114: AC van der Westhuizen | E114: Maskam | F114: Trusc Wireless | G114: 574 | H114: 0 | I114: 2 year | J114: 44162 | K114: 44892 | L114: TRUE
A115: 45576 | B115: VAN106 | C115: VAN106-1578 | D115: AC van der Westhuizen | E115: Maskam | F115: Trusc Wireless | G115: 344 | H115: 0 | I115: 2 year | J115: 44159 | K115: 44889 | L115: TRUE
A116: 45576 | B116: VAN1060 | D116: JP van der Mescht | L116: FALSE
A117: 45576 | B117: VAN1063 | D117: AH van der Merwe | L117: FALSE
A118: 45576 | B118: VAN1064 | D118: MI van der Merwe | L118: FALSE
A119: 45576 | B119: VAN1065 | D119: L Van Der Ross | L119: FALSE
A120: 45576 | B120: VAN1067 | D120: G Van Jaarsveld | L120: FALSE
A121: 45576 | B121: VAN1068 | D121: DB Van Wyk | L121: FALSE
A122: 45576 | B122: VAN1070 | D122: A van den Heever | L122: FALSE
A123: 45576 | B123: VAN1073 | D123: F Van Der Westhuizen | L123: FALSE
B124: VAN1076 | D124: TW van Wyk | L124: FALSE
B125: VAN1077 | D125: SJ Van Rooyen | L125: FALSE
B126: VAN1078 | D126: P Van Boven | L126: FALSE
B127: VAN1079 | D127: LJ Van Rhyn | L127: FALSE
B128: VAN1080 | D128: CP Van der Merwe | L128: FALSE
B129: VAN1081 | D129: L Van Rhyn | L129: FALSE
B130: VAN1087 | D130: MM Van Rooy | L130: FALSE
B131: VAN1091 | D131: JJ Van Rhyn | L131: FALSE
B132: VAN1094 | D132: IJ Van Lelyveld | L132: FALSE
B133: VAN1095 | D133: JH Van Wyk | L133: FALSE
B134: VAN1099 | D134: A Van Wyk | L134: FALSE
B135: VAN110 | D135: Anna Cape (Pty) Ltd | L135: FALSE
... B270: VAN1330 | D270: NB van Harte | L270: FALSE
B271: VAN1333 | C271: VAN1333-19145 | D271: N Van der Spuy | E271: Heuningberg | F271: Trusc Wireless | G271: 399 | H271: 0 | I271: 2 year | J271: 45531 | K271: 46261 | L271: TRUE
B272: VAN1337 | D272: MW van der Walt | L272: FALSE
B273: VAN1338 | D273: Andre van Zyl t/a Western Scrap | L273: FALSE
B274: VAN1339 | D274: A van Heerden | L274: FALSE
B275: VAN1341 | D275: DR van Rooy | L275: FALSE
B276: VAN1342 | D276: NP Van Zyl | L276: FALSE
B277: VAN1343 | D277: DL van Zyl | L277: FALSE
B278: VAN1344 | D278: S van Zyl | L278: FALSE
B279: VAN1347 | D279: JA Van Zyl | L279: FALSE
B280: VAN1348 | D280: SJ van Rhyn | L280: FALSE
B281: VAN1349 | D281: CE Van Wyk | L281: FALSE
B282: VAN1350 | D282: D van der Westhuizen | L282: FALSE
...

Sheet Clients (W - Z)
B1: =COUNTA(B4:B559) -> 556 | C1: =COUNTIF(C4:C559,"?*") -> 378
A2: Date | B2: Client Account | C2: Client Reference | D2: Client name | E2: Highsite / SC | F2: Type | G2: ISPMan Premium | H2: ISPMan EFT Fee | I2: Contract Duration | J2: Install Date | K2: Contract Expiry | L2: Have Contract
B3: ABC001 | C3: ABC001-12345 | D3: Mr Joe Soap | E3: Dwarskersbos S/C | F3: Trusc Wireless | I3: 1 Year | K3: 45626 | L3: TRUE | M3: Example line
A4: 45548 | B4: WAA001 | C4: WAA001-10016 | D4: A Waanar | E4: Voorberg | F4: Trusc Wireless | G4: 574 | H4: 0 | I4: 2 year | J4: 43987 | K4: 44717 | L4: TRUE
A5: 45548 | B5: WAA002 | C5: WAA002-17293 | D5: Waaidraai Boerdery | E5: Sishen | F5: Trusc Wireless | G5: 250 | H5: 0 | I5: 2 year | J5: 45295 | K5: 45661 | L5: TRUE
A6: 45548 | B6: WAD001 | C6: WAD001-23014 | D6: Wadrif Aartappels PTY LTD | E6: Spioenkop | F6: Trusc Wireless | G6: 976 | H6: 0 | L6: FALSE
A7: 45548 | B7: WAG004 | C7: WAG004-11574 | D7: G Wagner | E7: Heuningberg | F7: Trusc Wireless | G7: 574 | H7: 35 | I7: 2 year | J7: 44968 | K7: 45699 | L7: TRUE
A8: 45548 | B8: WAG005 | C8: WAG005-11795 | D8: SM Wagner | E8: Graafwater | F8: Trusc Wireless | G8: 350 | H8: 0 | I8: 2 year | J8: 45275 | K8: 46006 | L8: TRUE
A9: 45548 | B9: WAG008 | C9: WAG008-28075 | D9: AA Wagenstroom | E9: Graafwater | F9: Trusc Wireless | G9: 399 | H9: 0 | I9: 2 year | J9: 45548 | K9: 46278 | L9: TRUE
A10: 45548 | B10: WAG009 | C10: WAG009-15832 | D10: SC Wagemans | E10: Aasvoelkop SC | F10: Openserve | G10: 972 | H10: 0 | I10: 1 Year | J10: 44516 | K10: 44881 | L10: FALSE
A11: 45548 | B11: WAG010 | C11: WAG010-17217 | D11: LK Wagenaar | E11: Klawer | F11: Trusc Wireless | G11: 350 | H11: 0 | I11: 2 year | J11: 45283 | K11: 46017 | L11: TRUE
A12: 45548 | B12: WAG011 | C12: WAG011-20222 | D12: JS Wagener | E12: Admiral Island | F12: Trusc Fibre | G12: 599 | H12: 0 | I12: 2 year | J12: 44957 | K12: 45688 | L12: TRUE
A13: 45548 | B13: WAG013 | C13: WAG013-22512 | D13: PJ Wagner | E13: Klawer | F13: Trusc Wireless | G13: 574 | H13: 0 | I13: 2 year | J13: 45052 | K13: 45783 | L13: TRUE
A14: 45548 | B14: WAG014 | C14: WAG014-23557 | D14: THJ Wagenstroom | E14: Heuningberg | F14: Trusc Wireless | G14: 385 | H14: 0 | I14: 2 year | J14: 45188 | K14: 45919 | L14: TRUE
A15: 45548 | B15: WAG015 | C15: WAG015-25528 | D15: FJ Wagenaar | E15: klipberg | F15: Trusc Wireless | G15: 350 | H15: 0 | I15: 2 year | J15: 45351 | K15: 29 Feb 2026 | L15: FALSE
A16: 45548 | B16: WAG016 | C16: WAG016-25554 | D16: L Wagenaar | E16: Kalbaskraal | F16: Trusc Wireless | G16: 385 | H16: 0 | I16: 2 year | J16: 45361 | K16: 46091 | L16: TRUE
A17: 45548 | B17: WAG017 | C17: WAG017-26948 | D17: M Wagener | E17: Strand | F17: Trusc Wireless | G17: 649 | H17: 0 | I17: 2 year | J17: 45463 | K17: 46193 | L17: TRUE
A18: 45548 | B18: WAG018 | C18: WAG018-27563 | D18: CG Wagener | E18: Lambertsbay | F18: Trusc Wireless | G18: 348 | H18: 35 | I18: 2 year | J18: 45505 | K18: 46235 | L18: TRUE
A19: 45555 | B19: WAH001 | C19: WAH001-3267 | D19: K Wahl | E19: langebaan | F19: Trusc Wireless | G19: 574 | H19: 0 | I19: 2 year | J19: 44061 | K19: 44791 | L19: TRUE
A20: 45555 | B20: WAI001 | C20: WAI001-23403 | D20: MMM Waily | E20: Dwarskersbos S/C | F20: Trusc Fibre | G20: 399 | H20: 0 | I20: 2 year | J20: 45232 | K20: 45963 | L20: TRUE
A21: 45548 | B21: WAI002 | C21: WAI002-22880 | D21: The Waitrose Foundation | E21: vlan20_maanberg | F21: Trusc Wireless | G21: 574 | H21: 0 | I21: 2 year | J21: 45133 | K21: 45864 | L21: TRUE
A22: 45548 | B22: WAI002 | C22: WAI002-22932 | D22: The Waitrose Foundation | E22: grootfontein | F22: Trusc Wireless | G22: 574 | H22: 0 | I22: 2 year | J22: 45134 | K22: 45865 | L22: TRUE
A23: 45548 | B23: WAI002 | C23: WAI002-23032 | D23: The Waitrose Foundation | E23: Steelwater | F23: Trusc Wireless | G23: 574 | H23: 0 | I23: 2 year | J23: 45128 | K23: 45859 | L23: TRUE
A24: 45548 | B24: WAI002 | C24: WAI002-23474 | D24: The Waitrose Foundation | E24: moutons | F24: Trusc Wireless | G24: 576 | H24: 0 | I24: 2 year | J24: 45192 | K24: 45923 | L24: TRUE
A25: 45548 | B25: WAK001 | C25: WAK001-10079 | D25: AJ Wakefield | E25: Doornbaai | F25: Trusc Wireless | G25: 344 | H25: 35 | I25: 2 year | J25: 45080 | K25: 45811 | L25: TRUE
A26: 45548 | B26: WAK002 | C26: WAK002-27529 | D26: F Wakens | E26: Koringberg | F26: Trusc Wireless | G26: 399 | H26: 0 | I26: 2 year | J26: 45546 | K26: 46276 | L26: TRUE
A27: 45548 | B27: WAL001 | C27: WAL001-1647 | D27: MDM Walters | E27: lang | F27: Trusc Wireless | G27: 459 | H27: 0 | I27: 2 year | J27: 44845 | K27: 45576 | L27: TRUE
... A30: 45555 | B30: WAL010 | C30: WAL010-5556 | D30: ZM Walkers | E30: wt | F30: Trusc Wireless | G30: 804 | H30: 0 | I30: 2 year | J30: 44132 | K30: 44862 | L30: TRUE
A31: 45548 | B31: WAL012 | C31: WAL012-7006 | D31: JD Walker | E31: Masada | F31: Trusc Wireless | G31: 0 | H31: 0 | I31: 2 year | J31: 43608 | L31: TRUE
A32: 45548 | B32: WAL013 | C32: WAL013-9221 | D32: ZA Walters | E32: lang | F32: Trusc Wireless | G32: 229.5 | H32: 0 | I32: 2 year | J32: 44839 | K32: 45570 | L32: TRUE
A33: 45548 | B33: WAL017 | C33: WAL017-11345 | D33: OC Waldeck | E33: Oranjefontein | F33: Trusc Wireless | G33: 574 | H33: 0 | I33: 2 year | J33: 44132 | K33: 44862 | L33: TRUE
A34: 45548 | B34: WAL019 | C34: WAL019-12481 | D34: EN Walters | E34: Paardeberg | F34: Trusc Wireless | G34: 2070 | H34: 0 | I34: 2 year | J34: 44274 | K34: 45004 | L34: TRUE
A35: 45548 | B35: WAL021 | C35: WAL021-16923 | D35: SW Walker | E35: Koraan | F35: Trusc Wireless | G35: 350 | H35: 35 | I35: 2 year | J35: 45283 | K35: 46014 | L35: TRUE
A36: 45548 | B36: WAL022 | C36: WAL022-23645 | D36: K Walita | E36: Lutzville | F36: Trusc Wireless | G36: 344 | H36: 0 | I36: 2 year | J36: 45199 | K36: 45930 | L36: TRUE
A37: 45548 | B37: WAL023 | C37: WAL023-21978 | D37: SV Walaza | E37: Oranjefontein | F37: Trusc Wireless | G37: 689 | H37: 0 | I37: 2 year | J37: 44973 | K37: 45704 | L37: TRUE
A38: 45548 | B38: WAL025 | C38: WAL025-26198 | D38: JJ Waldeck | E38: saron | F38: Trusc Wireless | G38: 350 | H38: 0 | I38: 2 year | J38: 45408 | K38: 46138 | L38: TRUE
A39: 45555 | B39: WAN002 | C39: WAN002-3776 | D39: A Wanneburg | E39: Laaiplek | F39: Trusc Wireless | G39: 549 | H39: 0 | L39: FALSE
A40: 45548 | B40: WAN004 | C40: WAN004-11492 | D40: G Waneburg | E40: malms_gh | F40: Trusc Wireless | G40: 574 | H40: 0 | I40: 2 year | J40: 44152 | K40: 44882 | L40: TRUE
A41: 45548 | B41: WAR005 | C41: WAR005-6677 | D41: EA Warnich | E41: koringberg | F41: Trusc Wireless | G41: 574 | H41: 0 | I41: 2 year | J41: 43615 | K41: 43981 | L41: TRUE
A42: 45548 | B42: WAR011 | C42: WAR011-23071 | D42: E Warambwa | E42: Vredendal S/C | F42: Trusc Fibre | G42: 459 | H42: 35 | I42: 2 year | J42: 45156 | K42: 45887 | L42: FALSE
A43: 45548 | B43: WAR013 | C43: WAR013-23171 | D43: OK Wardell | E43: Admiral Island | F43: Trusc Fibre | G43: 399 | H43: 0 | I43: 2 year | J43: 45142 | K43: 45873 | L43: TRUE
A44: 45548 | B44: WAR019 | C44: WAR019-20684 | D44: E Ward | E44: Dwarskersbos S/C | F44: Trusc Fibre | G44: 459 | H44: 0 | I44: 2 year | J44: 45241 | K44: 45972 | L44: TRUE
A45: 45548 | B45: WAR020 | C45: WAR020-20907 | D45: S Warnich | E45: Strand | F45: Trusc Wireless | G45: 459 | H45: 0 | I45: 2 year | J45: 44888 | K45: 45619 | L45: TRUE
A46: 45548 | B46: WAR022 | C46: WAR022-24282 | D46: CN Warries | E46: Paardeberg | F46: Trusc Wireless | G46: 350 | H46: 0 | I46: 2 year | J46: 45260 | K46: 45991 | L46: TRUE
A47: 45548 | B47: WAR023 | C47: WAR023-25501 | D47: U Ward | E47: Admiral Island | F47: Trusc Fibre | G47: 399 | H47: 0 | I47: 2 year | J47: 45343 | K47: 46074 | L47: TRUE
A48: 45548 | B48: WAR024 | C48: WAR024-25717 | D48: HM Warild | E48: vlan60_laaiplek | F48: Trusc Wireless | G48: 350 | H48: 35 | I48: 2 year | J48: 45364 | K48: 46094 | L48: TRUE
A49: 45548 | B49: WAR025 | C49: WAR025-27381 | D49: D Warnick | E49: Klipberg | F49: Trusc Wireless | G49: 349 | I49: 2 year | J49: 45505 | K49: 46235 | L49: TRUE
A50: 45548 | B50: WAR026 | C50: WAR026-27686 | D50: RJM Warnick | E50: Klipberg | F50: Trusc Wireless | G50: 339 | H50: 0 | I50: 2 year | J50: 45510 | K50: 46240 | L50: TRUE
A51: 45553 | B51: WAS002 | C51: WAS002-4674 | D51: H Baumgarten TA Waste-Gro | E51: lm_bakwerke | F51: Trusc Wireless | G51: 574 | H51: 0 | I51: 2 year | J51: 43882 | K51: 44613 | L51: TRUE
A52: 45580 | B52: WAS003 | C52: WAS003-26683 | D52: L Wasserman | E52: Aasvoelkop SC | F52: Trusc Fibre | L52: FALSE
A53: 45553 | B53: WAT004 | C53: WAT004-2263 | D53: Arno Watson | E53: Aurora | F53: Trusc Wireless | G53: 977 | H53: 0 | I53: 2 year | J53: 43924 | K53: 44654 | L53: TRUE
A54: 45548 | B54: WAT007 | C54: WAT007-7372 | D54: JE Watson | E54: bottlefontein | F54: Trusc Wireless | G54: 459 | H54: 0 | L54: FALSE
A55: 45553 | B55: WAT012 | C55: WAT012-11187 | D55: E Waterboer | E55: kabiscouw | F55: Trusc Wireless | G55: 350 | H55: 0 | I55: 2 year | J55: 45184 | K55: 45915 | L55: TRUE
A56: 45553 | B56: WAT012 | C56: WAT012-23594 | D56: E Waterboer | E56: Vdal_res | F56: Trusc Wireless | G56: 350 | H56: 0 | I56: 2 year | J56: 45190 | K56: 45921 | L56: TRUE
A57: 45553 | B57: WAT016 | C57: WAT016-13477 | D57: DA Watt | E57: Springbok | F57: Trusc Wireless | G57: 287 | H57: 0 | I57: 2 year | J57: 44338 | K57: 45068 | L57: TRUE
A58: 45548 | B58: WAT017 | C58: WAT017-13834 | D58: NE Watson | E58: Modderfontein | F58: Trusc Wireless | G58: 574 | H58: 0 | I58: 2 year | J58: 44373 | K58: 45103 | L58: TRUE
A59: 45553 | B59: WAT020 | C59: WAT020-16188 | D59: DJ Waterboer | E59: Nababeep | F59: Trusc Wireless | G59: 574 | H59: 0 | I59: 2 year | J59: 44518 | K59: 45248 | L59: TRUE
A60: 45553 | B60: WAT022 | C60: WAT022-17247 | D60: AB Waterboer | E60: Koningskop | F60: Trusc Wireless | G60: 574 | H60: 0 | I60: 2 year | J60: 45232 | K60: 45963 | L60: TRUE
A61: 45553 | B61: WAT026 | C61: WAT026-20232 | D61: G Watermeyer | E61: Maskam | F61: Trusc Wireless | G61: 574 | H61: 0 | I61: 2 year | J61: 44840 | K61: 45571 | L61: TRUE
A62: 45553 | B62: WAT028 | C62: WAT028-20663 | D62: JM Waterboer | E62: Nababeep | F62: Trusc Wireless | G62: 344 | H62: 35 | I62: 2 year | J62: 44868 | K62: 45599 | L62: TRUE
A63: 45553 | B63: WAT029 | C63: WAT029-20799 | D63: AG Watermeyer | E63: Veldrift S/C | F63: Trusc Fibre | G63: 799 | H63: 0 | I63: 2 year | J63: 45590 | K63: 45955 | L63: TRUE
A64: 45553 | B64: WAT031 | C64: WAT031-22754 | D64: AW Wataro | E64: eben | F64: Trusc Wireless | G64: 574 | H64: 0 | I64: 2 year | L64: FALSE
A65: 45553 | B65: WAT032 | C65: WAT032-24388 | D65: M Watt | E65: Klipberg | F65: Trusc Wireless | G65: 350 | H65: 35 | I65: 2 year | J65: 45258 | K65: 45989 | L65: TRUE
A66: 45553 | B66: WAT033 | C66: WAT033-24554 | D66: S Watermeyer | E66: Kliprand | F66: Trusc Wireless | G66: 350 | H66: 0 | I66: 2 year | J66: 45274 | K66: 46005 | L66: TRUE
A67: 45553 | B67: WAT034 | C67: WAT034-25512 | D67: EA Waters | E67: Admiral Island | F67: Trusc Fibre | G67: 399 | H67: 0 | I67: 2 year | J67: 45351 | K67: 29/02/2026 | L67: TRUE
A68: 45553 | B68: WAT035 | C68: WAT035-26496 | D68: KE Waterboer | E68: Okiep | F68: Trusc Wireless | G68: 350 | H68: 0 | I68: 2 year | J68: 45419 | K68: 46149 | L68: TRUE
A69: 45553 | B69: WAT036 | C69: WAT036-27176 | D69: FT Watt | E69: Springbok | F69: Trusc Wireless | G69: 349 | H69: 0 | I69: 2 year | J69: 45471 | K69: 46201 | L69: TRUE
A70: 45553 | B70: WAT037 | C70: WAT037-27334 | D70: C Watermeyer | E70: kabiscouw | F70: Trusc Wireless | G70: 349 | H70: 0 | I70: 2 year | J70: 45484 | K70: 46214 | L70: TRUE
A71: 45553 | B71: WAT038 | C71: WAT038-28012 | D71: MK Waterboer | E71: Nababeep | F71: Trusc Wireless | G71: 399 | H71: 35 | I71: 2 year | J71: 45539 | K71: 46269 | L71: TRUE
A72: 45553 | B72: WAT039 | C72: WAT039-28163 | D72: A Waterboer | E72: rond | F72: Trusc Wireless | G72: 299 | H72: 0 | I72: 2 year | J72: 45548 | K72: 46278 | L72: TRUE
A73: 45561 | B73: WAV001 | C73: WAV001-27000 | D73: Wave Technologies SA CC | E73: Veldrift S/C | F73: Trusc Fibre | G73: 449 | H73: 0 | I73: 2 year | J73: 45491 | K73: 46221 | L73: TRUE
A74: 45574 | B74: WEA002 | C74: WEA002-13970 | D74: Esta Johanna Weavers | E74: Velddrift | F74: Trusc Wireless | G74: 344 | H74: 0 | I74: 2 year | J74: 44990 | K74: 45905 | L74: TRUE
A75: 45574 | B75: WEA003 | C75: WEA003-23210 | D75: Dr AK Weakley | E75: Veldrift S/C | F75: Trusc Fibre | G75: 399 | H75: 0 | I75: 2 year | J75: 45160 | K75: 45891 | L75: TRUE
A76: 45574 | B76: WEB001 | C76: WEB001-6727 | D76: KS Webster | E76: Goudmyn | F76: Trusc Wireless | G76: 459 | H76: 0 | I76: 2 year | J76: 43582 | K76: 44313 | L76: TRUE
A77: 45574 | B77: WEB002 | C77: WEB002-21903 | D77: BHL Webber | E77: Ebenhaezer | F77: Trusc Wireless | G77: 689 | H77: 0 | I77: 2 year | J77: 44964 | K77: 45695 | L77: TRUE
A78: 45574 | B78: WED002 | C78: WED002-10825 | D78: Wedgewood Insurance and Investment Brokers cc | E78: Ebenhaezer | F78: Trusc Wireless | G78: 1149 | H78: 0 | I78: 2 year | J78: 44095 | K78: 44825 | L78: TRUE
A79: 45574 | B79: WEE001 | C79: WEE001-2043 | D79: KB Weeks | E79: Ebenhaezer | F79: Trusc Wireless | G79: 689 | H79: 0 | I79: 2 year | J79: 44158 | K79: 44888 | L79: TRUE
A80: 45574 | B80: WEG002 | C80: WEG002-20079 | D80: KL Wegener | E80: Veldrift S/C | F80: Trusc Fibre | G80: 499 | H80: 0 | I80: 2 year | J80: 45155 | K80: 45886 | L80: TRUE
A81: 45574 | B81: WEI002 | C81: WEI002-3663 | D81: W Weiqiang | E81: Clan | F81: Trusc Wireless | G81: 549 | H81: 0 | L81: FALSE
A82: 45574 | B82: WEI005 | C82: WEI005-20167 | D82: AC Weil | E82: Aasvoelkop SC | F82: Openserve | G82: 685 | H82: 0 | I82: 2 year | J82: 44825 | K82: 45556 | L82: TRUE
A83: 45561 | B83: WEI007 | C83: WEI007-14430 | D83: N Weideman | E83: Paardeberg | F83: Trusc Wireless | G83: 299 | H83: 35 | I83: 2 year | J83: 45547 | K83: 46277 | L83: TRUE
A84: 45574 | B84: WEL001 | C84: WEL001-8932 | D84: Welgemeen Boerdery | E84: Synott | F84: Trusc Wireless | G84: 1149 | H84: 0 | I84: 2 year | J84: 44449 | K84: 45179 | L84: TRUE
A85: 45574 | B85: WEL004 | C85: WEL004-10746 | D85: Welgevonden Boerdery | E85: kabiscouw | F85: Trusc Wireless | G85: 344 | H85: 0 | I85: 2 year | J85: 44823 | K85: 45554 | L85: TRUE
A86: 45574 | B86: WEL004 | C86: WEL004-6365 | D86: Welgevonden Boerdery | E86: kabiscouw | F86: Trusc Wireless | G86: 350 | H86: 0 | I86: 2 year | J86: 45208 | K86: 45939 | L86: TRUE
A87: 45574 | B87: WEL007 | C87: WEL007-27882 | D87: Welbedacht Rooibos Boerdery PTY Ltd | E87: Biedouw | F87: Trusc Wireless | G87: 299 | H87: 0 | I87: 2 year | J87: 45512 | K87: 46242 | L87: TRUE
A88: 45574 | B88: WEL007 | C88: WEL007-8147 | D88: Welbedacht Rooibos Boerdery PTY Ltd | E88: Biedouw | F88: Trusc Wireless | G88: 399 | H88: 0 | I88: 2 year | J88: 45512 | K88: 46242 | L88: TRUE
A89: 45574 | B89: WEL007 | C89: WEL007-8148 | D89: Welbedacht Rooibos Boerdery PTY Ltd | E89: Biedouw | F89: Trusc Wireless | G89: 399 | H89: 0 | I89: 2 year | J89: 45512 | K89: 46242 | L89: TRUE
A90: 45574 | B90: WEL008 | C90: WEL008-24864 | D90: V Welgemoed | E90: Dwarskersbos S/C | F90: Trusc Fibre | G90: 399 | H90: 35 | I90: 2 year | J90: 45316 | K90: 46047 | L90: TRUE
A91: 45574 | B91: WEL008 | C91: WEL008-24866 | D91: V Welgemoed | E91: Dwarskersbos S/C | F91: Trusc Fibre | G91: 399 | H91: 0 | I91: 2 year | J91: 45314 | K91: 46045 | L91: TRUE
A92: 45574 | B92: WEL011 | C92: WEL011-12884 | D92: LJ Welthagen | E92: Blouwater | F92: Trusc Wireless | G92: 574 | H92: 0 | I92: Current Terms | J92: 44284 | K92: 45014 | L92: TRUE
A93: 45574 | B93: WEL013 | C93: WEL013-17575 | D93: R Wellman | E93: Lambex | F93: Trusc Wireless | G93: 287 | H93: 0 | I93: 2 year | J93: 44589 | K93: 45319 | L93: TRUE
... A102: 45574 | B102: WEN005 | C102: WEN005-4743 | D102: E Weng | E102: Modderfontein | F102: Trusc Wireless | G102: 350 | H102: 35 | I102: 2 year | J102: 45247 | K102: 45978 | L102: TRUE
A103: 45580 | B103: WEN008 | C103: WEN008-21662 | D103: CR Wentzel | E103: saron | F103: Trusc Wireless | I103: 2 year | L103: FALSE
A104: 45574 | B104: WEN009 | C104: WEN009-21725 | D104: WA Wentzel | E104: vlan130-koraan | F104: Trusc Wireless | G104: 574 | H104: 0 | I104: 2 year | J104: 44958 | K104: 45689 | L104: TRUE
A105: 45574 | B105: WEN009 | C105: WEN009-21727 | D105: WA Wentzel | E105: vlan130-koraan | F105: Trusc Wireless | G105: 574 | H105: 0 | I105: 2 year | J105: 44971 | K105: 45702 | L105: TRUE
A106: 45574 | B106: WES004 | C106: WES004-12318 | D106: Colour bay TA Strandfontein Accommodation | E106: Strand | F106: Trusc Wireless | G106: 350 | H106: 0 | I106: 1 Year | J106: 45279 | K106: 45645 | L106: TRUE
A107: 45574 | B107: WES011 | C107: WES011-944 | D107: Y van der Westhuizen | E107: urionskraal | F107: Trusc Wireless | G107: 574 | H107: 0 | I107: Current Terms | J107: 44302 | K107: 44302 | L107: TRUE
A108: 45574 | B108: WES012 | C108: WES012-949 | D108: SA van der Westhuizen | E108: Maskam | F108: Trusc Wireless | G108: 574 | H108: 0 | I108: 2 year | J108: 44158 | K108: 44888 | L108: TRUE
A109: 45574 | B109: WES013 | C109: WES013-950 | D109: GC van der Westhuizen | E109: Grysberg | F109: Trusc Wireless | G109: 350 | H109: 0 | I109: 1 Year | J109: 45289 | K109: 45655 | L109: TRUE
A110: 45574 | B110: WES014 | C110: WES014-11897 | D110: Doringrivier Boerdery Edms Bpk | E110: Strand | F110: Trusc Wireless | G110: 977 | H110: 0 | L110: FALSE
...

Sheet Data
A1: Term | B1: Highsite | C1: Type
A3: Month to Month | B3: Aasvoelkop SC | C3: Trusc Wireless
A4: 1 Year | B4: Aasvoelkop-aasvoelkop-switch1 | C4: Trusc Fibre
A5: 2 year | B5: Admiral Island | C5: Openserve
A6: Sponsorship Agreement | B6: De Hoek | C6: Octotel
A7: Current Terms | B7: deklip2 | C7: DFA
A8: Corporate Billing | B8: Biedouw | C8: Frogfoot
B9: Rooiberg | C9: Vumatel
B10: Veldrift
B11: Dwars
B12: Trusc - 10040
B13: pakhuis
B14: Openserve
B15: Wolvekop
B16: AP10030
B17: Duiwels
B18: AP10023
B19: Octotel Blouberg
B20: Vlan70
B21: wlan1
... B327: vlan20_meisies_koshuis-apa2
